Workbook

Sheet Start Here
C1: LRC Watchlist Builder — Swing & Investment
A2: Two tracks, one process: screen → shortlist → score → plan → review. US stocks via Finviz, JSE stocks via TradingView.
A4: The two tracks
A5: SWING (3–6 months) | B5: Weekly, every weekend. At least 5 new candidates — LONG (buy strong stocks in uptrends) or SHORT (sell weak stocks in downtrends). Set Direction on each row; the score, stop check, P/L and signals flip automatically. Lean long in RISK-ON markets, short in RISK-OFF. Tabs: How to Pick — Swing · Swing Watchlist · Weekly Review.
A6: INVESTMENT (5–10+ years) | B6: Monthly, first weekend. At least 5 new candidates. Excellent businesses at sensible prices, held while the thesis holds. Tabs: How to Pick — Investment · Investment Watchlist · Monthly Review.
A7: How the tabs fit
A8: Screener Settings | B8: The exact Finviz (US) and TradingView (JSE) filters: Swing Long, Swing Short and Investment. Save them as presets once.
A9: Watchlists | B9: Paste the screener numbers in the blue cells. Each stock gets a score, an A/B/C grade and a next step. Counters at the top check you hit the minimum of 5.
A10: Summary | B10: This week and this month at a glance, with the Top 5 by score.
A11: Reviews | B11: Tick-box checklists plus a log, so you follow the same process every time.
A12: Link to LRC process | B12: Swing A-grades → Technical Review in the LRC Stock Analysis Template for execution clearance. Investment A-grades → the full LRC Stock Analysis Template. Trades → LRC Portfolio Operations (Trade Log).
A13: Colour code
A14: Yellow cell, blue text | B14: You type here (percentages with the % sign, e.g. 12.5%)
A15: Grey cell | B15: Calculates — don't type over it
A16: Green / amber / red | B16: A / B / C grade, or a signal to act on
A17: First time setup | B17: This is a blank copy. Fill the yellow settings at the top of each watchlist first: review week (Saturday) and account size on the Swing Watchlist, review month on the Investment Watchlist. Update the S&P 500 and JSE 6-month performance every week.
A18: Important | B18: A screen is where research starts, not a buy signal. Scores rank candidates; your chart reading and judgement make the decision. Not financial advice.

Sheet Summary
C1: Watchlist Summary
A2: This week (swing) and this month (investment) at a glance: minimum-5 checks, grades, signals and the Top 5 by score.
A4: SWING — this week | H4: INVESTMENT — this month
A5: Week ending | D5: =IF('Swing Watchlist'!$C$4="","",'Swing Watchlist'!$C$4) -> 46316 | H5: Month | K5: =IF('Investment Watchlist'!$C$4="","",'Investment Watchlist'!$C$4) -> 46296
A6: New candidates | D6: ='Swing Watchlist'!U4 -> 13 | H6: New candidates | K6: ='Investment Watchlist'!L4 -> 10
A7: Minimum check | D7: ='Swing Watchlist'!V4 -> ✔ minimum met | H7: Minimum check | K7: ='Investment Watchlist'!M4 -> ✔ minimum met
A8: US / JSE · Long / Short | D8: ='Swing Watchlist'!U5&" · "&'Swing Watchlist'!U6 -> 13 / 0 · 3 / 10 | H8: US / JSE | K8: ='Investment Watchlist'!L5 -> 10 / 0
A9: Grade A / B / C | D9: =COUNTIFS('Swing Watchlist'!$A$11:$A$210,'Swing Watchlist'!$C$4,'Swing Watchlist'!$AK$11:$AK$210,"A")&" / "&COUNTIFS('Swing Watchlist'!$A$11:$A$210,'Swing Watchlist'!$C$4,'Swing Watchlist'!$AK$11:$AK$210,"B")&" / "&COUNTIFS('Swing Watchlist'!$A$11:$A$210,'Swing Watchlist'!$C$4,'Swing Watchlist'!$AK$11:$AK$210,"C") -> 0 / 9 / 4 | H9: Grade A / B / C | K9: =COUNTIFS('Investment Watchlist'!$A$9:$A$158,'Investment Watchlist'!$C$4,'Investment Watchlist'!$AG$9:$AG$158,"A")&" / "&COUNTIFS('Investment Watchlist'!$A$9:$A$158,'Investment Watchlist'!$C$4,'Investment Watchlist'!$AG$9:$AG$158,"B")&" / "&COUNTIFS('Investment Watchlist'!$A$9:$A$158,'Investment Watchlist'!$C$4,'Investment Watchlist'!$AG$9:$AG$158,"C") -> 5 / 4 / 1
A10: Open positions | D10: =COUNTIF('Swing Watchlist'!$AP$11:$AP$210,"Open position") -> 0 | H10: Owned | K10: =COUNTIF('Investment Watchlist'!$AI$9:$AI$158,"Owned") -> 0
A11: Sell / cover / take-profit signals | D11: =COUNTIF('Swing Watchlist'!$AU$11:$AU$210,"SELL*")+COUNTIF('Swing Watchlist'!$AU$11:$AU$210,"COVER*")+COUNTIF('Swing Watchlist'!$AU$11:$AU$210,"TAKE*") -> 0 | H11: Sent to full analysis | K11: =COUNTIF('Investment Watchlist'!$AH$9:$AH$158,"Full*") -> 5
A12: Review signals | D12: =COUNTIF('Swing Watchlist'!$AU$11:$AU$210,"REVIEW*") -> 0 | H12: Review signals | K12: =COUNTIF('Investment Watchlist'!$AH$9:$AH$158,"REVIEW*") -> 0
A14: Top 5 swing candidates this week | H14: Top 5 investment candidates this month
A15: # | B15: Ticker | C15: L/S | D15: Score | E15: Grade | F15: Next step | H15: # | I15: Ticker | J15: Mkt | K15: Score | L15: Grade | M15: Next step
A16: 1 | B16: =IFERROR(INDEX('Swing Watchlist'!$C$11:$C$210,MATCH(LARGE('Swing Watchlist'!$AX$11:$AX$210,1),'Swing Watchlist'!$AX$11:$AX$210,0)),"") -> NKE | C16: =IFERROR(IF(INDEX('Swing Watchlist'!$F$11:$F$210,MATCH(LARGE('Swing Watchlist'!$AX$11:$AX$210,1),'Swing Watchlist'!$AX$11:$AX$210,0))="Short","Short","Long"),"") -> Short | D16: =IFERROR(INDEX('Swing Watchlist'!$AJ$11:$AJ$210,MATCH(LARGE('Swing Watchlist'!$AX$11:$AX$210,1),'Swing Watchlist'!$AX$11:$AX$210,0)),"") -> 13 | E16: =IFERROR(INDEX('Swing Watchlist'!$AK$11:$AK$210,MATCH(LARGE('Swing Watchlist'!$AX$11:$AX$210,1),'Swing Watchlist'!$AX$11:$AX$210,0)),"") -> B | F16: =IFERROR(INDEX('Swing Watchlist'!$AU$11:$AU$210,MATCH(LARGE('Swing Watchlist'!$AX$11:$AX$210,1),'Swing Watchlist'!$AX$11:$AX$210,0)),"") -> Watch — wait for setup | H16: 1 | I16: =IFERROR(INDEX('Investment Watchlist'!$C$9:$C$158,MATCH(LARGE('Investment Watchlist'!$AP$9:$AP$158,1),'Investment Watchlist'!$AP$9:$AP$158,0)),"") -> INTU | J16: =IFERROR(INDEX('Investment Watchlist'!$B$9:$B$158,MATCH(LARGE('Investment Watchlist'!$AP$9:$AP$158,1),'Investment Watchlist'!$AP$9:$AP$158,0)),"") -> US | K16: =IFERROR(INDEX('Investment Watchlist'!$AF$9:$AF$158,MATCH(LARGE('Investment Watchlist'!$AP$9:$AP$158,1),'Investment Watchlist'!$AP$9:$AP$158,0)),"") -> 24 | L16: =IFERROR(INDEX('Investment Watchlist'!$AG$9:$AG$158,MATCH(LARGE('Investment Watchlist'!$AP$9:$AP$158,1),'Investment Watchlist'!$AP$9:$AP$158,0)),"") -> A | M16: =IFERROR(INDEX('Investment Watchlist'!$AH$9:$AH$158,MATCH(LARGE('Investment Watchlist'!$AP$9:$AP$158,1),'Investment Watchlist'!$AP$9:$AP$158,0)),"") -> Full LRC Stock Analysis
A17: 2 | B17: =IFERROR(INDEX('Swing Watchlist'!$C$11:$C$210,MATCH(LARGE('Swing Watchlist'!$AX$11:$AX$210,2),'Swing Watchlist'!$AX$11:$AX$210,0)),"") -> KEYS | C17: =IFERROR(IF(INDEX('Swing Watchlist'!$F$11:$F$210,MATCH(LARGE('Swing Watchlist'!$AX$11:$AX$210,2),'Swing Watchlist'!$AX$11:$AX$210,0))="Short","Short","Long"),"") -> Short | D17: =IFERROR(INDEX('Swing Watchlist'!$AJ$11:$AJ$210,MATCH(LARGE('Swing Watchlist'!$AX$11:$AX$210,2),'Swing Watchlist'!$AX$11:$AX$210,0)),"") -> 12 | E17: =IFERROR(INDEX('Swing Watchlist'!$AK$11:$AK$210,MATCH(LARGE('Swing Watchlist'!$AX$11:$AX$210,2),'Swing Watchlist'!$AX$11:$AX$210,0)),"") -> B | F17: =IFERROR(INDEX('Swing Watchlist'!$AU$11:$AU$210,MATCH(LARGE('Swing Watchlist'!$AX$11:$AX$210,2),'Swing Watchlist'!$AX$11:$AX$210,0)),"") -> Watch — wait for setup | H17: 2 | I17: =IFERROR(INDEX('Investment Watchlist'!$C$9:$C$158,MATCH(LARGE('Investment Watchlist'!$AP$9:$AP$158,2),'Investment Watchlist'!$AP$9:$AP$158,0)),"") -> DECK | J17: =IFERROR(INDEX('Investment Watchlist'!$B$9:$B$158,MATCH(LARGE('Investment Watchlist'!$AP$9:$AP$158,2),'Investment Watchlist'!$AP$9:$AP$158,0)),"") -> US | K17: =IFERROR(INDEX('Investment Watchlist'!$AF$9:$AF$158,MATCH(LARGE('Investment Watchlist'!$AP$9:$AP$158,2),'Investment Watchlist'!$AP$9:$AP$158,0)),"") -> 21 | L17: =IFERROR(INDEX('Investment Watchlist'!$AG$9:$AG$158,MATCH(LARGE('Investment Watchlist'!$AP$9:$AP$158,2),'Investment Watchlist'!$AP$9:$AP$158,0)),"") -> A | M17: =IFERROR(INDEX('Investment Watchlist'!$AH$9:$AH$158,MATCH(LARGE('Investment Watchlist'!$AP$9:$AP$158,2),'Investment Watchlist'!$AP$9:$AP$158,0)),"") -> Full LRC Stock Analysis
A18: 3 | B18: =IFERROR(INDEX('Swing Watchlist'!$C$11:$C$210,MATCH(LARGE('Swing Watchlist'!$AX$11:$AX$210,3),'Swing Watchlist'!$AX$11:$AX$210,0)),"") -> NVDA | C18: =IFERROR(IF(INDEX('Swing Watchlist'!$F$11:$F$210,MATCH(LARGE('Swing Watchlist'!$AX$11:$AX$210,3),'Swing Watchlist'!$AX$11:$AX$210,0))="Short","Short","Long"),"") -> Long | D18: =IFERROR(INDEX('Swing Watchlist'!$AJ$11:$AJ$210,MATCH(LARGE('Swing Watchlist'!$AX$11:$AX$210,3),'Swing Watchlist'!$AX$11:$AX$210,0)),"") -> 12 | E18: =IFERROR(INDEX('Swing Watchlist'!$AK$11:$AK$210,MATCH(LARGE('Swing Watchlist'!$AX$11:$AX$210,3),'Swing Watchlist'!$AX$11:$AX$210,0)),"") -> B | F18: =IFERROR(INDEX('Swing Watchlist'!$AU$11:$AU$210,MATCH(LARGE('Swing Watchlist'!$AX$11:$AX$210,3),'Swing Watchlist'!$AX$11:$AX$210,0)),"") -> Watch — wait for setup | H18: 3 | I18: =IFERROR(INDEX('Investment Watchlist'!$C$9:$C$158,MATCH(LARGE('Investment Watchlist'!$AP$9:$AP$158,3),'Investment Watchlist'!$AP$9:$AP$158,0)),"") -> NVDA | J18: =IFERROR(INDEX('Investment Watchlist'!$B$9:$B$158,MATCH(LARGE('Investment Watchlist'!$AP$9:$AP$158,3),'Investment Watchlist'!$AP$9:$AP$158,0)),"") -> US | K18: =IFERROR(INDEX('Investment Watchlist'!$AF$9:$AF$158,MATCH(LARGE('Investment Watchlist'!$AP$9:$AP$158,3),'Investment Watchlist'!$AP$9:$AP$158,0)),"") -> 21 | L18: =IFERROR(INDEX('Investment Watchlist'!$AG$9:$AG$158,MATCH(LARGE('Investment Watchlist'!$AP$9:$AP$158,3),'Investment Watchlist'!$AP$9:$AP$158,0)),"") -> A | M18: =IFERROR(INDEX('Investment Watchlist'!$AH$9:$AH$158,MATCH(LARGE('Investment Watchlist'!$AP$9:$AP$158,3),'Investment Watchlist'!$AP$9:$AP$158,0)),"") -> Full LRC Stock Analysis
A19: 4 | B19: =IFERROR(INDEX('Swing Watchlist'!$C$11:$C$210,MATCH(LARGE('Swing Watchlist'!$AX$11:$AX$210,4),'Swing Watchlist'!$AX$11:$AX$210,0)),"") -> GOOGL | C19: =IFERROR(IF(INDEX('Swing Watchlist'!$F$11:$F$210,MATCH(LARGE('Swing Watchlist'!$AX$11:$AX$210,4),'Swing Watchlist'!$AX$11:$AX$210,0))="Short","Short","Long"),"") -> Short | D19: =IFERROR(INDEX('Swing Watchlist'!$AJ$11:$AJ$210,MATCH(LARGE('Swing Watchlist'!$AX$11:$AX$210,4),'Swing Watchlist'!$AX$11:$AX$210,0)),"") -> 11 | E19: =IFERROR(INDEX('Swing Watchlist'!$AK$11:$AK$210,MATCH(LARGE('Swing Watchlist'!$AX$11:$AX$210,4),'Swing Watchlist'!$AX$11:$AX$210,0)),"") -> B | F19: =IFERROR(INDEX('Swing Watchlist'!$AU$11:$AU$210,MATCH(LARGE('Swing Watchlist'!$AX$11:$AX$210,4),'Swing Watchlist'!$AX$11:$AX$210,0)),"") -> Watch — wait for setup | H19: 4 | I19: =IFERROR(INDEX('Investment Watchlist'!$C$9:$C$158,MATCH(LARGE('Investment Watchlist'!$AP$9:$AP$158,4),'Investment Watchlist'!$AP$9:$AP$158,0)),"") -> PCTY | J19: =IFERROR(INDEX('Investment Watchlist'!$B$9:$B$158,MATCH(LARGE('Investment Watchlist'!$AP$9:$AP$158,4),'Investment Watchlist'!$AP$9:$AP$158,0)),"") -> US | K19: =IFERROR(INDEX('Investment Watchlist'!$AF$9:$AF$158,MATCH(LARGE('Investment Watchlist'!$AP$9:$AP$158,4),'Investment Watchlist'!$AP$9:$AP$158,0)),"") -> 20 | L19: =IFERROR(INDEX('Investment Watchlist'!$AG$9:$AG$158,MATCH(LARGE('Investment Watchlist'!$AP$9:$AP$158,4),'Investment Watchlist'!$AP$9:$AP$158,0)),"") -> A | M19: =IFERROR(INDEX('Investment Watchlist'!$AH$9:$AH$158,MATCH(LARGE('Investment Watchlist'!$AP$9:$AP$158,4),'Investment Watchlist'!$AP$9:$AP$158,0)),"") -> Full LRC Stock Analysis
A20: 5 | B20: =IFERROR(INDEX('Swing Watchlist'!$C$11:$C$210,MATCH(LARGE('Swing Watchlist'!$AX$11:$AX$210,5),'Swing Watchlist'!$AX$11:$AX$210,0)),"") -> ANET | C20: =IFERROR(IF(INDEX('Swing Watchlist'!$F$11:$F$210,MATCH(LARGE('Swing Watchlist'!$AX$11:$AX$210,5),'Swing Watchlist'!$AX$11:$AX$210,0))="Short","Short","Long"),"") -> Short | D20: =IFERROR(INDEX('Swing Watchlist'!$AJ$11:$AJ$210,MATCH(LARGE('Swing Watchlist'!$AX$11:$AX$210,5),'Swing Watchlist'!$AX$11:$AX$210,0)),"") -> 10 | E20: =IFERROR(INDEX('Swing Watchlist'!$AK$11:$AK$210,MATCH(LARGE('Swing Watchlist'!$AX$11:$AX$210,5),'Swing Watchlist'!$AX$11:$AX$210,0)),"") -> B | F20: =IFERROR(INDEX('Swing Watchlist'!$AU$11:$AU$210,MATCH(LARGE('Swing Watchlist'!$AX$11:$AX$210,5),'Swing Watchlist'!$AX$11:$AX$210,0)),"") -> Watch — wait for setup | H20: 5 | I20: =IFERROR(INDEX('Investment Watchlist'!$C$9:$C$158,MATCH(LARGE('Investment Watchlist'!$AP$9:$AP$158,5),'Investment Watchlist'!$AP$9:$AP$158,0)),"") -> META | J20: =IFERROR(INDEX('Investment Watchlist'!$B$9:$B$158,MATCH(LARGE('Investment Watchlist'!$AP$9:$AP$158,5),'Investment Watchlist'!$AP$9:$AP$158,0)),"") -> US | K20: =IFERROR(INDEX('Investment Watchlist'!$AF$9:$AF$158,MATCH(LARGE('Investment Watchlist'!$AP$9:$AP$158,5),'Investment Watchlist'!$AP$9:$AP$158,0)),"") -> 18 | L20: =IFERROR(INDEX('Investment Watchlist'!$AG$9:$AG$158,MATCH(LARGE('Investment Watchlist'!$AP$9:$AP$158,5),'Investment Watchlist'!$AP$9:$AP$158,0)),"") -> A | M20: =IFERROR(INDEX('Investment Watchlist'!$AH$9:$AH$158,MATCH(LARGE('Investment Watchlist'!$AP$9:$AP$158,5),'Investment Watchlist'!$AP$9:$AP$158,0)),"") -> Full LRC Stock Analysis

Sheet How to Pick — Swing
C1: Swing trades — LONG and SHORT (hold 3–6 months)
A2: Goal: buy strong stocks in uptrends (Long) and sell weak stocks in downtrends (Short), each at a low-risk point with a stop and a target. Target: at least 5 new candidates a week, any mix of long/short, US and JSE.
A4: Step-by-step (about 60–90 minutes)
A5: 1. Check the market (5 min) | B5: Is the S&P 500 above its 200-day average? Is the JSE All Share above its 200-day average? Both above = RISK-ON: mostly longs. Both below = RISK-OFF: mostly shorts. One of each = MIXED: both, smaller sizes. Record it on the Weekly Review tab — it tells you which way to lean.
A6: 2. Run BOTH screens (15 min) | B6: Run the LONG preset and the SHORT preset on the 'Screener Settings' tab — Finviz for US, TradingView for JSE. Save all four as presets so it's one click next week.
A7: 3. Sort and shortlist (15 min) | B7: LONGS: sort by 'Perf Half' highest first; keep clean uptrends (higher highs, higher lows, price above a rising 50-day). SHORTS: sort by 'Perf Half' lowest first; keep clean downtrends (lower highs, lower lows, price below a falling 50-day).
A8: 4. Find the setup (20 min) | B8: LONG setups: breakout from a base · pullback to the 20/50-day in an uptrend · trend continuation · earnings gap up that holds. SHORT setups: breakdown below support · rally into a falling 50-day that fails · downtrend continuation · earnings gap down that holds. No clear setup = Watch.
A9: 5. Plan the trade (10 min) | B9: LONG: entry above the trigger, stop BELOW (last swing low or ~2×ATR), target ABOVE. SHORT: entry below the trigger, stop ABOVE (last swing high or ~2×ATR), target BELOW (next support). Reward:risk under 2x = skip. The sheet flags a stop on the wrong side.
A10: 6. Enter in the sheet (10 min) | B10: Add at least 5 candidates on 'Swing Watchlist' with this week's date and set Direction = Long or Short. Paste the screener numbers — the score flips automatically for shorts. A = run the Technical Review (reversed for shorts) and get clearance; B = watch; C = drop.
A11: 7. Review what you hold (10 min) | B11: Update 'Price now' on every 'Open position' and read the Review signal. Long: SELL if stop hit. Short: COVER (buy back) if stop hit. Both: TAKE PROFIT at target; REVIEW if the trend breaks (long below / short above the 50-day) or no progress after 6 weeks; exit at 6 months.
A12: What the scores mean (Long ↔ Short)
A13: Trend /4 | B13: LONG: +1 each for price above the 20-, 50- and 200-day averages, and 50-day above 200-day. SHORT: +1 each for price BELOW them, and 50-day BELOW 200-day.
A14: Momentum /4 | B14: LONG: RSI 50–70 = 2 (40–50 or 70–75 = 1); 6-month performance beats the index = 2 (positive = 1). SHORT: RSI 30–50 = 2 (25–30 or 50–60 = 1); 6-month performance lags the index = 2 (negative = 1).
A15: Range position /2 | B15: LONG: within 10% of the 52-week HIGH = 2 (25% = 1) — leaders trade near highs. SHORT: within 10% of the 52-week LOW = 2 (25% = 1) — laggards trade near lows.
A16: Liquidity /2 | B16: Average daily value above the minimum in settings = 2; above a quarter of it = 1. Applies to both — shorts especially need liquidity.
A17: Fuel /2 | B17: LONG: earnings growing this year = 1. SHORT: earnings shrinking = 1. Both: relative volume 1.5x+ = 1.
A18: Reward:risk /4 | B18: 3x or better = 4; 2x–3x = 2; below 2x = 0. Fill entry, stop and target first (works both ways).
A19: Event risk | B19: −2 if results are due within 14 days of the review date — gap risk either way.
A20: Squeeze risk (shorts) | B20: −1 if short float is 20%+. Heavily shorted stocks can jump violently when shorts rush to buy back.
A21: Grades | B21: A = 14+ out of 18 · B = 10–13 · C = under 10. Same scale for longs and shorts.
A22: Why fundamentals matter in swing trading
A23: The short answer | B23: Price and trend tell you WHEN; fundamentals tell you WHY. Over 3–12 months a stock usually follows its earnings: big funds buy companies whose profits and sales are accelerating and sell the ones that are slowing. The longer you hold, the more fundamentals matter.
A24: What to look at (long) | B24: Latest quarter EPS growth 15%+ and sales growth 10%+ (versus a year ago), earnings beating forecasts, profit margins steady or rising. Avoid longs with falling sales even if the chart looks good.
A25: What to look at (short) | B25: Falling EPS and sales, earnings misses, margins shrinking, high debt. The best shorts are weak businesses in downtrends — not good businesses that dipped.
A26: What NOT to do | B26: Don't use deep valuation (P/E, DCF) to time swing trades — expensive stocks can keep rising and cheap ones keep falling for months. Valuation belongs to the investment track and the LRC Stock Analysis Template.
A27: Short-selling basics
A28: How a short works | B28: You sell first and buy back later. You profit if the price FALLS. P/L in the sheet = 1 − price now ÷ entry. Losses grow if the price RISES, and in theory have no ceiling — so the stop is not optional.
A29: How to short | B29: US: shares marked 'Shortable' at your broker, or CFDs. JSE: CFDs (or single-stock futures) — normal JSE share accounts can't short. Check borrow fees and dividends: a short pays the dividend.
A30: When to avoid shorts | B30: Short float above 20%, a takeover rumour, results within 2 weeks, or a strong RISK-ON market. Never short just because a stock 'looks expensive'.
A31: Rules that keep you safe
A32: Risk | B32: Never risk more than 1% of the account on one trade (the sheet sizes it). Never move a stop AGAINST you: not down on a long, not up on a short.
A33: Concentration | B33: No more than 2 open trades in the same sector, no more than 8 open swing trades, and no more than 4 shorts at once.
A34: Leverage | B34: On a margin account or CFD, size by the risk amount, not by the margin available.
A35: Discipline | B35: Write the plan before you trade. If the price never reaches the entry, there is no trade.

Sheet Swing Watchlist
C1: Swing Watchlist — weekly, LONG and SHORT (hold 3 to 6 months)
A2: Every week add at least 5 candidates — buys (Long) or sells/shorts (Short), US and JSE. Choose the Direction first: scores, reward:risk, position size, P/L and the review signal all follow it. Type percentages with the % sign.
A4: Current review week ending | C4: 46316 | D4: Saturday of the review week. Counts and the Top 5 use this date. | J4: S&P 500 6-month performance | L4: 0.1437 | M4: Benchmark for relative strength (Finviz: SPY 'Perf Half'). | S4: This week's candidates | U4: =COUNTIFS($A$11:$A$210,$C$4,$C$11:$C$210,"?*") -> 13 | V4: =IF(U4>=$C$5,"✔ minimum met","⚠ need "&($C$5-U4)&" more") -> ✔ minimum met
A5: Minimum new candidates per week | C5: 5 | D5: House rule (longs + shorts together). | J5: JSE All Share 6-month performance | L5: -0.0744 | M5: JSE All Share 6-month: 13 Oct 2026 vs 9 Apr 2026 (−7.4%). No JSE names this week. | S5: US / JSE this week | U5: =COUNTIFS($A$11:$A$210,$C$4,$B$11:$B$210,"US")&" / "&COUNTIFS($A$11:$A$210,$C$4,$B$11:$B$210,"JSE") -> 13 / 0
A6: Trading account size (base currency) | C6: 45.78 | D6: Est. broker equity 14 Oct ($45.78 = 48.66 + ΔUPNL − Δswap vs 3 Oct export) — replace with the broker figure. For position sizing. | J6: Liquidity: min avg daily value — US (millions $) | L6: 20 | M6: $20m+ a day trades easily. | S6: Long / Short this week | U6: =COUNTIFS($A$11:$A$210,$C$4,$C$11:$C$210,"?*",$F$11:$F$210,"<>Short")&" / "&COUNTIFS($A$11:$A$210,$C$4,$F$11:$F$210,"Short") -> 3 / 10
A7: Risk per trade (% of account) | C7: 0.01 | D7: 1% means a stop-out loses 1% of the account. | J7: Liquidity: min avg daily value — JSE (millions R) | L7: 20 | M7: R20m+ a day; smaller JSE shares are hard to exit. | S7: A-grades / open positions | U7: =COUNTIFS($A$11:$A$210,$C$4,$AK$11:$AK$210,"A")&" / "&COUNTIF($AP$11:$AP$210,"Open position") -> 0 / 0
A9: INPUTS FROM FINVIZ / TRADINGVIEW + YOUR TRADE PLAN | AB9: SCORE (automatic — follows Direction) | AL9: PLAN & POSITION SIZE | AP9: STATUS & MONITORING
A10: Week ending | B10: Market | C10: Ticker | D10: Company | E10: Sector | F10: Direction | G10: Price | H10: Mkt cap (bn) | I10: Avg volume (shares) | J10: Avg daily value (m) | K10: vs SMA20 | L10: vs SMA50 | M10: vs SMA200 | N10: RSI (14) | O10: Perf Quarter | P10: Perf Half | Q10: From 52W High | R10: From 52W Low | S10: Rel Volume | T10: EPS growth this yr | U10: Short float | V10: Next earnings | W10: ATR (14) | X10: Setup | Y10: Entry | Z10: Stop | AA10: Target | AB10: Trend /4 | AC10: Momentum /4 | AD10: Range position /2 | AE10: Liquidity /2 | AF10: Fuel /2 | AG10: Reward:risk /4 | AH10: Event risk | AI10: Squeeze risk | AJ10: SCORE /18 | AK10: Grade | AL10: Reward : risk | AM10: Risk / share | AN10: Position size (shares) | AO10: Position value | AP10: Status | AQ10: Entry date | AR10: Price now | AS10: P/L % | AT10: Days held | AU10: Review signal | AV10: Notes / chart
A11: 46298 | B11: US | C11: PCTY | D11: Paylocity Holding Corporation | E11: Technology | F11: Long | G11: 144.47 | H11: 7.67 | I11: 681700 | J11: =IF(OR(G11="",I11=""),"",G11*I11/1000000) -> 98.485199 | K11: -0.0016 | L11: -0.0137 | M11: 0.1551 | N11: 48.5 | O11: 0.2552 | P11: 0.3611 | Q11: -0.1078 | R11: 0.5536 | S11: 0.79 | T11: 0.0511 | U11: 0.0651 | V11: 46329 | W11: 4.15 | X11: LONG: Pullback to 20/50-day avg | Y11: 149 | Z11: 140.7 | AA11: 173.95 | AB11: =IF(C11="","",IF(F11="Short",(AND(M11<>"",N(M11)<0))+(AND(L11<>"",N(L11)<0))+(AND(K11<>"",N(K11)<0))+AND(L11<>"",M11<>"",N(M11)<N(L11)),(N(M11)>0)+(N(L11)>0)+(N(K11)>0)+AND(L11<>"",M11<>"",N(M11)>N(L11)))) -> 2 | AC11: =IF(C11="","",IF(F11="Short",IF(N11="",0,IF(AND(N11>=30,N11<=50),2,IF(OR(AND(N11>=25,N11<30),AND(N11>50,N11<=60)),1,0)))+IF(P11="",0,IF(AND(IF(B11="JSE",$L$5,$L$4)<>"",P11<IF(B11="JSE",$L$5,$L$4)),2,IF(P11<0,1,0))),IF(N11="",0,IF(AND(N11>=50,N11<=70),2,IF(OR(AND(N11>=40,N11<50),AND(N11>70,N11<=75)),1,0)))+IF(P11="",0,IF(AND(IF(B11="JSE",$L$5,$L$4)<>"",P11>IF(B11="JSE",$L$5,$L$4)),2,IF(P11>0,1,0))))) -> 3 | AD11: =IF(C11="","",IF(F11="Short",IF(R11="",0,IF(R11<=0.1,2,IF(R11<=0.25,1,0))),IF(Q11="",0,IF(Q11>=-0.1,2,IF(Q11>=-0.25,1,0))))) -> 1 | AE11: =IF(C11="","",IF(J11="",0,IF(J11>=IF(B11="JSE",$L$7,$L$6),2,IF(J11>=IF(B11="JSE",$L$7,$L$6)/4,1,0)))) -> 2 | AF11: =IF(C11="","",IF(F11="Short",AND(T11<>"",N(T11)<0),N(T11)>0)+(N(S11)>=1.5)) -> 1 | AG11: =IF(C11="","",IF(AL11="",0,IF(AL11>=3,4,IF(AL11>=2,2,0)))) -> 4 | AH11: =IF(C11="","",IF(AND(ISNUMBER(V11),ISNUMBER(A11),V11>=A11,V11-A11<=14),-2,0)) -> 0 | AI11: =IF(C11="","",IF(AND(F11="Short",N(U11)>=0.2),-1,0)) -> 0 | AJ11: =IF(C11="","",SUM(AB11:AI11)) -> 13 | AK11: =IF(C11="","",IF(AJ11>=14,"A",IF(AJ11>=10,"B","C"))) -> B | AL11: =IFERROR(IF(OR(Y11="",Z11="",AA11=""),"",IF(F11="Short",IF(Z11<=Y11,"",(Y11-AA11)/(Z11-Y11)),IF(Y11<=Z11,"",(AA11-Y11)/(Y11-Z11)))),"") -> 3.0060241 | AM11: =IF(OR(Y11="",Z11="",N(Y11)=N(Z11)),"",IF(OR(AND(F11="Short",Z11<Y11),AND(NOT(F11="Short"),Z11>Y11)),"stop on wrong side",ABS(Y11-Z11))) -> 8.3 | AN11: =IFERROR(IF(OR(NOT(ISNUMBER(AM11)),$C$6=""),"",ROUNDDOWN($C$6*$C$7/AM11,2)),"") -> 0.05 | AO11: =IFERROR(IF(AN11="","",AN11*Y11),"") -> 7.45 | AP11: Dropped | AS11: =IFERROR(IF(OR(AR11="",Y11="",AQ11=""),"",IF(F11="Short",1-AR11/Y11,AR11/Y11-1)),"") | AT11: =IF(AQ11="","",IF(ISNUMBER($C$4),$C$4,TODAY())-AQ11) | AU11: =IF(C11="","",IF(AP11="Open position",IF(IF(F11="Short",AND(ISNUMBER(AR11),ISNUMBER(Z11),AR11>=Z11),AND(ISNUMBER(AR11),ISNUMBER(Z11),AR11<=Z11)),IF(F11="Short","COVER — stop hit (buy back)","SELL — stop hit"),IF(IF(F11="Short",AND(ISNUMBER(AR11),ISNUMBER(AA11),AR11<=AA11),AND(ISNUMBER(AR11),ISNUMBER(AA11),AR11>=AA11)),"TAKE PROFIT — target hit",IF(AND(ISNUMBER(AT11),AT11>182),IF(F11="Short","COVER — 6-month time limit","SELL — 6-month time limit"),IF(AND(ISNUMBER(AT11),AT11>42,ISNUMBER(AS11),AS11<0.02),"REVIEW — no progress after 6 weeks",IF(IF(F11="Short",AND(L11<>"",N(L11)>0),AND(L11<>"",N(L11)<0)),IF(F11="Short","REVIEW — back above 50-day avg","REVIEW — below 50-day avg"),"HOLD"))))),IF(OR(AP11="Closed",AP11="Dropped"),"Closed",IF(AK11="A",IF(F11="Short","Run Technical Review — SHORT entry","Run Technical Review — LONG entry"),IF(AK11="B","Watch — wait for setup","Drop or re-check next week"))))) -> Closed | AV11: Trigger: Break above the 1 Oct high (148.57) and the 50-day (146.5). Long entry 149.00, stop 140.70 (2×ATR), target 173.95 (R:R 3.0). LRC Work-sheet 6-m rating: BUY (6-m target ~$163, +13%). BUY rating + technical clearance (staged entry) in the LRC Work-sheet. Fundamentals and trend agree. First profit-taking at the 6-m target ~$163; full target in the bull-case zone. Data: Yahoo Finance OHLCV to 2 Oct 2026 (SMA20, ATR14, rel. volume computed); SMA50/200, RSI, short float, earnings date: stockanalysis.com; EPS growth this yr = consensus current FY (adjusted). — P. Nkuna || 14 Oct update: trigger 149.00 was hit (~8 Oct) but the trade was NOT entered (not in the 14 Oct broker export). Price now $158.11 = our 6-m target; Work-sheet re-rated BUY → HOLD (target ~$157, −1%). No new entry; re-add below ~$146. — P. Nkuna | AX11: =IF(AND(C11<>"",A11=$C$4,ISNUMBER(AJ11)),AJ11+ROW()/100000,"")
A12: 46298 | B12: US | C12: WAB | D12: Westinghouse Air Brake Technologies Corporation (Wabtec) | E12: Industrials | F12: Short | G12: 287.54 | H12: 48.57 | I12: 769100 | J12: =IF(OR(G12="",I12=""),"",G12*I12/1000000) -> 221.14701 | K12: 0.0102 | L12: -0.0105 | M12: 0.0996 | N12: 51.1 | O12: 0.0967 | P12: 0.1324 | Q12: -0.0623 | R12: 0.5454 | S12: 1.19 | T12: 0.2114 | U12: 0.0215 | V12: 46316 | W12: 5.73 | X12: SHORT: Breakdown from base | Y12: 272.9 | Z12: 284.35 | AA12: 238.5 | AB12: =IF(C12="","",IF(F12="Short",(AND(M12<>"",N(M12)<0))+(AND(L12<>"",N(L12)<0))+(AND(K12<>"",N(K12)<0))+AND(L12<>"",M12<>"",N(M12)<N(L12)),(N(M12)>0)+(N(L12)>0)+(N(K12)>0)+AND(L12<>"",M12<>"",N(M12)>N(L12)))) -> 1 | AC12: =IF(C12="","",IF(F12="Short",IF(N12="",0,IF(AND(N12>=30,N12<=50),2,IF(OR(AND(N12>=25,N12<30),AND(N12>50,N12<=60)),1,0)))+IF(P12="",0,IF(AND(IF(B12="JSE",$L$5,$L$4)<>"",P12<IF(B12="JSE",$L$5,$L$4)),2,IF(P12<0,1,0))),IF(N12="",0,IF(AND(N12>=50,N12<=70),2,IF(OR(AND(N12>=40,N12<50),AND(N12>70,N12<=75)),1,0)))+IF(P12="",0,IF(AND(IF(B12="JSE",$L$5,$L$4)<>"",P12>IF(B12="JSE",$L$5,$L$4)),2,IF(P12>0,1,0))))) -> 3 | AD12: =IF(C12="","",IF(F12="Short",IF(R12="",0,IF(R12<=0.1,2,IF(R12<=0.25,1,0))),IF(Q12="",0,IF(Q12>=-0.1,2,IF(Q12>=-0.25,1,0))))) -> 0 | AE12: =IF(C12="","",IF(J12="",0,IF(J12>=IF(B12="JSE",$L$7,$L$6),2,IF(J12>=IF(B12="JSE",$L$7,$L$6)/4,1,0)))) -> 2 | AF12: =IF(C12="","",IF(F12="Short",AND(T12<>"",N(T12)<0),N(T12)>0)+(N(S12)>=1.5)) -> 0 | AG12: =IF(C12="","",IF(AL12="",0,IF(AL12>=3,4,IF(AL12>=2,2,0)))) -> 4 | AH12: =IF(C12="","",IF(AND(ISNUMBER(V12),ISNUMBER(A12),V12>=A12,V12-A12<=14),-2,0)) -> 0 | AI12: =IF(C12="","",IF(AND(F12="Short",N(U12)>=0.2),-1,0)) -> 0 | AJ12: =IF(C12="","",SUM(AB12:AI12)) -> 10 | AK12: =IF(C12="","",IF(AJ12>=14,"A",IF(AJ12>=10,"B","C"))) -> B | AL12: =IFERROR(IF(OR(Y12="",Z12="",AA12=""),"",IF(F12="Short",IF(Z12<=Y12,"",(Y12-AA12)/(Z12-Y12)),IF(Y12<=Z12,"",(AA12-Y12)/(Y12-Z12)))),"") -> 3.0043668 | AM12: =IF(OR(Y12="",Z12="",N(Y12)=N(Z12)),"",IF(OR(AND(F12="Short",Z12<Y12),AND(NOT(F12="Short"),Z12>Y12)),"stop on wrong side",ABS(Y12-Z12))) -> 11.45 | AN12: =IFERROR(IF(OR(NOT(ISNUMBER(AM12)),$C$6=""),"",ROUNDDOWN($C$6*$C$7/AM12,2)),"") -> 0.03 | AO12: =IFERROR(IF(AN12="","",AN12*Y12),"") -> 8.187 | AP12: Watch | AS12: =IFERROR(IF(OR(AR12="",Y12="",AQ12=""),"",IF(F12="Short",1-AR12/Y12,AR12/Y12-1)),"") | AT12: =IF(AQ12="","",IF(ISNUMBER($C$4),$C$4,TODAY())-AQ12) | AU12: =IF(C12="","",IF(AP12="Open position",IF(IF(F12="Short",AND(ISNUMBER(AR12),ISNUMBER(Z12),AR12>=Z12),AND(ISNUMBER(AR12),ISNUMBER(Z12),AR12<=Z12)),IF(F12="Short","COVER — stop hit (buy back)","SELL — stop hit"),IF(IF(F12="Short",AND(ISNUMBER(AR12),ISNUMBER(AA12),AR12<=AA12),AND(ISNUMBER(AR12),ISNUMBER(AA12),AR12>=AA12)),"TAKE PROFIT — target hit",IF(AND(ISNUMBER(AT12),AT12>182),IF(F12="Short","COVER — 6-month time limit","SELL — 6-month time limit"),IF(AND(ISNUMBER(AT12),AT12>42,ISNUMBER(AS12),AS12<0.02),"REVIEW — no progress after 6 weeks",IF(IF(F12="Short",AND(L12<>"",N(L12)>0),AND(L12<>"",N(L12)<0)),IF(F12="Short","REVIEW — back above 50-day avg","REVIEW — below 50-day avg"),"HOLD"))))),IF(OR(AP12="Closed",AP12="Dropped"),"Closed",IF(AK12="A",IF(F12="Short","Run Technical Review — SHORT entry","Run Technical Review — LONG entry"),IF(AK12="B","Watch — wait for setup","Drop or re-check next week"))))) -> Watch — wait for setup | AV12: Trigger: Sell stop below the 16 Sep swing low (273.01) — confirms the uptrend has broken. Short entry 272.90, stop 284.35 (2×ATR), target 238.50 (R:R 3.0). LRC Work-sheet 6-m rating: SELL (~$242, -16%). SELL rating + technical clearance in the LRC Work-sheet. Short only on a confirmed breakdown: the stock is still in an uptrend (above 200-day), so the trend score is low until it breaks. Target ~238 ≈ fundamental target $242. Results 21 Oct. Data: Yahoo Finance OHLCV to 2 Oct 2026 (SMA20, ATR14, rel. volume computed); SMA50/200, RSI, short float, earnings date: stockanalysis.com; EPS growth this yr = consensus current FY (adjusted). — P. Nkuna || 14 Oct update: still SELL (6-m target ~$248, −13%) + technically cleared. Price $286.51 is 5% above the 272.90 trigger — not triggered. Results 21 Oct inside 14 days: no new short before the print. Keep last week's levels; re-plan after results. — P. Nkuna | AX12: =IF(AND(C12<>"",A12=$C$4,ISNUMBER(AJ12)),AJ12+ROW()/100000,"")
A13: 46298 | B13: US | C13: ANET | D13: Arista Networks, Inc. | E13: Technology | F13: Short | G13: 207.35 | H13: 260.9 | I13: 4650000 | J13: =IF(OR(G13="",I13=""),"",G13*I13/1000000) -> 964.1775 | K13: 0.0376 | L13: 0.0684 | M13: 0.3015 | N13: 59.5 | O13: 0.296 | P13: 0.6368 | Q13: -0.0351 | R13: 0.8106 | S13: 0.89 | T13: 0.3799 | U13: 0.0126 | V13: 46329 | W13: 6.34 | X13: SHORT: Breakdown from base | Y13: 186 | Z13: 198.67 | AA13: 147.99 | AB13: =IF(C13="","",IF(F13="Short",(AND(M13<>"",N(M13)<0))+(AND(L13<>"",N(L13)<0))+(AND(K13<>"",N(K13)<0))+AND(L13<>"",M13<>"",N(M13)<N(L13)),(N(M13)>0)+(N(L13)>0)+(N(K13)>0)+AND(L13<>"",M13<>"",N(M13)>N(L13)))) -> 0 | AC13: =IF(C13="","",IF(F13="Short",IF(N13="",0,IF(AND(N13>=30,N13<=50),2,IF(OR(AND(N13>=25,N13<30),AND(N13>50,N13<=60)),1,0)))+IF(P13="",0,IF(AND(IF(B13="JSE",$L$5,$L$4)<>"",P13<IF(B13="JSE",$L$5,$L$4)),2,IF(P13<0,1,0))),IF(N13="",0,IF(AND(N13>=50,N13<=70),2,IF(OR(AND(N13>=40,N13<50),AND(N13>70,N13<=75)),1,0)))+IF(P13="",0,IF(AND(IF(B13="JSE",$L$5,$L$4)<>"",P13>IF(B13="JSE",$L$5,$L$4)),2,IF(P13>0,1,0))))) -> 1 | AD13: =IF(C13="","",IF(F13="Short",IF(R13="",0,IF(R13<=0.1,2,IF(R13<=0.25,1,0))),IF(Q13="",0,IF(Q13>=-0.1,2,IF(Q13>=-0.25,1,0))))) -> 0 | AE13: =IF(C13="","",IF(J13="",0,IF(J13>=IF(B13="JSE",$L$7,$L$6),2,IF(J13>=IF(B13="JSE",$L$7,$L$6)/4,1,0)))) -> 2 | AF13: =IF(C13="","",IF(F13="Short",AND(T13<>"",N(T13)<0),N(T13)>0)+(N(S13)>=1.5)) -> 0 | AG13: =IF(C13="","",IF(AL13="",0,IF(AL13>=3,4,IF(AL13>=2,2,0)))) -> 4 | AH13: =IF(C13="","",IF(AND(ISNUMBER(V13),ISNUMBER(A13),V13>=A13,V13-A13<=14),-2,0)) -> 0 | AI13: =IF(C13="","",IF(AND(F13="Short",N(U13)>=0.2),-1,0)) -> 0 | AJ13: =IF(C13="","",SUM(AB13:AI13)) -> 7 | AK13: =IF(C13="","",IF(AJ13>=14,"A",IF(AJ13>=10,"B","C"))) -> C | AL13: =IFERROR(IF(OR(Y13="",Z13="",AA13=""),"",IF(F13="Short",IF(Z13<=Y13,"",(Y13-AA13)/(Z13-Y13)),IF(Y13<=Z13,"",(AA13-Y13)/(Y13-Z13)))),"") -> 3 | AM13: =IF(OR(Y13="",Z13="",N(Y13)=N(Z13)),"",IF(OR(AND(F13="Short",Z13<Y13),AND(NOT(F13="Short"),Z13>Y13)),"stop on wrong side",ABS(Y13-Z13))) -> 12.67 | AN13: =IFERROR(IF(OR(NOT(ISNUMBER(AM13)),$C$6=""),"",ROUNDDOWN($C$6*$C$7/AM13,2)),"") -> 0.03 | AO13: =IFERROR(IF(AN13="","",AN13*Y13),"") -> 5.58 | AP13: Dropped | AS13: =IFERROR(IF(OR(AR13="",Y13="",AQ13=""),"",IF(F13="Short",1-AR13/Y13,AR13/Y13-1)),"") | AT13: =IF(AQ13="","",IF(ISNUMBER($C$4),$C$4,TODAY())-AQ13) | AU13: =IF(C13="","",IF(AP13="Open position",IF(IF(F13="Short",AND(ISNUMBER(AR13),ISNUMBER(Z13),AR13>=Z13),AND(ISNUMBER(AR13),ISNUMBER(Z13),AR13<=Z13)),IF(F13="Short","COVER — stop hit (buy back)","SELL — stop hit"),IF(IF(F13="Short",AND(ISNUMBER(AR13),ISNUMBER(AA13),AR13<=AA13),AND(ISNUMBER(AR13),ISNUMBER(AA13),AR13>=AA13)),"TAKE PROFIT — target hit",IF(AND(ISNUMBER(AT13),AT13>182),IF(F13="Short","COVER — 6-month time limit","SELL — 6-month time limit"),IF(AND(ISNUMBER(AT13),AT13>42,ISNUMBER(AS13),AS13<0.02),"REVIEW — no progress after 6 weeks",IF(IF(F13="Short",AND(L13<>"",N(L13)>0),AND(L13<>"",N(L13)<0)),IF(F13="Short","REVIEW — back above 50-day avg","REVIEW — below 50-day avg"),"HOLD"))))),IF(OR(AP13="Closed",AP13="Dropped"),"Closed",IF(AK13="A",IF(F13="Short","Run Technical Review — SHORT entry","Run Technical Review — LONG entry"),IF(AK13="B","Watch — wait for setup","Drop or re-check next week"))))) -> Closed | AV13: Trigger: Sell stop below the 14 Sep swing low (186.11) and the 50-day (194). Short entry 186.00, stop 198.67 (2×ATR), target 147.99 (R:R 3.0). LRC Work-sheet 6-m rating: SELL (~$144, -30%). SELL rating + technical clearance in the LRC Work-sheet. Short only on a confirmed breakdown below 186; today it is the strongest trend on our list (+64% in 6 months) — do NOT short strength. Target ~148 ≈ fundamental target $144. High beta (1.6): small size. Data: Yahoo Finance OHLCV to 2 Oct 2026 (SMA20, ATR14, rel. volume computed); SMA50/200, RSI, short float, earnings date: stockanalysis.com; EPS growth this yr = consensus current FY (adjusted). — P. Nkuna || 14 Oct update: replaced by a new ANET row this week (trigger 197.40, stop 211.02, target 156.54). Old trigger 186 not hit. — P. Nkuna | AX13: =IF(AND(C13<>"",A13=$C$4,ISNUMBER(AJ13)),AJ13+ROW()/100000,"")
A14: 46312 | B14: US | C14: NVDA | D14: NVIDIA Corporation | E14: Technology | F14: Long | G14: 228.52 | H14: 5520 | I14: 105231900 | J14: =IF(OR(G14="",I14=""),"",G14*I14/1000000) -> 24047.594 | K14: 0.0009 | L14: 0.0246 | M14: 0.1283 | N14: 52 | P14: 0.2071 | Q14: -0.061 | R14: 0.3911 | S14: 0.8 | T14: 0.9523 | U14: 0.0134 | V14: 46344 | W14: 5.31 | X14: LONG: Pullback to 20/50-day avg | Y14: 229.3 | Z14: 218.68 | AA14: 261.16 | AB14: =IF(C14="","",IF(F14="Short",(AND(M14<>"",N(M14)<0))+(AND(L14<>"",N(L14)<0))+(AND(K14<>"",N(K14)<0))+AND(L14<>"",M14<>"",N(M14)<N(L14)),(N(M14)>0)+(N(L14)>0)+(N(K14)>0)+AND(L14<>"",M14<>"",N(M14)>N(L14)))) -> 4 | AC14: =IF(C14="","",IF(F14="Short",IF(N14="",0,IF(AND(N14>=30,N14<=50),2,IF(OR(AND(N14>=25,N14<30),AND(N14>50,N14<=60)),1,0)))+IF(P14="",0,IF(AND(IF(B14="JSE",$L$5,$L$4)<>"",P14<IF(B14="JSE",$L$5,$L$4)),2,IF(P14<0,1,0))),IF(N14="",0,IF(AND(N14>=50,N14<=70),2,IF(OR(AND(N14>=40,N14<50),AND(N14>70,N14<=75)),1,0)))+IF(P14="",0,IF(AND(IF(B14="JSE",$L$5,$L$4)<>"",P14>IF(B14="JSE",$L$5,$L$4)),2,IF(P14>0,1,0))))) -> 4 | AD14: =IF(C14="","",IF(F14="Short",IF(R14="",0,IF(R14<=0.1,2,IF(R14<=0.25,1,0))),IF(Q14="",0,IF(Q14>=-0.1,2,IF(Q14>=-0.25,1,0))))) -> 2 | AE14: =IF(C14="","",IF(J14="",0,IF(J14>=IF(B14="JSE",$L$7,$L$6),2,IF(J14>=IF(B14="JSE",$L$7,$L$6)/4,1,0)))) -> 2 | AF14: =IF(C14="","",IF(F14="Short",AND(T14<>"",N(T14)<0),N(T14)>0)+(N(S14)>=1.5)) -> 1 | AG14: =IF(C14="","",IF(AL14="",0,IF(AL14>=3,4,IF(AL14>=2,2,0)))) -> 4 | AH14: =IF(C14="","",IF(AND(ISNUMBER(V14),ISNUMBER(A14),V14>=A14,V14-A14<=14),-2,0)) -> 0 | AI14: =IF(C14="","",IF(AND(F14="Short",N(U14)>=0.2),-1,0)) -> 0 | AJ14: =IF(C14="","",SUM(AB14:AI14)) -> 17 | AK14: =IF(C14="","",IF(AJ14>=14,"A",IF(AJ14>=10,"B","C"))) -> A | AL14: =IFERROR(IF(OR(Y14="",Z14="",AA14=""),"",IF(F14="Short",IF(Z14<=Y14,"",(Y14-AA14)/(Z14-Y14)),IF(Y14<=Z14,"",(AA14-Y14)/(Y14-Z14)))),"") -> 3 | AM14: =IF(OR(Y14="",Z14="",N(Y14)=N(Z14)),"",IF(OR(AND(F14="Short",Z14<Y14),AND(NOT(F14="Short"),Z14>Y14)),"stop on wrong side",ABS(Y14-Z14))) -> 10.62 | AN14: =IFERROR(IF(OR(NOT(ISNUMBER(AM14)),$C$6=""),"",ROUNDDOWN($C$6*$C$7/AM14,2)),"") -> 0.04 | AO14: =IFERROR(IF(AN14="","",AN14*Y14),"") -> 9.172 | AP14: Entry setup | AS14: =IFERROR(IF(OR(AR14="",Y14="",AQ14=""),"",IF(F14="Short",1-AR14/Y14,AR14/Y14-1)),"") | AT14: =IF(AQ14="","",IF(ISNUMBER($C$4),$C$4,TODAY())-AQ14) | AU14: =IF(C14="","",IF(AP14="Open position",IF(IF(F14="Short",AND(ISNUMBER(AR14),ISNUMBER(Z14),AR14>=Z14),AND(ISNUMBER(AR14),ISNUMBER(Z14),AR14<=Z14)),IF(F14="Short","COVER — stop hit (buy back)","SELL — stop hit"),IF(IF(F14="Short",AND(ISNUMBER(AR14),ISNUMBER(AA14),AR14<=AA14),AND(ISNUMBER(AR14),ISNUMBER(AA14),AR14>=AA14)),"TAKE PROFIT — target hit",IF(AND(ISNUMBER(AT14),AT14>182),IF(F14="Short","COVER — 6-month time limit","SELL — 6-month time limit"),IF(AND(ISNUMBER(AT14),AT14>42,ISNUMBER(AS14),AS14<0.02),"REVIEW — no progress after 6 weeks",IF(IF(F14="Short",AND(L14<>"",N(L14)>0),AND(L14<>"",N(L14)<0)),IF(F14="Short","REVIEW — back above 50-day avg","REVIEW — below 50-day avg"),"HOLD"))))),IF(OR(AP14="Closed",AP14="Dropped"),"Closed",IF(AK14="A",IF(F14="Short","Run Technical Review — SHORT entry","Run Technical Review — LONG entry"),IF(AK14="B","Watch — wait for setup","Drop or re-check next week"))))) -> Run Technical Review — LONG entry | AV14: Trigger: Buy stop above the 12-13 Oct highs (228.86); price sits on the 20-day (228.3) just above the 50-day (223.0). Long entry 229.30, stop 218.68 (2×ATR 5.31), target 261.16 (3R). LRC Work-sheet 14 Oct: BUY (6-m target ~$262.56, +15%; score 3.8/5; technical: CLEARED — STAGED ENTRY). Only name this week with BUY + technical clearance (CLEARED — staged entry). Fundamentals and trend agree. Target ≈ 6-m fundamental target. Results 18 Nov (outside 14 days). Data 13 Oct close: stockanalysis statistics + daily history to 13 Oct (SMA20/ATR14 computed); Perf Half vs ~13 Apr close; EPS growth this yr = consensus current FY (adjusted). Perf Quarter n/f (history page holds 50 sessions). Finviz itself blocked for us — same filters applied manually. — P. Nkuna | AX14: =IF(AND(C14<>"",A14=$C$4,ISNUMBER(AJ14)),AJ14+ROW()/100000,"")
A15: 46312 | B15: US | C15: INTU | D15: Intuit Inc. | E15: Technology | F15: Long | G15: 301.45 | H15: 80.56 | I15: 3875886 | J15: =IF(OR(G15="",I15=""),"",G15*I15/1000000) -> 1168.3858 | K15: 0.0335 | L15: -0.0614 | M15: -0.2081 | N15: 49.9 | P15: -0.184 | Q15: -0.5626 | R15: 0.1923 | S15: 0.95 | T15: -0.0133 | U15: 0.0279 | V15: 46345 | W15: 10.41 | X15: LONG: Reversal (higher low) | Y15: 322 | Z15: 301.18 | AA15: 384.46 | AB15: =IF(C15="","",IF(F15="Short",(AND(M15<>"",N(M15)<0))+(AND(L15<>"",N(L15)<0))+(AND(K15<>"",N(K15)<0))+AND(L15<>"",M15<>"",N(M15)<N(L15)),(N(M15)>0)+(N(L15)>0)+(N(K15)>0)+AND(L15<>"",M15<>"",N(M15)>N(L15)))) -> 1 | AC15: =IF(C15="","",IF(F15="Short",IF(N15="",0,IF(AND(N15>=30,N15<=50),2,IF(OR(AND(N15>=25,N15<30),AND(N15>50,N15<=60)),1,0)))+IF(P15="",0,IF(AND(IF(B15="JSE",$L$5,$L$4)<>"",P15<IF(B15="JSE",$L$5,$L$4)),2,IF(P15<0,1,0))),IF(N15="",0,IF(AND(N15>=50,N15<=70),2,IF(OR(AND(N15>=40,N15<50),AND(N15>70,N15<=75)),1,0)))+IF(P15="",0,IF(AND(IF(B15="JSE",$L$5,$L$4)<>"",P15>IF(B15="JSE",$L$5,$L$4)),2,IF(P15>0,1,0))))) -> 1 | AD15: =IF(C15="","",IF(F15="Short",IF(R15="",0,IF(R15<=0.1,2,IF(R15<=0.25,1,0))),IF(Q15="",0,IF(Q15>=-0.1,2,IF(Q15>=-0.25,1,0))))) -> 0 | AE15: =IF(C15="","",IF(J15="",0,IF(J15>=IF(B15="JSE",$L$7,$L$6),2,IF(J15>=IF(B15="JSE",$L$7,$L$6)/4,1,0)))) -> 2 | AF15: =IF(C15="","",IF(F15="Short",AND(T15<>"",N(T15)<0),N(T15)>0)+(N(S15)>=1.5)) -> 0 | AG15: =IF(C15="","",IF(AL15="",0,IF(AL15>=3,4,IF(AL15>=2,2,0)))) -> 4 | AH15: =IF(C15="","",IF(AND(ISNUMBER(V15),ISNUMBER(A15),V15>=A15,V15-A15<=14),-2,0)) -> 0 | AI15: =IF(C15="","",IF(AND(F15="Short",N(U15)>=0.2),-1,0)) -> 0 | AJ15: =IF(C15="","",SUM(AB15:AI15)) -> 8 | AK15: =IF(C15="","",IF(AJ15>=14,"A",IF(AJ15>=10,"B","C"))) -> C | AL15: =IFERROR(IF(OR(Y15="",Z15="",AA15=""),"",IF(F15="Short",IF(Z15<=Y15,"",(Y15-AA15)/(Z15-Y15)),IF(Y15<=Z15,"",(AA15-Y15)/(Y15-Z15)))),"") -> 3 | AM15: =IF(OR(Y15="",Z15="",N(Y15)=N(Z15)),"",IF(OR(AND(F15="Short",Z15<Y15),AND(NOT(F15="Short"),Z15>Y15)),"stop on wrong side",ABS(Y15-Z15))) -> 20.82 | AN15: =IFERROR(IF(OR(NOT(ISNUMBER(AM15)),$C$6=""),"",ROUNDDOWN($C$6*$C$7/AM15,2)),"") -> 0.02 | AO15: =IFERROR(IF(AN15="","",AN15*Y15),"") -> 6.44 | AP15: Watch | AS15: =IFERROR(IF(OR(AR15="",Y15="",AQ15=""),"",IF(F15="Short",1-AR15/Y15,AR15/Y15-1)),"") | AT15: =IF(AQ15="","",IF(ISNUMBER($C$4),$C$4,TODAY())-AQ15) | AU15: =IF(C15="","",IF(AP15="Open position",IF(IF(F15="Short",AND(ISNUMBER(AR15),ISNUMBER(Z15),AR15>=Z15),AND(ISNUMBER(AR15),ISNUMBER(Z15),AR15<=Z15)),IF(F15="Short","COVER — stop hit (buy back)","SELL — stop hit"),IF(IF(F15="Short",AND(ISNUMBER(AR15),ISNUMBER(AA15),AR15<=AA15),AND(ISNUMBER(AR15),ISNUMBER(AA15),AR15>=AA15)),"TAKE PROFIT — target hit",IF(AND(ISNUMBER(AT15),AT15>182),IF(F15="Short","COVER — 6-month time limit","SELL — 6-month time limit"),IF(AND(ISNUMBER(AT15),AT15>42,ISNUMBER(AS15),AS15<0.02),"REVIEW — no progress after 6 weeks",IF(IF(F15="Short",AND(L15<>"",N(L15)>0),AND(L15<>"",N(L15)<0)),IF(F15="Short","REVIEW — back above 50-day avg","REVIEW — below 50-day avg"),"HOLD"))))),IF(OR(AP15="Closed",AP15="Dropped"),"Closed",IF(AK15="A",IF(F15="Short","Run Technical Review — SHORT entry","Run Technical Review — LONG entry"),IF(AK15="B","Watch — wait for setup","Drop or re-check next week"))))) -> Drop or re-check next week | AV15: Trigger: Only on a close back above the 50-day average (321.16) — today the trend is DOWN (below 50/200-day). Long entry 322.00, stop 301.18 (2×ATR 10.41), target 384.46 (3R). LRC Work-sheet 14 Oct: BUY (6-m target ~$426.00, +41%; score 4.0/5; technical: NOT CLEARED — score below 70%). BUY on fundamentals (+41%) but NOT technically cleared (downtrend). Watch only — do not trade until the Technical Review is re-ticked and cleared above the 50-day. Results 19 Nov. Data 13 Oct close: stockanalysis statistics/history (Finviz-preset replica, short screen); Perf Half vs ~13 Apr close; EPS growth this yr = consensus current FY (adjusted). Perf Quarter n/f (history page holds 50 sessions). Finviz itself blocked for us — same filters applied manually. — P. Nkuna | AX15: =IF(AND(C15<>"",A15=$C$4,ISNUMBER(AJ15)),AJ15+ROW()/100000,"")
A16: 46312 | B16: US | C16: DECK | D16: Deckers Outdoor Corporation | E16: Consumer Discretionary | F16: Long | G16: 84.02 | H16: 11.44 | I16: 3159200 | J16: =IF(OR(G16="",I16=""),"",G16*I16/1000000) -> 265.43598 | K16: 0.0496 | L16: -0.0157 | M16: -0.1649 | N16: 56.2 | P16: -0.223 | Q16: -0.3129 | R16: 0.0883 | S16: 0.95 | T16: 0.0733 | U16: 0.0877 | V16: 46317 | W16: 1.96 | X16: LONG: Reversal (higher low) | Y16: 86.3 | Z16: 82.38 | AA16: 98.06 | AB16: =IF(C16="","",IF(F16="Short",(AND(M16<>"",N(M16)<0))+(AND(L16<>"",N(L16)<0))+(AND(K16<>"",N(K16)<0))+AND(L16<>"",M16<>"",N(M16)<N(L16)),(N(M16)>0)+(N(L16)>0)+(N(K16)>0)+AND(L16<>"",M16<>"",N(M16)>N(L16)))) -> 1 | AC16: =IF(C16="","",IF(F16="Short",IF(N16="",0,IF(AND(N16>=30,N16<=50),2,IF(OR(AND(N16>=25,N16<30),AND(N16>50,N16<=60)),1,0)))+IF(P16="",0,IF(AND(IF(B16="JSE",$L$5,$L$4)<>"",P16<IF(B16="JSE",$L$5,$L$4)),2,IF(P16<0,1,0))),IF(N16="",0,IF(AND(N16>=50,N16<=70),2,IF(OR(AND(N16>=40,N16<50),AND(N16>70,N16<=75)),1,0)))+IF(P16="",0,IF(AND(IF(B16="JSE",$L$5,$L$4)<>"",P16>IF(B16="JSE",$L$5,$L$4)),2,IF(P16>0,1,0))))) -> 2 | AD16: =IF(C16="","",IF(F16="Short",IF(R16="",0,IF(R16<=0.1,2,IF(R16<=0.25,1,0))),IF(Q16="",0,IF(Q16>=-0.1,2,IF(Q16>=-0.25,1,0))))) -> 0 | AE16: =IF(C16="","",IF(J16="",0,IF(J16>=IF(B16="JSE",$L$7,$L$6),2,IF(J16>=IF(B16="JSE",$L$7,$L$6)/4,1,0)))) -> 2 | AF16: =IF(C16="","",IF(F16="Short",AND(T16<>"",N(T16)<0),N(T16)>0)+(N(S16)>=1.5)) -> 1 | AG16: =IF(C16="","",IF(AL16="",0,IF(AL16>=3,4,IF(AL16>=2,2,0)))) -> 4 | AH16: =IF(C16="","",IF(AND(ISNUMBER(V16),ISNUMBER(A16),V16>=A16,V16-A16<=14),-2,0)) -> -2 | AI16: =IF(C16="","",IF(AND(F16="Short",N(U16)>=0.2),-1,0)) -> 0 | AJ16: =IF(C16="","",SUM(AB16:AI16)) -> 8 | AK16: =IF(C16="","",IF(AJ16>=14,"A",IF(AJ16>=10,"B","C"))) -> C | AL16: =IFERROR(IF(OR(Y16="",Z16="",AA16=""),"",IF(F16="Short",IF(Z16<=Y16,"",(Y16-AA16)/(Z16-Y16)),IF(Y16<=Z16,"",(AA16-Y16)/(Y16-Z16)))),"") -> 3 | AM16: =IF(OR(Y16="",Z16="",N(Y16)=N(Z16)),"",IF(OR(AND(F16="Short",Z16<Y16),AND(NOT(F16="Short"),Z16>Y16)),"stop on wrong side",ABS(Y16-Z16))) -> 3.92 | AN16: =IFERROR(IF(OR(NOT(ISNUMBER(AM16)),$C$6=""),"",ROUNDDOWN($C$6*$C$7/AM16,2)),"") -> 0.11 | AO16: =IFERROR(IF(AN16="","",AN16*Y16),"") -> 9.493 | AP16: Watch | AS16: =IFERROR(IF(OR(AR16="",Y16="",AQ16=""),"",IF(F16="Short",1-AR16/Y16,AR16/Y16-1)),"") | AT16: =IF(AQ16="","",IF(ISNUMBER($C$4),$C$4,TODAY())-AQ16) | AU16: =IF(C16="","",IF(AP16="Open position",IF(IF(F16="Short",AND(ISNUMBER(AR16),ISNUMBER(Z16),AR16>=Z16),AND(ISNUMBER(AR16),ISNUMBER(Z16),AR16<=Z16)),IF(F16="Short","COVER — stop hit (buy back)","SELL — stop hit"),IF(IF(F16="Short",AND(ISNUMBER(AR16),ISNUMBER(AA16),AR16<=AA16),AND(ISNUMBER(AR16),ISNUMBER(AA16),AR16>=AA16)),"TAKE PROFIT — target hit",IF(AND(ISNUMBER(AT16),AT16>182),IF(F16="Short","COVER — 6-month time limit","SELL — 6-month time limit"),IF(AND(ISNUMBER(AT16),AT16>42,ISNUMBER(AS16),AS16<0.02),"REVIEW — no progress after 6 weeks",IF(IF(F16="Short",AND(L16<>"",N(L16)>0),AND(L16<>"",N(L16)<0)),IF(F16="Short","REVIEW — back above 50-day avg","REVIEW — below 50-day avg"),"HOLD"))))),IF(OR(AP16="Closed",AP16="Dropped"),"Closed",IF(AK16="A",IF(F16="Short","Run Technical Review — SHORT entry","Run Technical Review — LONG entry"),IF(AK16="B","Watch — wait for setup","Drop or re-check next week"))))) -> Drop or re-check next week | AV16: Trigger: Above the 15-day high (86.25) and the 50-day (85.36); results 22 Oct — wait for the print. Long entry 86.30, stop 82.38 (2×ATR 1.96), target 98.06 (3R). LRC Work-sheet 14 Oct: BUY (6-m target ~$103.00, +23%; score 3.8/5; technical: NOT CLEARED — score below 70%). BUY on fundamentals (+23%) but NOT technically cleared (downtrend). Results 22 Oct inside 14 days (event risk). Watch only until cleared. Data 13 Oct close: stockanalysis statistics + daily history to 13 Oct (SMA20/ATR14 computed); Perf Half vs ~13 Apr close; EPS growth this yr = consensus current FY (adjusted). Perf Quarter n/f (history page holds 50 sessions). Finviz itself blocked for us — same filters applied manually. — P. Nkuna | AX16: =IF(AND(C16<>"",A16=$C$4,ISNUMBER(AJ16)),AJ16+ROW()/100000,"")
A17: 46312 | B17: US | C17: NKE | D17: NIKE, Inc. | E17: Consumer Discretionary | F17: Short | G17: 35.33 | H17: 52.48 | I17: 45217604 | J17: =IF(OR(G17="",I17=""),"",G17*I17/1000000) -> 1597.5379 | K17: -0.0011 | L17: -0.0671 | M17: -0.2604 | N17: 43.7 | P17: -0.1604 | Q17: -0.4984 | R17: 0.1051 | S17: 0.67 | T17: -0.1642 | U17: 0.0842 | W17: 1.13 | X17: SHORT: Downtrend continuation | Y17: 34.9 | Z17: 37.16 | AA17: 28.12 | AB17: =IF(C17="","",IF(F17="Short",(AND(M17<>"",N(M17)<0))+(AND(L17<>"",N(L17)<0))+(AND(K17<>"",N(K17)<0))+AND(L17<>"",M17<>"",N(M17)<N(L17)),(N(M17)>0)+(N(L17)>0)+(N(K17)>0)+AND(L17<>"",M17<>"",N(M17)>N(L17)))) -> 4 | AC17: =IF(C17="","",IF(F17="Short",IF(N17="",0,IF(AND(N17>=30,N17<=50),2,IF(OR(AND(N17>=25,N17<30),AND(N17>50,N17<=60)),1,0)))+IF(P17="",0,IF(AND(IF(B17="JSE",$L$5,$L$4)<>"",P17<IF(B17="JSE",$L$5,$L$4)),2,IF(P17<0,1,0))),IF(N17="",0,IF(AND(N17>=50,N17<=70),2,IF(OR(AND(N17>=40,N17<50),AND(N17>70,N17<=75)),1,0)))+IF(P17="",0,IF(AND(IF(B17="JSE",$L$5,$L$4)<>"",P17>IF(B17="JSE",$L$5,$L$4)),2,IF(P17>0,1,0))))) -> 4 | AD17: =IF(C17="","",IF(F17="Short",IF(R17="",0,IF(R17<=0.1,2,IF(R17<=0.25,1,0))),IF(Q17="",0,IF(Q17>=-0.1,2,IF(Q17>=-0.25,1,0))))) -> 1 | AE17: =IF(C17="","",IF(J17="",0,IF(J17>=IF(B17="JSE",$L$7,$L$6),2,IF(J17>=IF(B17="JSE",$L$7,$L$6)/4,1,0)))) -> 2 | AF17: =IF(C17="","",IF(F17="Short",AND(T17<>"",N(T17)<0),N(T17)>0)+(N(S17)>=1.5)) -> 1 | AG17: =IF(C17="","",IF(AL17="",0,IF(AL17>=3,4,IF(AL17>=2,2,0)))) -> 4 | AH17: =IF(C17="","",IF(AND(ISNUMBER(V17),ISNUMBER(A17),V17>=A17,V17-A17<=14),-2,0)) -> 0 | AI17: =IF(C17="","",IF(AND(F17="Short",N(U17)>=0.2),-1,0)) -> 0 | AJ17: =IF(C17="","",SUM(AB17:AI17)) -> 16 | AK17: =IF(C17="","",IF(AJ17>=14,"A",IF(AJ17>=10,"B","C"))) -> A | AL17: =IFERROR(IF(OR(Y17="",Z17="",AA17=""),"",IF(F17="Short",IF(Z17<=Y17,"",(Y17-AA17)/(Z17-Y17)),IF(Y17<=Z17,"",(AA17-Y17)/(Y17-Z17)))),"") -> 3 | AM17: =IF(OR(Y17="",Z17="",N(Y17)=N(Z17)),"",IF(OR(AND(F17="Short",Z17<Y17),AND(NOT(F17="Short"),Z17>Y17)),"stop on wrong side",ABS(Y17-Z17))) -> 2.26 | AN17: =IFERROR(IF(OR(NOT(ISNUMBER(AM17)),$C$6=""),"",ROUNDDOWN($C$6*$C$7/AM17,2)),"") -> 0.2 | AO17: =IFERROR(IF(AN17="","",AN17*Y17),"") -> 6.98 | AP17: Entry setup | AS17: =IFERROR(IF(OR(AR17="",Y17="",AQ17=""),"",IF(F17="Short",1-AR17/Y17,AR17/Y17-1)),"") | AT17: =IF(AQ17="","",IF(ISNUMBER($C$4),$C$4,TODAY())-AQ17) | AU17: =IF(C17="","",IF(AP17="Open position",IF(IF(F17="Short",AND(ISNUMBER(AR17),ISNUMBER(Z17),AR17>=Z17),AND(ISNUMBER(AR17),ISNUMBER(Z17),AR17<=Z17)),IF(F17="Short","COVER — stop hit (buy back)","SELL — stop hit"),IF(IF(F17="Short",AND(ISNUMBER(AR17),ISNUMBER(AA17),AR17<=AA17),AND(ISNUMBER(AR17),ISNUMBER(AA17),AR17>=AA17)),"TAKE PROFIT — target hit",IF(AND(ISNUMBER(AT17),AT17>182),IF(F17="Short","COVER — 6-month time limit","SELL — 6-month time limit"),IF(AND(ISNUMBER(AT17),AT17>42,ISNUMBER(AS17),AS17<0.02),"REVIEW — no progress after 6 weeks",IF(IF(F17="Short",AND(L17<>"",N(L17)>0),AND(L17<>"",N(L17)<0)),IF(F17="Short","REVIEW — back above 50-day avg","REVIEW — below 50-day avg"),"HOLD"))))),IF(OR(AP17="Closed",AP17="Dropped"),"Closed",IF(AK17="A",IF(F17="Short","Run Technical Review — SHORT entry","Run Technical Review — LONG entry"),IF(AK17="B","Watch — wait for setup","Drop or re-check next week"))))) -> Run Technical Review — SHORT entry | AV17: Trigger: Sell stop below 34.90 (price under the 20-day 35.37 and falling 50/200-day); stop above the 50-day zone. Short entry 34.90, stop 37.16 (2×ATR 1.13), target 28.12 (3R). LRC Work-sheet 14 Oct: SELL (6-m target ~$29.75, -16%; score 3.1/5; technical: NOT CLEARED — score below 70%). SELL (−16%) and full pass on the Finviz short preset. LRC Technical Review rules are written for LONG entries, so "NOT CLEARED / downtrend" here supports a short — PM to confirm. No results date inside 14 days (next ~Dec). Priority short #1. Data 13 Oct close: stockanalysis statistics/history (Finviz-preset replica, short screen); Perf Half vs ~13 Apr close; EPS growth this yr = consensus current FY (adjusted). Perf Quarter n/f (history page holds 50 sessions). Finviz itself blocked for us — same filters applied manually. — P. Nkuna | AX17: =IF(AND(C17<>"",A17=$C$4,ISNUMBER(AJ17)),AJ17+ROW()/100000,"")
A18: 46312 | B18: US | C18: ANET | D18: Arista Networks, Inc. | E18: Technology | F18: Short | G18: 204.52 | H18: 257.95 | I18: 4946200 | J18: =IF(OR(G18="",I18=""),"",G18*I18/1000000) -> 1011.5968 | K18: -0.0089 | L18: 0.0284 | M18: 0.2637 | N18: 50.5 | P18: 0.3453 | Q18: -0.0593 | R18: 0.7859 | S18: 1.61 | T18: 0.3799 | U18: 0.0114 | V18: 46329 | W18: 6.81 | X18: SHORT: Failed breakout / lower high | Y18: 197.4 | Z18: 211.02 | AA18: 156.54 | AB18: =IF(C18="","",IF(F18="Short",(AND(M18<>"",N(M18)<0))+(AND(L18<>"",N(L18)<0))+(AND(K18<>"",N(K18)<0))+AND(L18<>"",M18<>"",N(M18)<N(L18)),(N(M18)>0)+(N(L18)>0)+(N(K18)>0)+AND(L18<>"",M18<>"",N(M18)>N(L18)))) -> 1 | AC18: =IF(C18="","",IF(F18="Short",IF(N18="",0,IF(AND(N18>=30,N18<=50),2,IF(OR(AND(N18>=25,N18<30),AND(N18>50,N18<=60)),1,0)))+IF(P18="",0,IF(AND(IF(B18="JSE",$L$5,$L$4)<>"",P18<IF(B18="JSE",$L$5,$L$4)),2,IF(P18<0,1,0))),IF(N18="",0,IF(AND(N18>=50,N18<=70),2,IF(OR(AND(N18>=40,N18<50),AND(N18>70,N18<=75)),1,0)))+IF(P18="",0,IF(AND(IF(B18="JSE",$L$5,$L$4)<>"",P18>IF(B18="JSE",$L$5,$L$4)),2,IF(P18>0,1,0))))) -> 1 | AD18: =IF(C18="","",IF(F18="Short",IF(R18="",0,IF(R18<=0.1,2,IF(R18<=0.25,1,0))),IF(Q18="",0,IF(Q18>=-0.1,2,IF(Q18>=-0.25,1,0))))) -> 0 | AE18: =IF(C18="","",IF(J18="",0,IF(J18>=IF(B18="JSE",$L$7,$L$6),2,IF(J18>=IF(B18="JSE",$L$7,$L$6)/4,1,0)))) -> 2 | AF18: =IF(C18="","",IF(F18="Short",AND(T18<>"",N(T18)<0),N(T18)>0)+(N(S18)>=1.5)) -> 1 | AG18: =IF(C18="","",IF(AL18="",0,IF(AL18>=3,4,IF(AL18>=2,2,0)))) -> 4 | AH18: =IF(C18="","",IF(AND(ISNUMBER(V18),ISNUMBER(A18),V18>=A18,V18-A18<=14),-2,0)) -> 0 | AI18: =IF(C18="","",IF(AND(F18="Short",N(U18)>=0.2),-1,0)) -> 0 | AJ18: =IF(C18="","",SUM(AB18:AI18)) -> 9 | AK18: =IF(C18="","",IF(AJ18>=14,"A",IF(AJ18>=10,"B","C"))) -> C | AL18: =IFERROR(IF(OR(Y18="",Z18="",AA18=""),"",IF(F18="Short",IF(Z18<=Y18,"",(Y18-AA18)/(Z18-Y18)),IF(Y18<=Z18,"",(AA18-Y18)/(Y18-Z18)))),"") -> 3 | AM18: =IF(OR(Y18="",Z18="",N(Y18)=N(Z18)),"",IF(OR(AND(F18="Short",Z18<Y18),AND(NOT(F18="Short"),Z18>Y18)),"stop on wrong side",ABS(Y18-Z18))) -> 13.62 | AN18: =IFERROR(IF(OR(NOT(ISNUMBER(AM18)),$C$6=""),"",ROUNDDOWN($C$6*$C$7/AM18,2)),"") -> 0.03 | AO18: =IFERROR(IF(AN18="","",AN18*Y18),"") -> 5.922 | AP18: Watch | AS18: =IFERROR(IF(OR(AR18="",Y18="",AQ18=""),"",IF(F18="Short",1-AR18/Y18,AR18/Y18-1)),"") | AT18: =IF(AQ18="","",IF(ISNUMBER($C$4),$C$4,TODAY())-AQ18) | AU18: =IF(C18="","",IF(AP18="Open position",IF(IF(F18="Short",AND(ISNUMBER(AR18),ISNUMBER(Z18),AR18>=Z18),AND(ISNUMBER(AR18),ISNUMBER(Z18),AR18<=Z18)),IF(F18="Short","COVER — stop hit (buy back)","SELL — stop hit"),IF(IF(F18="Short",AND(ISNUMBER(AR18),ISNUMBER(AA18),AR18<=AA18),AND(ISNUMBER(AR18),ISNUMBER(AA18),AR18>=AA18)),"TAKE PROFIT — target hit",IF(AND(ISNUMBER(AT18),AT18>182),IF(F18="Short","COVER — 6-month time limit","SELL — 6-month time limit"),IF(AND(ISNUMBER(AT18),AT18>42,ISNUMBER(AS18),AS18<0.02),"REVIEW — no progress after 6 weeks",IF(IF(F18="Short",AND(L18<>"",N(L18)>0),AND(L18<>"",N(L18)<0)),IF(F18="Short","REVIEW — back above 50-day avg","REVIEW — below 50-day avg"),"HOLD"))))),IF(OR(AP18="Closed",AP18="Dropped"),"Closed",IF(AK18="A",IF(F18="Short","Run Technical Review — SHORT entry","Run Technical Review — LONG entry"),IF(AK18="B","Watch — wait for setup","Drop or re-check next week"))))) -> Drop or re-check next week | AV18: Trigger: Sell stop below the 13 Oct low (197.60) after the failed push to the 52-week high (217.41) on 9 Oct. Short entry 197.40, stop 211.02 (2×ATR 6.81), target 156.54 (3R). LRC Work-sheet 14 Oct: SELL (6-m target ~$144.61, -29%; score 3.7/5; technical: CLEARED — STAGED ENTRY). SELL (−29%) + technical clearance. Carried from last week (old trigger 186 replaced). 13 Oct reversal on 1.6x volume. High beta (1.6): small size. Results 3 Nov. Priority short #2. Data 13 Oct close: stockanalysis statistics + daily history to 13 Oct (SMA20/ATR14 computed); Perf Half vs ~13 Apr close; EPS growth this yr = consensus current FY (adjusted). Perf Quarter n/f (history page holds 50 sessions). Finviz itself blocked for us — same filters applied manually. — P. Nkuna | AX18: =IF(AND(C18<>"",A18=$C$4,ISNUMBER(AJ18)),AJ18+ROW()/100000,"")
A19: 46312 | B19: US | C19: AMD | D19: Advanced Micro Devices, Inc. | E19: Technology | F19: Short | G19: 605.53 | H19: 988.51 | I19: 21561387 | J19: =IF(OR(G19="",I19=""),"",G19*I19/1000000) -> 13056.067 | K19: -0.0044 | L19: 0.1346 | M19: 0.556 | N19: 55.8 | O19: 0.1444 | P19: 1.4532 | Q19: -0.0805 | R19: 2.2171 | S19: 0.83 | T19: 0.819 | U19: 0.0242 | V19: 46329 | W19: 23.77 | X19: SHORT: Failed breakout / lower high | Y19: 569.5 | Z19: 617.04 | AA19: 426.88 | AB19: =IF(C19="","",IF(F19="Short",(AND(M19<>"",N(M19)<0))+(AND(L19<>"",N(L19)<0))+(AND(K19<>"",N(K19)<0))+AND(L19<>"",M19<>"",N(M19)<N(L19)),(N(M19)>0)+(N(L19)>0)+(N(K19)>0)+AND(L19<>"",M19<>"",N(M19)>N(L19)))) -> 1 | AC19: =IF(C19="","",IF(F19="Short",IF(N19="",0,IF(AND(N19>=30,N19<=50),2,IF(OR(AND(N19>=25,N19<30),AND(N19>50,N19<=60)),1,0)))+IF(P19="",0,IF(AND(IF(B19="JSE",$L$5,$L$4)<>"",P19<IF(B19="JSE",$L$5,$L$4)),2,IF(P19<0,1,0))),IF(N19="",0,IF(AND(N19>=50,N19<=70),2,IF(OR(AND(N19>=40,N19<50),AND(N19>70,N19<=75)),1,0)))+IF(P19="",0,IF(AND(IF(B19="JSE",$L$5,$L$4)<>"",P19>IF(B19="JSE",$L$5,$L$4)),2,IF(P19>0,1,0))))) -> 1 | AD19: =IF(C19="","",IF(F19="Short",IF(R19="",0,IF(R19<=0.1,2,IF(R19<=0.25,1,0))),IF(Q19="",0,IF(Q19>=-0.1,2,IF(Q19>=-0.25,1,0))))) -> 0 | AE19: =IF(C19="","",IF(J19="",0,IF(J19>=IF(B19="JSE",$L$7,$L$6),2,IF(J19>=IF(B19="JSE",$L$7,$L$6)/4,1,0)))) -> 2 | AF19: =IF(C19="","",IF(F19="Short",AND(T19<>"",N(T19)<0),N(T19)>0)+(N(S19)>=1.5)) -> 0 | AG19: =IF(C19="","",IF(AL19="",0,IF(AL19>=3,4,IF(AL19>=2,2,0)))) -> 4 | AH19: =IF(C19="","",IF(AND(ISNUMBER(V19),ISNUMBER(A19),V19>=A19,V19-A19<=14),-2,0)) -> 0 | AI19: =IF(C19="","",IF(AND(F19="Short",N(U19)>=0.2),-1,0)) -> 0 | AJ19: =IF(C19="","",SUM(AB19:AI19)) -> 8 | AK19: =IF(C19="","",IF(AJ19>=14,"A",IF(AJ19>=10,"B","C"))) -> C | AL19: =IFERROR(IF(OR(Y19="",Z19="",AA19=""),"",IF(F19="Short",IF(Z19<=Y19,"",(Y19-AA19)/(Z19-Y19)),IF(Y19<=Z19,"",(AA19-Y19)/(Y19-Z19)))),"") -> 3 | AM19: =IF(OR(Y19="",Z19="",N(Y19)=N(Z19)),"",IF(OR(AND(F19="Short",Z19<Y19),AND(NOT(F19="Short"),Z19>Y19)),"stop on wrong side",ABS(Y19-Z19))) -> 47.54 | AN19: =IFERROR(IF(OR(NOT(ISNUMBER(AM19)),$C$6=""),"",ROUNDDOWN($C$6*$C$7/AM19,2)),"") -> 0 | AO19: =IFERROR(IF(AN19="","",AN19*Y19),"") -> 0 | AP19: Watch | AS19: =IFERROR(IF(OR(AR19="",Y19="",AQ19=""),"",IF(F19="Short",1-AR19/Y19,AR19/Y19-1)),"") | AT19: =IF(AQ19="","",IF(ISNUMBER($C$4),$C$4,TODAY())-AQ19) | AU19: =IF(C19="","",IF(AP19="Open position",IF(IF(F19="Short",AND(ISNUMBER(AR19),ISNUMBER(Z19),AR19>=Z19),AND(ISNUMBER(AR19),ISNUMBER(Z19),AR19<=Z19)),IF(F19="Short","COVER — stop hit (buy back)","SELL — stop hit"),IF(IF(F19="Short",AND(ISNUMBER(AR19),ISNUMBER(AA19),AR19<=AA19),AND(ISNUMBER(AR19),ISNUMBER(AA19),AR19>=AA19)),"TAKE PROFIT — target hit",IF(AND(ISNUMBER(AT19),AT19>182),IF(F19="Short","COVER — 6-month time limit","SELL — 6-month time limit"),IF(AND(ISNUMBER(AT19),AT19>42,ISNUMBER(AS19),AS19<0.02),"REVIEW — no progress after 6 weeks",IF(IF(F19="Short",AND(L19<>"",N(L19)>0),AND(L19<>"",N(L19)<0)),IF(F19="Short","REVIEW — back above 50-day avg","REVIEW — below 50-day avg"),"HOLD"))))),IF(OR(AP19="Closed",AP19="Dropped"),"Closed",IF(AK19="A",IF(F19="Short","Run Technical Review — SHORT entry","Run Technical Review — LONG entry"),IF(AK19="B","Watch — wait for setup","Drop or re-check next week"))))) -> Drop or re-check next week | AV19: Trigger: Sell stop below the 15-day swing low (570.60); 52-week high 658.52 was 8% above. Short entry 569.50, stop 617.04 (2×ATR 23.77), target 426.88 (3R). LRC Work-sheet 14 Oct: SELL (6-m target ~$402.73, -33%; score 3.3/5; technical: CLEARED — STAGED ENTRY). SELL (−33%) + technical clearance. Do NOT short strength — act only below the trigger. Beta 2.45: half size. Results 3 Nov. Priority short #3. Data 13 Oct close: stockanalysis statistics/history (Finviz-preset replica, long screen); Perf Half vs ~13 Apr close; EPS growth this yr = consensus current FY (adjusted). Finviz itself blocked for us — same filters applied manually. — P. Nkuna | AX19: =IF(AND(C19<>"",A19=$C$4,ISNUMBER(AJ19)),AJ19+ROW()/100000,"")
A20: 46312 | B20: US | C20: DELL | D20: Dell Technologies Inc. | E20: Technology | F20: Short | G20: 572.47 | H20: 363.98 | I20: 7033783 | J20: =IF(OR(G20="",I20=""),"",G20*I20/1000000) -> 4026.6298 | K20: 0.0193 | L20: 0.1182 | M20: 0.8542 | N20: 57.4 | O20: 0.3872 | P20: 2.0307 | Q20: -0.0387 | R20: 4.1939 | S20: 0.79 | T20: 1.514 | U20: 0.0469 | V20: 46350 | W20: 25.01 | X20: SHORT: Breakdown from base | Y20: 519 | Z20: 569.02 | AA20: 368.94 | AB20: =IF(C20="","",IF(F20="Short",(AND(M20<>"",N(M20)<0))+(AND(L20<>"",N(L20)<0))+(AND(K20<>"",N(K20)<0))+AND(L20<>"",M20<>"",N(M20)<N(L20)),(N(M20)>0)+(N(L20)>0)+(N(K20)>0)+AND(L20<>"",M20<>"",N(M20)>N(L20)))) -> 0 | AC20: =IF(C20="","",IF(F20="Short",IF(N20="",0,IF(AND(N20>=30,N20<=50),2,IF(OR(AND(N20>=25,N20<30),AND(N20>50,N20<=60)),1,0)))+IF(P20="",0,IF(AND(IF(B20="JSE",$L$5,$L$4)<>"",P20<IF(B20="JSE",$L$5,$L$4)),2,IF(P20<0,1,0))),IF(N20="",0,IF(AND(N20>=50,N20<=70),2,IF(OR(AND(N20>=40,N20<50),AND(N20>70,N20<=75)),1,0)))+IF(P20="",0,IF(AND(IF(B20="JSE",$L$5,$L$4)<>"",P20>IF(B20="JSE",$L$5,$L$4)),2,IF(P20>0,1,0))))) -> 1 | AD20: =IF(C20="","",IF(F20="Short",IF(R20="",0,IF(R20<=0.1,2,IF(R20<=0.25,1,0))),IF(Q20="",0,IF(Q20>=-0.1,2,IF(Q20>=-0.25,1,0))))) -> 0 | AE20: =IF(C20="","",IF(J20="",0,IF(J20>=IF(B20="JSE",$L$7,$L$6),2,IF(J20>=IF(B20="JSE",$L$7,$L$6)/4,1,0)))) -> 2 | AF20: =IF(C20="","",IF(F20="Short",AND(T20<>"",N(T20)<0),N(T20)>0)+(N(S20)>=1.5)) -> 0 | AG20: =IF(C20="","",IF(AL20="",0,IF(AL20>=3,4,IF(AL20>=2,2,0)))) -> 4 | AH20: =IF(C20="","",IF(AND(ISNUMBER(V20),ISNUMBER(A20),V20>=A20,V20-A20<=14),-2,0)) -> 0 | AI20: =IF(C20="","",IF(AND(F20="Short",N(U20)>=0.2),-1,0)) -> 0 | AJ20: =IF(C20="","",SUM(AB20:AI20)) -> 7 | AK20: =IF(C20="","",IF(AJ20>=14,"A",IF(AJ20>=10,"B","C"))) -> C | AL20: =IFERROR(IF(OR(Y20="",Z20="",AA20=""),"",IF(F20="Short",IF(Z20<=Y20,"",(Y20-AA20)/(Z20-Y20)),IF(Y20<=Z20,"",(AA20-Y20)/(Y20-Z20)))),"") -> 3 | AM20: =IF(OR(Y20="",Z20="",N(Y20)=N(Z20)),"",IF(OR(AND(F20="Short",Z20<Y20),AND(NOT(F20="Short"),Z20>Y20)),"stop on wrong side",ABS(Y20-Z20))) -> 50.02 | AN20: =IFERROR(IF(OR(NOT(ISNUMBER(AM20)),$C$6=""),"",ROUNDDOWN($C$6*$C$7/AM20,2)),"") -> 0 | AO20: =IFERROR(IF(AN20="","",AN20*Y20),"") -> 0 | AP20: Watch | AS20: =IFERROR(IF(OR(AR20="",Y20="",AQ20=""),"",IF(F20="Short",1-AR20/Y20,AR20/Y20-1)),"") | AT20: =IF(AQ20="","",IF(ISNUMBER($C$4),$C$4,TODAY())-AQ20) | AU20: =IF(C20="","",IF(AP20="Open position",IF(IF(F20="Short",AND(ISNUMBER(AR20),ISNUMBER(Z20),AR20>=Z20),AND(ISNUMBER(AR20),ISNUMBER(Z20),AR20<=Z20)),IF(F20="Short","COVER — stop hit (buy back)","SELL — stop hit"),IF(IF(F20="Short",AND(ISNUMBER(AR20),ISNUMBER(AA20),AR20<=AA20),AND(ISNUMBER(AR20),ISNUMBER(AA20),AR20>=AA20)),"TAKE PROFIT — target hit",IF(AND(ISNUMBER(AT20),AT20>182),IF(F20="Short","COVER — 6-month time limit","SELL — 6-month time limit"),IF(AND(ISNUMBER(AT20),AT20>42,ISNUMBER(AS20),AS20<0.02),"REVIEW — no progress after 6 weeks",IF(IF(F20="Short",AND(L20<>"",N(L20)>0),AND(L20<>"",N(L20)<0)),IF(F20="Short","REVIEW — back above 50-day avg","REVIEW — below 50-day avg"),"HOLD"))))),IF(OR(AP20="Closed",AP20="Dropped"),"Closed",IF(AK20="A",IF(F20="Short","Run Technical Review — SHORT entry","Run Technical Review — LONG entry"),IF(AK20="B","Watch — wait for setup","Drop or re-check next week"))))) -> Drop or re-check next week | AV20: Trigger: Sell stop below the 15-day swing low (520.18); still a strong uptrend until then. Short entry 519.00, stop 569.02 (2×ATR 25.01), target 368.94 (3R). LRC Work-sheet 14 Oct: SELL (6-m target ~$404.70, -29%; score 3.1/5; technical: CLEARED — STAGED ENTRY). SELL (−29%) + technical clearance. Trigger is 9% below the price: may not fire this week. Results 24 Nov. Priority short #4. Data 13 Oct close: stockanalysis statistics/history (Finviz-preset replica, long screen); Perf Half vs ~13 Apr close; EPS growth this yr = consensus current FY (adjusted). Finviz itself blocked for us — same filters applied manually. — P. Nkuna | AX20: =IF(AND(C20<>"",A20=$C$4,ISNUMBER(AJ20)),AJ20+ROW()/100000,"")
A21: 46312 | B21: US | C21: FAST | D21: Fastenal Company | E21: Industrials | F21: Short | G21: 51.43 | H21: 59.02 | I21: 7109800 | J21: =IF(OR(G21="",I21=""),"",G21*I21/1000000) -> 365.65701 | K21: 0.0229 | L21: 0.0219 | M21: 0.1051 | N21: 60.2 | P21: 0.1351 | Q21: -0.0282 | R21: 0.3197 | S21: 1.41 | T21: 0.1605 | U21: 0.0302 | V21: 46309 | W21: 0.98 | X21: SHORT: Breakdown from base | Y21: 49 | Z21: 50.96 | AA21: 43.12 | AB21: =IF(C21="","",IF(F21="Short",(AND(M21<>"",N(M21)<0))+(AND(L21<>"",N(L21)<0))+(AND(K21<>"",N(K21)<0))+AND(L21<>"",M21<>"",N(M21)<N(L21)),(N(M21)>0)+(N(L21)>0)+(N(K21)>0)+AND(L21<>"",M21<>"",N(M21)>N(L21)))) -> 0 | AC21: =IF(C21="","",IF(F21="Short",IF(N21="",0,IF(AND(N21>=30,N21<=50),2,IF(OR(AND(N21>=25,N21<30),AND(N21>50,N21<=60)),1,0)))+IF(P21="",0,IF(AND(IF(B21="JSE",$L$5,$L$4)<>"",P21<IF(B21="JSE",$L$5,$L$4)),2,IF(P21<0,1,0))),IF(N21="",0,IF(AND(N21>=50,N21<=70),2,IF(OR(AND(N21>=40,N21<50),AND(N21>70,N21<=75)),1,0)))+IF(P21="",0,IF(AND(IF(B21="JSE",$L$5,$L$4)<>"",P21>IF(B21="JSE",$L$5,$L$4)),2,IF(P21>0,1,0))))) -> 2 | AD21: =IF(C21="","",IF(F21="Short",IF(R21="",0,IF(R21<=0.1,2,IF(R21<=0.25,1,0))),IF(Q21="",0,IF(Q21>=-0.1,2,IF(Q21>=-0.25,1,0))))) -> 0 | AE21: =IF(C21="","",IF(J21="",0,IF(J21>=IF(B21="JSE",$L$7,$L$6),2,IF(J21>=IF(B21="JSE",$L$7,$L$6)/4,1,0)))) -> 2 | AF21: =IF(C21="","",IF(F21="Short",AND(T21<>"",N(T21)<0),N(T21)>0)+(N(S21)>=1.5)) -> 0 | AG21: =IF(C21="","",IF(AL21="",0,IF(AL21>=3,4,IF(AL21>=2,2,0)))) -> 4 | AH21: =IF(C21="","",IF(AND(ISNUMBER(V21),ISNUMBER(A21),V21>=A21,V21-A21<=14),-2,0)) -> 0 | AI21: =IF(C21="","",IF(AND(F21="Short",N(U21)>=0.2),-1,0)) -> 0 | AJ21: =IF(C21="","",SUM(AB21:AI21)) -> 8 | AK21: =IF(C21="","",IF(AJ21>=14,"A",IF(AJ21>=10,"B","C"))) -> C | AL21: =IFERROR(IF(OR(Y21="",Z21="",AA21=""),"",IF(F21="Short",IF(Z21<=Y21,"",(Y21-AA21)/(Z21-Y21)),IF(Y21<=Z21,"",(AA21-Y21)/(Y21-Z21)))),"") -> 3 | AM21: =IF(OR(Y21="",Z21="",N(Y21)=N(Z21)),"",IF(OR(AND(F21="Short",Z21<Y21),AND(NOT(F21="Short"),Z21>Y21)),"stop on wrong side",ABS(Y21-Z21))) -> 1.96 | AN21: =IFERROR(IF(OR(NOT(ISNUMBER(AM21)),$C$6=""),"",ROUNDDOWN($C$6*$C$7/AM21,2)),"") -> 0.23 | AO21: =IFERROR(IF(AN21="","",AN21*Y21),"") -> 11.27 | AP21: Watch | AS21: =IFERROR(IF(OR(AR21="",Y21="",AQ21=""),"",IF(F21="Short",1-AR21/Y21,AR21/Y21-1)),"") | AT21: =IF(AQ21="","",IF(ISNUMBER($C$4),$C$4,TODAY())-AQ21) | AU21: =IF(C21="","",IF(AP21="Open position",IF(IF(F21="Short",AND(ISNUMBER(AR21),ISNUMBER(Z21),AR21>=Z21),AND(ISNUMBER(AR21),ISNUMBER(Z21),AR21<=Z21)),IF(F21="Short","COVER — stop hit (buy back)","SELL — stop hit"),IF(IF(F21="Short",AND(ISNUMBER(AR21),ISNUMBER(AA21),AR21<=AA21),AND(ISNUMBER(AR21),ISNUMBER(AA21),AR21>=AA21)),"TAKE PROFIT — target hit",IF(AND(ISNUMBER(AT21),AT21>182),IF(F21="Short","COVER — 6-month time limit","SELL — 6-month time limit"),IF(AND(ISNUMBER(AT21),AT21>42,ISNUMBER(AS21),AS21<0.02),"REVIEW — no progress after 6 weeks",IF(IF(F21="Short",AND(L21<>"",N(L21)>0),AND(L21<>"",N(L21)<0)),IF(F21="Short","REVIEW — back above 50-day avg","REVIEW — below 50-day avg"),"HOLD"))))),IF(OR(AP21="Closed",AP21="Dropped"),"Closed",IF(AK21="A",IF(F21="Short","Run Technical Review — SHORT entry","Run Technical Review — LONG entry"),IF(AK21="B","Watch — wait for setup","Drop or re-check next week"))))) -> Drop or re-check next week | AV21: Trigger: Sell stop below the 15-day low (49.11) — only AFTER the 14 Oct results are digested. Short entry 49.00, stop 50.96 (2×ATR 0.98), target 43.12 (3R). LRC Work-sheet 14 Oct: SELL (6-m target ~$38.37, -25%; score 3.5/5; technical: CLEARED — STAGED ENTRY). SELL (−25%) + technical clearance. Results 14 Oct (today) — wait for the reaction. 5th short: house limit is 4 open shorts, so only if one of the others has not triggered. Data 13 Oct close: stockanalysis statistics + daily history to 13 Oct (SMA20/ATR14 computed); Perf Half vs ~13 Apr close; EPS growth this yr = consensus current FY (adjusted). Perf Quarter n/f (history page holds 50 sessions). Finviz itself blocked for us — same filters applied manually. — P. Nkuna | AX21: =IF(AND(C21<>"",A21=$C$4,ISNUMBER(AJ21)),AJ21+ROW()/100000,"")
A22: 46316 | B22: US | C22: NVDA | D22: NVIDIA | E22: Technology | F22: Long | G22: 221.97 | I22: 117533575 | J22: =IF(OR(G22="",I22=""),"",G22*I22/1000000) -> 26088.928 | K22: -0.0216 | L22: -0.0047 | M22: 0.0911 | N22: 47.91 | O22: 0.0633 | P22: 0.0961 | Q22: -0.0879 | R22: 0.3513 | S22: 0.74 | U22: 0.0134 | V22: 46344 | W22: 5.9 | X22: LONG: Pullback to 20/50-day avg | Y22: 222.63 | Z22: 210.83 | AA22: 258.03 | AB22: =IF(C22="","",IF(F22="Short",(AND(M22<>"",N(M22)<0))+(AND(L22<>"",N(L22)<0))+(AND(K22<>"",N(K22)<0))+AND(L22<>"",M22<>"",N(M22)<N(L22)),(N(M22)>0)+(N(L22)>0)+(N(K22)>0)+AND(L22<>"",M22<>"",N(M22)>N(L22)))) -> 2 | AC22: =IF(C22="","",IF(F22="Short",IF(N22="",0,IF(AND(N22>=30,N22<=50),2,IF(OR(AND(N22>=25,N22<30),AND(N22>50,N22<=60)),1,0)))+IF(P22="",0,IF(AND(IF(B22="JSE",$L$5,$L$4)<>"",P22<IF(B22="JSE",$L$5,$L$4)),2,IF(P22<0,1,0))),IF(N22="",0,IF(AND(N22>=50,N22<=70),2,IF(OR(AND(N22>=40,N22<50),AND(N22>70,N22<=75)),1,0)))+IF(P22="",0,IF(AND(IF(B22="JSE",$L$5,$L$4)<>"",P22>IF(B22="JSE",$L$5,$L$4)),2,IF(P22>0,1,0))))) -> 2 | AD22: =IF(C22="","",IF(F22="Short",IF(R22="",0,IF(R22<=0.1,2,IF(R22<=0.25,1,0))),IF(Q22="",0,IF(Q22>=-0.1,2,IF(Q22>=-0.25,1,0))))) -> 2 | AE22: =IF(C22="","",IF(J22="",0,IF(J22>=IF(B22="JSE",$L$7,$L$6),2,IF(J22>=IF(B22="JSE",$L$7,$L$6)/4,1,0)))) -> 2 | AF22: =IF(C22="","",IF(F22="Short",AND(T22<>"",N(T22)<0),N(T22)>0)+(N(S22)>=1.5)) -> 0 | AG22: =IF(C22="","",IF(AL22="",0,IF(AL22>=3,4,IF(AL22>=2,2,0)))) -> 4 | AH22: =IF(C22="","",IF(AND(ISNUMBER(V22),ISNUMBER(A22),V22>=A22,V22-A22<=14),-2,0)) -> 0 | AI22: =IF(C22="","",IF(AND(F22="Short",N(U22)>=0.2),-1,0)) -> 0 | AJ22: =IF(C22="","",SUM(AB22:AI22)) -> 12 | AK22: =IF(C22="","",IF(AJ22>=14,"A",IF(AJ22>=10,"B","C"))) -> B | AL22: =IFERROR(IF(OR(Y22="",Z22="",AA22=""),"",IF(F22="Short",IF(Z22<=Y22,"",(Y22-AA22)/(Z22-Y22)),IF(Y22<=Z22,"",(AA22-Y22)/(Y22-Z22)))),"") -> 3 | AM22: =IF(OR(Y22="",Z22="",N(Y22)=N(Z22)),"",IF(OR(AND(F22="Short",Z22<Y22),AND(NOT(F22="Short"),Z22>Y22)),"stop on wrong side",ABS(Y22-Z22))) -> 11.8 | AN22: =IFERROR(IF(OR(NOT(ISNUMBER(AM22)),$C$6=""),"",ROUNDDOWN($C$6*$C$7/AM22,2)),"") -> 0.03 | AO22: =IFERROR(IF(AN22="","",AN22*Y22),"") -> 6.6789 | AP22: Watch | AS22: =IFERROR(IF(OR(AR22="",Y22="",AQ22=""),"",IF(F22="Short",1-AR22/Y22,AR22/Y22-1)),"") | AT22: =IF(AQ22="","",IF(ISNUMBER($C$4),$C$4,TODAY())-AQ22) | AU22: =IF(C22="","",IF(AP22="Open position",IF(IF(F22="Short",AND(ISNUMBER(AR22),ISNUMBER(Z22),AR22>=Z22),AND(ISNUMBER(AR22),ISNUMBER(Z22),AR22<=Z22)),IF(F22="Short","COVER — stop hit (buy back)","SELL — stop hit"),IF(IF(F22="Short",AND(ISNUMBER(AR22),ISNUMBER(AA22),AR22<=AA22),AND(ISNUMBER(AR22),ISNUMBER(AA22),AR22>=AA22)),"TAKE PROFIT — target hit",IF(AND(ISNUMBER(AT22),AT22>182),IF(F22="Short","COVER — 6-month time limit","SELL — 6-month time limit"),IF(AND(ISNUMBER(AT22),AT22>42,ISNUMBER(AS22),AS22<0.02),"REVIEW — no progress after 6 weeks",IF(IF(F22="Short",AND(L22<>"",N(L22)>0),AND(L22<>"",N(L22)<0)),IF(F22="Short","REVIEW — back above 50-day avg","REVIEW — below 50-day avg"),"HOLD"))))),IF(OR(AP22="Closed",AP22="Dropped"),"Closed",IF(AK22="A",IF(F22="Short","Run Technical Review — SHORT entry","Run Technical Review — LONG entry"),IF(AK22="B","Watch — wait for setup","Drop or re-check next week"))))) -> Watch — wait for setup | AV22: Agent 2026-10-23T03:09+02:00: LRC rating BUY (6-m value 262.56); CLEARED. Entry 222.63, stop 210.83 (2×ATR), target 258.03 (3R). — LRC Watchlist Agent | AX22: =IF(AND(C22<>"",A22=$C$4,ISNUMBER(AJ22)),AJ22+ROW()/100000,"") -> 12.00022
A23: 46316 | B23: US | C23: INTU | D23: Intuit | E23: Technology | F23: Long | G23: 335.61 | I23: 3793417 | J23: =IF(OR(G23="",I23=""),"",G23*I23/1000000) -> 1273.1087 | K23: 0.1228 | L23: 0.0454 | M23: -0.0948 | N23: 65.3 | O23: 0.1921 | P23: -0.1788 | Q23: -0.513 | R23: 0.3274 | S23: 0.48 | T23: -0.0133 | U23: 0.0279 | V23: 46345 | W23: 12.13 | X23: LONG: Pullback to 20/50-day avg | Y23: 342.47 | Z23: 318.21 | AA23: 415.25 | AB23: =IF(C23="","",IF(F23="Short",(AND(M23<>"",N(M23)<0))+(AND(L23<>"",N(L23)<0))+(AND(K23<>"",N(K23)<0))+AND(L23<>"",M23<>"",N(M23)<N(L23)),(N(M23)>0)+(N(L23)>0)+(N(K23)>0)+AND(L23<>"",M23<>"",N(M23)>N(L23)))) -> 2 | AC23: =IF(C23="","",IF(F23="Short",IF(N23="",0,IF(AND(N23>=30,N23<=50),2,IF(OR(AND(N23>=25,N23<30),AND(N23>50,N23<=60)),1,0)))+IF(P23="",0,IF(AND(IF(B23="JSE",$L$5,$L$4)<>"",P23<IF(B23="JSE",$L$5,$L$4)),2,IF(P23<0,1,0))),IF(N23="",0,IF(AND(N23>=50,N23<=70),2,IF(OR(AND(N23>=40,N23<50),AND(N23>70,N23<=75)),1,0)))+IF(P23="",0,IF(AND(IF(B23="JSE",$L$5,$L$4)<>"",P23>IF(B23="JSE",$L$5,$L$4)),2,IF(P23>0,1,0))))) -> 2 | AD23: =IF(C23="","",IF(F23="Short",IF(R23="",0,IF(R23<=0.1,2,IF(R23<=0.25,1,0))),IF(Q23="",0,IF(Q23>=-0.1,2,IF(Q23>=-0.25,1,0))))) -> 0 | AE23: =IF(C23="","",IF(J23="",0,IF(J23>=IF(B23="JSE",$L$7,$L$6),2,IF(J23>=IF(B23="JSE",$L$7,$L$6)/4,1,0)))) -> 2 | AF23: =IF(C23="","",IF(F23="Short",AND(T23<>"",N(T23)<0),N(T23)>0)+(N(S23)>=1.5)) -> 0 | AG23: =IF(C23="","",IF(AL23="",0,IF(AL23>=3,4,IF(AL23>=2,2,0)))) -> 4 | AH23: =IF(C23="","",IF(AND(ISNUMBER(V23),ISNUMBER(A23),V23>=A23,V23-A23<=14),-2,0)) -> 0 | AI23: =IF(C23="","",IF(AND(F23="Short",N(U23)>=0.2),-1,0)) -> 0 | AJ23: =IF(C23="","",SUM(AB23:AI23)) -> 10 | AK23: =IF(C23="","",IF(AJ23>=14,"A",IF(AJ23>=10,"B","C"))) -> B | AL23: =IFERROR(IF(OR(Y23="",Z23="",AA23=""),"",IF(F23="Short",IF(Z23<=Y23,"",(Y23-AA23)/(Z23-Y23)),IF(Y23<=Z23,"",(AA23-Y23)/(Y23-Z23)))),"") -> 3 | AM23: =IF(OR(Y23="",Z23="",N(Y23)=N(Z23)),"",IF(OR(AND(F23="Short",Z23<Y23),AND(NOT(F23="Short"),Z23>Y23)),"stop on wrong side",ABS(Y23-Z23))) -> 24.26 | AN23: =IFERROR(IF(OR(NOT(ISNUMBER(AM23)),$C$6=""),"",ROUNDDOWN($C$6*$C$7/AM23,2)),"") -> 0.01 | AO23: =IFERROR(IF(AN23="","",AN23*Y23),"") -> 3.4247 | AP23: Watch | AS23: =IFERROR(IF(OR(AR23="",Y23="",AQ23=""),"",IF(F23="Short",1-AR23/Y23,AR23/Y23-1)),"") | AT23: =IF(AQ23="","",IF(ISNUMBER($C$4),$C$4,TODAY())-AQ23) | AU23: =IF(C23="","",IF(AP23="Open position",IF(IF(F23="Short",AND(ISNUMBER(AR23),ISNUMBER(Z23),AR23>=Z23),AND(ISNUMBER(AR23),ISNUMBER(Z23),AR23<=Z23)),IF(F23="Short","COVER — stop hit (buy back)","SELL — stop hit"),IF(IF(F23="Short",AND(ISNUMBER(AR23),ISNUMBER(AA23),AR23<=AA23),AND(ISNUMBER(AR23),ISNUMBER(AA23),AR23>=AA23)),"TAKE PROFIT — target hit",IF(AND(ISNUMBER(AT23),AT23>182),IF(F23="Short","COVER — 6-month time limit","SELL — 6-month time limit"),IF(AND(ISNUMBER(AT23),AT23>42,ISNUMBER(AS23),AS23<0.02),"REVIEW — no progress after 6 weeks",IF(IF(F23="Short",AND(L23<>"",N(L23)>0),AND(L23<>"",N(L23)<0)),IF(F23="Short","REVIEW — back above 50-day avg","REVIEW — below 50-day avg"),"HOLD"))))),IF(OR(AP23="Closed",AP23="Dropped"),"Closed",IF(AK23="A",IF(F23="Short","Run Technical Review — SHORT entry","Run Technical Review — LONG entry"),IF(AK23="B","Watch — wait for setup","Drop or re-check next week"))))) -> Watch — wait for setup | AV23: Agent 2026-10-23T03:09+02:00: LRC rating BUY (6-m value 426.0); NOT CLEARED. Entry 342.47, stop 318.21 (2×ATR), target 415.25 (3R). — LRC Watchlist Agent | AX23: =IF(AND(C23<>"",A23=$C$4,ISNUMBER(AJ23)),AJ23+ROW()/100000,"") -> 10.00023
A24: 46316 | B24: US | C24: DECK | D24: Deckers Outdoor | E24: Technology | F24: Long | G24: 85.49 | I24: 2911073 | J24: =IF(OR(G24="",I24=""),"",G24*I24/1000000) -> 248.86763 | K24: 0.0417 | L24: 0.0183 | M24: -0.1454 | N24: 55.85 | O24: -0.1116 | P24: -0.2061 | Q24: -0.3009 | R24: 0.1074 | S24: 1.01 | U24: 0.0877 | V24: 46317 | W24: 2.49 | X24: LONG: Pullback to 20/50-day avg | Y24: 88.16 | Z24: 83.18 | AA24: 103.1 | AB24: =IF(C24="","",IF(F24="Short",(AND(M24<>"",N(M24)<0))+(AND(L24<>"",N(L24)<0))+(AND(K24<>"",N(K24)<0))+AND(L24<>"",M24<>"",N(M24)<N(L24)),(N(M24)>0)+(N(L24)>0)+(N(K24)>0)+AND(L24<>"",M24<>"",N(M24)>N(L24)))) -> 2 | AC24: =IF(C24="","",IF(F24="Short",IF(N24="",0,IF(AND(N24>=30,N24<=50),2,IF(OR(AND(N24>=25,N24<30),AND(N24>50,N24<=60)),1,0)))+IF(P24="",0,IF(AND(IF(B24="JSE",$L$5,$L$4)<>"",P24<IF(B24="JSE",$L$5,$L$4)),2,IF(P24<0,1,0))),IF(N24="",0,IF(AND(N24>=50,N24<=70),2,IF(OR(AND(N24>=40,N24<50),AND(N24>70,N24<=75)),1,0)))+IF(P24="",0,IF(AND(IF(B24="JSE",$L$5,$L$4)<>"",P24>IF(B24="JSE",$L$5,$L$4)),2,IF(P24>0,1,0))))) -> 2 | AD24: =IF(C24="","",IF(F24="Short",IF(R24="",0,IF(R24<=0.1,2,IF(R24<=0.25,1,0))),IF(Q24="",0,IF(Q24>=-0.1,2,IF(Q24>=-0.25,1,0))))) -> 0 | AE24: =IF(C24="","",IF(J24="",0,IF(J24>=IF(B24="JSE",$L$7,$L$6),2,IF(J24>=IF(B24="JSE",$L$7,$L$6)/4,1,0)))) -> 2 | AF24: =IF(C24="","",IF(F24="Short",AND(T24<>"",N(T24)<0),N(T24)>0)+(N(S24)>=1.5)) -> 0 | AG24: =IF(C24="","",IF(AL24="",0,IF(AL24>=3,4,IF(AL24>=2,2,0)))) -> 4 | AH24: =IF(C24="","",IF(AND(ISNUMBER(V24),ISNUMBER(A24),V24>=A24,V24-A24<=14),-2,0)) -> -2 | AI24: =IF(C24="","",IF(AND(F24="Short",N(U24)>=0.2),-1,0)) -> 0 | AJ24: =IF(C24="","",SUM(AB24:AI24)) -> 8 | AK24: =IF(C24="","",IF(AJ24>=14,"A",IF(AJ24>=10,"B","C"))) -> C | AL24: =IFERROR(IF(OR(Y24="",Z24="",AA24=""),"",IF(F24="Short",IF(Z24<=Y24,"",(Y24-AA24)/(Z24-Y24)),IF(Y24<=Z24,"",(AA24-Y24)/(Y24-Z24)))),"") -> 3 | AM24: =IF(OR(Y24="",Z24="",N(Y24)=N(Z24)),"",IF(OR(AND(F24="Short",Z24<Y24),AND(NOT(F24="Short"),Z24>Y24)),"stop on wrong side",ABS(Y24-Z24))) -> 4.98 | AN24: =IFERROR(IF(OR(NOT(ISNUMBER(AM24)),$C$6=""),"",ROUNDDOWN($C$6*$C$7/AM24,2)),"") -> 0.09 | AO24: =IFERROR(IF(AN24="","",AN24*Y24),"") -> 7.9344 | AP24: Watch | AS24: =IFERROR(IF(OR(AR24="",Y24="",AQ24=""),"",IF(F24="Short",1-AR24/Y24,AR24/Y24-1)),"") | AT24: =IF(AQ24="","",IF(ISNUMBER($C$4),$C$4,TODAY())-AQ24) | AU24: =IF(C24="","",IF(AP24="Open position",IF(IF(F24="Short",AND(ISNUMBER(AR24),ISNUMBER(Z24),AR24>=Z24),AND(ISNUMBER(AR24),ISNUMBER(Z24),AR24<=Z24)),IF(F24="Short","COVER — stop hit (buy back)","SELL — stop hit"),IF(IF(F24="Short",AND(ISNUMBER(AR24),ISNUMBER(AA24),AR24<=AA24),AND(ISNUMBER(AR24),ISNUMBER(AA24),AR24>=AA24)),"TAKE PROFIT — target hit",IF(AND(ISNUMBER(AT24),AT24>182),IF(F24="Short","COVER — 6-month time limit","SELL — 6-month time limit"),IF(AND(ISNUMBER(AT24),AT24>42,ISNUMBER(AS24),AS24<0.02),"REVIEW — no progress after 6 weeks",IF(IF(F24="Short",AND(L24<>"",N(L24)>0),AND(L24<>"",N(L24)<0)),IF(F24="Short","REVIEW — back above 50-day avg","REVIEW — below 50-day avg"),"HOLD"))))),IF(OR(AP24="Closed",AP24="Dropped"),"Closed",IF(AK24="A",IF(F24="Short","Run Technical Review — SHORT entry","Run Technical Review — LONG entry"),IF(AK24="B","Watch — wait for setup","Drop or re-check next week"))))) -> Drop or re-check next week | AV24: Agent 2026-10-23T03:09+02:00: LRC rating BUY (6-m value 103.0); NOT CLEARED — results within 14 days. Entry 88.16, stop 83.18 (2×ATR), target 103.1 (3R). Results 2026-10-22 — LRC Watchlist Agent | AX24: =IF(AND(C24<>"",A24=$C$4,ISNUMBER(AJ24)),AJ24+ROW()/100000,"") -> 8.00024
A25: 46316 | B25: US | C25: GOOGL | D25: Alphabet | E25: Technology | F25: Short | G25: 334.76 | I25: 25764278 | J25: =IF(OR(G25="",I25=""),"",G25*I25/1000000) -> 8624.8497 | K25: -0.0302 | L25: -0.0264 | M25: -0.0191 | N25: 40.25 | O25: 0.0537 | P25: -0.0134 | Q25: -0.1807 | R25: 0.3711 | S25: 1.13 | U25: 0.0074 | V25: 46323 | W25: 8.63 | X25: SHORT: Downtrend continuation | Y25: 329.72 | Z25: 346.98 | AA25: 277.94 | AB25: =IF(C25="","",IF(F25="Short",(AND(M25<>"",N(M25)<0))+(AND(L25<>"",N(L25)<0))+(AND(K25<>"",N(K25)<0))+AND(L25<>"",M25<>"",N(M25)<N(L25)),(N(M25)>0)+(N(L25)>0)+(N(K25)>0)+AND(L25<>"",M25<>"",N(M25)>N(L25)))) -> 3 | AC25: =IF(C25="","",IF(F25="Short",IF(N25="",0,IF(AND(N25>=30,N25<=50),2,IF(OR(AND(N25>=25,N25<30),AND(N25>50,N25<=60)),1,0)))+IF(P25="",0,IF(AND(IF(B25="JSE",$L$5,$L$4)<>"",P25<IF(B25="JSE",$L$5,$L$4)),2,IF(P25<0,1,0))),IF(N25="",0,IF(AND(N25>=50,N25<=70),2,IF(OR(AND(N25>=40,N25<50),AND(N25>70,N25<=75)),1,0)))+IF(P25="",0,IF(AND(IF(B25="JSE",$L$5,$L$4)<>"",P25>IF(B25="JSE",$L$5,$L$4)),2,IF(P25>0,1,0))))) -> 4 | AD25: =IF(C25="","",IF(F25="Short",IF(R25="",0,IF(R25<=0.1,2,IF(R25<=0.25,1,0))),IF(Q25="",0,IF(Q25>=-0.1,2,IF(Q25>=-0.25,1,0))))) -> 0 | AE25: =IF(C25="","",IF(J25="",0,IF(J25>=IF(B25="JSE",$L$7,$L$6),2,IF(J25>=IF(B25="JSE",$L$7,$L$6)/4,1,0)))) -> 2 | AF25: =IF(C25="","",IF(F25="Short",AND(T25<>"",N(T25)<0),N(T25)>0)+(N(S25)>=1.5)) -> 0 | AG25: =IF(C25="","",IF(AL25="",0,IF(AL25>=3,4,IF(AL25>=2,2,0)))) -> 4 | AH25: =IF(C25="","",IF(AND(ISNUMBER(V25),ISNUMBER(A25),V25>=A25,V25-A25<=14),-2,0)) -> -2 | AI25: =IF(C25="","",IF(AND(F25="Short",N(U25)>=0.2),-1,0)) -> 0 | AJ25: =IF(C25="","",SUM(AB25:AI25)) -> 11 | AK25: =IF(C25="","",IF(AJ25>=14,"A",IF(AJ25>=10,"B","C"))) -> B | AL25: =IFERROR(IF(OR(Y25="",Z25="",AA25=""),"",IF(F25="Short",IF(Z25<=Y25,"",(Y25-AA25)/(Z25-Y25)),IF(Y25<=Z25,"",(AA25-Y25)/(Y25-Z25)))),"") -> 3 | AM25: =IF(OR(Y25="",Z25="",N(Y25)=N(Z25)),"",IF(OR(AND(F25="Short",Z25<Y25),AND(NOT(F25="Short"),Z25>Y25)),"stop on wrong side",ABS(Y25-Z25))) -> 17.26 | AN25: =IFERROR(IF(OR(NOT(ISNUMBER(AM25)),$C$6=""),"",ROUNDDOWN($C$6*$C$7/AM25,2)),"") -> 0.02 | AO25: =IFERROR(IF(AN25="","",AN25*Y25),"") -> 6.5944 | AP25: Watch | AS25: =IFERROR(IF(OR(AR25="",Y25="",AQ25=""),"",IF(F25="Short",1-AR25/Y25,AR25/Y25-1)),"") | AT25: =IF(AQ25="","",IF(ISNUMBER($C$4),$C$4,TODAY())-AQ25) | AU25: =IF(C25="","",IF(AP25="Open position",IF(IF(F25="Short",AND(ISNUMBER(AR25),ISNUMBER(Z25),AR25>=Z25),AND(ISNUMBER(AR25),ISNUMBER(Z25),AR25<=Z25)),IF(F25="Short","COVER — stop hit (buy back)","SELL — stop hit"),IF(IF(F25="Short",AND(ISNUMBER(AR25),ISNUMBER(AA25),AR25<=AA25),AND(ISNUMBER(AR25),ISNUMBER(AA25),AR25>=AA25)),"TAKE PROFIT — target hit",IF(AND(ISNUMBER(AT25),AT25>182),IF(F25="Short","COVER — 6-month time limit","SELL — 6-month time limit"),IF(AND(ISNUMBER(AT25),AT25>42,ISNUMBER(AS25),AS25<0.02),"REVIEW — no progress after 6 weeks",IF(IF(F25="Short",AND(L25<>"",N(L25)>0),AND(L25<>"",N(L25)<0)),IF(F25="Short","REVIEW — back above 50-day avg","REVIEW — below 50-day avg"),"HOLD"))))),IF(OR(AP25="Closed",AP25="Dropped"),"Closed",IF(AK25="A",IF(F25="Short","Run Technical Review — SHORT entry","Run Technical Review — LONG entry"),IF(AK25="B","Watch — wait for setup","Drop or re-check next week"))))) -> Watch — wait for setup | AV25: Agent 2026-10-23T03:09+02:00: LRC rating SELL (6-m value 319.72); CLEARED — results within 14 days. Entry 329.72, stop 346.98 (2×ATR), target 277.94 (3R). Results 2026-10-28 — LRC Watchlist Agent | AX25: =IF(AND(C25<>"",A25=$C$4,ISNUMBER(AJ25)),AJ25+ROW()/100000,"") -> 11.00025
A26: 46316 | B26: US | C26: DELL | D26: Dell Technologies | E26: Technology | F26: Short | G26: 485.88 | I26: 7680617 | J26: =IF(OR(G26="",I26=""),"",G26*I26/1000000) -> 3731.8582 | K26: -0.0897 | L26: -0.0552 | M26: 0.5226 | N26: 42.44 | O26: 0.1059 | P26: 1.2636 | Q26: -0.1841 | R26: 3.4083 | S26: 0.89 | T26: 1.514 | U26: 0.0469 | V26: 46350 | W26: 31.67 | X26: SHORT: Breakdown from base | Y26: 438.62 | Z26: 501.96 | AA26: 248.6 | AB26: =IF(C26="","",IF(F26="Short",(AND(M26<>"",N(M26)<0))+(AND(L26<>"",N(L26)<0))+(AND(K26<>"",N(K26)<0))+AND(L26<>"",M26<>"",N(M26)<N(L26)),(N(M26)>0)+(N(L26)>0)+(N(K26)>0)+AND(L26<>"",M26<>"",N(M26)>N(L26)))) -> 2 | AC26: =IF(C26="","",IF(F26="Short",IF(N26="",0,IF(AND(N26>=30,N26<=50),2,IF(OR(AND(N26>=25,N26<30),AND(N26>50,N26<=60)),1,0)))+IF(P26="",0,IF(AND(IF(B26="JSE",$L$5,$L$4)<>"",P26<IF(B26="JSE",$L$5,$L$4)),2,IF(P26<0,1,0))),IF(N26="",0,IF(AND(N26>=50,N26<=70),2,IF(OR(AND(N26>=40,N26<50),AND(N26>70,N26<=75)),1,0)))+IF(P26="",0,IF(AND(IF(B26="JSE",$L$5,$L$4)<>"",P26>IF(B26="JSE",$L$5,$L$4)),2,IF(P26>0,1,0))))) -> 2 | AD26: =IF(C26="","",IF(F26="Short",IF(R26="",0,IF(R26<=0.1,2,IF(R26<=0.25,1,0))),IF(Q26="",0,IF(Q26>=-0.1,2,IF(Q26>=-0.25,1,0))))) -> 0 | AE26: =IF(C26="","",IF(J26="",0,IF(J26>=IF(B26="JSE",$L$7,$L$6),2,IF(J26>=IF(B26="JSE",$L$7,$L$6)/4,1,0)))) -> 2 | AF26: =IF(C26="","",IF(F26="Short",AND(T26<>"",N(T26)<0),N(T26)>0)+(N(S26)>=1.5)) -> 0 | AG26: =IF(C26="","",IF(AL26="",0,IF(AL26>=3,4,IF(AL26>=2,2,0)))) -> 4 | AH26: =IF(C26="","",IF(AND(ISNUMBER(V26),ISNUMBER(A26),V26>=A26,V26-A26<=14),-2,0)) -> 0 | AI26: =IF(C26="","",IF(AND(F26="Short",N(U26)>=0.2),-1,0)) -> 0 | AJ26: =IF(C26="","",SUM(AB26:AI26)) -> 10 | AK26: =IF(C26="","",IF(AJ26>=14,"A",IF(AJ26>=10,"B","C"))) -> B | AL26: =IFERROR(IF(OR(Y26="",Z26="",AA26=""),"",IF(F26="Short",IF(Z26<=Y26,"",(Y26-AA26)/(Z26-Y26)),IF(Y26<=Z26,"",(AA26-Y26)/(Y26-Z26)))),"") -> 3 | AM26: =IF(OR(Y26="",Z26="",N(Y26)=N(Z26)),"",IF(OR(AND(F26="Short",Z26<Y26),AND(NOT(F26="Short"),Z26>Y26)),"stop on wrong side",ABS(Y26-Z26))) -> 63.34 | AN26: =IFERROR(IF(OR(NOT(ISNUMBER(AM26)),$C$6=""),"",ROUNDDOWN($C$6*$C$7/AM26,2)),"") -> 0 | AO26: =IFERROR(IF(AN26="","",AN26*Y26),"") -> 0 | AP26: Watch | AS26: =IFERROR(IF(OR(AR26="",Y26="",AQ26=""),"",IF(F26="Short",1-AR26/Y26,AR26/Y26-1)),"") | AT26: =IF(AQ26="","",IF(ISNUMBER($C$4),$C$4,TODAY())-AQ26) | AU26: =IF(C26="","",IF(AP26="Open position",IF(IF(F26="Short",AND(ISNUMBER(AR26),ISNUMBER(Z26),AR26>=Z26),AND(ISNUMBER(AR26),ISNUMBER(Z26),AR26<=Z26)),IF(F26="Short","COVER — stop hit (buy back)","SELL — stop hit"),IF(IF(F26="Short",AND(ISNUMBER(AR26),ISNUMBER(AA26),AR26<=AA26),AND(ISNUMBER(AR26),ISNUMBER(AA26),AR26>=AA26)),"TAKE PROFIT — target hit",IF(AND(ISNUMBER(AT26),AT26>182),IF(F26="Short","COVER — 6-month time limit","SELL — 6-month time limit"),IF(AND(ISNUMBER(AT26),AT26>42,ISNUMBER(AS26),AS26<0.02),"REVIEW — no progress after 6 weeks",IF(IF(F26="Short",AND(L26<>"",N(L26)>0),AND(L26<>"",N(L26)<0)),IF(F26="Short","REVIEW — back above 50-day avg","REVIEW — below 50-day avg"),"HOLD"))))),IF(OR(AP26="Closed",AP26="Dropped"),"Closed",IF(AK26="A",IF(F26="Short","Run Technical Review — SHORT entry","Run Technical Review — LONG entry"),IF(AK26="B","Watch — wait for setup","Drop or re-check next week"))))) -> Watch — wait for setup | AV26: Agent 2026-10-23T03:09+02:00: LRC rating SELL (6-m value 404.7); CLEARED. Entry 438.62, stop 501.96 (2×ATR), target 248.6 (3R). — LRC Watchlist Agent | AX26: =IF(AND(C26<>"",A26=$C$4,ISNUMBER(AJ26)),AJ26+ROW()/100000,"") -> 10.00026
A27: 46316 | B27: US | C27: KEYS | D27: Keysight | E27: Technology | F27: Short | G27: 341.35 | I27: 1226576 | J27: =IF(OR(G27="",I27=""),"",G27*I27/1000000) -> 418.69172 | K27: -0.0601 | L27: -0.0068 | M27: 0.0914 | N27: 43.84 | O27: 0.0499 | P27: 0.007 | Q27: -0.1246 | R27: 1.0901 | S27: 0.85 | T27: 0.6025 | U27: 0.0144 | V27: 46349 | W27: 12.4 | X27: SHORT: Breakdown from base | Y27: 322.42 | Z27: 347.22 | AA27: 248.02 | AB27: =IF(C27="","",IF(F27="Short",(AND(M27<>"",N(M27)<0))+(AND(L27<>"",N(L27)<0))+(AND(K27<>"",N(K27)<0))+AND(L27<>"",M27<>"",N(M27)<N(L27)),(N(M27)>0)+(N(L27)>0)+(N(K27)>0)+AND(L27<>"",M27<>"",N(M27)>N(L27)))) -> 2 | AC27: =IF(C27="","",IF(F27="Short",IF(N27="",0,IF(AND(N27>=30,N27<=50),2,IF(OR(AND(N27>=25,N27<30),AND(N27>50,N27<=60)),1,0)))+IF(P27="",0,IF(AND(IF(B27="JSE",$L$5,$L$4)<>"",P27<IF(B27="JSE",$L$5,$L$4)),2,IF(P27<0,1,0))),IF(N27="",0,IF(AND(N27>=50,N27<=70),2,IF(OR(AND(N27>=40,N27<50),AND(N27>70,N27<=75)),1,0)))+IF(P27="",0,IF(AND(IF(B27="JSE",$L$5,$L$4)<>"",P27>IF(B27="JSE",$L$5,$L$4)),2,IF(P27>0,1,0))))) -> 4 | AD27: =IF(C27="","",IF(F27="Short",IF(R27="",0,IF(R27<=0.1,2,IF(R27<=0.25,1,0))),IF(Q27="",0,IF(Q27>=-0.1,2,IF(Q27>=-0.25,1,0))))) -> 0 | AE27: =IF(C27="","",IF(J27="",0,IF(J27>=IF(B27="JSE",$L$7,$L$6),2,IF(J27>=IF(B27="JSE",$L$7,$L$6)/4,1,0)))) -> 2 | AF27: =IF(C27="","",IF(F27="Short",AND(T27<>"",N(T27)<0),N(T27)>0)+(N(S27)>=1.5)) -> 0 | AG27: =IF(C27="","",IF(AL27="",0,IF(AL27>=3,4,IF(AL27>=2,2,0)))) -> 4 | AH27: =IF(C27="","",IF(AND(ISNUMBER(V27),ISNUMBER(A27),V27>=A27,V27-A27<=14),-2,0)) -> 0 | AI27: =IF(C27="","",IF(AND(F27="Short",N(U27)>=0.2),-1,0)) -> 0 | AJ27: =IF(C27="","",SUM(AB27:AI27)) -> 12 | AK27: =IF(C27="","",IF(AJ27>=14,"A",IF(AJ27>=10,"B","C"))) -> B | AL27: =IFERROR(IF(OR(Y27="",Z27="",AA27=""),"",IF(F27="Short",IF(Z27<=Y27,"",(Y27-AA27)/(Z27-Y27)),IF(Y27<=Z27,"",(AA27-Y27)/(Y27-Z27)))),"") -> 3 | AM27: =IF(OR(Y27="",Z27="",N(Y27)=N(Z27)),"",IF(OR(AND(F27="Short",Z27<Y27),AND(NOT(F27="Short"),Z27>Y27)),"stop on wrong side",ABS(Y27-Z27))) -> 24.8 | AN27: =IFERROR(IF(OR(NOT(ISNUMBER(AM27)),$C$6=""),"",ROUNDDOWN($C$6*$C$7/AM27,2)),"") -> 0.01 | AO27: =IFERROR(IF(AN27="","",AN27*Y27),"") -> 3.2242 | AP27: Watch | AS27: =IFERROR(IF(OR(AR27="",Y27="",AQ27=""),"",IF(F27="Short",1-AR27/Y27,AR27/Y27-1)),"") | AT27: =IF(AQ27="","",IF(ISNUMBER($C$4),$C$4,TODAY())-AQ27) | AU27: =IF(C27="","",IF(AP27="Open position",IF(IF(F27="Short",AND(ISNUMBER(AR27),ISNUMBER(Z27),AR27>=Z27),AND(ISNUMBER(AR27),ISNUMBER(Z27),AR27<=Z27)),IF(F27="Short","COVER — stop hit (buy back)","SELL — stop hit"),IF(IF(F27="Short",AND(ISNUMBER(AR27),ISNUMBER(AA27),AR27<=AA27),AND(ISNUMBER(AR27),ISNUMBER(AA27),AR27>=AA27)),"TAKE PROFIT — target hit",IF(AND(ISNUMBER(AT27),AT27>182),IF(F27="Short","COVER — 6-month time limit","SELL — 6-month time limit"),IF(AND(ISNUMBER(AT27),AT27>42,ISNUMBER(AS27),AS27<0.02),"REVIEW — no progress after 6 weeks",IF(IF(F27="Short",AND(L27<>"",N(L27)>0),AND(L27<>"",N(L27)<0)),IF(F27="Short","REVIEW — back above 50-day avg","REVIEW — below 50-day avg"),"HOLD"))))),IF(OR(AP27="Closed",AP27="Dropped"),"Closed",IF(AK27="A",IF(F27="Short","Run Technical Review — SHORT entry","Run Technical Review — LONG entry"),IF(AK27="B","Watch — wait for setup","Drop or re-check next week"))))) -> Watch — wait for setup | AV27: Agent 2026-10-23T03:09+02:00: LRC rating SELL (6-m value 319.77); CLEARED. Entry 322.42, stop 347.22 (2×ATR), target 248.02 (3R). — LRC Watchlist Agent | AX27: =IF(AND(C27<>"",A27=$C$4,ISNUMBER(AJ27)),AJ27+ROW()/100000,"") -> 12.00027
A28: 46316 | B28: US | C28: APH | D28: Amphenol | E28: Technology | F28: Short | G28: 79.2 | I28: 12129273 | J28: =IF(OR(G28="",I28=""),"",G28*I28/1000000) -> 960.63842 | K28: -0.059 | L28: -0.0338 | M28: 0.0532 | N28: 39.48 | O28: 0.0062 | P28: 0.0693 | Q28: -0.1193 | R28: 0.3421 | S28: 1 | T28: 0.6088 | U28: 0.0125 | V28: 46323 | W28: 2.68 | X28: SHORT: Breakdown from base | Y28: 77.72 | Z28: 83.08 | AA28: 61.64 | AB28: =IF(C28="","",IF(F28="Short",(AND(M28<>"",N(M28)<0))+(AND(L28<>"",N(L28)<0))+(AND(K28<>"",N(K28)<0))+AND(L28<>"",M28<>"",N(M28)<N(L28)),(N(M28)>0)+(N(L28)>0)+(N(K28)>0)+AND(L28<>"",M28<>"",N(M28)>N(L28)))) -> 2 | AC28: =IF(C28="","",IF(F28="Short",IF(N28="",0,IF(AND(N28>=30,N28<=50),2,IF(OR(AND(N28>=25,N28<30),AND(N28>50,N28<=60)),1,0)))+IF(P28="",0,IF(AND(IF(B28="JSE",$L$5,$L$4)<>"",P28<IF(B28="JSE",$L$5,$L$4)),2,IF(P28<0,1,0))),IF(N28="",0,IF(AND(N28>=50,N28<=70),2,IF(OR(AND(N28>=40,N28<50),AND(N28>70,N28<=75)),1,0)))+IF(P28="",0,IF(AND(IF(B28="JSE",$L$5,$L$4)<>"",P28>IF(B28="JSE",$L$5,$L$4)),2,IF(P28>0,1,0))))) -> 4 | AD28: =IF(C28="","",IF(F28="Short",IF(R28="",0,IF(R28<=0.1,2,IF(R28<=0.25,1,0))),IF(Q28="",0,IF(Q28>=-0.1,2,IF(Q28>=-0.25,1,0))))) -> 0 | AE28: =IF(C28="","",IF(J28="",0,IF(J28>=IF(B28="JSE",$L$7,$L$6),2,IF(J28>=IF(B28="JSE",$L$7,$L$6)/4,1,0)))) -> 2 | AF28: =IF(C28="","",IF(F28="Short",AND(T28<>"",N(T28)<0),N(T28)>0)+(N(S28)>=1.5)) -> 0 | AG28: =IF(C28="","",IF(AL28="",0,IF(AL28>=3,4,IF(AL28>=2,2,0)))) -> 4 | AH28: =IF(C28="","",IF(AND(ISNUMBER(V28),ISNUMBER(A28),V28>=A28,V28-A28<=14),-2,0)) -> -2 | AI28: =IF(C28="","",IF(AND(F28="Short",N(U28)>=0.2),-1,0)) -> 0 | AJ28: =IF(C28="","",SUM(AB28:AI28)) -> 10 | AK28: =IF(C28="","",IF(AJ28>=14,"A",IF(AJ28>=10,"B","C"))) -> B | AL28: =IFERROR(IF(OR(Y28="",Z28="",AA28=""),"",IF(F28="Short",IF(Z28<=Y28,"",(Y28-AA28)/(Z28-Y28)),IF(Y28<=Z28,"",(AA28-Y28)/(Y28-Z28)))),"") -> 3 | AM28: =IF(OR(Y28="",Z28="",N(Y28)=N(Z28)),"",IF(OR(AND(F28="Short",Z28<Y28),AND(NOT(F28="Short"),Z28>Y28)),"stop on wrong side",ABS(Y28-Z28))) -> 5.36 | AN28: =IFERROR(IF(OR(NOT(ISNUMBER(AM28)),$C$6=""),"",ROUNDDOWN($C$6*$C$7/AM28,2)),"") -> 0.08 | AO28: =IFERROR(IF(AN28="","",AN28*Y28),"") -> 6.2176 | AP28: Watch | AS28: =IFERROR(IF(OR(AR28="",Y28="",AQ28=""),"",IF(F28="Short",1-AR28/Y28,AR28/Y28-1)),"") | AT28: =IF(AQ28="","",IF(ISNUMBER($C$4),$C$4,TODAY())-AQ28) | AU28: =IF(C28="","",IF(AP28="Open position",IF(IF(F28="Short",AND(ISNUMBER(AR28),ISNUMBER(Z28),AR28>=Z28),AND(ISNUMBER(AR28),ISNUMBER(Z28),AR28<=Z28)),IF(F28="Short","COVER — stop hit (buy back)","SELL — stop hit"),IF(IF(F28="Short",AND(ISNUMBER(AR28),ISNUMBER(AA28),AR28<=AA28),AND(ISNUMBER(AR28),ISNUMBER(AA28),AR28>=AA28)),"TAKE PROFIT — target hit",IF(AND(ISNUMBER(AT28),AT28>182),IF(F28="Short","COVER — 6-month time limit","SELL — 6-month time limit"),IF(AND(ISNUMBER(AT28),AT28>42,ISNUMBER(AS28),AS28<0.02),"REVIEW — no progress after 6 weeks",IF(IF(F28="Short",AND(L28<>"",N(L28)>0),AND(L28<>"",N(L28)<0)),IF(F28="Short","REVIEW — back above 50-day avg","REVIEW — below 50-day avg"),"HOLD"))))),IF(OR(AP28="Closed",AP28="Dropped"),"Closed",IF(AK28="A",IF(F28="Short","Run Technical Review — SHORT entry","Run Technical Review — LONG entry"),IF(AK28="B","Watch — wait for setup","Drop or re-check next week"))))) -> Watch — wait for setup | AV28: Agent 2026-10-23T03:09+02:00: LRC rating SELL (6-m value 75.63); CLEARED — results within 14 days. Entry 77.72, stop 83.08 (2×ATR), target 61.64 (3R). Results 2026-10-28 — LRC Watchlist Agent | AX28: =IF(AND(C28<>"",A28=$C$4,ISNUMBER(AJ28)),AJ28+ROW()/100000,"") -> 10.00028
A29: 46316 | B29: US | C29: NKE | D29: Nike | E29: Technology | F29: Short | G29: 37.53 | I29: 33149133 | J29: =IF(OR(G29="",I29=""),"",G29*I29/1000000) -> 1244.087 | K29: 0.0518 | L29: 0.0062 | M29: -0.2017 | N29: 59.37 | O29: -0.0844 | P29: -0.1784 | Q29: -0.4672 | R29: 0.1739 | S29: 0.55 | T29: -0.1642 | U29: 0.0842 | W29: 1.06 | X29: SHORT: Downtrend continuation | Y29: 31.91 | Z29: 34.03 | AA29: 25.55 | AB29: =IF(C29="","",IF(F29="Short",(AND(M29<>"",N(M29)<0))+(AND(L29<>"",N(L29)<0))+(AND(K29<>"",N(K29)<0))+AND(L29<>"",M29<>"",N(M29)<N(L29)),(N(M29)>0)+(N(L29)>0)+(N(K29)>0)+AND(L29<>"",M29<>"",N(M29)>N(L29)))) -> 2 | AC29: =IF(C29="","",IF(F29="Short",IF(N29="",0,IF(AND(N29>=30,N29<=50),2,IF(OR(AND(N29>=25,N29<30),AND(N29>50,N29<=60)),1,0)))+IF(P29="",0,IF(AND(IF(B29="JSE",$L$5,$L$4)<>"",P29<IF(B29="JSE",$L$5,$L$4)),2,IF(P29<0,1,0))),IF(N29="",0,IF(AND(N29>=50,N29<=70),2,IF(OR(AND(N29>=40,N29<50),AND(N29>70,N29<=75)),1,0)))+IF(P29="",0,IF(AND(IF(B29="JSE",$L$5,$L$4)<>"",P29>IF(B29="JSE",$L$5,$L$4)),2,IF(P29>0,1,0))))) -> 3 | AD29: =IF(C29="","",IF(F29="Short",IF(R29="",0,IF(R29<=0.1,2,IF(R29<=0.25,1,0))),IF(Q29="",0,IF(Q29>=-0.1,2,IF(Q29>=-0.25,1,0))))) -> 1 | AE29: =IF(C29="","",IF(J29="",0,IF(J29>=IF(B29="JSE",$L$7,$L$6),2,IF(J29>=IF(B29="JSE",$L$7,$L$6)/4,1,0)))) -> 2 | AF29: =IF(C29="","",IF(F29="Short",AND(T29<>"",N(T29)<0),N(T29)>0)+(N(S29)>=1.5)) -> 1 | AG29: =IF(C29="","",IF(AL29="",0,IF(AL29>=3,4,IF(AL29>=2,2,0)))) -> 4 | AH29: =IF(C29="","",IF(AND(ISNUMBER(V29),ISNUMBER(A29),V29>=A29,V29-A29<=14),-2,0)) -> 0 | AI29: =IF(C29="","",IF(AND(F29="Short",N(U29)>=0.2),-1,0)) -> 0 | AJ29: =IF(C29="","",SUM(AB29:AI29)) -> 13 | AK29: =IF(C29="","",IF(AJ29>=14,"A",IF(AJ29>=10,"B","C"))) -> B | AL29: =IFERROR(IF(OR(Y29="",Z29="",AA29=""),"",IF(F29="Short",IF(Z29<=Y29,"",(Y29-AA29)/(Z29-Y29)),IF(Y29<=Z29,"",(AA29-Y29)/(Y29-Z29)))),"") -> 3 | AM29: =IF(OR(Y29="",Z29="",N(Y29)=N(Z29)),"",IF(OR(AND(F29="Short",Z29<Y29),AND(NOT(F29="Short"),Z29>Y29)),"stop on wrong side",ABS(Y29-Z29))) -> 2.12 | AN29: =IFERROR(IF(OR(NOT(ISNUMBER(AM29)),$C$6=""),"",ROUNDDOWN($C$6*$C$7/AM29,2)),"") -> 0.21 | AO29: =IFERROR(IF(AN29="","",AN29*Y29),"") -> 6.7011 | AP29: Watch | AS29: =IFERROR(IF(OR(AR29="",Y29="",AQ29=""),"",IF(F29="Short",1-AR29/Y29,AR29/Y29-1)),"") | AT29: =IF(AQ29="","",IF(ISNUMBER($C$4),$C$4,TODAY())-AQ29) | AU29: =IF(C29="","",IF(AP29="Open position",IF(IF(F29="Short",AND(ISNUMBER(AR29),ISNUMBER(Z29),AR29>=Z29),AND(ISNUMBER(AR29),ISNUMBER(Z29),AR29<=Z29)),IF(F29="Short","COVER — stop hit (buy back)","SELL — stop hit"),IF(IF(F29="Short",AND(ISNUMBER(AR29),ISNUMBER(AA29),AR29<=AA29),AND(ISNUMBER(AR29),ISNUMBER(AA29),AR29>=AA29)),"TAKE PROFIT — target hit",IF(AND(ISNUMBER(AT29),AT29>182),IF(F29="Short","COVER — 6-month time limit","SELL — 6-month time limit"),IF(AND(ISNUMBER(AT29),AT29>42,ISNUMBER(AS29),AS29<0.02),"REVIEW — no progress after 6 weeks",IF(IF(F29="Short",AND(L29<>"",N(L29)>0),AND(L29<>"",N(L29)<0)),IF(F29="Short","REVIEW — back above 50-day avg","REVIEW — below 50-day avg"),"HOLD"))))),IF(OR(AP29="Closed",AP29="Dropped"),"Closed",IF(AK29="A",IF(F29="Short","Run Technical Review — SHORT entry","Run Technical Review — LONG entry"),IF(AK29="B","Watch — wait for setup","Drop or re-check next week"))))) -> Watch — wait for setup | AV29: Agent 2026-10-23T03:09+02:00: LRC rating SELL (6-m value 29.75); CLEARED. Entry 31.91, stop 34.03 (2×ATR), target 25.55 (3R). house limit: max 4 shorts — LRC Watchlist Agent | AX29: =IF(AND(C29<>"",A29=$C$4,ISNUMBER(AJ29)),AJ29+ROW()/100000,"") -> 13.00029
A30: 46316 | B30: US | C30: META | D30: Meta Platforms | E30: Technology | F30: Short | G30: 697.52 | I30: 19309160 | J30: =IF(OR(G30="",I30=""),"",G30*I30/1000000) -> 13468.525 | K30: -0.0439 | L30: 0.0545 | M30: 0.1026 | N30: 47.35 | O30: 0.1508 | P30: 0.0338 | Q30: -0.1055 | R30: 0.3407 | S30: 1.51 | U30: 0.0152 | V30: 46316 | W30: 24.5 | X30: SHORT: Breakdown from base | Y30: 679.69 | Z30: 728.69 | AA30: 532.69 | AB30: =IF(C30="","",IF(F30="Short",(AND(M30<>"",N(M30)<0))+(AND(L30<>"",N(L30)<0))+(AND(K30<>"",N(K30)<0))+AND(L30<>"",M30<>"",N(M30)<N(L30)),(N(M30)>0)+(N(L30)>0)+(N(K30)>0)+AND(L30<>"",M30<>"",N(M30)>N(L30)))) -> 1 | AC30: =IF(C30="","",IF(F30="Short",IF(N30="",0,IF(AND(N30>=30,N30<=50),2,IF(OR(AND(N30>=25,N30<30),AND(N30>50,N30<=60)),1,0)))+IF(P30="",0,IF(AND(IF(B30="JSE",$L$5,$L$4)<>"",P30<IF(B30="JSE",$L$5,$L$4)),2,IF(P30<0,1,0))),IF(N30="",0,IF(AND(N30>=50,N30<=70),2,IF(OR(AND(N30>=40,N30<50),AND(N30>70,N30<=75)),1,0)))+IF(P30="",0,IF(AND(IF(B30="JSE",$L$5,$L$4)<>"",P30>IF(B30="JSE",$L$5,$L$4)),2,IF(P30>0,1,0))))) -> 4 | AD30: =IF(C30="","",IF(F30="Short",IF(R30="",0,IF(R30<=0.1,2,IF(R30<=0.25,1,0))),IF(Q30="",0,IF(Q30>=-0.1,2,IF(Q30>=-0.25,1,0))))) -> 0 | AE30: =IF(C30="","",IF(J30="",0,IF(J30>=IF(B30="JSE",$L$7,$L$6),2,IF(J30>=IF(B30="JSE",$L$7,$L$6)/4,1,0)))) -> 2 | AF30: =IF(C30="","",IF(F30="Short",AND(T30<>"",N(T30)<0),N(T30)>0)+(N(S30)>=1.5)) -> 1 | AG30: =IF(C30="","",IF(AL30="",0,IF(AL30>=3,4,IF(AL30>=2,2,0)))) -> 4 | AH30: =IF(C30="","",IF(AND(ISNUMBER(V30),ISNUMBER(A30),V30>=A30,V30-A30<=14),-2,0)) -> -2 | AI30: =IF(C30="","",IF(AND(F30="Short",N(U30)>=0.2),-1,0)) -> 0 | AJ30: =IF(C30="","",SUM(AB30:AI30)) -> 10 | AK30: =IF(C30="","",IF(AJ30>=14,"A",IF(AJ30>=10,"B","C"))) -> B | AL30: =IFERROR(IF(OR(Y30="",Z30="",AA30=""),"",IF(F30="Short",IF(Z30<=Y30,"",(Y30-AA30)/(Z30-Y30)),IF(Y30<=Z30,"",(AA30-Y30)/(Y30-Z30)))),"") -> 3 | AM30: =IF(OR(Y30="",Z30="",N(Y30)=N(Z30)),"",IF(OR(AND(F30="Short",Z30<Y30),AND(NOT(F30="Short"),Z30>Y30)),"stop on wrong side",ABS(Y30-Z30))) -> 49 | AN30: =IFERROR(IF(OR(NOT(ISNUMBER(AM30)),$C$6=""),"",ROUNDDOWN($C$6*$C$7/AM30,2)),"") -> 0 | AO30: =IFERROR(IF(AN30="","",AN30*Y30),"") -> 0 | AP30: Watch | AS30: =IFERROR(IF(OR(AR30="",Y30="",AQ30=""),"",IF(F30="Short",1-AR30/Y30,AR30/Y30-1)),"") | AT30: =IF(AQ30="","",IF(ISNUMBER($C$4),$C$4,TODAY())-AQ30) | AU30: =IF(C30="","",IF(AP30="Open position",IF(IF(F30="Short",AND(ISNUMBER(AR30),ISNUMBER(Z30),AR30>=Z30),AND(ISNUMBER(AR30),ISNUMBER(Z30),AR30<=Z30)),IF(F30="Short","COVER — stop hit (buy back)","SELL — stop hit"),IF(IF(F30="Short",AND(ISNUMBER(AR30),ISNUMBER(AA30),AR30<=AA30),AND(ISNUMBER(AR30),ISNUMBER(AA30),AR30>=AA30)),"TAKE PROFIT — target hit",IF(AND(ISNUMBER(AT30),AT30>182),IF(F30="Short","COVER — 6-month time limit","SELL — 6-month time limit"),IF(AND(ISNUMBER(AT30),AT30>42,ISNUMBER(AS30),AS30<0.02),"REVIEW — no progress after 6 weeks",IF(IF(F30="Short",AND(L30<>"",N(L30)>0),AND(L30<>"",N(L30)<0)),IF(F30="Short","REVIEW — back above 50-day avg","REVIEW — below 50-day avg"),"HOLD"))))),IF(OR(AP30="Closed",AP30="Dropped"),"Closed",IF(AK30="A",IF(F30="Short","Run Technical Review — SHORT entry","Run Technical Review — LONG entry"),IF(AK30="B","Watch — wait for setup","Drop or re-check next week"))))) -> Watch — wait for setup | AV30: Agent 2026-10-23T03:09+02:00: LRC rating SELL (6-m value 677.14); CLEARED — results within 14 days. Entry 679.69, stop 728.69 (2×ATR), target 532.69 (3R). Results 2026-10-21; house limit: max 4 shorts — LRC Watchlist Agent | AX30: =IF(AND(C30<>"",A30=$C$4,ISNUMBER(AJ30)),AJ30+ROW()/100000,"") -> 10.0003
A31: 46316 | B31: US | C31: ANET | D31: Arista Networks | E31: Technology | F31: Short | G31: 184.33 | I31: 6108406 | J31: =IF(OR(G31="",I31=""),"",G31*I31/1000000) -> 1125.9625 | K31: -0.0837 | L31: -0.0682 | M31: 0.1283 | N31: 39.57 | O31: 0.0437 | P31: 0.0371 | Q31: -0.1522 | R31: 0.6096 | S31: 1.08 | U31: 0.0114 | V31: 46329 | W31: 8.2 | X31: SHORT: Breakdown from base | Y31: 176.42 | Z31: 192.82 | AA31: 127.22 | AB31: =IF(C31="","",IF(F31="Short",(AND(M31<>"",N(M31)<0))+(AND(L31<>"",N(L31)<0))+(AND(K31<>"",N(K31)<0))+AND(L31<>"",M31<>"",N(M31)<N(L31)),(N(M31)>0)+(N(L31)>0)+(N(K31)>0)+AND(L31<>"",M31<>"",N(M31)>N(L31)))) -> 2 | AC31: =IF(C31="","",IF(F31="Short",IF(N31="",0,IF(AND(N31>=30,N31<=50),2,IF(OR(AND(N31>=25,N31<30),AND(N31>50,N31<=60)),1,0)))+IF(P31="",0,IF(AND(IF(B31="JSE",$L$5,$L$4)<>"",P31<IF(B31="JSE",$L$5,$L$4)),2,IF(P31<0,1,0))),IF(N31="",0,IF(AND(N31>=50,N31<=70),2,IF(OR(AND(N31>=40,N31<50),AND(N31>70,N31<=75)),1,0)))+IF(P31="",0,IF(AND(IF(B31="JSE",$L$5,$L$4)<>"",P31>IF(B31="JSE",$L$5,$L$4)),2,IF(P31>0,1,0))))) -> 4 | AD31: =IF(C31="","",IF(F31="Short",IF(R31="",0,IF(R31<=0.1,2,IF(R31<=0.25,1,0))),IF(Q31="",0,IF(Q31>=-0.1,2,IF(Q31>=-0.25,1,0))))) -> 0 | AE31: =IF(C31="","",IF(J31="",0,IF(J31>=IF(B31="JSE",$L$7,$L$6),2,IF(J31>=IF(B31="JSE",$L$7,$L$6)/4,1,0)))) -> 2 | AF31: =IF(C31="","",IF(F31="Short",AND(T31<>"",N(T31)<0),N(T31)>0)+(N(S31)>=1.5)) -> 0 | AG31: =IF(C31="","",IF(AL31="",0,IF(AL31>=3,4,IF(AL31>=2,2,0)))) -> 4 | AH31: =IF(C31="","",IF(AND(ISNUMBER(V31),ISNUMBER(A31),V31>=A31,V31-A31<=14),-2,0)) -> -2 | AI31: =IF(C31="","",IF(AND(F31="Short",N(U31)>=0.2),-1,0)) -> 0 | AJ31: =IF(C31="","",SUM(AB31:AI31)) -> 10 | AK31: =IF(C31="","",IF(AJ31>=14,"A",IF(AJ31>=10,"B","C"))) -> B | AL31: =IFERROR(IF(OR(Y31="",Z31="",AA31=""),"",IF(F31="Short",IF(Z31<=Y31,"",(Y31-AA31)/(Z31-Y31)),IF(Y31<=Z31,"",(AA31-Y31)/(Y31-Z31)))),"") -> 3 | AM31: =IF(OR(Y31="",Z31="",N(Y31)=N(Z31)),"",IF(OR(AND(F31="Short",Z31<Y31),AND(NOT(F31="Short"),Z31>Y31)),"stop on wrong side",ABS(Y31-Z31))) -> 16.4 | AN31: =IFERROR(IF(OR(NOT(ISNUMBER(AM31)),$C$6=""),"",ROUNDDOWN($C$6*$C$7/AM31,2)),"") -> 0.02 | AO31: =IFERROR(IF(AN31="","",AN31*Y31),"") -> 3.5284 | AP31: Watch | AS31: =IFERROR(IF(OR(AR31="",Y31="",AQ31=""),"",IF(F31="Short",1-AR31/Y31,AR31/Y31-1)),"") | AT31: =IF(AQ31="","",IF(ISNUMBER($C$4),$C$4,TODAY())-AQ31) | AU31: =IF(C31="","",IF(AP31="Open position",IF(IF(F31="Short",AND(ISNUMBER(AR31),ISNUMBER(Z31),AR31>=Z31),AND(ISNUMBER(AR31),ISNUMBER(Z31),AR31<=Z31)),IF(F31="Short","COVER — stop hit (buy back)","SELL — stop hit"),IF(IF(F31="Short",AND(ISNUMBER(AR31),ISNUMBER(AA31),AR31<=AA31),AND(ISNUMBER(AR31),ISNUMBER(AA31),AR31>=AA31)),"TAKE PROFIT — target hit",IF(AND(ISNUMBER(AT31),AT31>182),IF(F31="Short","COVER — 6-month time limit","SELL — 6-month time limit"),IF(AND(ISNUMBER(AT31),AT31>42,ISNUMBER(AS31),AS31<0.02),"REVIEW — no progress after 6 weeks",IF(IF(F31="Short",AND(L31<>"",N(L31)>0),AND(L31<>"",N(L31)<0)),IF(F31="Short","REVIEW — back above 50-day avg","REVIEW — below 50-day avg"),"HOLD"))))),IF(OR(AP31="Closed",AP31="Dropped"),"Closed",IF(AK31="A",IF(F31="Short","Run Technical Review — SHORT entry","Run Technical Review — LONG entry"),IF(AK31="B","Watch — wait for setup","Drop or re-check next week"))))) -> Watch — wait for setup | AV31: Agent 2026-10-23T03:09+02:00: LRC rating SELL (6-m value 144.61); CLEARED — results within 14 days. Entry 176.42, stop 192.82 (2×ATR), target 127.22 (3R). Results 2026-11-03; house limit: max 4 shorts — LRC Watchlist Agent | AX31: =IF(AND(C31<>"",A31=$C$4,ISNUMBER(AJ31)),AJ31+ROW()/100000,"") -> 10.00031
A32: 46316 | B32: US | C32: FAST | D32: Fastenal | E32: Technology | F32: Short | G32: 52.49 | I32: 7468324 | J32: =IF(OR(G32="",I32=""),"",G32*I32/1000000) -> 392.01233 | K32: 0.0331 | L32: 0.0421 | M32: 0.1204 | N32: 62.92 | O32: 0.1374 | P32: 0.1714 | Q32: -0.0081 | R32: 0.3469 | S32: 0.85 | U32: 0.0302 | V32: 46309 | W32: 1.32 | X32: SHORT: Breakdown from base | Y32: 47.21 | Z32: 49.85 | AA32: 39.29 | AB32: =IF(C32="","",IF(F32="Short",(AND(M32<>"",N(M32)<0))+(AND(L32<>"",N(L32)<0))+(AND(K32<>"",N(K32)<0))+AND(L32<>"",M32<>"",N(M32)<N(L32)),(N(M32)>0)+(N(L32)>0)+(N(K32)>0)+AND(L32<>"",M32<>"",N(M32)>N(L32)))) -> 0 | AC32: =IF(C32="","",IF(F32="Short",IF(N32="",0,IF(AND(N32>=30,N32<=50),2,IF(OR(AND(N32>=25,N32<30),AND(N32>50,N32<=60)),1,0)))+IF(P32="",0,IF(AND(IF(B32="JSE",$L$5,$L$4)<>"",P32<IF(B32="JSE",$L$5,$L$4)),2,IF(P32<0,1,0))),IF(N32="",0,IF(AND(N32>=50,N32<=70),2,IF(OR(AND(N32>=40,N32<50),AND(N32>70,N32<=75)),1,0)))+IF(P32="",0,IF(AND(IF(B32="JSE",$L$5,$L$4)<>"",P32>IF(B32="JSE",$L$5,$L$4)),2,IF(P32>0,1,0))))) -> 0 | AD32: =IF(C32="","",IF(F32="Short",IF(R32="",0,IF(R32<=0.1,2,IF(R32<=0.25,1,0))),IF(Q32="",0,IF(Q32>=-0.1,2,IF(Q32>=-0.25,1,0))))) -> 0 | AE32: =IF(C32="","",IF(J32="",0,IF(J32>=IF(B32="JSE",$L$7,$L$6),2,IF(J32>=IF(B32="JSE",$L$7,$L$6)/4,1,0)))) -> 2 | AF32: =IF(C32="","",IF(F32="Short",AND(T32<>"",N(T32)<0),N(T32)>0)+(N(S32)>=1.5)) -> 0 | AG32: =IF(C32="","",IF(AL32="",0,IF(AL32>=3,4,IF(AL32>=2,2,0)))) -> 4 | AH32: =IF(C32="","",IF(AND(ISNUMBER(V32),ISNUMBER(A32),V32>=A32,V32-A32<=14),-2,0)) -> 0 | AI32: =IF(C32="","",IF(AND(F32="Short",N(U32)>=0.2),-1,0)) -> 0 | AJ32: =IF(C32="","",SUM(AB32:AI32)) -> 6 | AK32: =IF(C32="","",IF(AJ32>=14,"A",IF(AJ32>=10,"B","C"))) -> C | AL32: =IFERROR(IF(OR(Y32="",Z32="",AA32=""),"",IF(F32="Short",IF(Z32<=Y32,"",(Y32-AA32)/(Z32-Y32)),IF(Y32<=Z32,"",(AA32-Y32)/(Y32-Z32)))),"") -> 3 | AM32: =IF(OR(Y32="",Z32="",N(Y32)=N(Z32)),"",IF(OR(AND(F32="Short",Z32<Y32),AND(NOT(F32="Short"),Z32>Y32)),"stop on wrong side",ABS(Y32-Z32))) -> 2.64 | AN32: =IFERROR(IF(OR(NOT(ISNUMBER(AM32)),$C$6=""),"",ROUNDDOWN($C$6*$C$7/AM32,2)),"") -> 0.17 | AO32: =IFERROR(IF(AN32="","",AN32*Y32),"") -> 8.0257 | AP32: Watch | AS32: =IFERROR(IF(OR(AR32="",Y32="",AQ32=""),"",IF(F32="Short",1-AR32/Y32,AR32/Y32-1)),"") | AT32: =IF(AQ32="","",IF(ISNUMBER($C$4),$C$4,TODAY())-AQ32) | AU32: =IF(C32="","",IF(AP32="Open position",IF(IF(F32="Short",AND(ISNUMBER(AR32),ISNUMBER(Z32),AR32>=Z32),AND(ISNUMBER(AR32),ISNUMBER(Z32),AR32<=Z32)),IF(F32="Short","COVER — stop hit (buy back)","SELL — stop hit"),IF(IF(F32="Short",AND(ISNUMBER(AR32),ISNUMBER(AA32),AR32<=AA32),AND(ISNUMBER(AR32),ISNUMBER(AA32),AR32>=AA32)),"TAKE PROFIT — target hit",IF(AND(ISNUMBER(AT32),AT32>182),IF(F32="Short","COVER — 6-month time limit","SELL — 6-month time limit"),IF(AND(ISNUMBER(AT32),AT32>42,ISNUMBER(AS32),AS32<0.02),"REVIEW — no progress after 6 weeks",IF(IF(F32="Short",AND(L32<>"",N(L32)>0),AND(L32<>"",N(L32)<0)),IF(F32="Short","REVIEW — back above 50-day avg","REVIEW — below 50-day avg"),"HOLD"))))),IF(OR(AP32="Closed",AP32="Dropped"),"Closed",IF(AK32="A",IF(F32="Short","Run Technical Review — SHORT entry","Run Technical Review — LONG entry"),IF(AK32="B","Watch — wait for setup","Drop or re-check next week"))))) -> Drop or re-check next week | AV32: Agent 2026-10-23T03:09+02:00: LRC rating SELL (6-m value 38.37); CLEARED. Entry 47.21, stop 49.85 (2×ATR), target 39.29 (3R). house limit: max 4 shorts — LRC Watchlist Agent | AX32: =IF(AND(C32<>"",A32=$C$4,ISNUMBER(AJ32)),AJ32+ROW()/100000,"") -> 6.00032
A33: 46316 | B33: US | C33: AMD | D33: Advanced Micro Devices | E33: Technology | F33: Short | G33: 552.72 | I33: 22280195 | J33: =IF(OR(G33="",I33=""),"",G33*I33/1000000) -> 12314.709 | K33: -0.0772 | L33: 0.0215 | M33: 0.385 | N33: 45.07 | O33: 0.0241 | P33: 0.8214 | Q33: -0.1607 | R33: 1.9366 | S33: 0.81 | T33: 0.819 | U33: 0.0242 | V33: 46329 | W33: 26.55 | X33: SHORT: Breakdown from base | Y33: 523.55 | Z33: 576.65 | AA33: 364.25 | AB33: =IF(C33="","",IF(F33="Short",(AND(M33<>"",N(M33)<0))+(AND(L33<>"",N(L33)<0))+(AND(K33<>"",N(K33)<0))+AND(L33<>"",M33<>"",N(M33)<N(L33)),(N(M33)>0)+(N(L33)>0)+(N(K33)>0)+AND(L33<>"",M33<>"",N(M33)>N(L33)))) -> 1 | AC33: =IF(C33="","",IF(F33="Short",IF(N33="",0,IF(AND(N33>=30,N33<=50),2,IF(OR(AND(N33>=25,N33<30),AND(N33>50,N33<=60)),1,0)))+IF(P33="",0,IF(AND(IF(B33="JSE",$L$5,$L$4)<>"",P33<IF(B33="JSE",$L$5,$L$4)),2,IF(P33<0,1,0))),IF(N33="",0,IF(AND(N33>=50,N33<=70),2,IF(OR(AND(N33>=40,N33<50),AND(N33>70,N33<=75)),1,0)))+IF(P33="",0,IF(AND(IF(B33="JSE",$L$5,$L$4)<>"",P33>IF(B33="JSE",$L$5,$L$4)),2,IF(P33>0,1,0))))) -> 2 | AD33: =IF(C33="","",IF(F33="Short",IF(R33="",0,IF(R33<=0.1,2,IF(R33<=0.25,1,0))),IF(Q33="",0,IF(Q33>=-0.1,2,IF(Q33>=-0.25,1,0))))) -> 0 | AE33: =IF(C33="","",IF(J33="",0,IF(J33>=IF(B33="JSE",$L$7,$L$6),2,IF(J33>=IF(B33="JSE",$L$7,$L$6)/4,1,0)))) -> 2 | AF33: =IF(C33="","",IF(F33="Short",AND(T33<>"",N(T33)<0),N(T33)>0)+(N(S33)>=1.5)) -> 0 | AG33: =IF(C33="","",IF(AL33="",0,IF(AL33>=3,4,IF(AL33>=2,2,0)))) -> 4 | AH33: =IF(C33="","",IF(AND(ISNUMBER(V33),ISNUMBER(A33),V33>=A33,V33-A33<=14),-2,0)) -> -2 | AI33: =IF(C33="","",IF(AND(F33="Short",N(U33)>=0.2),-1,0)) -> 0 | AJ33: =IF(C33="","",SUM(AB33:AI33)) -> 7 | AK33: =IF(C33="","",IF(AJ33>=14,"A",IF(AJ33>=10,"B","C"))) -> C | AL33: =IFERROR(IF(OR(Y33="",Z33="",AA33=""),"",IF(F33="Short",IF(Z33<=Y33,"",(Y33-AA33)/(Z33-Y33)),IF(Y33<=Z33,"",(AA33-Y33)/(Y33-Z33)))),"") -> 3 | AM33: =IF(OR(Y33="",Z33="",N(Y33)=N(Z33)),"",IF(OR(AND(F33="Short",Z33<Y33),AND(NOT(F33="Short"),Z33>Y33)),"stop on wrong side",ABS(Y33-Z33))) -> 53.1 | AN33: =IFERROR(IF(OR(NOT(ISNUMBER(AM33)),$C$6=""),"",ROUNDDOWN($C$6*$C$7/AM33,2)),"") -> 0 | AO33: =IFERROR(IF(AN33="","",AN33*Y33),"") -> 0 | AP33: Watch | AS33: =IFERROR(IF(OR(AR33="",Y33="",AQ33=""),"",IF(F33="Short",1-AR33/Y33,AR33/Y33-1)),"") | AT33: =IF(AQ33="","",IF(ISNUMBER($C$4),$C$4,TODAY())-AQ33) | AU33: =IF(C33="","",IF(AP33="Open position",IF(IF(F33="Short",AND(ISNUMBER(AR33),ISNUMBER(Z33),AR33>=Z33),AND(ISNUMBER(AR33),ISNUMBER(Z33),AR33<=Z33)),IF(F33="Short","COVER — stop hit (buy back)","SELL — stop hit"),IF(IF(F33="Short",AND(ISNUMBER(AR33),ISNUMBER(AA33),AR33<=AA33),AND(ISNUMBER(AR33),ISNUMBER(AA33),AR33>=AA33)),"TAKE PROFIT — target hit",IF(AND(ISNUMBER(AT33),AT33>182),IF(F33="Short","COVER — 6-month time limit","SELL — 6-month time limit"),IF(AND(ISNUMBER(AT33),AT33>42,ISNUMBER(AS33),AS33<0.02),"REVIEW — no progress after 6 weeks",IF(IF(F33="Short",AND(L33<>"",N(L33)>0),AND(L33<>"",N(L33)<0)),IF(F33="Short","REVIEW — back above 50-day avg","REVIEW — below 50-day avg"),"HOLD"))))),IF(OR(AP33="Closed",AP33="Dropped"),"Closed",IF(AK33="A",IF(F33="Short","Run Technical Review — SHORT entry","Run Technical Review — LONG entry"),IF(AK33="B","Watch — wait for setup","Drop or re-check next week"))))) -> Drop or re-check next week | AV33: Agent 2026-10-23T03:09+02:00: LRC rating SELL (6-m value 402.73); CLEARED — results within 14 days. Entry 523.55, stop 576.65 (2×ATR), target 364.25 (3R). Results 2026-11-03; house limit: max 4 shorts — LRC Watchlist Agent | AX33: =IF(AND(C33<>"",A33=$C$4,ISNUMBER(AJ33)),AJ33+ROW()/100000,"") -> 7.00033
A34: 46316 | B34: US | C34: WAB | D34: Wabtec | E34: Technology | F34: Short | G34: 288.96 | I34: 891537 | J34: =IF(OR(G34="",I34=""),"",G34*I34/1000000) -> 257.61853 | K34: 0.0053 | L34: 0.0035 | M34: 0.0862 | N34: 53.74 | O34: -0.0303 | P34: 0.1049 | Q34: -0.0577 | R34: 0.553 | S34: 2.87 | U34: 0.0212 | V34: 46316 | W34: 7 | X34: SHORT: Breakdown from base | Y34: 274.58 | Z34: 288.58 | AA34: 232.58 | AB34: =IF(C34="","",IF(F34="Short",(AND(M34<>"",N(M34)<0))+(AND(L34<>"",N(L34)<0))+(AND(K34<>"",N(K34)<0))+AND(L34<>"",M34<>"",N(M34)<N(L34)),(N(M34)>0)+(N(L34)>0)+(N(K34)>0)+AND(L34<>"",M34<>"",N(M34)>N(L34)))) -> 0 | AC34: =IF(C34="","",IF(F34="Short",IF(N34="",0,IF(AND(N34>=30,N34<=50),2,IF(OR(AND(N34>=25,N34<30),AND(N34>50,N34<=60)),1,0)))+IF(P34="",0,IF(AND(IF(B34="JSE",$L$5,$L$4)<>"",P34<IF(B34="JSE",$L$5,$L$4)),2,IF(P34<0,1,0))),IF(N34="",0,IF(AND(N34>=50,N34<=70),2,IF(OR(AND(N34>=40,N34<50),AND(N34>70,N34<=75)),1,0)))+IF(P34="",0,IF(AND(IF(B34="JSE",$L$5,$L$4)<>"",P34>IF(B34="JSE",$L$5,$L$4)),2,IF(P34>0,1,0))))) -> 3 | AD34: =IF(C34="","",IF(F34="Short",IF(R34="",0,IF(R34<=0.1,2,IF(R34<=0.25,1,0))),IF(Q34="",0,IF(Q34>=-0.1,2,IF(Q34>=-0.25,1,0))))) -> 0 | AE34: =IF(C34="","",IF(J34="",0,IF(J34>=IF(B34="JSE",$L$7,$L$6),2,IF(J34>=IF(B34="JSE",$L$7,$L$6)/4,1,0)))) -> 2 | AF34: =IF(C34="","",IF(F34="Short",AND(T34<>"",N(T34)<0),N(T34)>0)+(N(S34)>=1.5)) -> 1 | AG34: =IF(C34="","",IF(AL34="",0,IF(AL34>=3,4,IF(AL34>=2,2,0)))) -> 4 | AH34: =IF(C34="","",IF(AND(ISNUMBER(V34),ISNUMBER(A34),V34>=A34,V34-A34<=14),-2,0)) -> -2 | AI34: =IF(C34="","",IF(AND(F34="Short",N(U34)>=0.2),-1,0)) -> 0 | AJ34: =IF(C34="","",SUM(AB34:AI34)) -> 8 | AK34: =IF(C34="","",IF(AJ34>=14,"A",IF(AJ34>=10,"B","C"))) -> C | AL34: =IFERROR(IF(OR(Y34="",Z34="",AA34=""),"",IF(F34="Short",IF(Z34<=Y34,"",(Y34-AA34)/(Z34-Y34)),IF(Y34<=Z34,"",(AA34-Y34)/(Y34-Z34)))),"") -> 3 | AM34: =IF(OR(Y34="",Z34="",N(Y34)=N(Z34)),"",IF(OR(AND(F34="Short",Z34<Y34),AND(NOT(F34="Short"),Z34>Y34)),"stop on wrong side",ABS(Y34-Z34))) -> 14 | AN34: =IFERROR(IF(OR(NOT(ISNUMBER(AM34)),$C$6=""),"",ROUNDDOWN($C$6*$C$7/AM34,2)),"") -> 0.03 | AO34: =IFERROR(IF(AN34="","",AN34*Y34),"") -> 8.2374 | AP34: Watch | AS34: =IFERROR(IF(OR(AR34="",Y34="",AQ34=""),"",IF(F34="Short",1-AR34/Y34,AR34/Y34-1)),"") | AT34: =IF(AQ34="","",IF(ISNUMBER($C$4),$C$4,TODAY())-AQ34) | AU34: =IF(C34="","",IF(AP34="Open position",IF(IF(F34="Short",AND(ISNUMBER(AR34),ISNUMBER(Z34),AR34>=Z34),AND(ISNUMBER(AR34),ISNUMBER(Z34),AR34<=Z34)),IF(F34="Short","COVER — stop hit (buy back)","SELL — stop hit"),IF(IF(F34="Short",AND(ISNUMBER(AR34),ISNUMBER(AA34),AR34<=AA34),AND(ISNUMBER(AR34),ISNUMBER(AA34),AR34>=AA34)),"TAKE PROFIT — target hit",IF(AND(ISNUMBER(AT34),AT34>182),IF(F34="Short","COVER — 6-month time limit","SELL — 6-month time limit"),IF(AND(ISNUMBER(AT34),AT34>42,ISNUMBER(AS34),AS34<0.02),"REVIEW — no progress after 6 weeks",IF(IF(F34="Short",AND(L34<>"",N(L34)>0),AND(L34<>"",N(L34)<0)),IF(F34="Short","REVIEW — back above 50-day avg","REVIEW — below 50-day avg"),"HOLD"))))),IF(OR(AP34="Closed",AP34="Dropped"),"Closed",IF(AK34="A",IF(F34="Short","Run Technical Review — SHORT entry","Run Technical Review — LONG entry"),IF(AK34="B","Watch — wait for setup","Drop or re-check next week"))))) -> Drop or re-check next week | AV34: Agent 2026-10-23T03:09+02:00: LRC rating SELL (6-m value 248.07); CLEARED — results within 14 days. Entry 274.58, stop 288.58 (2×ATR), target 232.58 (3R). Results 2026-10-21; house limit: max 4 shorts — LRC Watchlist Agent | AX34: =IF(AND(C34<>"",A34=$C$4,ISNUMBER(AJ34)),AJ34+ROW()/100000,"") -> 8.00034
J35: =IF(OR(G35="",I35=""),"",G35*I35/1000000) | AB35: =IF(C35="","",IF(F35="Short",(AND(M35<>"",N(M35)<0))+(AND(L35<>"",N(L35)<0))+(AND(K35<>"",N(K35)<0))+AND(L35<>"",M35<>"",N(M35)<N(L35)),(N(M35)>0)+(N(L35)>0)+(N(K35)>0)+AND(L35<>"",M35<>"",N(M35)>N(L35)))) | AC35: =IF(C35="","",IF(F35="Short",IF(N35="",0,IF(AND(N35>=30,N35<=50),2,IF(OR(AND(N35>=25,N35<30),AND(N35>50,N35<=60)),1,0)))+IF(P35="",0,IF(AND(IF(B35="JSE",$L$5,$L$4)<>"",P35<IF(B35="JSE",$L$5,$L$4)),2,IF(P35<0,1,0))),IF(N35="",0,IF(AND(N35>=50,N35<=70),2,IF(OR(AND(N35>=40,N35<50),AND(N35>70,N35<=75)),1,0)))+IF(P35="",0,IF(AND(IF(B35="JSE",$L$5,$L$4)<>"",P35>IF(B35="JSE",$L$5,$L$4)),2,IF(P35>0,1,0))))) | AD35: =IF(C35="","",IF(F35="Short",IF(R35="",0,IF(R35<=0.1,2,IF(R35<=0.25,1,0))),IF(Q35="",0,IF(Q35>=-0.1,2,IF(Q35>=-0.25,1,0))))) | AE35: =IF(C35="","",IF(J35="",0,IF(J35>=IF(B35="JSE",$L$7,$L$6),2,IF(J35>=IF(B35="JSE",$L$7,$L$6)/4,1,0)))) | AF35: =IF(C35="","",IF(F35="Short",AND(T35<>"",N(T35)<0),N(T35)>0)+(N(S35)>=1.5)) | AG35: =IF(C35="","",IF(AL35="",0,IF(AL35>=3,4,IF(AL35>=2,2,0)))) | AH35: =IF(C35="","",IF(AND(ISNUMBER(V35),ISNUMBER(A35),V35>=A35,V35-A35<=14),-2,0)) | AI35: =IF(C35="","",IF(AND(F35="Short",N(U35)>=0.2),-1,0)) | AJ35: =IF(C35="","",SUM(AB35:AI35)) | AK35: =IF(C35="","",IF(AJ35>=14,"A",IF(AJ35>=10,"B","C"))) | AL35: =IFERROR(IF(OR(Y35="",Z35="",AA35=""),"",IF(F35="Short",IF(Z35<=Y35,"",(Y35-AA35)/(Z35-Y35)),IF(Y35<=Z35,"",(AA35-Y35)/(Y35-Z35)))),"") | AM35: =IF(OR(Y35="",Z35="",N(Y35)=N(Z35)),"",IF(OR(AND(F35="Short",Z35<Y35),AND(NOT(F35="Short"),Z35>Y35)),"stop on wrong side",ABS(Y35-Z35))) | AN35: =IFERROR(IF(OR(NOT(ISNUMBER(AM35)),$C$6=""),"",ROUNDDOWN($C$6*$C$7/AM35,2)),"") | AO35: =IFERROR(IF(AN35="","",AN35*Y35),"") | AS35: =IFERROR(IF(OR(AR35="",Y35="",AQ35=""),"",IF(F35="Short",1-AR35/Y35,AR35/Y35-1)),"") | AT35: =IF(AQ35="","",IF(ISNUMBER($C$4),$C$4,TODAY())-AQ35) | AU35: =IF(C35="","",IF(AP35="Open position",IF(IF(F35="Short",AND(ISNUMBER(AR35),ISNUMBER(Z35),AR35>=Z35),AND(ISNUMBER(AR35),ISNUMBER(Z35),AR35<=Z35)),IF(F35="Short","COVER — stop hit (buy back)","SELL — stop hit"),IF(IF(F35="Short",AND(ISNUMBER(AR35),ISNUMBER(AA35),AR35<=AA35),AND(ISNUMBER(AR35),ISNUMBER(AA35),AR35>=AA35)),"TAKE PROFIT — target hit",IF(AND(ISNUMBER(AT35),AT35>182),IF(F35="Short","COVER — 6-month time limit","SELL — 6-month time limit"),IF(AND(ISNUMBER(AT35),AT35>42,ISNUMBER(AS35),AS35<0.02),"REVIEW — no progress after 6 weeks",IF(IF(F35="Short",AND(L35<>"",N(L35)>0),AND(L35<>"",N(L35)<0)),IF(F35="Short","REVIEW — back above 50-day avg","REVIEW — below 50-day avg"),"HOLD"))))),IF(OR(AP35="Closed",AP35="Dropped"),"Closed",IF(AK35="A",IF(F35="Short","Run Technical Review — SHORT entry","Run Technical Review — LONG entry"),IF(AK35="B","Watch — wait for setup","Drop or re-check next week"))))) | AX35: =IF(AND(C35<>"",A35=$C$4,ISNUMBER(AJ35)),AJ35+ROW()/100000,"")
J36: =IF(OR(G36="",I36=""),"",G36*I36/1000000) | AB36: =IF(C36="","",IF(F36="Short",(AND(M36<>"",N(M36)<0))+(AND(L36<>"",N(L36)<0))+(AND(K36<>"",N(K36)<0))+AND(L36<>"",M36<>"",N(M36)<N(L36)),(N(M36)>0)+(N(L36)>0)+(N(K36)>0)+AND(L36<>"",M36<>"",N(M36)>N(L36)))) | AC36: =IF(C36="","",IF(F36="Short",IF(N36="",0,IF(AND(N36>=30,N36<=50),2,IF(OR(AND(N36>=25,N36<30),AND(N36>50,N36<=60)),1,0)))+IF(P36="",0,IF(AND(IF(B36="JSE",$L$5,$L$4)<>"",P36<IF(B36="JSE",$L$5,$L$4)),2,IF(P36<0,1,0))),IF(N36="",0,IF(AND(N36>=50,N36<=70),2,IF(OR(AND(N36>=40,N36<50),AND(N36>70,N36<=75)),1,0)))+IF(P36="",0,IF(AND(IF(B36="JSE",$L$5,$L$4)<>"",P36>IF(B36="JSE",$L$5,$L$4)),2,IF(P36>0,1,0))))) | AD36: =IF(C36="","",IF(F36="Short",IF(R36="",0,IF(R36<=0.1,2,IF(R36<=0.25,1,0))),IF(Q36="",0,IF(Q36>=-0.1,2,IF(Q36>=-0.25,1,0))))) | AE36: =IF(C36="","",IF(J36="",0,IF(J36>=IF(B36="JSE",$L$7,$L$6),2,IF(J36>=IF(B36="JSE",$L$7,$L$6)/4,1,0)))) | AF36: =IF(C36="","",IF(F36="Short",AND(T36<>"",N(T36)<0),N(T36)>0)+(N(S36)>=1.5)) | AG36: =IF(C36="","",IF(AL36="",0,IF(AL36>=3,4,IF(AL36>=2,2,0)))) | AH36: =IF(C36="","",IF(AND(ISNUMBER(V36),ISNUMBER(A36),V36>=A36,V36-A36<=14),-2,0)) | AI36: =IF(C36="","",IF(AND(F36="Short",N(U36)>=0.2),-1,0)) | AJ36: =IF(C36="","",SUM(AB36:AI36)) | AK36: =IF(C36="","",IF(AJ36>=14,"A",IF(AJ36>=10,"B","C"))) | AL36: =IFERROR(IF(OR(Y36="",Z36="",AA36=""),"",IF(F36="Short",IF(Z36<=Y36,"",(Y36-AA36)/(Z36-Y36)),IF(Y36<=Z36,"",(AA36-Y36)/(Y36-Z36)))),"") | AM36: =IF(OR(Y36="",Z36="",N(Y36)=N(Z36)),"",IF(OR(AND(F36="Short",Z36<Y36),AND(NOT(F36="Short"),Z36>Y36)),"stop on wrong side",ABS(Y36-Z36))) | AN36: =IFERROR(IF(OR(NOT(ISNUMBER(AM36)),$C$6=""),"",ROUNDDOWN($C$6*$C$7/AM36,2)),"") | AO36: =IFERROR(IF(AN36="","",AN36*Y36),"") | AS36: =IFERROR(IF(OR(AR36="",Y36="",AQ36=""),"",IF(F36="Short",1-AR36/Y36,AR36/Y36-1)),"") | AT36: =IF(AQ36="","",IF(ISNUMBER($C$4),$C$4,TODAY())-AQ36) | AU36: =IF(C36="","",IF(AP36="Open position",IF(IF(F36="Short",AND(ISNUMBER(AR36),ISNUMBER(Z36),AR36>=Z36),AND(ISNUMBER(AR36),ISNUMBER(Z36),AR36<=Z36)),IF(F36="Short","COVER — stop hit (buy back)","SELL — stop hit"),IF(IF(F36="Short",AND(ISNUMBER(AR36),ISNUMBER(AA36),AR36<=AA36),AND(ISNUMBER(AR36),ISNUMBER(AA36),AR36>=AA36)),"TAKE PROFIT — target hit",IF(AND(ISNUMBER(AT36),AT36>182),IF(F36="Short","COVER — 6-month time limit","SELL — 6-month time limit"),IF(AND(ISNUMBER(AT36),AT36>42,ISNUMBER(AS36),AS36<0.02),"REVIEW — no progress after 6 weeks",IF(IF(F36="Short",AND(L36<>"",N(L36)>0),AND(L36<>"",N(L36)<0)),IF(F36="Short","REVIEW — back above 50-day avg","REVIEW — below 50-day avg"),"HOLD"))))),IF(OR(AP36="Closed",AP36="Dropped"),"Closed",IF(AK36="A",IF(F36="Short","Run Technical Review — SHORT entry","Run Technical Review — LONG entry"),IF(AK36="B","Watch — wait for setup","Drop or re-check next week"))))) | AX36: =IF(AND(C36<>"",A36=$C$4,ISNUMBER(AJ36)),AJ36+ROW()/100000,"")
J37: =IF(OR(G37="",I37=""),"",G37*I37/1000000) | AB37: =IF(C37="","",IF(F37="Short",(AND(M37<>"",N(M37)<0))+(AND(L37<>"",N(L37)<0))+(AND(K37<>"",N(K37)<0))+AND(L37<>"",M37<>"",N(M37)<N(L37)),(N(M37)>0)+(N(L37)>0)+(N(K37)>0)+AND(L37<>"",M37<>"",N(M37)>N(L37)))) | AC37: =IF(C37="","",IF(F37="Short",IF(N37="",0,IF(AND(N37>=30,N37<=50),2,IF(OR(AND(N37>=25,N37<30),AND(N37>50,N37<=60)),1,0)))+IF(P37="",0,IF(AND(IF(B37="JSE",$L$5,$L$4)<>"",P37<IF(B37="JSE",$L$5,$L$4)),2,IF(P37<0,1,0))),IF(N37="",0,IF(AND(N37>=50,N37<=70),2,IF(OR(AND(N37>=40,N37<50),AND(N37>70,N37<=75)),1,0)))+IF(P37="",0,IF(AND(IF(B37="JSE",$L$5,$L$4)<>"",P37>IF(B37="JSE",$L$5,$L$4)),2,IF(P37>0,1,0))))) | AD37: =IF(C37="","",IF(F37="Short",IF(R37="",0,IF(R37<=0.1,2,IF(R37<=0.25,1,0))),IF(Q37="",0,IF(Q37>=-0.1,2,IF(Q37>=-0.25,1,0))))) | AE37: =IF(C37="","",IF(J37="",0,IF(J37>=IF(B37="JSE",$L$7,$L$6),2,IF(J37>=IF(B37="JSE",$L$7,$L$6)/4,1,0)))) | AF37: =IF(C37="","",IF(F37="Short",AND(T37<>"",N(T37)<0),N(T37)>0)+(N(S37)>=1.5)) | AG37: =IF(C37="","",IF(AL37="",0,IF(AL37>=3,4,IF(AL37>=2,2,0)))) | AH37: =IF(C37="","",IF(AND(ISNUMBER(V37),ISNUMBER(A37),V37>=A37,V37-A37<=14),-2,0)) | AI37: =IF(C37="","",IF(AND(F37="Short",N(U37)>=0.2),-1,0)) | AJ37: =IF(C37="","",SUM(AB37:AI37)) | AK37: =IF(C37="","",IF(AJ37>=14,"A",IF(AJ37>=10,"B","C"))) | AL37: =IFERROR(IF(OR(Y37="",Z37="",AA37=""),"",IF(F37="Short",IF(Z37<=Y37,"",(Y37-AA37)/(Z37-Y37)),IF(Y37<=Z37,"",(AA37-Y37)/(Y37-Z37)))),"") | AM37: =IF(OR(Y37="",Z37="",N(Y37)=N(Z37)),"",IF(OR(AND(F37="Short",Z37<Y37),AND(NOT(F37="Short"),Z37>Y37)),"stop on wrong side",ABS(Y37-Z37))) | AN37: =IFERROR(IF(OR(NOT(ISNUMBER(AM37)),$C$6=""),"",ROUNDDOWN($C$6*$C$7/AM37,2)),"") | AO37: =IFERROR(IF(AN37="","",AN37*Y37),"") | AS37: =IFERROR(IF(OR(AR37="",Y37="",AQ37=""),"",IF(F37="Short",1-AR37/Y37,AR37/Y37-1)),"") | AT37: =IF(AQ37="","",IF(ISNUMBER($C$4),$C$4,TODAY())-AQ37) | AU37: =IF(C37="","",IF(AP37="Open position",IF(IF(F37="Short",AND(ISNUMBER(AR37),ISNUMBER(Z37),AR37>=Z37),AND(ISNUMBER(AR37),ISNUMBER(Z37),AR37<=Z37)),IF(F37="Short","COVER — stop hit (buy back)","SELL — stop hit"),IF(IF(F37="Short",AND(ISNUMBER(AR37),ISNUMBER(AA37),AR37<=AA37),AND(ISNUMBER(AR37),ISNUMBER(AA37),AR37>=AA37)),"TAKE PROFIT — target hit",IF(AND(ISNUMBER(AT37),AT37>182),IF(F37="Short","COVER — 6-month time limit","SELL — 6-month time limit"),IF(AND(ISNUMBER(AT37),AT37>42,ISNUMBER(AS37),AS37<0.02),"REVIEW — no progress after 6 weeks",IF(IF(F37="Short",AND(L37<>"",N(L37)>0),AND(L37<>"",N(L37)<0)),IF(F37="Short","REVIEW — back above 50-day avg","REVIEW — below 50-day avg"),"HOLD"))))),IF(OR(AP37="Closed",AP37="Dropped"),"Closed",IF(AK37="A",IF(F37="Short","Run Technical Review — SHORT entry","Run Technical Review — LONG entry"),IF(AK37="B","Watch — wait for setup","Drop or re-check next week"))))) | AX37: =IF(AND(C37<>"",A37=$C$4,ISNUMBER(AJ37)),AJ37+ROW()/100000,"")
J38: =IF(OR(G38="",I38=""),"",G38*I38/1000000) | AB38: =IF(C38="","",IF(F38="Short",(AND(M38<>"",N(M38)<0))+(AND(L38<>"",N(L38)<0))+(AND(K38<>"",N(K38)<0))+AND(L38<>"",M38<>"",N(M38)<N(L38)),(N(M38)>0)+(N(L38)>0)+(N(K38)>0)+AND(L38<>"",M38<>"",N(M38)>N(L38)))) | AC38: =IF(C38="","",IF(F38="Short",IF(N38="",0,IF(AND(N38>=30,N38<=50),2,IF(OR(AND(N38>=25,N38<30),AND(N38>50,N38<=60)),1,0)))+IF(P38="",0,IF(AND(IF(B38="JSE",$L$5,$L$4)<>"",P38<IF(B38="JSE",$L$5,$L$4)),2,IF(P38<0,1,0))),IF(N38="",0,IF(AND(N38>=50,N38<=70),2,IF(OR(AND(N38>=40,N38<50),AND(N38>70,N38<=75)),1,0)))+IF(P38="",0,IF(AND(IF(B38="JSE",$L$5,$L$4)<>"",P38>IF(B38="JSE",$L$5,$L$4)),2,IF(P38>0,1,0))))) | AD38: =IF(C38="","",IF(F38="Short",IF(R38="",0,IF(R38<=0.1,2,IF(R38<=0.25,1,0))),IF(Q38="",0,IF(Q38>=-0.1,2,IF(Q38>=-0.25,1,0))))) | AE38: =IF(C38="","",IF(J38="",0,IF(J38>=IF(B38="JSE",$L$7,$L$6),2,IF(J38>=IF(B38="JSE",$L$7,$L$6)/4,1,0)))) | AF38: =IF(C38="","",IF(F38="Short",AND(T38<>"",N(T38)<0),N(T38)>0)+(N(S38)>=1.5)) | AG38: =IF(C38="","",IF(AL38="",0,IF(AL38>=3,4,IF(AL38>=2,2,0)))) | AH38: =IF(C38="","",IF(AND(ISNUMBER(V38),ISNUMBER(A38),V38>=A38,V38-A38<=14),-2,0)) | AI38: =IF(C38="","",IF(AND(F38="Short",N(U38)>=0.2),-1,0)) | AJ38: =IF(C38="","",SUM(AB38:AI38)) | AK38: =IF(C38="","",IF(AJ38>=14,"A",IF(AJ38>=10,"B","C"))) | AL38: =IFERROR(IF(OR(Y38="",Z38="",AA38=""),"",IF(F38="Short",IF(Z38<=Y38,"",(Y38-AA38)/(Z38-Y38)),IF(Y38<=Z38,"",(AA38-Y38)/(Y38-Z38)))),"") | AM38: =IF(OR(Y38="",Z38="",N(Y38)=N(Z38)),"",IF(OR(AND(F38="Short",Z38<Y38),AND(NOT(F38="Short"),Z38>Y38)),"stop on wrong side",ABS(Y38-Z38))) | AN38: =IFERROR(IF(OR(NOT(ISNUMBER(AM38)),$C$6=""),"",ROUNDDOWN($C$6*$C$7/AM38,2)),"") | AO38: =IFERROR(IF(AN38="","",AN38*Y38),"") | AS38: =IFERROR(IF(OR(AR38="",Y38="",AQ38=""),"",IF(F38="Short",1-AR38/Y38,AR38/Y38-1)),"") | AT38: =IF(AQ38="","",IF(ISNUMBER($C$4),$C$4,TODAY())-AQ38) | AU38: =IF(C38="","",IF(AP38="Open position",IF(IF(F38="Short",AND(ISNUMBER(AR38),ISNUMBER(Z38),AR38>=Z38),AND(ISNUMBER(AR38),ISNUMBER(Z38),AR38<=Z38)),IF(F38="Short","COVER — stop hit (buy back)","SELL — stop hit"),IF(IF(F38="Short",AND(ISNUMBER(AR38),ISNUMBER(AA38),AR38<=AA38),AND(ISNUMBER(AR38),ISNUMBER(AA38),AR38>=AA38)),"TAKE PROFIT — target hit",IF(AND(ISNUMBER(AT38),AT38>182),IF(F38="Short","COVER — 6-month time limit","SELL — 6-month time limit"),IF(AND(ISNUMBER(AT38),AT38>42,ISNUMBER(AS38),AS38<0.02),"REVIEW — no progress after 6 weeks",IF(IF(F38="Short",AND(L38<>"",N(L38)>0),AND(L38<>"",N(L38)<0)),IF(F38="Short","REVIEW — back above 50-day avg","REVIEW — below 50-day avg"),"HOLD"))))),IF(OR(AP38="Closed",AP38="Dropped"),"Closed",IF(AK38="A",IF(F38="Short","Run Technical Review — SHORT entry","Run Technical Review — LONG entry"),IF(AK38="B","Watch — wait for setup","Drop or re-check next week"))))) | AX38: =IF(AND(C38<>"",A38=$C$4,ISNUMBER(AJ38)),AJ38+ROW()/100000,"")
J39: =IF(OR(G39="",I39=""),"",G39*I39/1000000) | AB39: =IF(C39="","",IF(F39="Short",(AND(M39<>"",N(M39)<0))+(AND(L39<>"",N(L39)<0))+(AND(K39<>"",N(K39)<0))+AND(L39<>"",M39<>"",N(M39)<N(L39)),(N(M39)>0)+(N(L39)>0)+(N(K39)>0)+AND(L39<>"",M39<>"",N(M39)>N(L39)))) | AC39: =IF(C39="","",IF(F39="Short",IF(N39="",0,IF(AND(N39>=30,N39<=50),2,IF(OR(AND(N39>=25,N39<30),AND(N39>50,N39<=60)),1,0)))+IF(P39="",0,IF(AND(IF(B39="JSE",$L$5,$L$4)<>"",P39<IF(B39="JSE",$L$5,$L$4)),2,IF(P39<0,1,0))),IF(N39="",0,IF(AND(N39>=50,N39<=70),2,IF(OR(AND(N39>=40,N39<50),AND(N39>70,N39<=75)),1,0)))+IF(P39="",0,IF(AND(IF(B39="JSE",$L$5,$L$4)<>"",P39>IF(B39="JSE",$L$5,$L$4)),2,IF(P39>0,1,0))))) | AD39: =IF(C39="","",IF(F39="Short",IF(R39="",0,IF(R39<=0.1,2,IF(R39<=0.25,1,0))),IF(Q39="",0,IF(Q39>=-0.1,2,IF(Q39>=-0.25,1,0))))) | AE39: =IF(C39="","",IF(J39="",0,IF(J39>=IF(B39="JSE",$L$7,$L$6),2,IF(J39>=IF(B39="JSE",$L$7,$L$6)/4,1,0)))) | AF39: =IF(C39="","",IF(F39="Short",AND(T39<>"",N(T39)<0),N(T39)>0)+(N(S39)>=1.5)) | AG39: =IF(C39="","",IF(AL39="",0,IF(AL39>=3,4,IF(AL39>=2,2,0)))) | AH39: =IF(C39="","",IF(AND(ISNUMBER(V39),ISNUMBER(A39),V39>=A39,V39-A39<=14),-2,0)) | AI39: =IF(C39="","",IF(AND(F39="Short",N(U39)>=0.2),-1,0)) | AJ39: =IF(C39="","",SUM(AB39:AI39)) | AK39: =IF(C39="","",IF(AJ39>=14,"A",IF(AJ39>=10,"B","C"))) | AL39: =IFERROR(IF(OR(Y39="",Z39="",AA39=""),"",IF(F39="Short",IF(Z39<=Y39,"",(Y39-AA39)/(Z39-Y39)),IF(Y39<=Z39,"",(AA39-Y39)/(Y39-Z39)))),"") | AM39: =IF(OR(Y39="",Z39="",N(Y39)=N(Z39)),"",IF(OR(AND(F39="Short",Z39<Y39),AND(NOT(F39="Short"),Z39>Y39)),"stop on wrong side",ABS(Y39-Z39))) | AN39: =IFERROR(IF(OR(NOT(ISNUMBER(AM39)),$C$6=""),"",ROUNDDOWN($C$6*$C$7/AM39,2)),"") | AO39: =IFERROR(IF(AN39="","",AN39*Y39),"") | AS39: =IFERROR(IF(OR(AR39="",Y39="",AQ39=""),"",IF(F39="Short",1-AR39/Y39,AR39/Y39-1)),"") | AT39: =IF(AQ39="","",IF(ISNUMBER($C$4),$C$4,TODAY())-AQ39) | AU39: =IF(C39="","",IF(AP39="Open position",IF(IF(F39="Short",AND(ISNUMBER(AR39),ISNUMBER(Z39),AR39>=Z39),AND(ISNUMBER(AR39),ISNUMBER(Z39),AR39<=Z39)),IF(F39="Short","COVER — stop hit (buy back)","SELL — stop hit"),IF(IF(F39="Short",AND(ISNUMBER(AR39),ISNUMBER(AA39),AR39<=AA39),AND(ISNUMBER(AR39),ISNUMBER(AA39),AR39>=AA39)),"TAKE PROFIT — target hit",IF(AND(ISNUMBER(AT39),AT39>182),IF(F39="Short","COVER — 6-month time limit","SELL — 6-month time limit"),IF(AND(ISNUMBER(AT39),AT39>42,ISNUMBER(AS39),AS39<0.02),"REVIEW — no progress after 6 weeks",IF(IF(F39="Short",AND(L39<>"",N(L39)>0),AND(L39<>"",N(L39)<0)),IF(F39="Short","REVIEW — back above 50-day avg","REVIEW — below 50-day avg"),"HOLD"))))),IF(OR(AP39="Closed",AP39="Dropped"),"Closed",IF(AK39="A",IF(F39="Short","Run Technical Review — SHORT entry","Run Technical Review — LONG entry"),IF(AK39="B","Watch — wait for setup","Drop or re-check next week"))))) | AX39: =IF(AND(C39<>"",A39=$C$4,ISNUMBER(AJ39)),AJ39+ROW()/100000,"")
J40: =IF(OR(G40="",I40=""),"",G40*I40/1000000) | AB40: =IF(C40="","",IF(F40="Short",(AND(M40<>"",N(M40)<0))+(AND(L40<>"",N(L40)<0))+(AND(K40<>"",N(K40)<0))+AND(L40<>"",M40<>"",N(M40)<N(L40)),(N(M40)>0)+(N(L40)>0)+(N(K40)>0)+AND(L40<>"",M40<>"",N(M40)>N(L40)))) | AC40: =IF(C40="","",IF(F40="Short",IF(N40="",0,IF(AND(N40>=30,N40<=50),2,IF(OR(AND(N40>=25,N40<30),AND(N40>50,N40<=60)),1,0)))+IF(P40="",0,IF(AND(IF(B40="JSE",$L$5,$L$4)<>"",P40<IF(B40="JSE",$L$5,$L$4)),2,IF(P40<0,1,0))),IF(N40="",0,IF(AND(N40>=50,N40<=70),2,IF(OR(AND(N40>=40,N40<50),AND(N40>70,N40<=75)),1,0)))+IF(P40="",0,IF(AND(IF(B40="JSE",$L$5,$L$4)<>"",P40>IF(B40="JSE",$L$5,$L$4)),2,IF(P40>0,1,0))))) | AD40: =IF(C40="","",IF(F40="Short",IF(R40="",0,IF(R40<=0.1,2,IF(R40<=0.25,1,0))),IF(Q40="",0,IF(Q40>=-0.1,2,IF(Q40>=-0.25,1,0))))) | AE40: =IF(C40="","",IF(J40="",0,IF(J40>=IF(B40="JSE",$L$7,$L$6),2,IF(J40>=IF(B40="JSE",$L$7,$L$6)/4,1,0)))) | AF40: =IF(C40="","",IF(F40="Short",AND(T40<>"",N(T40)<0),N(T40)>0)+(N(S40)>=1.5)) | AG40: =IF(C40="","",IF(AL40="",0,IF(AL40>=3,4,IF(AL40>=2,2,0)))) | AH40: =IF(C40="","",IF(AND(ISNUMBER(V40),ISNUMBER(A40),V40>=A40,V40-A40<=14),-2,0)) | AI40: =IF(C40="","",IF(AND(F40="Short",N(U40)>=0.2),-1,0)) | AJ40: =IF(C40="","",SUM(AB40:AI40)) | AK40: =IF(C40="","",IF(AJ40>=14,"A",IF(AJ40>=10,"B","C"))) | AL40: =IFERROR(IF(OR(Y40="",Z40="",AA40=""),"",IF(F40="Short",IF(Z40<=Y40,"",(Y40-AA40)/(Z40-Y40)),IF(Y40<=Z40,"",(AA40-Y40)/(Y40-Z40)))),"") | AM40: =IF(OR(Y40="",Z40="",N(Y40)=N(Z40)),"",IF(OR(AND(F40="Short",Z40<Y40),AND(NOT(F40="Short"),Z40>Y40)),"stop on wrong side",ABS(Y40-Z40))) | AN40: =IFERROR(IF(OR(NOT(ISNUMBER(AM40)),$C$6=""),"",ROUNDDOWN($C$6*$C$7/AM40,2)),"") | AO40: =IFERROR(IF(AN40="","",AN40*Y40),"") | AS40: =IFERROR(IF(OR(AR40="",Y40="",AQ40=""),"",IF(F40="Short",1-AR40/Y40,AR40/Y40-1)),"") | AT40: =IF(AQ40="","",IF(ISNUMBER($C$4),$C$4,TODAY())-AQ40) | AU40: =IF(C40="","",IF(AP40="Open position",IF(IF(F40="Short",AND(ISNUMBER(AR40),ISNUMBER(Z40),AR40>=Z40),AND(ISNUMBER(AR40),ISNUMBER(Z40),AR40<=Z40)),IF(F40="Short","COVER — stop hit (buy back)","SELL — stop hit"),IF(IF(F40="Short",AND(ISNUMBER(AR40),ISNUMBER(AA40),AR40<=AA40),AND(ISNUMBER(AR40),ISNUMBER(AA40),AR40>=AA40)),"TAKE PROFIT — target hit",IF(AND(ISNUMBER(AT40),AT40>182),IF(F40="Short","COVER — 6-month time limit","SELL — 6-month time limit"),IF(AND(ISNUMBER(AT40),AT40>42,ISNUMBER(AS40),AS40<0.02),"REVIEW — no progress after 6 weeks",IF(IF(F40="Short",AND(L40<>"",N(L40)>0),AND(L40<>"",N(L40)<0)),IF(F40="Short","REVIEW — back above 50-day avg","REVIEW — below 50-day avg"),"HOLD"))))),IF(OR(AP40="Closed",AP40="Dropped"),"Closed",IF(AK40="A",IF(F40="Short","Run Technical Review — SHORT entry","Run Technical Review — LONG entry"),IF(AK40="B","Watch — wait for setup","Drop or re-check next week"))))) | AX40: =IF(AND(C40<>"",A40=$C$4,ISNUMBER(AJ40)),AJ40+ROW()/100000,"")
J41: =IF(OR(G41="",I41=""),"",G41*I41/1000000) | AB41: =IF(C41="","",IF(F41="Short",(AND(M41<>"",N(M41)<0))+(AND(L41<>"",N(L41)<0))+(AND(K41<>"",N(K41)<0))+AND(L41<>"",M41<>"",N(M41)<N(L41)),(N(M41)>0)+(N(L41)>0)+(N(K41)>0)+AND(L41<>"",M41<>"",N(M41)>N(L41)))) | AC41: =IF(C41="","",IF(F41="Short",IF(N41="",0,IF(AND(N41>=30,N41<=50),2,IF(OR(AND(N41>=25,N41<30),AND(N41>50,N41<=60)),1,0)))+IF(P41="",0,IF(AND(IF(B41="JSE",$L$5,$L$4)<>"",P41<IF(B41="JSE",$L$5,$L$4)),2,IF(P41<0,1,0))),IF(N41="",0,IF(AND(N41>=50,N41<=70),2,IF(OR(AND(N41>=40,N41<50),AND(N41>70,N41<=75)),1,0)))+IF(P41="",0,IF(AND(IF(B41="JSE",$L$5,$L$4)<>"",P41>IF(B41="JSE",$L$5,$L$4)),2,IF(P41>0,1,0))))) | AD41: =IF(C41="","",IF(F41="Short",IF(R41="",0,IF(R41<=0.1,2,IF(R41<=0.25,1,0))),IF(Q41="",0,IF(Q41>=-0.1,2,IF(Q41>=-0.25,1,0))))) | AE41: =IF(C41="","",IF(J41="",0,IF(J41>=IF(B41="JSE",$L$7,$L$6),2,IF(J41>=IF(B41="JSE",$L$7,$L$6)/4,1,0)))) | AF41: =IF(C41="","",IF(F41="Short",AND(T41<>"",N(T41)<0),N(T41)>0)+(N(S41)>=1.5)) | AG41: =IF(C41="","",IF(AL41="",0,IF(AL41>=3,4,IF(AL41>=2,2,0)))) | AH41: =IF(C41="","",IF(AND(ISNUMBER(V41),ISNUMBER(A41),V41>=A41,V41-A41<=14),-2,0)) | AI41: =IF(C41="","",IF(AND(F41="Short",N(U41)>=0.2),-1,0)) | AJ41: =IF(C41="","",SUM(AB41:AI41)) | AK41: =IF(C41="","",IF(AJ41>=14,"A",IF(AJ41>=10,"B","C"))) | AL41: =IFERROR(IF(OR(Y41="",Z41="",AA41=""),"",IF(F41="Short",IF(Z41<=Y41,"",(Y41-AA41)/(Z41-Y41)),IF(Y41<=Z41,"",(AA41-Y41)/(Y41-Z41)))),"") | AM41: =IF(OR(Y41="",Z41="",N(Y41)=N(Z41)),"",IF(OR(AND(F41="Short",Z41<Y41),AND(NOT(F41="Short"),Z41>Y41)),"stop on wrong side",ABS(Y41-Z41))) | AN41: =IFERROR(IF(OR(NOT(ISNUMBER(AM41)),$C$6=""),"",ROUNDDOWN($C$6*$C$7/AM41,2)),"") | AO41: =IFERROR(IF(AN41="","",AN41*Y41),"") | AS41: =IFERROR(IF(OR(AR41="",Y41="",AQ41=""),"",IF(F41="Short",1-AR41/Y41,AR41/Y41-1)),"") | AT41: =IF(AQ41="","",IF(ISNUMBER($C$4),$C$4,TODAY())-AQ41) | AU41: =IF(C41="","",IF(AP41="Open position",IF(IF(F41="Short",AND(ISNUMBER(AR41),ISNUMBER(Z41),AR41>=Z41),AND(ISNUMBER(AR41),ISNUMBER(Z41),AR41<=Z41)),IF(F41="Short","COVER — stop hit (buy back)","SELL — stop hit"),IF(IF(F41="Short",AND(ISNUMBER(AR41),ISNUMBER(AA41),AR41<=AA41),AND(ISNUMBER(AR41),ISNUMBER(AA41),AR41>=AA41)),"TAKE PROFIT — target hit",IF(AND(ISNUMBER(AT41),AT41>182),IF(F41="Short","COVER — 6-month time limit","SELL — 6-month time limit"),IF(AND(ISNUMBER(AT41),AT41>42,ISNUMBER(AS41),AS41<0.02),"REVIEW — no progress after 6 weeks",IF(IF(F41="Short",AND(L41<>"",N(L41)>0),AND(L41<>"",N(L41)<0)),IF(F41="Short","REVIEW — back above 50-day avg","REVIEW — below 50-day avg"),"HOLD"))))),IF(OR(AP41="Closed",AP41="Dropped"),"Closed",IF(AK41="A",IF(F41="Short","Run Technical Review — SHORT entry","Run Technical Review — LONG entry"),IF(AK41="B","Watch — wait for setup","Drop or re-check next week"))))) | AX41: =IF(AND(C41<>"",A41=$C$4,ISNUMBER(AJ41)),AJ41+ROW()/100000,"")
J42: =IF(OR(G42="",I42=""),"",G42*I42/1000000) | AB42: =IF(C42="","",IF(F42="Short",(AND(M42<>"",N(M42)<0))+(AND(L42<>"",N(L42)<0))+(AND(K42<>"",N(K42)<0))+AND(L42<>"",M42<>"",N(M42)<N(L42)),(N(M42)>0)+(N(L42)>0)+(N(K42)>0)+AND(L42<>"",M42<>"",N(M42)>N(L42)))) | AC42: =IF(C42="","",IF(F42="Short",IF(N42="",0,IF(AND(N42>=30,N42<=50),2,IF(OR(AND(N42>=25,N42<30),AND(N42>50,N42<=60)),1,0)))+IF(P42="",0,IF(AND(IF(B42="JSE",$L$5,$L$4)<>"",P42<IF(B42="JSE",$L$5,$L$4)),2,IF(P42<0,1,0))),IF(N42="",0,IF(AND(N42>=50,N42<=70),2,IF(OR(AND(N42>=40,N42<50),AND(N42>70,N42<=75)),1,0)))+IF(P42="",0,IF(AND(IF(B42="JSE",$L$5,$L$4)<>"",P42>IF(B42="JSE",$L$5,$L$4)),2,IF(P42>0,1,0))))) | AD42: =IF(C42="","",IF(F42="Short",IF(R42="",0,IF(R42<=0.1,2,IF(R42<=0.25,1,0))),IF(Q42="",0,IF(Q42>=-0.1,2,IF(Q42>=-0.25,1,0))))) | AE42: =IF(C42="","",IF(J42="",0,IF(J42>=IF(B42="JSE",$L$7,$L$6),2,IF(J42>=IF(B42="JSE",$L$7,$L$6)/4,1,0)))) | AF42: =IF(C42="","",IF(F42="Short",AND(T42<>"",N(T42)<0),N(T42)>0)+(N(S42)>=1.5)) | AG42: =IF(C42="","",IF(AL42="",0,IF(AL42>=3,4,IF(AL42>=2,2,0)))) | AH42: =IF(C42="","",IF(AND(ISNUMBER(V42),ISNUMBER(A42),V42>=A42,V42-A42<=14),-2,0)) | AI42: =IF(C42="","",IF(AND(F42="Short",N(U42)>=0.2),-1,0)) | AJ42: =IF(C42="","",SUM(AB42:AI42)) | AK42: =IF(C42="","",IF(AJ42>=14,"A",IF(AJ42>=10,"B","C"))) | AL42: =IFERROR(IF(OR(Y42="",Z42="",AA42=""),"",IF(F42="Short",IF(Z42<=Y42,"",(Y42-AA42)/(Z42-Y42)),IF(Y42<=Z42,"",(AA42-Y42)/(Y42-Z42)))),"") | AM42: =IF(OR(Y42="",Z42="",N(Y42)=N(Z42)),"",IF(OR(AND(F42="Short",Z42<Y42),AND(NOT(F42="Short"),Z42>Y42)),"stop on wrong side",ABS(Y42-Z42))) | AN42: =IFERROR(IF(OR(NOT(ISNUMBER(AM42)),$C$6=""),"",ROUNDDOWN($C$6*$C$7/AM42,2)),"") | AO42: =IFERROR(IF(AN42="","",AN42*Y42),"") | AS42: =IFERROR(IF(OR(AR42="",Y42="",AQ42=""),"",IF(F42="Short",1-AR42/Y42,AR42/Y42-1)),"") | AT42: =IF(AQ42="","",IF(ISNUMBER($C$4),$C$4,TODAY())-AQ42) | AU42: =IF(C42="","",IF(AP42="Open position",IF(IF(F42="Short",AND(ISNUMBER(AR42),ISNUMBER(Z42),AR42>=Z42),AND(ISNUMBER(AR42),ISNUMBER(Z42),AR42<=Z42)),IF(F42="Short","COVER — stop hit (buy back)","SELL — stop hit"),IF(IF(F42="Short",AND(ISNUMBER(AR42),ISNUMBER(AA42),AR42<=AA42),AND(ISNUMBER(AR42),ISNUMBER(AA42),AR42>=AA42)),"TAKE PROFIT — target hit",IF(AND(ISNUMBER(AT42),AT42>182),IF(F42="Short","COVER — 6-month time limit","SELL — 6-month time limit"),IF(AND(ISNUMBER(AT42),AT42>42,ISNUMBER(AS42),AS42<0.02),"REVIEW — no progress after 6 weeks",IF(IF(F42="Short",AND(L42<>"",N(L42)>0),AND(L42<>"",N(L42)<0)),IF(F42="Short","REVIEW — back above 50-day avg","REVIEW — below 50-day avg"),"HOLD"))))),IF(OR(AP42="Closed",AP42="Dropped"),"Closed",IF(AK42="A",IF(F42="Short","Run Technical Review — SHORT entry","Run Technical Review — LONG entry"),IF(AK42="B","Watch — wait for setup","Drop or re-check next week"))))) | AX42: =IF(AND(C42<>"",A42=$C$4,ISNUMBER(AJ42)),AJ42+ROW()/100000,"")
J43: =IF(OR(G43="",I43=""),"",G43*I43/1000000) | AB43: =IF(C43="","",IF(F43="Short",(AND(M43<>"",N(M43)<0))+(AND(L43<>"",N(L43)<0))+(AND(K43<>"",N(K43)<0))+AND(L43<>"",M43<>"",N(M43)<N(L43)),(N(M43)>0)+(N(L43)>0)+(N(K43)>0)+AND(L43<>"",M43<>"",N(M43)>N(L43)))) | AC43: =IF(C43="","",IF(F43="Short",IF(N43="",0,IF(AND(N43>=30,N43<=50),2,IF(OR(AND(N43>=25,N43<30),AND(N43>50,N43<=60)),1,0)))+IF(P43="",0,IF(AND(IF(B43="JSE",$L$5,$L$4)<>"",P43<IF(B43="JSE",$L$5,$L$4)),2,IF(P43<0,1,0))),IF(N43="",0,IF(AND(N43>=50,N43<=70),2,IF(OR(AND(N43>=40,N43<50),AND(N43>70,N43<=75)),1,0)))+IF(P43="",0,IF(AND(IF(B43="JSE",$L$5,$L$4)<>"",P43>IF(B43="JSE",$L$5,$L$4)),2,IF(P43>0,1,0))))) | AD43: =IF(C43="","",IF(F43="Short",IF(R43="",0,IF(R43<=0.1,2,IF(R43<=0.25,1,0))),IF(Q43="",0,IF(Q43>=-0.1,2,IF(Q43>=-0.25,1,0))))) | AE43: =IF(C43="","",IF(J43="",0,IF(J43>=IF(B43="JSE",$L$7,$L$6),2,IF(J43>=IF(B43="JSE",$L$7,$L$6)/4,1,0)))) | AF43: =IF(C43="","",IF(F43="Short",AND(T43<>"",N(T43)<0),N(T43)>0)+(N(S43)>=1.5)) | AG43: =IF(C43="","",IF(AL43="",0,IF(AL43>=3,4,IF(AL43>=2,2,0)))) | AH43: =IF(C43="","",IF(AND(ISNUMBER(V43),ISNUMBER(A43),V43>=A43,V43-A43<=14),-2,0)) | AI43: =IF(C43="","",IF(AND(F43="Short",N(U43)>=0.2),-1,0)) | AJ43: =IF(C43="","",SUM(AB43:AI43)) | AK43: =IF(C43="","",IF(AJ43>=14,"A",IF(AJ43>=10,"B","C"))) | AL43: =IFERROR(IF(OR(Y43="",Z43="",AA43=""),"",IF(F43="Short",IF(Z43<=Y43,"",(Y43-AA43)/(Z43-Y43)),IF(Y43<=Z43,"",(AA43-Y43)/(Y43-Z43)))),"") | AM43: =IF(OR(Y43="",Z43="",N(Y43)=N(Z43)),"",IF(OR(AND(F43="Short",Z43<Y43),AND(NOT(F43="Short"),Z43>Y43)),"stop on wrong side",ABS(Y43-Z43))) | AN43: =IFERROR(IF(OR(NOT(ISNUMBER(AM43)),$C$6=""),"",ROUNDDOWN($C$6*$C$7/AM43,2)),"") | AO43: =IFERROR(IF(AN43="","",AN43*Y43),"") | AS43: =IFERROR(IF(OR(AR43="",Y43="",AQ43=""),"",IF(F43="Short",1-AR43/Y43,AR43/Y43-1)),"") | AT43: =IF(AQ43="","",IF(ISNUMBER($C$4),$C$4,TODAY())-AQ43) | AU43: =IF(C43="","",IF(AP43="Open position",IF(IF(F43="Short",AND(ISNUMBER(AR43),ISNUMBER(Z43),AR43>=Z43),AND(ISNUMBER(AR43),ISNUMBER(Z43),AR43<=Z43)),IF(F43="Short","COVER — stop hit (buy back)","SELL — stop hit"),IF(IF(F43="Short",AND(ISNUMBER(AR43),ISNUMBER(AA43),AR43<=AA43),AND(ISNUMBER(AR43),ISNUMBER(AA43),AR43>=AA43)),"TAKE PROFIT — target hit",IF(AND(ISNUMBER(AT43),AT43>182),IF(F43="Short","COVER — 6-month time limit","SELL — 6-month time limit"),IF(AND(ISNUMBER(AT43),AT43>42,ISNUMBER(AS43),AS43<0.02),"REVIEW — no progress after 6 weeks",IF(IF(F43="Short",AND(L43<>"",N(L43)>0),AND(L43<>"",N(L43)<0)),IF(F43="Short","REVIEW — back above 50-day avg","REVIEW — below 50-day avg"),"HOLD"))))),IF(OR(AP43="Closed",AP43="Dropped"),"Closed",IF(AK43="A",IF(F43="Short","Run Technical Review — SHORT entry","Run Technical Review — LONG entry"),IF(AK43="B","Watch — wait for setup","Drop or re-check next week"))))) | AX43: =IF(AND(C43<>"",A43=$C$4,ISNUMBER(AJ43)),AJ43+ROW()/100000,"")
J44: =IF(OR(G44="",I44=""),"",G44*I44/1000000) | AB44: =IF(C44="","",IF(F44="Short",(AND(M44<>"",N(M44)<0))+(AND(L44<>"",N(L44)<0))+(AND(K44<>"",N(K44)<0))+AND(L44<>"",M44<>"",N(M44)<N(L44)),(N(M44)>0)+(N(L44)>0)+(N(K44)>0)+AND(L44<>"",M44<>"",N(M44)>N(L44)))) | AC44: =IF(C44="","",IF(F44="Short",IF(N44="",0,IF(AND(N44>=30,N44<=50),2,IF(OR(AND(N44>=25,N44<30),AND(N44>50,N44<=60)),1,0)))+IF(P44="",0,IF(AND(IF(B44="JSE",$L$5,$L$4)<>"",P44<IF(B44="JSE",$L$5,$L$4)),2,IF(P44<0,1,0))),IF(N44="",0,IF(AND(N44>=50,N44<=70),2,IF(OR(AND(N44>=40,N44<50),AND(N44>70,N44<=75)),1,0)))+IF(P44="",0,IF(AND(IF(B44="JSE",$L$5,$L$4)<>"",P44>IF(B44="JSE",$L$5,$L$4)),2,IF(P44>0,1,0))))) | AD44: =IF(C44="","",IF(F44="Short",IF(R44="",0,IF(R44<=0.1,2,IF(R44<=0.25,1,0))),IF(Q44="",0,IF(Q44>=-0.1,2,IF(Q44>=-0.25,1,0))))) | AE44: =IF(C44="","",IF(J44="",0,IF(J44>=IF(B44="JSE",$L$7,$L$6),2,IF(J44>=IF(B44="JSE",$L$7,$L$6)/4,1,0)))) | AF44: =IF(C44="","",IF(F44="Short",AND(T44<>"",N(T44)<0),N(T44)>0)+(N(S44)>=1.5)) | AG44: =IF(C44="","",IF(AL44="",0,IF(AL44>=3,4,IF(AL44>=2,2,0)))) | AH44: =IF(C44="","",IF(AND(ISNUMBER(V44),ISNUMBER(A44),V44>=A44,V44-A44<=14),-2,0)) | AI44: =IF(C44="","",IF(AND(F44="Short",N(U44)>=0.2),-1,0)) | AJ44: =IF(C44="","",SUM(AB44:AI44)) | AK44: =IF(C44="","",IF(AJ44>=14,"A",IF(AJ44>=10,"B","C"))) | AL44: =IFERROR(IF(OR(Y44="",Z44="",AA44=""),"",IF(F44="Short",IF(Z44<=Y44,"",(Y44-AA44)/(Z44-Y44)),IF(Y44<=Z44,"",(AA44-Y44)/(Y44-Z44)))),"") | AM44: =IF(OR(Y44="",Z44="",N(Y44)=N(Z44)),"",IF(OR(AND(F44="Short",Z44<Y44),AND(NOT(F44="Short"),Z44>Y44)),"stop on wrong side",ABS(Y44-Z44))) | AN44: =IFERROR(IF(OR(NOT(ISNUMBER(AM44)),$C$6=""),"",ROUNDDOWN($C$6*$C$7/AM44,2)),"") | AO44: =IFERROR(IF(AN44="","",AN44*Y44),"") | AS44: =IFERROR(IF(OR(AR44="",Y44="",AQ44=""),"",IF(F44="Short",1-AR44/Y44,AR44/Y44-1)),"") | AT44: =IF(AQ44="","",IF(ISNUMBER($C$4),$C$4,TODAY())-AQ44) | AU44: =IF(C44="","",IF(AP44="Open position",IF(IF(F44="Short",AND(ISNUMBER(AR44),ISNUMBER(Z44),AR44>=Z44),AND(ISNUMBER(AR44),ISNUMBER(Z44),AR44<=Z44)),IF(F44="Short","COVER — stop hit (buy back)","SELL — stop hit"),IF(IF(F44="Short",AND(ISNUMBER(AR44),ISNUMBER(AA44),AR44<=AA44),AND(ISNUMBER(AR44),ISNUMBER(AA44),AR44>=AA44)),"TAKE PROFIT — target hit",IF(AND(ISNUMBER(AT44),AT44>182),IF(F44="Short","COVER — 6-month time limit","SELL — 6-month time limit"),IF(AND(ISNUMBER(AT44),AT44>42,ISNUMBER(AS44),AS44<0.02),"REVIEW — no progress after 6 weeks",IF(IF(F44="Short",AND(L44<>"",N(L44)>0),AND(L44<>"",N(L44)<0)),IF(F44="Short","REVIEW — back above 50-day avg","REVIEW — below 50-day avg"),"HOLD"))))),IF(OR(AP44="Closed",AP44="Dropped"),"Closed",IF(AK44="A",IF(F44="Short","Run Technical Review — SHORT entry","Run Technical Review — LONG entry"),IF(AK44="B","Watch — wait for setup","Drop or re-check next week"))))) | AX44: =IF(AND(C44<>"",A44=$C$4,ISNUMBER(AJ44)),AJ44+ROW()/100000,"")
J45: =IF(OR(G45="",I45=""),"",G45*I45/1000000) | AB45: =IF(C45="","",IF(F45="Short",(AND(M45<>"",N(M45)<0))+(AND(L45<>"",N(L45)<0))+(AND(K45<>"",N(K45)<0))+AND(L45<>"",M45<>"",N(M45)<N(L45)),(N(M45)>0)+(N(L45)>0)+(N(K45)>0)+AND(L45<>"",M45<>"",N(M45)>N(L45)))) | AC45: =IF(C45="","",IF(F45="Short",IF(N45="",0,IF(AND(N45>=30,N45<=50),2,IF(OR(AND(N45>=25,N45<30),AND(N45>50,N45<=60)),1,0)))+IF(P45="",0,IF(AND(IF(B45="JSE",$L$5,$L$4)<>"",P45<IF(B45="JSE",$L$5,$L$4)),2,IF(P45<0,1,0))),IF(N45="",0,IF(AND(N45>=50,N45<=70),2,IF(OR(AND(N45>=40,N45<50),AND(N45>70,N45<=75)),1,0)))+IF(P45="",0,IF(AND(IF(B45="JSE",$L$5,$L$4)<>"",P45>IF(B45="JSE",$L$5,$L$4)),2,IF(P45>0,1,0))))) | AD45: =IF(C45="","",IF(F45="Short",IF(R45="",0,IF(R45<=0.1,2,IF(R45<=0.25,1,0))),IF(Q45="",0,IF(Q45>=-0.1,2,IF(Q45>=-0.25,1,0))))) | AE45: =IF(C45="","",IF(J45="",0,IF(J45>=IF(B45="JSE",$L$7,$L$6),2,IF(J45>=IF(B45="JSE",$L$7,$L$6)/4,1,0)))) | AF45: =IF(C45="","",IF(F45="Short",AND(T45<>"",N(T45)<0),N(T45)>0)+(N(S45)>=1.5)) | AG45: =IF(C45="","",IF(AL45="",0,IF(AL45>=3,4,IF(AL45>=2,2,0)))) | AH45: =IF(C45="","",IF(AND(ISNUMBER(V45),ISNUMBER(A45),V45>=A45,V45-A45<=14),-2,0)) | AI45: =IF(C45="","",IF(AND(F45="Short",N(U45)>=0.2),-1,0)) | AJ45: =IF(C45="","",SUM(AB45:AI45)) | AK45: =IF(C45="","",IF(AJ45>=14,"A",IF(AJ45>=10,"B","C"))) | AL45: =IFERROR(IF(OR(Y45="",Z45="",AA45=""),"",IF(F45="Short",IF(Z45<=Y45,"",(Y45-AA45)/(Z45-Y45)),IF(Y45<=Z45,"",(AA45-Y45)/(Y45-Z45)))),"") | AM45: =IF(OR(Y45="",Z45="",N(Y45)=N(Z45)),"",IF(OR(AND(F45="Short",Z45<Y45),AND(NOT(F45="Short"),Z45>Y45)),"stop on wrong side",ABS(Y45-Z45))) | AN45: =IFERROR(IF(OR(NOT(ISNUMBER(AM45)),$C$6=""),"",ROUNDDOWN($C$6*$C$7/AM45,2)),"") | AO45: =IFERROR(IF(AN45="","",AN45*Y45),"") | AS45: =IFERROR(IF(OR(AR45="",Y45="",AQ45=""),"",IF(F45="Short",1-AR45/Y45,AR45/Y45-1)),"") | AT45: =IF(AQ45="","",IF(ISNUMBER($C$4),$C$4,TODAY())-AQ45) | AU45: =IF(C45="","",IF(AP45="Open position",IF(IF(F45="Short",AND(ISNUMBER(AR45),ISNUMBER(Z45),AR45>=Z45),AND(ISNUMBER(AR45),ISNUMBER(Z45),AR45<=Z45)),IF(F45="Short","COVER — stop hit (buy back)","SELL — stop hit"),IF(IF(F45="Short",AND(ISNUMBER(AR45),ISNUMBER(AA45),AR45<=AA45),AND(ISNUMBER(AR45),ISNUMBER(AA45),AR45>=AA45)),"TAKE PROFIT — target hit",IF(AND(ISNUMBER(AT45),AT45>182),IF(F45="Short","COVER — 6-month time limit","SELL — 6-month time limit"),IF(AND(ISNUMBER(AT45),AT45>42,ISNUMBER(AS45),AS45<0.02),"REVIEW — no progress after 6 weeks",IF(IF(F45="Short",AND(L45<>"",N(L45)>0),AND(L45<>"",N(L45)<0)),IF(F45="Short","REVIEW — back above 50-day avg","REVIEW — below 50-day avg"),"HOLD"))))),IF(OR(AP45="Closed",AP45="Dropped"),"Closed",IF(AK45="A",IF(F45="Short","Run Technical Review — SHORT entry","Run Technical Review — LONG entry"),IF(AK45="B","Watch — wait for setup","Drop or re-check next week"))))) | AX45: =IF(AND(C45<>"",A45=$C$4,ISNUMBER(AJ45)),AJ45+ROW()/100000,"")
J46: =IF(OR(G46="",I46=""),"",G46*I46/1000000) | AB46: =IF(C46="","",IF(F46="Short",(AND(M46<>"",N(M46)<0))+(AND(L46<>"",N(L46)<0))+(AND(K46<>"",N(K46)<0))+AND(L46<>"",M46<>"",N(M46)<N(L46)),(N(M46)>0)+(N(L46)>0)+(N(K46)>0)+AND(L46<>"",M46<>"",N(M46)>N(L46)))) | AC46: =IF(C46="","",IF(F46="Short",IF(N46="",0,IF(AND(N46>=30,N46<=50),2,IF(OR(AND(N46>=25,N46<30),AND(N46>50,N46<=60)),1,0)))+IF(P46="",0,IF(AND(IF(B46="JSE",$L$5,$L$4)<>"",P46<IF(B46="JSE",$L$5,$L$4)),2,IF(P46<0,1,0))),IF(N46="",0,IF(AND(N46>=50,N46<=70),2,IF(OR(AND(N46>=40,N46<50),AND(N46>70,N46<=75)),1,0)))+IF(P46="",0,IF(AND(IF(B46="JSE",$L$5,$L$4)<>"",P46>IF(B46="JSE",$L$5,$L$4)),2,IF(P46>0,1,0))))) | AD46: =IF(C46="","",IF(F46="Short",IF(R46="",0,IF(R46<=0.1,2,IF(R46<=0.25,1,0))),IF(Q46="",0,IF(Q46>=-0.1,2,IF(Q46>=-0.25,1,0))))) | AE46: =IF(C46="","",IF(J46="",0,IF(J46>=IF(B46="JSE",$L$7,$L$6),2,IF(J46>=IF(B46="JSE",$L$7,$L$6)/4,1,0)))) | AF46: =IF(C46="","",IF(F46="Short",AND(T46<>"",N(T46)<0),N(T46)>0)+(N(S46)>=1.5)) | AG46: =IF(C46="","",IF(AL46="",0,IF(AL46>=3,4,IF(AL46>=2,2,0)))) | AH46: =IF(C46="","",IF(AND(ISNUMBER(V46),ISNUMBER(A46),V46>=A46,V46-A46<=14),-2,0)) | AI46: =IF(C46="","",IF(AND(F46="Short",N(U46)>=0.2),-1,0)) | AJ46: =IF(C46="","",SUM(AB46:AI46)) | AK46: =IF(C46="","",IF(AJ46>=14,"A",IF(AJ46>=10,"B","C"))) | AL46: =IFERROR(IF(OR(Y46="",Z46="",AA46=""),"",IF(F46="Short",IF(Z46<=Y46,"",(Y46-AA46)/(Z46-Y46)),IF(Y46<=Z46,"",(AA46-Y46)/(Y46-Z46)))),"") | AM46: =IF(OR(Y46="",Z46="",N(Y46)=N(Z46)),"",IF(OR(AND(F46="Short",Z46<Y46),AND(NOT(F46="Short"),Z46>Y46)),"stop on wrong side",ABS(Y46-Z46))) | AN46: =IFERROR(IF(OR(NOT(ISNUMBER(AM46)),$C$6=""),"",ROUNDDOWN($C$6*$C$7/AM46,2)),"") | AO46: =IFERROR(IF(AN46="","",AN46*Y46),"") | AS46: =IFERROR(IF(OR(AR46="",Y46="",AQ46=""),"",IF(F46="Short",1-AR46/Y46,AR46/Y46-1)),"") | AT46: =IF(AQ46="","",IF(ISNUMBER($C$4),$C$4,TODAY())-AQ46) | AU46: =IF(C46="","",IF(AP46="Open position",IF(IF(F46="Short",AND(ISNUMBER(AR46),ISNUMBER(Z46),AR46>=Z46),AND(ISNUMBER(AR46),ISNUMBER(Z46),AR46<=Z46)),IF(F46="Short","COVER — stop hit (buy back)","SELL — stop hit"),IF(IF(F46="Short",AND(ISNUMBER(AR46),ISNUMBER(AA46),AR46<=AA46),AND(ISNUMBER(AR46),ISNUMBER(AA46),AR46>=AA46)),"TAKE PROFIT — target hit",IF(AND(ISNUMBER(AT46),AT46>182),IF(F46="Short","COVER — 6-month time limit","SELL — 6-month time limit"),IF(AND(ISNUMBER(AT46),AT46>42,ISNUMBER(AS46),AS46<0.02),"REVIEW — no progress after 6 weeks",IF(IF(F46="Short",AND(L46<>"",N(L46)>0),AND(L46<>"",N(L46)<0)),IF(F46="Short","REVIEW — back above 50-day avg","REVIEW — below 50-day avg"),"HOLD"))))),IF(OR(AP46="Closed",AP46="Dropped"),"Closed",IF(AK46="A",IF(F46="Short","Run Technical Review — SHORT entry","Run Technical Review — LONG entry"),IF(AK46="B","Watch — wait for setup","Drop or re-check next week"))))) | AX46: =IF(AND(C46<>"",A46=$C$4,ISNUMBER(AJ46)),AJ46+ROW()/100000,"")
... J210: =IF(OR(G210="",I210=""),"",G210*I210/1000000) | AB210: =IF(C210="","",IF(F210="Short",(AND(M210<>"",N(M210)<0))+(AND(L210<>"",N(L210)<0))+(AND(K210<>"",N(K210)<0))+AND(L210<>"",M210<>"",N(M210)<N(L210)),(N(M210)>0)+(N(L210)>0)+(N(K210)>0)+AND(L210<>"",M210<>"",N(M210)>N(L210)))) | AC210: =IF(C210="","",IF(F210="Short",IF(N210="",0,IF(AND(N210>=30,N210<=50),2,IF(OR(AND(N210>=25,N210<30),AND(N210>50,N210<=60)),1,0)))+IF(P210="",0,IF(AND(IF(B210="JSE",$L$5,$L$4)<>"",P210<IF(B210="JSE",$L$5,$L$4)),2,IF(P210<0,1,0))),IF(N210="",0,IF(AND(N210>=50,N210<=70),2,IF(OR(AND(N210>=40,N210<50),AND(N210>70,N210<=75)),1,0)))+IF(P210="",0,IF(AND(IF(B210="JSE",$L$5,$L$4)<>"",P210>IF(B210="JSE",$L$5,$L$4)),2,IF(P210>0,1,0))))) | AD210: =IF(C210="","",IF(F210="Short",IF(R210="",0,IF(R210<=0.1,2,IF(R210<=0.25,1,0))),IF(Q210="",0,IF(Q210>=-0.1,2,IF(Q210>=-0.25,1,0))))) | AE210: =IF(C210="","",IF(J210="",0,IF(J210>=IF(B210="JSE",$L$7,$L$6),2,IF(J210>=IF(B210="JSE",$L$7,$L$6)/4,1,0)))) | AF210: =IF(C210="","",IF(F210="Short",AND(T210<>"",N(T210)<0),N(T210)>0)+(N(S210)>=1.5)) | AG210: =IF(C210="","",IF(AL210="",0,IF(AL210>=3,4,IF(AL210>=2,2,0)))) | AH210: =IF(C210="","",IF(AND(ISNUMBER(V210),ISNUMBER(A210),V210>=A210,V210-A210<=14),-2,0)) | AI210: =IF(C210="","",IF(AND(F210="Short",N(U210)>=0.2),-1,0)) | AJ210: =IF(C210="","",SUM(AB210:AI210)) | AK210: =IF(C210="","",IF(AJ210>=14,"A",IF(AJ210>=10,"B","C"))) | AL210: =IFERROR(IF(OR(Y210="",Z210="",AA210=""),"",IF(F210="Short",IF(Z210<=Y210,"",(Y210-AA210)/(Z210-Y210)),IF(Y210<=Z210,"",(AA210-Y210)/(Y210-Z210)))),"") | AM210: =IF(OR(Y210="",Z210="",N(Y210)=N(Z210)),"",IF(OR(AND(F210="Short",Z210<Y210),AND(NOT(F210="Short"),Z210>Y210)),"stop on wrong side",ABS(Y210-Z210))) | AN210: =IFERROR(IF(OR(NOT(ISNUMBER(AM210)),$C$6=""),"",ROUNDDOWN($C$6*$C$7/AM210,2)),"") | AO210: =IFERROR(IF(AN210="","",AN210*Y210),"") | AS210: =IFERROR(IF(OR(AR210="",Y210="",AQ210=""),"",IF(F210="Short",1-AR210/Y210,AR210/Y210-1)),"") | AT210: =IF(AQ210="","",IF(ISNUMBER($C$4),$C$4,TODAY())-AQ210) | AU210: =IF(C210="","",IF(AP210="Open position",IF(IF(F210="Short",AND(ISNUMBER(AR210),ISNUMBER(Z210),AR210>=Z210),AND(ISNUMBER(AR210),ISNUMBER(Z210),AR210<=Z210)),IF(F210="Short","COVER — stop hit (buy back)","SELL — stop hit"),IF(IF(F210="Short",AND(ISNUMBER(AR210),ISNUMBER(AA210),AR210<=AA210),AND(ISNUMBER(AR210),ISNUMBER(AA210),AR210>=AA210)),"TAKE PROFIT — target hit",IF(AND(ISNUMBER(AT210),AT210>182),IF(F210="Short","COVER — 6-month time limit","SELL — 6-month time limit"),IF(AND(ISNUMBER(AT210),AT210>42,ISNUMBER(AS210),AS210<0.02),"REVIEW — no progress after 6 weeks",IF(IF(F210="Short",AND(L210<>"",N(L210)>0),AND(L210<>"",N(L210)<0)),IF(F210="Short","REVIEW — back above 50-day avg","REVIEW — below 50-day avg"),"HOLD"))))),IF(OR(AP210="Closed",AP210="Dropped"),"Closed",IF(AK210="A",IF(F210="Short","Run Technical Review — SHORT entry","Run Technical Review — LONG entry"),IF(AK210="B","Watch — wait for setup","Drop or re-check next week"))))) | AX210: =IF(AND(C210<>"",A210=$C$4,ISNUMBER(AJ210)),AJ210+ROW()/100000,"")

Sheet Weekly Review
C1: Weekly Review — swing (every weekend)
A2: Do this every Saturday or Sunday, in order. Log the result so you can see your process improve.
A4: Checklist — tick each step (✔)
A5: 1. Market regime: S&P 500 and JSE All Share vs their 200-day averages (log below) | I5: ✔
A6: 2. Run the Finviz (US) and TradingView (JSE) swing presets | I6: ✔
A7: 3. Shortlist 20–30 by 6-month performance; check charts for clean uptrends and setups | I7: ✔
A8: 4. Add at least 5 candidates to the Swing Watchlist with this week's date (check the minimum counter) | I8: ✔
A9: 5. Plan entry, stop and target for every A/B candidate (reward:risk 2x+) | I9: ✔
A10: 6. Run the LRC Technical Review for A-grades you want to buy; trade only with clearance | I10: ✔
A11: 7. Update 'Price now' on every open trade and act on each Review signal | I11: ✔
A12: 8. Check results dates for the next 2 weeks (event risk) | I12: ✔
A13: 9. Log the week below: trades opened/closed and one lesson | I13: ✔
A15: Review log — one row per review
A16: Week ending | B16: S&P 500 above 200-day? (Y/N) | C16: JSE All Share above 200-day? (Y/N) | D16: Market regime → bias | E16: New candidates | F16: A-grades | G16: Trades opened | H16: Trades closed (why) | I16: Lessons / actions for next week
A17: 46298 | B17: Y | C17: N | D17: =IF(OR(B17="",C17=""),"",IF(AND(B17="Y",C17="Y"),"RISK-ON → favour longs",IF(AND(B17="N",C17="N"),"RISK-OFF → favour shorts","MIXED → both, smaller"))) -> MIXED → both, smaller | E17: =IF(A17="","",COUNTIFS('Swing Watchlist'!$A$11:$A$210,A17,'Swing Watchlist'!$C$11:$C$210,"?*")) -> 3 | F17: =IF(A17="","",COUNTIFS('Swing Watchlist'!$A$11:$A$210,A17,'Swing Watchlist'!$AK$11:$AK$210,"A")) -> 0 | G17: 0 | H17: None (no swing positions open) | I17: LRC RULE: only Work-sheet names with a BUY/SELL rating AND technical clearance go on the watchlist (BUY = Long, SELL = Short). This week: PCTY (Long), WAB and ANET (Short). FAST (SELL) not added — technical clearance failed (score <70%). 7 HOLDs not added. House minimum of 5 not met — run more Work-sheets to feed the list. S&P 500 above 200-day; JSE All Share below (MA as of 26 Aug, stale). Shorts WAB/ANET are still in uptrends — act only on the breakdown triggers.
A18: 46312 | B18: Y | C18: N | D18: =IF(OR(B18="",C18=""),"",IF(AND(B18="Y",C18="Y"),"RISK-ON → favour longs",IF(AND(B18="N",C18="N"),"RISK-OFF → favour shorts","MIXED → both, smaller"))) -> MIXED → both, smaller | E18: =IF(A18="","",COUNTIFS('Swing Watchlist'!$A$11:$A$210,A18,'Swing Watchlist'!$C$11:$C$210,"?*")) -> 8 | F18: =IF(A18="","",COUNTIFS('Swing Watchlist'!$A$11:$A$210,A18,'Swing Watchlist'!$AK$11:$AK$210,"A")) -> 2 | G18: 0 | H18: None. PCTY long trigger (149) was hit ~8 Oct but no trade was entered; no swing positions open. | I18: Finviz is blocked for our tools, so the Swing Long / Swing Short presets were applied manually on stockanalysis.com data (13 Oct closes). LRC RULE: only BUY/SELL-rated names with technical clearance are tradeable. LONGS: only NVDA qualifies; INTU and DECK are BUY-rated but in downtrends (watch only). 2 long slots unfilled — the momentum names the long preset finds (DELL, HPE, KEYS, APH, AMD) all rate SELL on valuation. SHORTS: NKE, ANET, AMD, DELL, FAST (max 4 open; FAST only after its 14 Oct results). Event risk inside 14 days: WAB 21 Oct, DECK 22 Oct, META 21 Oct, APH/GOOGL 28 Oct. S&P 500 above its 200-day; JSE All Share below (−7.4% in 6 months). Lesson: an un-entered trigger cost us the PCTY move (+9%) — set conditional orders when a setup is approved. — P. Nkuna
A19: 46316 | D19: =IF(OR(B19="",C19=""),"",IF(AND(B19="Y",C19="Y"),"RISK-ON → favour longs",IF(AND(B19="N",C19="N"),"RISK-OFF → favour shorts","MIXED → both, smaller"))) | E19: =IF(A19="","",COUNTIFS('Swing Watchlist'!$A$11:$A$210,A19,'Swing Watchlist'!$C$11:$C$210,"?*")) -> 13 | F19: =IF(A19="","",COUNTIFS('Swing Watchlist'!$A$11:$A$210,A19,'Swing Watchlist'!$AK$11:$AK$210,"A")) -> 0 | G19: 0 | I19: Built by the LRC Watchlist Agent 2026-10-23T03:09+02:00: 3 long / 10 short candidates under house rules. Analyst to review before any trade.
D20: =IF(OR(B20="",C20=""),"",IF(AND(B20="Y",C20="Y"),"RISK-ON → favour longs",IF(AND(B20="N",C20="N"),"RISK-OFF → favour shorts","MIXED → both, smaller"))) | E20: =IF(A20="","",COUNTIFS('Swing Watchlist'!$A$11:$A$210,A20,'Swing Watchlist'!$C$11:$C$210,"?*")) | F20: =IF(A20="","",COUNTIFS('Swing Watchlist'!$A$11:$A$210,A20,'Swing Watchlist'!$AK$11:$AK$210,"A"))
D21: =IF(OR(B21="",C21=""),"",IF(AND(B21="Y",C21="Y"),"RISK-ON → favour longs",IF(AND(B21="N",C21="N"),"RISK-OFF → favour shorts","MIXED → both, smaller"))) | E21: =IF(A21="","",COUNTIFS('Swing Watchlist'!$A$11:$A$210,A21,'Swing Watchlist'!$C$11:$C$210,"?*")) | F21: =IF(A21="","",COUNTIFS('Swing Watchlist'!$A$11:$A$210,A21,'Swing Watchlist'!$AK$11:$AK$210,"A"))
D22: =IF(OR(B22="",C22=""),"",IF(AND(B22="Y",C22="Y"),"RISK-ON → favour longs",IF(AND(B22="N",C22="N"),"RISK-OFF → favour shorts","MIXED → both, smaller"))) | E22: =IF(A22="","",COUNTIFS('Swing Watchlist'!$A$11:$A$210,A22,'Swing Watchlist'!$C$11:$C$210,"?*")) | F22: =IF(A22="","",COUNTIFS('Swing Watchlist'!$A$11:$A$210,A22,'Swing Watchlist'!$AK$11:$AK$210,"A"))
D23: =IF(OR(B23="",C23=""),"",IF(AND(B23="Y",C23="Y"),"RISK-ON → favour longs",IF(AND(B23="N",C23="N"),"RISK-OFF → favour shorts","MIXED → both, smaller"))) | E23: =IF(A23="","",COUNTIFS('Swing Watchlist'!$A$11:$A$210,A23,'Swing Watchlist'!$C$11:$C$210,"?*")) | F23: =IF(A23="","",COUNTIFS('Swing Watchlist'!$A$11:$A$210,A23,'Swing Watchlist'!$AK$11:$AK$210,"A"))
D24: =IF(OR(B24="",C24=""),"",IF(AND(B24="Y",C24="Y"),"RISK-ON → favour longs",IF(AND(B24="N",C24="N"),"RISK-OFF → favour shorts","MIXED → both, smaller"))) | E24: =IF(A24="","",COUNTIFS('Swing Watchlist'!$A$11:$A$210,A24,'Swing Watchlist'!$C$11:$C$210,"?*")) | F24: =IF(A24="","",COUNTIFS('Swing Watchlist'!$A$11:$A$210,A24,'Swing Watchlist'!$AK$11:$AK$210,"A"))
D25: =IF(OR(B25="",C25=""),"",IF(AND(B25="Y",C25="Y"),"RISK-ON → favour longs",IF(AND(B25="N",C25="N"),"RISK-OFF → favour shorts","MIXED → both, smaller"))) | E25: =IF(A25="","",COUNTIFS('Swing Watchlist'!$A$11:$A$210,A25,'Swing Watchlist'!$C$11:$C$210,"?*")) | F25: =IF(A25="","",COUNTIFS('Swing Watchlist'!$A$11:$A$210,A25,'Swing Watchlist'!$AK$11:$AK$210,"A"))
D26: =IF(OR(B26="",C26=""),"",IF(AND(B26="Y",C26="Y"),"RISK-ON → favour longs",IF(AND(B26="N",C26="N"),"RISK-OFF → favour shorts","MIXED → both, smaller"))) | E26: =IF(A26="","",COUNTIFS('Swing Watchlist'!$A$11:$A$210,A26,'Swing Watchlist'!$C$11:$C$210,"?*")) | F26: =IF(A26="","",COUNTIFS('Swing Watchlist'!$A$11:$A$210,A26,'Swing Watchlist'!$AK$11:$AK$210,"A"))
D27: =IF(OR(B27="",C27=""),"",IF(AND(B27="Y",C27="Y"),"RISK-ON → favour longs",IF(AND(B27="N",C27="N"),"RISK-OFF → favour shorts","MIXED → both, smaller"))) | E27: =IF(A27="","",COUNTIFS('Swing Watchlist'!$A$11:$A$210,A27,'Swing Watchlist'!$C$11:$C$210,"?*")) | F27: =IF(A27="","",COUNTIFS('Swing Watchlist'!$A$11:$A$210,A27,'Swing Watchlist'!$AK$11:$AK$210,"A"))
D28: =IF(OR(B28="",C28=""),"",IF(AND(B28="Y",C28="Y"),"RISK-ON → favour longs",IF(AND(B28="N",C28="N"),"RISK-OFF → favour shorts","MIXED → both, smaller"))) | E28: =IF(A28="","",COUNTIFS('Swing Watchlist'!$A$11:$A$210,A28,'Swing Watchlist'!$C$11:$C$210,"?*")) | F28: =IF(A28="","",COUNTIFS('Swing Watchlist'!$A$11:$A$210,A28,'Swing Watchlist'!$AK$11:$AK$210,"A"))
D29: =IF(OR(B29="",C29=""),"",IF(AND(B29="Y",C29="Y"),"RISK-ON → favour longs",IF(AND(B29="N",C29="N"),"RISK-OFF → favour shorts","MIXED → both, smaller"))) | E29: =IF(A29="","",COUNTIFS('Swing Watchlist'!$A$11:$A$210,A29,'Swing Watchlist'!$C$11:$C$210,"?*")) | F29: =IF(A29="","",COUNTIFS('Swing Watchlist'!$A$11:$A$210,A29,'Swing Watchlist'!$AK$11:$AK$210,"A"))
D30: =IF(OR(B30="",C30=""),"",IF(AND(B30="Y",C30="Y"),"RISK-ON → favour longs",IF(AND(B30="N",C30="N"),"RISK-OFF → favour shorts","MIXED → both, smaller"))) | E30: =IF(A30="","",COUNTIFS('Swing Watchlist'!$A$11:$A$210,A30,'Swing Watchlist'!$C$11:$C$210,"?*")) | F30: =IF(A30="","",COUNTIFS('Swing Watchlist'!$A$11:$A$210,A30,'Swing Watchlist'!$AK$11:$AK$210,"A"))
D31: =IF(OR(B31="",C31=""),"",IF(AND(B31="Y",C31="Y"),"RISK-ON → favour longs",IF(AND(B31="N",C31="N"),"RISK-OFF → favour shorts","MIXED → both, smaller"))) | E31: =IF(A31="","",COUNTIFS('Swing Watchlist'!$A$11:$A$210,A31,'Swing Watchlist'!$C$11:$C$210,"?*")) | F31: =IF(A31="","",COUNTIFS('Swing Watchlist'!$A$11:$A$210,A31,'Swing Watchlist'!$AK$11:$AK$210,"A"))
... D68: =IF(OR(B68="",C68=""),"",IF(AND(B68="Y",C68="Y"),"RISK-ON → favour longs",IF(AND(B68="N",C68="N"),"RISK-OFF → favour shorts","MIXED → both, smaller"))) | E68: =IF(A68="","",COUNTIFS('Swing Watchlist'!$A$11:$A$210,A68,'Swing Watchlist'!$C$11:$C$210,"?*")) | F68: =IF(A68="","",COUNTIFS('Swing Watchlist'!$A$11:$A$210,A68,'Swing Watchlist'!$AK$11:$AK$210,"A"))

Sheet How to Pick — Investment
C1: How to pick long-term investments (hold 5 to 10+ years) — every month
A2: Goal: own excellent businesses bought at sensible prices, and hold them while the business keeps compounding. Target: at least 5 new candidates a month, US and JSE.
A4: Step-by-step (about 2–3 hours a month)
A5: 1. Run the quality screen (15 min) | B5: US: the Finviz 'Investment' preset on the Screener Settings tab. JSE: the TradingView preset, then check the annual report — JSE data on screeners is patchier.
A6: 2. Shortlist on quality first (30 min) | B6: Prefer businesses with high returns on capital (ROE 15%+, ROIC 12%+), strong margins, low debt and steady growth for 5+ years. Price comes second: a great business at a fair price beats a fair business at a great price.
A7: 3. Understand the business (60 min) | B7: For each shortlisted name, answer in one line: what it sells, who pays, why customers stay (the moat), and what could break it. Read the latest annual report summary and results presentation.
A8: 4. Judge moat and management (0–2 each) | B8: Moat: 2 = clear lasting advantage (brand, network, switching costs, scale, licence); 1 = some; 0 = none. Management: 2 = proven, honest, owner-like, sensible capital allocation; 1 = average or changing; 0 = concerns.
A9: 5. Estimate fair value (optional, 30 min) | B9: Use the Valuation tab of the LRC Stock Analysis Template, or a simple check: FCF yield vs bond yield, P/E vs history and peers. The sheet then shows the margin of safety.
A10: 6. Enter in the sheet | B10: Add at least 5 candidates on 'Investment Watchlist' with this month's date. A = start the full LRC Stock Analysis Template; B = watch and re-check next month; C = reject.
A11: 7. Review what you own (monthly) | B11: Update 'Price now'. Hold while the thesis is intact. Review if the price runs 20%+ above fair value, the quality score drops below 13, or a thesis-breaker appears (moat eroding, bad acquisition, management change).
A12: What the scores mean
A13: Quality /6 | B13: ROE 15%+ = 2 (10%+ = 1); ROIC 12%+ = 2 (8%+ = 1); operating margin 15%+ = 1; gross margin 40%+ = 1.
A14: Growth /4 | B14: EPS growth past 5 years 10%+ = 2 (5%+ = 1); sales growth past 5 years 8%+ = 2 (4%+ = 1).
A15: Balance sheet /3 | B15: Debt/equity 0.5 or less = 2 (1.0 or less = 1); current ratio 1.2+ = 1. Banks and insurers: use your judgement instead.
A16: Valuation /4 | B16: Forward P/E 20 or less = 2 (30 or less = 1); price/free cash flow 20 or less = 2 (30 or less = 1).
A17: Owner /1 | B17: Insiders own 1%+ or dividend yield 2%+.
A18: Judgement /4 | B18: Your moat + management scores.
A19: Margin of safety /2 | B19: Fair value 25%+ above price = 2; 10%+ = 1.
A20: Grades | B20: A = 18+ out of 24 · B = 13–17 · C = under 13.
A21: Rules
A22: Patience | B22: Long-term means years. Don't sell a great business because of one bad quarter; do sell if the thesis breaks.
A23: Diversify | B23: Aim for 10–20 holdings across sectors and both markets over time; no single holding above 10% at purchase.
A24: Avoid traps | B24: A very low P/E with falling sales is usually a value trap. High debt + cyclical earnings = danger in a downturn.

Sheet Investment Watchlist
C1: Investment Watchlist — monthly (hold 5 to 10+ years)
A2: Every month add at least 5 quality candidates (US from Finviz, JSE from TradingView / annual reports). A-grades go into the full LRC Stock Analysis Template. Type percentages with the % sign. 'Price' = price when screened; update 'Price now' at each monthly review.
A4: Current review month (1st of month) | C4: 46296 | D4: Counts and the Top 5 use this month. | J4: This month's candidates | L4: =COUNTIFS($A$9:$A$158,$C$4,$C$9:$C$158,"?*") -> 10 | M4: =IF(L4>=$C$5,"✔ minimum met","⚠ need "&($C$5-L4)&" more") -> ✔ minimum met
A5: Minimum new candidates per month | C5: 5 | D5: House rule. | J5: US / JSE this month | L5: =COUNTIFS($A$9:$A$158,$C$4,$B$9:$B$158,"US")&" / "&COUNTIFS($A$9:$A$158,$C$4,$B$9:$B$158,"JSE") -> 10 / 0
A7: INPUTS FROM FINVIZ / TRADINGVIEW + YOUR JUDGEMENT | X7: SCORE (automatic) | AH7: NEXT | AI7: STATUS & THESIS
A8: Month | B8: Market | C8: Ticker | D8: Company | E8: Sector | F8: Price | G8: Mkt cap (bn) | H8: Forward P/E | I8: PEG | J8: P/FCF | K8: ROE | L8: ROIC / ROI | M8: Gross margin | N8: Oper. margin | O8: Debt / Equity | P8: Current ratio | Q8: EPS growth 5y | R8: Sales growth 5y | S8: Dividend yield | T8: Insider own | U8: Moat 0-2 | V8: Management 0-2 | W8: Fair value | X8: Quality /6 | Y8: Growth /4 | Z8: Balance sheet /3 | AA8: Valuation /4 | AB8: Owner /1 | AC8: Judgement /4 | AD8: Margin of safety | AE8: MoS pts /2 | AF8: SCORE /24 | AG8: Grade | AH8: Next step | AI8: Status | AJ8: One-line thesis | AK8: Date added | AL8: Price now | AM8: Change since added | AN8: Notes
A9: 46296 | B9: US | C9: INTU | D9: Intuit Inc. | E9: Technology | F9: 301.45 | G9: 80.56 | H9: 12.59 | I9: 0.95 | J9: 9.3 | K9: 0.236 | L9: 0.2289 | M9: 0.8098 | N9: 0.288 | O9: 0.44 | P9: 1.51 | Q9: 0.2262 | R9: 0.1394 | S9: 0.0183 | T9: 0.0222 | U9: 2 | V9: 2 | W9: 426 | X9: =IF(C9="","",IF(K9="",0,IF(K9>=0.15,2,IF(K9>=0.1,1,0)))+IF(L9="",0,IF(L9>=0.12,2,IF(L9>=0.08,1,0)))+(AND(N9<>"",N(N9)>=0.15))+(AND(M9<>"",N(M9)>=0.4))) -> 6 | Y9: =IF(C9="","",IF(Q9="",0,IF(Q9>=0.1,2,IF(Q9>=0.05,1,0)))+IF(R9="",0,IF(R9>=0.08,2,IF(R9>=0.04,1,0)))) -> 4 | Z9: =IF(C9="","",IF(O9="",0,IF(O9<=0.5,2,IF(O9<=1,1,0)))+(AND(P9<>"",N(P9)>=1.2))) -> 3 | AA9: =IF(C9="","",IF(H9="",0,IF(AND(H9>0,H9<=20),2,IF(AND(H9>0,H9<=30),1,0)))+IF(J9="",0,IF(AND(J9>0,J9<=20),2,IF(AND(J9>0,J9<=30),1,0)))) -> 4 | AB9: =IF(C9="","",IF(OR(N(T9)>=0.01,N(S9)>=0.02),1,0)) -> 1 | AC9: =IF(C9="","",MIN(2,N(U9))+MIN(2,N(V9))) -> 4 | AD9: =IFERROR(IF(OR(W9="",F9="",N(F9)=0),"",W9/F9-1),"") -> 0.41316968 | AE9: =IF(C9="","",IF(AD9="",0,IF(AD9>=0.25,2,IF(AD9>=0.1,1,0)))) -> 2 | AF9: =IF(C9="","",X9+Y9+Z9+AA9+AB9+AC9+AE9) -> 24 | AG9: =IF(C9="","",IF(AF9>=18,"A",IF(AF9>=13,"B","C"))) -> A | AH9: =IF(C9="","",IF(OR(AI9="Sold",AI9="Rejected"),"Closed",IF(AI9="Owned",IF(AND(ISNUMBER(W9),ISNUMBER(AL9),AL9>W9*1.2),"REVIEW — price 20%+ above fair value",IF(AF9<13,"REVIEW — quality score fell below 13","HOLD — re-check thesis yearly")),IF(AG9="A","Full LRC Stock Analysis",IF(AG9="B","Watch — re-check next month","Reject"))))) -> Full LRC Stock Analysis | AI9: Full analysis | AJ9: AI-disruption fear has priced a 40%-FCF-margin software franchise at ~12.6x forward EPS; we think QuickBooks and TurboTax are stickier than the market believes. | AK9: 46309 | AL9: 301.45 | AM9: =IFERROR(IF(OR(AL9="",F9="",N(F9)=0),"",AL9/F9-1),"") -> 0 | AN9: LRC Work-sheet 14 Oct: BUY, 6-m target $426.00 (+41%), score 4.0/5. Fair value = the 6-MONTH Work-sheet target (a long-term DCF value would be higher for the growers). Growth = FY2022-FY2026 (4-yr CAGR) CAGR. Data: stockanalysis.com 13 Oct 2026 (Finviz Investment preset applied manually — Finviz blocked). — P. Nkuna | AP9: =IF(AND(C9<>"",A9=$C$4,ISNUMBER(AF9)),AF9+ROW()/100000,"") -> 24.00009
A10: 46296 | B10: US | C10: NVDA | D10: NVIDIA Corporation | E10: Technology | F10: 228.52 | G10: 5520 | H10: 18.89 | I10: 0.38 | J10: 43.45 | K10: 1.1721 | L10: 0.9203 | M10: 0.7467 | N10: 0.6521 | O10: 0.17 | P10: 4.59 | Q10: 0.8827 | R10: 0.683 | S10: 0.0044 | T10: 0.039 | U10: 2 | V10: 2 | W10: 262.56 | X10: =IF(C10="","",IF(K10="",0,IF(K10>=0.15,2,IF(K10>=0.1,1,0)))+IF(L10="",0,IF(L10>=0.12,2,IF(L10>=0.08,1,0)))+(AND(N10<>"",N(N10)>=0.15))+(AND(M10<>"",N(M10)>=0.4))) -> 6 | Y10: =IF(C10="","",IF(Q10="",0,IF(Q10>=0.1,2,IF(Q10>=0.05,1,0)))+IF(R10="",0,IF(R10>=0.08,2,IF(R10>=0.04,1,0)))) -> 4 | Z10: =IF(C10="","",IF(O10="",0,IF(O10<=0.5,2,IF(O10<=1,1,0)))+(AND(P10<>"",N(P10)>=1.2))) -> 3 | AA10: =IF(C10="","",IF(H10="",0,IF(AND(H10>0,H10<=20),2,IF(AND(H10>0,H10<=30),1,0)))+IF(J10="",0,IF(AND(J10>0,J10<=20),2,IF(AND(J10>0,J10<=30),1,0)))) -> 2 | AB10: =IF(C10="","",IF(OR(N(T10)>=0.01,N(S10)>=0.02),1,0)) -> 1 | AC10: =IF(C10="","",MIN(2,N(U10))+MIN(2,N(V10))) -> 4 | AD10: =IFERROR(IF(OR(W10="",F10="",N(F10)=0),"",W10/F10-1),"") -> 0.14895852 | AE10: =IF(C10="","",IF(AD10="",0,IF(AD10>=0.25,2,IF(AD10>=0.1,1,0)))) -> 1 | AF10: =IF(C10="","",X10+Y10+Z10+AA10+AB10+AC10+AE10) -> 21 | AG10: =IF(C10="","",IF(AF10>=18,"A",IF(AF10>=13,"B","C"))) -> A | AH10: =IF(C10="","",IF(OR(AI10="Sold",AI10="Rejected"),"Closed",IF(AI10="Owned",IF(AND(ISNUMBER(W10),ISNUMBER(AL10),AL10>W10*1.2),"REVIEW — price 20%+ above fair value",IF(AF10<13,"REVIEW — quality score fell below 13","HOLD — re-check thesis yearly")),IF(AG10="A","Full LRC Stock Analysis",IF(AG10="B","Watch — re-check next month","Reject"))))) -> Full LRC Stock Analysis | AI10: Full analysis | AJ10: AI-compute leader growing 70-90% a year at ~19x forward EPS — cheaper than its chip peers despite better margins. | AK10: 46309 | AL10: 228.52 | AM10: =IFERROR(IF(OR(AL10="",F10="",N(F10)=0),"",AL10/F10-1),"") -> 0 | AN10: LRC Work-sheet 14 Oct: BUY, 6-m target $262.56 (+15%), score 3.8/5. Fair value = the 6-MONTH Work-sheet target (a long-term DCF value would be higher for the growers). Growth = FY2022-FY2026 (4-yr CAGR) CAGR. Data: stockanalysis.com 13 Oct 2026 (Finviz Investment preset applied manually — Finviz blocked). — P. Nkuna | AP10: =IF(AND(C10<>"",A10=$C$4,ISNUMBER(AF10)),AF10+ROW()/100000,"") -> 21.0001
A11: 46296 | B11: US | C11: DECK | D11: Deckers Outdoor Corporation | E11: Consumer Discretionary | F11: 84.02 | G11: 11.44 | H11: 11 | I11: 1.54 | J11: 10.24 | K11: 0.4256 | L11: 0.9059 | M11: 0.578 | N11: 0.2267 | O11: 0.21 | P11: 2.75 | Q11: 0.2687 | R11: 0.148 | T11: 0.0102 | U11: 1 | V11: 1 | W11: 103 | X11: =IF(C11="","",IF(K11="",0,IF(K11>=0.15,2,IF(K11>=0.1,1,0)))+IF(L11="",0,IF(L11>=0.12,2,IF(L11>=0.08,1,0)))+(AND(N11<>"",N(N11)>=0.15))+(AND(M11<>"",N(M11)>=0.4))) -> 6 | Y11: =IF(C11="","",IF(Q11="",0,IF(Q11>=0.1,2,IF(Q11>=0.05,1,0)))+IF(R11="",0,IF(R11>=0.08,2,IF(R11>=0.04,1,0)))) -> 4 | Z11: =IF(C11="","",IF(O11="",0,IF(O11<=0.5,2,IF(O11<=1,1,0)))+(AND(P11<>"",N(P11)>=1.2))) -> 3 | AA11: =IF(C11="","",IF(H11="",0,IF(AND(H11>0,H11<=20),2,IF(AND(H11>0,H11<=30),1,0)))+IF(J11="",0,IF(AND(J11>0,J11<=20),2,IF(AND(J11>0,J11<=30),1,0)))) -> 4 | AB11: =IF(C11="","",IF(OR(N(T11)>=0.01,N(S11)>=0.02),1,0)) -> 1 | AC11: =IF(C11="","",MIN(2,N(U11))+MIN(2,N(V11))) -> 2 | AD11: =IFERROR(IF(OR(W11="",F11="",N(F11)=0),"",W11/F11-1),"") -> 0.2258986 | AE11: =IF(C11="","",IF(AD11="",0,IF(AD11>=0.25,2,IF(AD11>=0.1,1,0)))) -> 1 | AF11: =IF(C11="","",X11+Y11+Z11+AA11+AB11+AC11+AE11) -> 21 | AG11: =IF(C11="","",IF(AF11>=18,"A",IF(AF11>=13,"B","C"))) -> A | AH11: =IF(C11="","",IF(OR(AI11="Sold",AI11="Rejected"),"Closed",IF(AI11="Owned",IF(AND(ISNUMBER(W11),ISNUMBER(AL11),AL11>W11*1.2),"REVIEW — price 20%+ above fair value",IF(AF11<13,"REVIEW — quality score fell below 13","HOLD — re-check thesis yearly")),IF(AG11="A","Full LRC Stock Analysis",IF(AG11="B","Watch — re-check next month","Reject"))))) -> Full LRC Stock Analysis | AI11: Full analysis | AJ11: Two strong brands (HOKA, UGG), net cash and 23% margins at ~11x forward EPS; growth slowing but positive. | AK11: 46309 | AL11: 84.02 | AM11: =IFERROR(IF(OR(AL11="",F11="",N(F11)=0),"",AL11/F11-1),"") -> 0 | AN11: LRC Work-sheet 14 Oct: BUY, 6-m target $103.00 (+23%), score 3.8/5. Fair value = the 6-MONTH Work-sheet target (a long-term DCF value would be higher for the growers). Growth = FY2022-FY2026 (4-yr CAGR) CAGR. Data: stockanalysis.com 13 Oct 2026 (Finviz Investment preset applied manually — Finviz blocked). — P. Nkuna | AP11: =IF(AND(C11<>"",A11=$C$4,ISNUMBER(AF11)),AF11+ROW()/100000,"") -> 21.00011
A12: 46296 | B12: US | C12: PCTY | D12: Paylocity Holding Corporation | E12: Technology | F12: 158.11 | G12: 8.39 | H12: 18.09 | I12: 1.46 | J12: 16.79 | K12: 0.2197 | L12: 0.2567 | M12: 0.6928 | N12: 0.2183 | O12: 0.11 | P12: 1.09 | Q12: 0.3222 | R12: 0.2005 | T12: 0.1988 | U12: 1 | V12: 2 | W12: 157.05 | X12: =IF(C12="","",IF(K12="",0,IF(K12>=0.15,2,IF(K12>=0.1,1,0)))+IF(L12="",0,IF(L12>=0.12,2,IF(L12>=0.08,1,0)))+(AND(N12<>"",N(N12)>=0.15))+(AND(M12<>"",N(M12)>=0.4))) -> 6 | Y12: =IF(C12="","",IF(Q12="",0,IF(Q12>=0.1,2,IF(Q12>=0.05,1,0)))+IF(R12="",0,IF(R12>=0.08,2,IF(R12>=0.04,1,0)))) -> 4 | Z12: =IF(C12="","",IF(O12="",0,IF(O12<=0.5,2,IF(O12<=1,1,0)))+(AND(P12<>"",N(P12)>=1.2))) -> 2 | AA12: =IF(C12="","",IF(H12="",0,IF(AND(H12>0,H12<=20),2,IF(AND(H12>0,H12<=30),1,0)))+IF(J12="",0,IF(AND(J12>0,J12<=20),2,IF(AND(J12>0,J12<=30),1,0)))) -> 4 | AB12: =IF(C12="","",IF(OR(N(T12)>=0.01,N(S12)>=0.02),1,0)) -> 1 | AC12: =IF(C12="","",MIN(2,N(U12))+MIN(2,N(V12))) -> 3 | AD12: =IFERROR(IF(OR(W12="",F12="",N(F12)=0),"",W12/F12-1),"") -> -0.0067041933 | AE12: =IF(C12="","",IF(AD12="",0,IF(AD12>=0.25,2,IF(AD12>=0.1,1,0)))) -> 0 | AF12: =IF(C12="","",X12+Y12+Z12+AA12+AB12+AC12+AE12) -> 20 | AG12: =IF(C12="","",IF(AF12>=18,"A",IF(AF12>=13,"B","C"))) -> A | AH12: =IF(C12="","",IF(OR(AI12="Sold",AI12="Rejected"),"Closed",IF(AI12="Owned",IF(AND(ISNUMBER(W12),ISNUMBER(AL12),AL12>W12*1.2),"REVIEW — price 20%+ above fair value",IF(AF12<13,"REVIEW — quality score fell below 13","HOLD — re-check thesis yearly")),IF(AG12="A","Full LRC Stock Analysis",IF(AG12="B","Watch — re-check next month","Reject"))))) -> Full LRC Stock Analysis | AI12: Watch | AJ12: Quality payroll/HR software at 18x; our 6-month target is reached — accumulate below ~$146. | AK12: 46309 | AL12: 158.11 | AM12: =IFERROR(IF(OR(AL12="",F12="",N(F12)=0),"",AL12/F12-1),"") -> 0 | AN12: LRC Work-sheet 14 Oct: HOLD, 6-m target $157.05 (-1%), score 3.8/5. Fair value = the 6-MONTH Work-sheet target (a long-term DCF value would be higher for the growers). Growth = FY2022-FY2026 (4-yr CAGR) CAGR. Data: stockanalysis.com 13 Oct 2026 (Finviz Investment preset applied manually — Finviz blocked). — P. Nkuna | AP12: =IF(AND(C12<>"",A12=$C$4,ISNUMBER(AF12)),AF12+ROW()/100000,"") -> 20.00012
A13: 46296 | B13: US | C13: META | D13: Meta Platforms, Inc. | E13: Telecommunications | F13: 762.5 | G13: 1940 | H13: 23.71 | I13: 1.19 | J13: 47.41 | K13: 0.2985 | L13: 0.254 | M13: 0.8175 | N13: 0.3808 | O13: 0.43 | P13: 2.23 | Q13: 0.1428 | R13: 0.1426 | S13: 0.0028 | T13: 0.1342 | U13: 2 | V13: 1 | W13: 677.14 | X13: =IF(C13="","",IF(K13="",0,IF(K13>=0.15,2,IF(K13>=0.1,1,0)))+IF(L13="",0,IF(L13>=0.12,2,IF(L13>=0.08,1,0)))+(AND(N13<>"",N(N13)>=0.15))+(AND(M13<>"",N(M13)>=0.4))) -> 6 | Y13: =IF(C13="","",IF(Q13="",0,IF(Q13>=0.1,2,IF(Q13>=0.05,1,0)))+IF(R13="",0,IF(R13>=0.08,2,IF(R13>=0.04,1,0)))) -> 4 | Z13: =IF(C13="","",IF(O13="",0,IF(O13<=0.5,2,IF(O13<=1,1,0)))+(AND(P13<>"",N(P13)>=1.2))) -> 3 | AA13: =IF(C13="","",IF(H13="",0,IF(AND(H13>0,H13<=20),2,IF(AND(H13>0,H13<=30),1,0)))+IF(J13="",0,IF(AND(J13>0,J13<=20),2,IF(AND(J13>0,J13<=30),1,0)))) -> 1 | AB13: =IF(C13="","",IF(OR(N(T13)>=0.01,N(S13)>=0.02),1,0)) -> 1 | AC13: =IF(C13="","",MIN(2,N(U13))+MIN(2,N(V13))) -> 3 | AD13: =IFERROR(IF(OR(W13="",F13="",N(F13)=0),"",W13/F13-1),"") -> -0.11194754 | AE13: =IF(C13="","",IF(AD13="",0,IF(AD13>=0.25,2,IF(AD13>=0.1,1,0)))) -> 0 | AF13: =IF(C13="","",X13+Y13+Z13+AA13+AB13+AC13+AE13) -> 18 | AG13: =IF(C13="","",IF(AF13>=18,"A",IF(AF13>=13,"B","C"))) -> A | AH13: =IF(C13="","",IF(OR(AI13="Sold",AI13="Rejected"),"Closed",IF(AI13="Owned",IF(AND(ISNUMBER(W13),ISNUMBER(AL13),AL13>W13*1.2),"REVIEW — price 20%+ above fair value",IF(AF13<13,"REVIEW — quality score fell below 13","HOLD — re-check thesis yearly")),IF(AG13="A","Full LRC Stock Analysis",IF(AG13="B","Watch — re-check next month","Reject"))))) -> Full LRC Stock Analysis | AI13: Watch | AJ13: Superb ad franchise, but AI capex is cutting FCF and the shares sit above our 6-month value — wait for a better price. | AK13: 46309 | AL13: 762.5 | AM13: =IFERROR(IF(OR(AL13="",F13="",N(F13)=0),"",AL13/F13-1),"") -> 0 | AN13: LRC Work-sheet 14 Oct: SELL, 6-m target $677.14 (-11%), score 3.5/5. Fair value = the 6-MONTH Work-sheet target (a long-term DCF value would be higher for the growers). Growth = FY2021-FY2025 (4-yr CAGR) CAGR. Data: stockanalysis.com 13 Oct 2026 (Finviz Investment preset applied manually — Finviz blocked). — P. Nkuna | AP13: =IF(AND(C13<>"",A13=$C$4,ISNUMBER(AF13)),AF13+ROW()/100000,"") -> 18.00013
A14: 46296 | B14: US | C14: AMD | D14: Advanced Micro Devices, Inc. | E14: Technology | F14: 605.53 | G14: 988.51 | H14: 54.53 | J14: 146.77 | K14: 0.102 | L14: 0.0977 | M14: 0.5572 | N14: 0.1582 | O14: 0.06 | P14: 2.85 | Q14: 0.4666 | R14: 0.1364 | T14: 0.0044 | U14: 1 | V14: 2 | W14: 402.73 | X14: =IF(C14="","",IF(K14="",0,IF(K14>=0.15,2,IF(K14>=0.1,1,0)))+IF(L14="",0,IF(L14>=0.12,2,IF(L14>=0.08,1,0)))+(AND(N14<>"",N(N14)>=0.15))+(AND(M14<>"",N(M14)>=0.4))) -> 4 | Y14: =IF(C14="","",IF(Q14="",0,IF(Q14>=0.1,2,IF(Q14>=0.05,1,0)))+IF(R14="",0,IF(R14>=0.08,2,IF(R14>=0.04,1,0)))) -> 4 | Z14: =IF(C14="","",IF(O14="",0,IF(O14<=0.5,2,IF(O14<=1,1,0)))+(AND(P14<>"",N(P14)>=1.2))) -> 3 | AA14: =IF(C14="","",IF(H14="",0,IF(AND(H14>0,H14<=20),2,IF(AND(H14>0,H14<=30),1,0)))+IF(J14="",0,IF(AND(J14>0,J14<=20),2,IF(AND(J14>0,J14<=30),1,0)))) -> 0 | AB14: =IF(C14="","",IF(OR(N(T14)>=0.01,N(S14)>=0.02),1,0)) -> 0 | AC14: =IF(C14="","",MIN(2,N(U14))+MIN(2,N(V14))) -> 3 | AD14: =IFERROR(IF(OR(W14="",F14="",N(F14)=0),"",W14/F14-1),"") -> -0.33491322 | AE14: =IF(C14="","",IF(AD14="",0,IF(AD14>=0.25,2,IF(AD14>=0.1,1,0)))) -> 0 | AF14: =IF(C14="","",X14+Y14+Z14+AA14+AB14+AC14+AE14) -> 14 | AG14: =IF(C14="","",IF(AF14>=18,"A",IF(AF14>=13,"B","C"))) -> B | AH14: =IF(C14="","",IF(OR(AI14="Sold",AI14="Rejected"),"Closed",IF(AI14="Owned",IF(AND(ISNUMBER(W14),ISNUMBER(AL14),AL14>W14*1.2),"REVIEW — price 20%+ above fair value",IF(AF14<13,"REVIEW — quality score fell below 13","HOLD — re-check thesis yearly")),IF(AG14="A","Full LRC Stock Analysis",IF(AG14="B","Watch — re-check next month","Reject"))))) -> Closed | AI14: Rejected | AJ14: AVOID / SELL-rated: ~55x forward EPS prices near-perfect AI GPU execution; NVIDIA offers more growth at ~19x. | AK14: 46309 | AL14: 605.53 | AM14: =IFERROR(IF(OR(AL14="",F14="",N(F14)=0),"",AL14/F14-1),"") -> 0 | AN14: LRC Work-sheet 14 Oct: SELL, 6-m target $402.73 (-33%), score 3.3/5. Fair value = the 6-MONTH Work-sheet target (a long-term DCF value would be higher for the growers). Growth = FY2022-FY2025 3-yr CAGR (5-yr not gathered). Data: stockanalysis.com 13 Oct 2026 (Finviz Investment preset applied manually — Finviz blocked). LRC's investment track is LONG-ONLY: recorded as an avoid / SELL idea, not a short. — P. Nkuna | AP14: =IF(AND(C14<>"",A14=$C$4,ISNUMBER(AF14)),AF14+ROW()/100000,"") -> 14.00014
A15: 46296 | B15: US | C15: DELL | D15: Dell Technologies Inc. | E15: Technology | F15: 572.47 | G15: 363.98 | H15: 20.34 | J15: 42.56 | L15: 0.2936 | M15: 0.1991 | N15: 0.099 | P15: 0.91 | Q15: 0.3889 | R15: 0.0353 | S15: 0.0044 | T15: 0.4708 | U15: 1 | V15: 2 | W15: 404.7 | X15: =IF(C15="","",IF(K15="",0,IF(K15>=0.15,2,IF(K15>=0.1,1,0)))+IF(L15="",0,IF(L15>=0.12,2,IF(L15>=0.08,1,0)))+(AND(N15<>"",N(N15)>=0.15))+(AND(M15<>"",N(M15)>=0.4))) -> 2 | Y15: =IF(C15="","",IF(Q15="",0,IF(Q15>=0.1,2,IF(Q15>=0.05,1,0)))+IF(R15="",0,IF(R15>=0.08,2,IF(R15>=0.04,1,0)))) -> 2 | Z15: =IF(C15="","",IF(O15="",0,IF(O15<=0.5,2,IF(O15<=1,1,0)))+(AND(P15<>"",N(P15)>=1.2))) -> 0 | AA15: =IF(C15="","",IF(H15="",0,IF(AND(H15>0,H15<=20),2,IF(AND(H15>0,H15<=30),1,0)))+IF(J15="",0,IF(AND(J15>0,J15<=20),2,IF(AND(J15>0,J15<=30),1,0)))) -> 1 | AB15: =IF(C15="","",IF(OR(N(T15)>=0.01,N(S15)>=0.02),1,0)) -> 1 | AC15: =IF(C15="","",MIN(2,N(U15))+MIN(2,N(V15))) -> 3 | AD15: =IFERROR(IF(OR(W15="",F15="",N(F15)=0),"",W15/F15-1),"") -> -0.29306339 | AE15: =IF(C15="","",IF(AD15="",0,IF(AD15>=0.25,2,IF(AD15>=0.1,1,0)))) -> 0 | AF15: =IF(C15="","",X15+Y15+Z15+AA15+AB15+AC15+AE15) -> 9 | AG15: =IF(C15="","",IF(AF15>=18,"A",IF(AF15>=13,"B","C"))) -> C | AH15: =IF(C15="","",IF(OR(AI15="Sold",AI15="Rejected"),"Closed",IF(AI15="Owned",IF(AND(ISNUMBER(W15),ISNUMBER(AL15),AL15>W15*1.2),"REVIEW — price 20%+ above fair value",IF(AF15<13,"REVIEW — quality score fell below 13","HOLD — re-check thesis yearly")),IF(AG15="A","Full LRC Stock Analysis",IF(AG15="B","Watch — re-check next month","Reject"))))) -> Closed | AI15: Rejected | AJ15: AVOID / SELL-rated: AI-server winner but a thin-margin hardware business priced at ~20x after tripling in six months; negative equity. | AK15: 46309 | AL15: 572.47 | AM15: =IFERROR(IF(OR(AL15="",F15="",N(F15)=0),"",AL15/F15-1),"") -> 0 | AN15: LRC Work-sheet 14 Oct: SELL, 6-m target $404.70 (-29%), score 3.1/5. Fair value = the 6-MONTH Work-sheet target (a long-term DCF value would be higher for the growers). Growth = FY2023-FY2026 3-yr CAGR (5-yr not gathered). Data: stockanalysis.com 13 Oct 2026 (Finviz Investment preset applied manually — Finviz blocked). LRC's investment track is LONG-ONLY: recorded as an avoid / SELL idea, not a short. — P. Nkuna | AP15: =IF(AND(C15<>"",A15=$C$4,ISNUMBER(AF15)),AF15+ROW()/100000,"") -> 9.00015
A16: 46296 | B16: US | C16: ANET | D16: Arista Networks, Inc. | E16: Technology | F16: 204.52 | G16: 257.95 | H16: 43.99 | J16: 60.66 | K16: 0.3148 | M16: 0.63 | N16: 0.4314 | O16: 0.01 | P16: 3.05 | Q16: 0.3698 | R16: 0.2715 | T16: 0.1666 | U16: 2 | V16: 2 | W16: 144.61 | X16: =IF(C16="","",IF(K16="",0,IF(K16>=0.15,2,IF(K16>=0.1,1,0)))+IF(L16="",0,IF(L16>=0.12,2,IF(L16>=0.08,1,0)))+(AND(N16<>"",N(N16)>=0.15))+(AND(M16<>"",N(M16)>=0.4))) -> 4 | Y16: =IF(C16="","",IF(Q16="",0,IF(Q16>=0.1,2,IF(Q16>=0.05,1,0)))+IF(R16="",0,IF(R16>=0.08,2,IF(R16>=0.04,1,0)))) -> 4 | Z16: =IF(C16="","",IF(O16="",0,IF(O16<=0.5,2,IF(O16<=1,1,0)))+(AND(P16<>"",N(P16)>=1.2))) -> 3 | AA16: =IF(C16="","",IF(H16="",0,IF(AND(H16>0,H16<=20),2,IF(AND(H16>0,H16<=30),1,0)))+IF(J16="",0,IF(AND(J16>0,J16<=20),2,IF(AND(J16>0,J16<=30),1,0)))) -> 0 | AB16: =IF(C16="","",IF(OR(N(T16)>=0.01,N(S16)>=0.02),1,0)) -> 1 | AC16: =IF(C16="","",MIN(2,N(U16))+MIN(2,N(V16))) -> 4 | AD16: =IFERROR(IF(OR(W16="",F16="",N(F16)=0),"",W16/F16-1),"") -> -0.29292979 | AE16: =IF(C16="","",IF(AD16="",0,IF(AD16>=0.25,2,IF(AD16>=0.1,1,0)))) -> 0 | AF16: =IF(C16="","",X16+Y16+Z16+AA16+AB16+AC16+AE16) -> 16 | AG16: =IF(C16="","",IF(AF16>=18,"A",IF(AF16>=13,"B","C"))) -> B | AH16: =IF(C16="","",IF(OR(AI16="Sold",AI16="Rejected"),"Closed",IF(AI16="Owned",IF(AND(ISNUMBER(W16),ISNUMBER(AL16),AL16>W16*1.2),"REVIEW — price 20%+ above fair value",IF(AF16<13,"REVIEW — quality score fell below 13","HOLD — re-check thesis yearly")),IF(AG16="A","Full LRC Stock Analysis",IF(AG16="B","Watch — re-check next month","Reject"))))) -> Closed | AI16: Rejected | AJ16: AVOID / SELL-rated at this price: brilliant business at ~44x forward EPS with two customers >10% of sales. | AK16: 46309 | AL16: 204.52 | AM16: =IFERROR(IF(OR(AL16="",F16="",N(F16)=0),"",AL16/F16-1),"") -> 0 | AN16: LRC Work-sheet 14 Oct: SELL, 6-m target $144.61 (-29%), score 3.7/5. Fair value = the 6-MONTH Work-sheet target (a long-term DCF value would be higher for the growers). Growth = FY2022-FY2025 3-yr CAGR (5-yr not gathered). Data: stockanalysis.com 13 Oct 2026 (Finviz Investment preset applied manually — Finviz blocked). LRC's investment track is LONG-ONLY: recorded as an avoid / SELL idea, not a short. — P. Nkuna | AP16: =IF(AND(C16<>"",A16=$C$4,ISNUMBER(AF16)),AF16+ROW()/100000,"") -> 16.00016
A17: 46296 | B17: US | C17: FAST | D17: Fastenal Company | E17: Industrials | F17: 51.43 | G17: 59.02 | H17: 38.23 | J17: 56.17 | K17: 0.3433 | L17: 0.3206 | M17: 0.447 | N17: 0.2029 | O17: 0.11 | P17: 4.85 | Q17: 0.0506 | R17: 0.0552 | S17: 0.0189 | T17: 0.0009 | U17: 2 | V17: 2 | W17: 38.37 | X17: =IF(C17="","",IF(K17="",0,IF(K17>=0.15,2,IF(K17>=0.1,1,0)))+IF(L17="",0,IF(L17>=0.12,2,IF(L17>=0.08,1,0)))+(AND(N17<>"",N(N17)>=0.15))+(AND(M17<>"",N(M17)>=0.4))) -> 6 | Y17: =IF(C17="","",IF(Q17="",0,IF(Q17>=0.1,2,IF(Q17>=0.05,1,0)))+IF(R17="",0,IF(R17>=0.08,2,IF(R17>=0.04,1,0)))) -> 2 | Z17: =IF(C17="","",IF(O17="",0,IF(O17<=0.5,2,IF(O17<=1,1,0)))+(AND(P17<>"",N(P17)>=1.2))) -> 3 | AA17: =IF(C17="","",IF(H17="",0,IF(AND(H17>0,H17<=20),2,IF(AND(H17>0,H17<=30),1,0)))+IF(J17="",0,IF(AND(J17>0,J17<=20),2,IF(AND(J17>0,J17<=30),1,0)))) -> 0 | AB17: =IF(C17="","",IF(OR(N(T17)>=0.01,N(S17)>=0.02),1,0)) -> 0 | AC17: =IF(C17="","",MIN(2,N(U17))+MIN(2,N(V17))) -> 4 | AD17: =IFERROR(IF(OR(W17="",F17="",N(F17)=0),"",W17/F17-1),"") -> -0.25393739 | AE17: =IF(C17="","",IF(AD17="",0,IF(AD17>=0.25,2,IF(AD17>=0.1,1,0)))) -> 0 | AF17: =IF(C17="","",X17+Y17+Z17+AA17+AB17+AC17+AE17) -> 15 | AG17: =IF(C17="","",IF(AF17>=18,"A",IF(AF17>=13,"B","C"))) -> B | AH17: =IF(C17="","",IF(OR(AI17="Sold",AI17="Rejected"),"Closed",IF(AI17="Owned",IF(AND(ISNUMBER(W17),ISNUMBER(AL17),AL17>W17*1.2),"REVIEW — price 20%+ above fair value",IF(AF17<13,"REVIEW — quality score fell below 13","HOLD — re-check thesis yearly")),IF(AG17="A","Full LRC Stock Analysis",IF(AG17="B","Watch — re-check next month","Reject"))))) -> Closed | AI17: Rejected | AJ17: AVOID / SELL-rated at this price: superb distributor at ~38x forward EPS for ~9% growth. | AK17: 46309 | AL17: 51.43 | AM17: =IFERROR(IF(OR(AL17="",F17="",N(F17)=0),"",AL17/F17-1),"") -> 0 | AN17: LRC Work-sheet 14 Oct: SELL, 6-m target $38.37 (-25%), score 3.5/5. Fair value = the 6-MONTH Work-sheet target (a long-term DCF value would be higher for the growers). Growth = FY2022-FY2025 3-yr CAGR (5-yr not gathered). Data: stockanalysis.com 13 Oct 2026 (Finviz Investment preset applied manually — Finviz blocked). LRC's investment track is LONG-ONLY: recorded as an avoid / SELL idea, not a short. — P. Nkuna | AP17: =IF(AND(C17<>"",A17=$C$4,ISNUMBER(AF17)),AF17+ROW()/100000,"") -> 15.00017
A18: 46296 | B18: US | C18: WAB | D18: Westinghouse Air Brake Technologies Corporation (Wabtec) | E18: Industrials | F18: 286.51 | G18: 48.39 | H18: 24.9 | J18: 32.28 | K18: 0.1155 | L18: 0.0918 | M18: 0.3573 | N18: 0.1792 | O18: 0.5 | P18: 1.11 | Q18: 0.2544 | R18: 0.1012 | S18: 0.0043 | T18: 0.0071 | U18: 1 | V18: 2 | W18: 248.07 | X18: =IF(C18="","",IF(K18="",0,IF(K18>=0.15,2,IF(K18>=0.1,1,0)))+IF(L18="",0,IF(L18>=0.12,2,IF(L18>=0.08,1,0)))+(AND(N18<>"",N(N18)>=0.15))+(AND(M18<>"",N(M18)>=0.4))) -> 3 | Y18: =IF(C18="","",IF(Q18="",0,IF(Q18>=0.1,2,IF(Q18>=0.05,1,0)))+IF(R18="",0,IF(R18>=0.08,2,IF(R18>=0.04,1,0)))) -> 4 | Z18: =IF(C18="","",IF(O18="",0,IF(O18<=0.5,2,IF(O18<=1,1,0)))+(AND(P18<>"",N(P18)>=1.2))) -> 2 | AA18: =IF(C18="","",IF(H18="",0,IF(AND(H18>0,H18<=20),2,IF(AND(H18>0,H18<=30),1,0)))+IF(J18="",0,IF(AND(J18>0,J18<=20),2,IF(AND(J18>0,J18<=30),1,0)))) -> 1 | AB18: =IF(C18="","",IF(OR(N(T18)>=0.01,N(S18)>=0.02),1,0)) -> 0 | AC18: =IF(C18="","",MIN(2,N(U18))+MIN(2,N(V18))) -> 3 | AD18: =IFERROR(IF(OR(W18="",F18="",N(F18)=0),"",W18/F18-1),"") -> -0.13416635 | AE18: =IF(C18="","",IF(AD18="",0,IF(AD18>=0.25,2,IF(AD18>=0.1,1,0)))) -> 0 | AF18: =IF(C18="","",X18+Y18+Z18+AA18+AB18+AC18+AE18) -> 13 | AG18: =IF(C18="","",IF(AF18>=18,"A",IF(AF18>=13,"B","C"))) -> B | AH18: =IF(C18="","",IF(OR(AI18="Sold",AI18="Rejected"),"Closed",IF(AI18="Owned",IF(AND(ISNUMBER(W18),ISNUMBER(AL18),AL18>W18*1.2),"REVIEW — price 20%+ above fair value",IF(AF18<13,"REVIEW — quality score fell below 13","HOLD — re-check thesis yearly")),IF(AG18="A","Full LRC Stock Analysis",IF(AG18="B","Watch — re-check next month","Reject"))))) -> Closed | AI18: Rejected | AJ18: AVOID / SELL-rated at this price: strong rail franchise at ~25x vs industrial peers ~15x. | AK18: 46309 | AL18: 286.51 | AM18: =IFERROR(IF(OR(AL18="",F18="",N(F18)=0),"",AL18/F18-1),"") -> 0 | AN18: LRC Work-sheet 14 Oct: SELL, 6-m target $248.07 (-13%), score 3.5/5. Fair value = the 6-MONTH Work-sheet target (a long-term DCF value would be higher for the growers). Growth = FY2022-FY2025 3-yr CAGR (5-yr not gathered). Data: stockanalysis.com 13 Oct 2026 (Finviz Investment preset applied manually — Finviz blocked). LRC's investment track is LONG-ONLY: recorded as an avoid / SELL idea, not a short. — P. Nkuna | AP18: =IF(AND(C18<>"",A18=$C$4,ISNUMBER(AF18)),AF18+ROW()/100000,"") -> 13.00018
X19: =IF(C19="","",IF(K19="",0,IF(K19>=0.15,2,IF(K19>=0.1,1,0)))+IF(L19="",0,IF(L19>=0.12,2,IF(L19>=0.08,1,0)))+(AND(N19<>"",N(N19)>=0.15))+(AND(M19<>"",N(M19)>=0.4))) | Y19: =IF(C19="","",IF(Q19="",0,IF(Q19>=0.1,2,IF(Q19>=0.05,1,0)))+IF(R19="",0,IF(R19>=0.08,2,IF(R19>=0.04,1,0)))) | Z19: =IF(C19="","",IF(O19="",0,IF(O19<=0.5,2,IF(O19<=1,1,0)))+(AND(P19<>"",N(P19)>=1.2))) | AA19: =IF(C19="","",IF(H19="",0,IF(AND(H19>0,H19<=20),2,IF(AND(H19>0,H19<=30),1,0)))+IF(J19="",0,IF(AND(J19>0,J19<=20),2,IF(AND(J19>0,J19<=30),1,0)))) | AB19: =IF(C19="","",IF(OR(N(T19)>=0.01,N(S19)>=0.02),1,0)) | AC19: =IF(C19="","",MIN(2,N(U19))+MIN(2,N(V19))) | AD19: =IFERROR(IF(OR(W19="",F19="",N(F19)=0),"",W19/F19-1),"") | AE19: =IF(C19="","",IF(AD19="",0,IF(AD19>=0.25,2,IF(AD19>=0.1,1,0)))) | AF19: =IF(C19="","",X19+Y19+Z19+AA19+AB19+AC19+AE19) | AG19: =IF(C19="","",IF(AF19>=18,"A",IF(AF19>=13,"B","C"))) | AH19: =IF(C19="","",IF(OR(AI19="Sold",AI19="Rejected"),"Closed",IF(AI19="Owned",IF(AND(ISNUMBER(W19),ISNUMBER(AL19),AL19>W19*1.2),"REVIEW — price 20%+ above fair value",IF(AF19<13,"REVIEW — quality score fell below 13","HOLD — re-check thesis yearly")),IF(AG19="A","Full LRC Stock Analysis",IF(AG19="B","Watch — re-check next month","Reject"))))) | AM19: =IFERROR(IF(OR(AL19="",F19="",N(F19)=0),"",AL19/F19-1),"") | AP19: =IF(AND(C19<>"",A19=$C$4,ISNUMBER(AF19)),AF19+ROW()/100000,"")
X20: =IF(C20="","",IF(K20="",0,IF(K20>=0.15,2,IF(K20>=0.1,1,0)))+IF(L20="",0,IF(L20>=0.12,2,IF(L20>=0.08,1,0)))+(AND(N20<>"",N(N20)>=0.15))+(AND(M20<>"",N(M20)>=0.4))) | Y20: =IF(C20="","",IF(Q20="",0,IF(Q20>=0.1,2,IF(Q20>=0.05,1,0)))+IF(R20="",0,IF(R20>=0.08,2,IF(R20>=0.04,1,0)))) | Z20: =IF(C20="","",IF(O20="",0,IF(O20<=0.5,2,IF(O20<=1,1,0)))+(AND(P20<>"",N(P20)>=1.2))) | AA20: =IF(C20="","",IF(H20="",0,IF(AND(H20>0,H20<=20),2,IF(AND(H20>0,H20<=30),1,0)))+IF(J20="",0,IF(AND(J20>0,J20<=20),2,IF(AND(J20>0,J20<=30),1,0)))) | AB20: =IF(C20="","",IF(OR(N(T20)>=0.01,N(S20)>=0.02),1,0)) | AC20: =IF(C20="","",MIN(2,N(U20))+MIN(2,N(V20))) | AD20: =IFERROR(IF(OR(W20="",F20="",N(F20)=0),"",W20/F20-1),"") | AE20: =IF(C20="","",IF(AD20="",0,IF(AD20>=0.25,2,IF(AD20>=0.1,1,0)))) | AF20: =IF(C20="","",X20+Y20+Z20+AA20+AB20+AC20+AE20) | AG20: =IF(C20="","",IF(AF20>=18,"A",IF(AF20>=13,"B","C"))) | AH20: =IF(C20="","",IF(OR(AI20="Sold",AI20="Rejected"),"Closed",IF(AI20="Owned",IF(AND(ISNUMBER(W20),ISNUMBER(AL20),AL20>W20*1.2),"REVIEW — price 20%+ above fair value",IF(AF20<13,"REVIEW — quality score fell below 13","HOLD — re-check thesis yearly")),IF(AG20="A","Full LRC Stock Analysis",IF(AG20="B","Watch — re-check next month","Reject"))))) | AM20: =IFERROR(IF(OR(AL20="",F20="",N(F20)=0),"",AL20/F20-1),"") | AP20: =IF(AND(C20<>"",A20=$C$4,ISNUMBER(AF20)),AF20+ROW()/100000,"")
X21: =IF(C21="","",IF(K21="",0,IF(K21>=0.15,2,IF(K21>=0.1,1,0)))+IF(L21="",0,IF(L21>=0.12,2,IF(L21>=0.08,1,0)))+(AND(N21<>"",N(N21)>=0.15))+(AND(M21<>"",N(M21)>=0.4))) | Y21: =IF(C21="","",IF(Q21="",0,IF(Q21>=0.1,2,IF(Q21>=0.05,1,0)))+IF(R21="",0,IF(R21>=0.08,2,IF(R21>=0.04,1,0)))) | Z21: =IF(C21="","",IF(O21="",0,IF(O21<=0.5,2,IF(O21<=1,1,0)))+(AND(P21<>"",N(P21)>=1.2))) | AA21: =IF(C21="","",IF(H21="",0,IF(AND(H21>0,H21<=20),2,IF(AND(H21>0,H21<=30),1,0)))+IF(J21="",0,IF(AND(J21>0,J21<=20),2,IF(AND(J21>0,J21<=30),1,0)))) | AB21: =IF(C21="","",IF(OR(N(T21)>=0.01,N(S21)>=0.02),1,0)) | AC21: =IF(C21="","",MIN(2,N(U21))+MIN(2,N(V21))) | AD21: =IFERROR(IF(OR(W21="",F21="",N(F21)=0),"",W21/F21-1),"") | AE21: =IF(C21="","",IF(AD21="",0,IF(AD21>=0.25,2,IF(AD21>=0.1,1,0)))) | AF21: =IF(C21="","",X21+Y21+Z21+AA21+AB21+AC21+AE21) | AG21: =IF(C21="","",IF(AF21>=18,"A",IF(AF21>=13,"B","C"))) | AH21: =IF(C21="","",IF(OR(AI21="Sold",AI21="Rejected"),"Closed",IF(AI21="Owned",IF(AND(ISNUMBER(W21),ISNUMBER(AL21),AL21>W21*1.2),"REVIEW — price 20%+ above fair value",IF(AF21<13,"REVIEW — quality score fell below 13","HOLD — re-check thesis yearly")),IF(AG21="A","Full LRC Stock Analysis",IF(AG21="B","Watch — re-check next month","Reject"))))) | AM21: =IFERROR(IF(OR(AL21="",F21="",N(F21)=0),"",AL21/F21-1),"") | AP21: =IF(AND(C21<>"",A21=$C$4,ISNUMBER(AF21)),AF21+ROW()/100000,"")
X22: =IF(C22="","",IF(K22="",0,IF(K22>=0.15,2,IF(K22>=0.1,1,0)))+IF(L22="",0,IF(L22>=0.12,2,IF(L22>=0.08,1,0)))+(AND(N22<>"",N(N22)>=0.15))+(AND(M22<>"",N(M22)>=0.4))) | Y22: =IF(C22="","",IF(Q22="",0,IF(Q22>=0.1,2,IF(Q22>=0.05,1,0)))+IF(R22="",0,IF(R22>=0.08,2,IF(R22>=0.04,1,0)))) | Z22: =IF(C22="","",IF(O22="",0,IF(O22<=0.5,2,IF(O22<=1,1,0)))+(AND(P22<>"",N(P22)>=1.2))) | AA22: =IF(C22="","",IF(H22="",0,IF(AND(H22>0,H22<=20),2,IF(AND(H22>0,H22<=30),1,0)))+IF(J22="",0,IF(AND(J22>0,J22<=20),2,IF(AND(J22>0,J22<=30),1,0)))) | AB22: =IF(C22="","",IF(OR(N(T22)>=0.01,N(S22)>=0.02),1,0)) | AC22: =IF(C22="","",MIN(2,N(U22))+MIN(2,N(V22))) | AD22: =IFERROR(IF(OR(W22="",F22="",N(F22)=0),"",W22/F22-1),"") | AE22: =IF(C22="","",IF(AD22="",0,IF(AD22>=0.25,2,IF(AD22>=0.1,1,0)))) | AF22: =IF(C22="","",X22+Y22+Z22+AA22+AB22+AC22+AE22) | AG22: =IF(C22="","",IF(AF22>=18,"A",IF(AF22>=13,"B","C"))) | AH22: =IF(C22="","",IF(OR(AI22="Sold",AI22="Rejected"),"Closed",IF(AI22="Owned",IF(AND(ISNUMBER(W22),ISNUMBER(AL22),AL22>W22*1.2),"REVIEW — price 20%+ above fair value",IF(AF22<13,"REVIEW — quality score fell below 13","HOLD — re-check thesis yearly")),IF(AG22="A","Full LRC Stock Analysis",IF(AG22="B","Watch — re-check next month","Reject"))))) | AM22: =IFERROR(IF(OR(AL22="",F22="",N(F22)=0),"",AL22/F22-1),"") | AP22: =IF(AND(C22<>"",A22=$C$4,ISNUMBER(AF22)),AF22+ROW()/100000,"")
X23: =IF(C23="","",IF(K23="",0,IF(K23>=0.15,2,IF(K23>=0.1,1,0)))+IF(L23="",0,IF(L23>=0.12,2,IF(L23>=0.08,1,0)))+(AND(N23<>"",N(N23)>=0.15))+(AND(M23<>"",N(M23)>=0.4))) | Y23: =IF(C23="","",IF(Q23="",0,IF(Q23>=0.1,2,IF(Q23>=0.05,1,0)))+IF(R23="",0,IF(R23>=0.08,2,IF(R23>=0.04,1,0)))) | Z23: =IF(C23="","",IF(O23="",0,IF(O23<=0.5,2,IF(O23<=1,1,0)))+(AND(P23<>"",N(P23)>=1.2))) | AA23: =IF(C23="","",IF(H23="",0,IF(AND(H23>0,H23<=20),2,IF(AND(H23>0,H23<=30),1,0)))+IF(J23="",0,IF(AND(J23>0,J23<=20),2,IF(AND(J23>0,J23<=30),1,0)))) | AB23: =IF(C23="","",IF(OR(N(T23)>=0.01,N(S23)>=0.02),1,0)) | AC23: =IF(C23="","",MIN(2,N(U23))+MIN(2,N(V23))) | AD23: =IFERROR(IF(OR(W23="",F23="",N(F23)=0),"",W23/F23-1),"") | AE23: =IF(C23="","",IF(AD23="",0,IF(AD23>=0.25,2,IF(AD23>=0.1,1,0)))) | AF23: =IF(C23="","",X23+Y23+Z23+AA23+AB23+AC23+AE23) | AG23: =IF(C23="","",IF(AF23>=18,"A",IF(AF23>=13,"B","C"))) | AH23: =IF(C23="","",IF(OR(AI23="Sold",AI23="Rejected"),"Closed",IF(AI23="Owned",IF(AND(ISNUMBER(W23),ISNUMBER(AL23),AL23>W23*1.2),"REVIEW — price 20%+ above fair value",IF(AF23<13,"REVIEW — quality score fell below 13","HOLD — re-check thesis yearly")),IF(AG23="A","Full LRC Stock Analysis",IF(AG23="B","Watch — re-check next month","Reject"))))) | AM23: =IFERROR(IF(OR(AL23="",F23="",N(F23)=0),"",AL23/F23-1),"") | AP23: =IF(AND(C23<>"",A23=$C$4,ISNUMBER(AF23)),AF23+ROW()/100000,"")
X24: =IF(C24="","",IF(K24="",0,IF(K24>=0.15,2,IF(K24>=0.1,1,0)))+IF(L24="",0,IF(L24>=0.12,2,IF(L24>=0.08,1,0)))+(AND(N24<>"",N(N24)>=0.15))+(AND(M24<>"",N(M24)>=0.4))) | Y24: =IF(C24="","",IF(Q24="",0,IF(Q24>=0.1,2,IF(Q24>=0.05,1,0)))+IF(R24="",0,IF(R24>=0.08,2,IF(R24>=0.04,1,0)))) | Z24: =IF(C24="","",IF(O24="",0,IF(O24<=0.5,2,IF(O24<=1,1,0)))+(AND(P24<>"",N(P24)>=1.2))) | AA24: =IF(C24="","",IF(H24="",0,IF(AND(H24>0,H24<=20),2,IF(AND(H24>0,H24<=30),1,0)))+IF(J24="",0,IF(AND(J24>0,J24<=20),2,IF(AND(J24>0,J24<=30),1,0)))) | AB24: =IF(C24="","",IF(OR(N(T24)>=0.01,N(S24)>=0.02),1,0)) | AC24: =IF(C24="","",MIN(2,N(U24))+MIN(2,N(V24))) | AD24: =IFERROR(IF(OR(W24="",F24="",N(F24)=0),"",W24/F24-1),"") | AE24: =IF(C24="","",IF(AD24="",0,IF(AD24>=0.25,2,IF(AD24>=0.1,1,0)))) | AF24: =IF(C24="","",X24+Y24+Z24+AA24+AB24+AC24+AE24) | AG24: =IF(C24="","",IF(AF24>=18,"A",IF(AF24>=13,"B","C"))) | AH24: =IF(C24="","",IF(OR(AI24="Sold",AI24="Rejected"),"Closed",IF(AI24="Owned",IF(AND(ISNUMBER(W24),ISNUMBER(AL24),AL24>W24*1.2),"REVIEW — price 20%+ above fair value",IF(AF24<13,"REVIEW — quality score fell below 13","HOLD — re-check thesis yearly")),IF(AG24="A","Full LRC Stock Analysis",IF(AG24="B","Watch — re-check next month","Reject"))))) | AM24: =IFERROR(IF(OR(AL24="",F24="",N(F24)=0),"",AL24/F24-1),"") | AP24: =IF(AND(C24<>"",A24=$C$4,ISNUMBER(AF24)),AF24+ROW()/100000,"")
X25: =IF(C25="","",IF(K25="",0,IF(K25>=0.15,2,IF(K25>=0.1,1,0)))+IF(L25="",0,IF(L25>=0.12,2,IF(L25>=0.08,1,0)))+(AND(N25<>"",N(N25)>=0.15))+(AND(M25<>"",N(M25)>=0.4))) | Y25: =IF(C25="","",IF(Q25="",0,IF(Q25>=0.1,2,IF(Q25>=0.05,1,0)))+IF(R25="",0,IF(R25>=0.08,2,IF(R25>=0.04,1,0)))) | Z25: =IF(C25="","",IF(O25="",0,IF(O25<=0.5,2,IF(O25<=1,1,0)))+(AND(P25<>"",N(P25)>=1.2))) | AA25: =IF(C25="","",IF(H25="",0,IF(AND(H25>0,H25<=20),2,IF(AND(H25>0,H25<=30),1,0)))+IF(J25="",0,IF(AND(J25>0,J25<=20),2,IF(AND(J25>0,J25<=30),1,0)))) | AB25: =IF(C25="","",IF(OR(N(T25)>=0.01,N(S25)>=0.02),1,0)) | AC25: =IF(C25="","",MIN(2,N(U25))+MIN(2,N(V25))) | AD25: =IFERROR(IF(OR(W25="",F25="",N(F25)=0),"",W25/F25-1),"") | AE25: =IF(C25="","",IF(AD25="",0,IF(AD25>=0.25,2,IF(AD25>=0.1,1,0)))) | AF25: =IF(C25="","",X25+Y25+Z25+AA25+AB25+AC25+AE25) | AG25: =IF(C25="","",IF(AF25>=18,"A",IF(AF25>=13,"B","C"))) | AH25: =IF(C25="","",IF(OR(AI25="Sold",AI25="Rejected"),"Closed",IF(AI25="Owned",IF(AND(ISNUMBER(W25),ISNUMBER(AL25),AL25>W25*1.2),"REVIEW — price 20%+ above fair value",IF(AF25<13,"REVIEW — quality score fell below 13","HOLD — re-check thesis yearly")),IF(AG25="A","Full LRC Stock Analysis",IF(AG25="B","Watch — re-check next month","Reject"))))) | AM25: =IFERROR(IF(OR(AL25="",F25="",N(F25)=0),"",AL25/F25-1),"") | AP25: =IF(AND(C25<>"",A25=$C$4,ISNUMBER(AF25)),AF25+ROW()/100000,"")
X26: =IF(C26="","",IF(K26="",0,IF(K26>=0.15,2,IF(K26>=0.1,1,0)))+IF(L26="",0,IF(L26>=0.12,2,IF(L26>=0.08,1,0)))+(AND(N26<>"",N(N26)>=0.15))+(AND(M26<>"",N(M26)>=0.4))) | Y26: =IF(C26="","",IF(Q26="",0,IF(Q26>=0.1,2,IF(Q26>=0.05,1,0)))+IF(R26="",0,IF(R26>=0.08,2,IF(R26>=0.04,1,0)))) | Z26: =IF(C26="","",IF(O26="",0,IF(O26<=0.5,2,IF(O26<=1,1,0)))+(AND(P26<>"",N(P26)>=1.2))) | AA26: =IF(C26="","",IF(H26="",0,IF(AND(H26>0,H26<=20),2,IF(AND(H26>0,H26<=30),1,0)))+IF(J26="",0,IF(AND(J26>0,J26<=20),2,IF(AND(J26>0,J26<=30),1,0)))) | AB26: =IF(C26="","",IF(OR(N(T26)>=0.01,N(S26)>=0.02),1,0)) | AC26: =IF(C26="","",MIN(2,N(U26))+MIN(2,N(V26))) | AD26: =IFERROR(IF(OR(W26="",F26="",N(F26)=0),"",W26/F26-1),"") | AE26: =IF(C26="","",IF(AD26="",0,IF(AD26>=0.25,2,IF(AD26>=0.1,1,0)))) | AF26: =IF(C26="","",X26+Y26+Z26+AA26+AB26+AC26+AE26) | AG26: =IF(C26="","",IF(AF26>=18,"A",IF(AF26>=13,"B","C"))) | AH26: =IF(C26="","",IF(OR(AI26="Sold",AI26="Rejected"),"Closed",IF(AI26="Owned",IF(AND(ISNUMBER(W26),ISNUMBER(AL26),AL26>W26*1.2),"REVIEW — price 20%+ above fair value",IF(AF26<13,"REVIEW — quality score fell below 13","HOLD — re-check thesis yearly")),IF(AG26="A","Full LRC Stock Analysis",IF(AG26="B","Watch — re-check next month","Reject"))))) | AM26: =IFERROR(IF(OR(AL26="",F26="",N(F26)=0),"",AL26/F26-1),"") | AP26: =IF(AND(C26<>"",A26=$C$4,ISNUMBER(AF26)),AF26+ROW()/100000,"")
