Workbook

Sheet Start Here
A1: Leago Rifumo Capital — Stock Analysis Checklist
A2: For intern and first-year analysts. Work through the tabs in order: 1 → 5. Budget about 2–3 days for a first full analysis.
A4: How to use this workbook
A5: Step 1 Company Info | B5: Basic details, share price and market data. Takes 15 minutes. The sheet checks your market cap against a published figure to catch unit mistakes.
A6: Step 2 Financials | B6: Copy 3 years + latest year from the annual reports into the yellow cells. ~20 ratios calculate themselves, each with a plain-English explanation. Fix any 'CHECK' in the data checks.
A7: Step 3 Checklist | B7: 50 questions in 10 sections. For each: read 'Why it matters' and 'Where to find it', find the evidence, write it in your notes with the source, then score 1–5. Numeric items get a suggested score — you decide the final one.
A8: Step 4 Valuation | B8: Pick peers, set your assumptions, get three valuations and a blended target price. Clear every FLAG in the sanity checks.
A9: Step 5 Rating Summary | B9: Your BUY / HOLD / SELL rating appears once ≥80% of items are scored and you have a target price. Write your thesis, then send to your reviewer.
A10: Step 6 Fundamentals Scorecard | B10: One printable page: ~30 key ratios, each flagged GREAT / OK / WEAK against editable limits, with an overall health score. Fills itself from Steps 1, 2 and 4.
A11: Step 7 Technical Review | B11: Chart data → green/amber/red timing signals → an automatic TIMING CALL and tranche plan, plus the 9 LRC timing rules. Never changes the rating; feeds checklist items I4 (trend) and J5 (liquidity).
A12: Step 8 Investor Summary | B12: Last tab. One printable page explaining the thesis to an everyday investor in plain English. Numbers fill in automatically; replace the yellow prompts with your own words — no jargon.
A13: Step 9 Analyst Summary | B13: Final tab. One-page tear sheet for your reviewer / investment committee: snapshot, thesis, valuation, financials, scores, risks, catalysts, open questions and the BOTTOM LINE.
A14: Tip | B14: Columns E–G on the Checklist (guidance) can be collapsed with the [–] button above them once you know the questions.
A16: Colour code
A17: Yellow cell, blue text | B17: You type here
A18: Grey cell | B18: Calculates automatically — don't type over it
A19: Green text | B19: Pulled from another sheet
A20: Red 'CHECK' / 'FLAG' | B20: Something to fix or explain
A22: Scoring scale (Step 3)
A23: 5 | B23: Strong evidence for BUY
A24: 4 | B24: Supports BUY
A25: 3 | B25: Neutral / average
A26: 2 | B26: A concern
A27: 1 | B27: Serious red flag
A28: N/A | B28: Doesn't apply (e.g. gross margin for a bank). Excluded from the score.
A29: Section J (risks) | B29: 5 = LOW risk, 1 = HIGH risk
A31: How the rating is decided
A32: BUY | B32: Upside ≥ 15% AND overall score ≥ 3.5 AND no critical item (B3 disruption, F1 debt, G2 leadership, G4 accounting) scored 2 or lower
A33: SELL | B33: Downside of 10% or more OR overall score below 2.5
A34: HOLD | B34: Everything in between
A35: INCOMPLETE | B35: Less than 80% of items scored, or no target price yet
A36: Important | B36: The calculated rating is a starting point. Your reviewer can override it — with a written reason.
A38: Adjust for the industry
A39: Banks & insurers | B39: Gross margin, EBITDA, current ratio and net debt don't apply — mark N/A. Focus on ROE, price/book, cost-to-income, credit loss ratio, capital ratio (CET1).
A40: Mining & resources | B40: Results swing with commodity prices and the rand. Use mid-cycle prices, check all-in sustaining costs and where mines sit on the cost curve. Capex will be high.
A41: Property (REITs) | B41: Use distribution per share, loan-to-value and NAV discount instead of EPS and P/E.
A42: Retail | B42: Gross margins of 20–40% are normal. Check like-for-like sales, trading density and stock turn.
A43: Growth / loss-making | B43: P/E won't work. Use EV/Sales and the DCF, and check cash runway (months of cash left).
A45: Not investment advice. Internal training template — check every figure against the company's own documents.

Sheet Glossary
A1: Glossary — plain-English definitions
A2: Look up any term you don't know. Add your own at the bottom.
A4: Term | B4: What it means | C4: Simple example
A5: Annual / integrated report | B5: The company's yearly report with audited financial statements. In SA usually called the integrated annual report. | C5: Read the CEO letter, segment results and notes.
A6: SENS | B6: The JSE's Stock Exchange News Service. Where JSE companies publish results and announcements. | C6: Directors' share dealings appear on SENS.
A7: 10-K / 10-Q | B7: US annual (10-K) and quarterly (10-Q) reports, filed on SEC EDGAR.
A8: Revenue (turnover) | B8: Total sales before any costs.
A9: Gross profit / margin | B9: Revenue minus direct costs of making or buying the product. Margin = gross profit ÷ revenue. | C9: R100 sales, R60 cost of goods → R40 gross profit, 40% margin.
A10: Operating profit (EBIT) | B10: Profit after all operating costs, before interest and tax.
A11: EBITDA | B11: EBIT + depreciation + amortisation. A rough measure of operating cash profit.
A12: Net income | B12: Final profit after interest and tax, belonging to shareholders.
A13: EPS | B13: Earnings per share = net income ÷ number of shares. | C13: R1bn profit ÷ 500m shares = R2.00 EPS.
A14: HEPS | B14: Headline EPS: SA measure that strips out certain one-off gains/losses (e.g. selling property). JSE companies report it.
A15: Diluted shares | B15: Share count including options and convertibles that could become shares.
A16: Free cash flow (FCF) | B16: Cash from operations minus capital expenditure. The cash truly available to owners.
A17: Capex | B17: Capital expenditure: money spent on long-term assets (factories, equipment, software).
A18: Net debt | B18: Total debt minus cash. Negative = net cash.
A19: Current ratio | B19: Current assets ÷ current liabilities. Ability to pay bills due within a year.
A20: ROE | B20: Return on equity = net income ÷ shareholders' equity.
A21: ROIC | B21: Return on invested capital = after-tax operating profit ÷ (debt + equity − cash). | C21: ROIC 20% with WACC 12% → creating value.
A22: Market capitalisation | B22: Share price × shares outstanding. What the market values the equity at.
A23: Enterprise value (EV) | B23: Market cap + net debt. The value of the whole business.
A24: P/E ratio | B24: Share price ÷ EPS. Trailing uses last year's EPS; forward uses next year's estimate. | C24: Price R40, EPS R4 → 10x.
A25: EV/EBITDA | B25: Enterprise value ÷ EBITDA. Compares companies regardless of debt.
A26: FCF yield | B26: FCF ÷ market cap. Like an interest rate on the business's cash.
A27: Dividend yield | B27: Dividend per share ÷ share price.
A28: Beta | B28: How much a share moves relative to the market. 1.5 = moves 50% more.
A29: Risk-free rate | B29: Return on a government bond — the 'safe' return.
A30: Equity risk premium (ERP) | B30: Extra return investors demand for owning shares instead of bonds.
A31: CAPM | B31: Cost of equity = risk-free rate + beta × ERP. | C31: 4% + 1.2 × 6% = 11.2%.
A32: WACC | B32: Weighted average cost of capital: the blended return required by shareholders and lenders. Used as the DCF discount rate.
A33: DCF | B33: Discounted cash flow: value = today's value of all future free cash flows.
A34: Discount factor | B34: 1 ÷ (1 + WACC)^years. Converts a future amount into today's money. | C34: R100 in 2 years at 10% = R100 × 0.826 = R82.60.
A35: Terminal value | B35: The value of all cash flows after the forecast period (here, after year 5).
A36: Terminal growth | B36: The growth rate assumed forever after year 5. Must be low (2–5%).
A37: CAGR | B37: Compound annual growth rate: the average yearly growth over several years. | C37: R100 → R133 over 3 yrs = 10% CAGR.
A38: Consensus | B38: The average of professional analysts' forecasts or ratings.
A39: Guidance | B39: Management's own forecast for the coming period.
A40: Catalyst | B40: An event that could make the market change its view on the share.
A41: Moat | B41: A lasting competitive advantage that protects profits.
A42: Dilution | B42: When new shares are issued, each existing share owns less of the company.
A43: Share-based compensation | B43: Paying staff in shares or options. A real cost to shareholders.
A44: Upside / downside | B44: Target price ÷ current price − 1. | C44: Target R120, price R100 → +20% upside.
A45: Basis point (bp) | B45: One-hundredth of a percentage point. 50bp = 0.5%.
A46: ZAc vs ZAR | B46: JSE prices are quoted in cents (ZAc). R1 = 100c. Always convert. | C46: Price 4,500c = R45.00.

Sheet Sources & Mistakes
A1: Where to find data — and the mistakes everyone makes once
A2: Always cite your source (document + page) in the Checklist so your reviewer can check it.
A4: Where to find the data
A5: Source | B5: What you'll find | C5: Notes
A6: Company investor-relations website | B6: Annual/integrated reports, results booklets, presentations, webcasts | C6: Always start here. Primary source.
A7: JSE SENS | B7: All JSE announcements: results, trading statements, director dealings, deals | C7: Trading statements give early warning of results.
A8: SEC EDGAR (US companies) | B8: 10-K, 10-Q, 8-K, proxy statements, Form 4 insider trades | C8: sec.gov/edgar
A9: Results presentation & webcast Q&A | B9: Management tone, guidance, answers to analysts' tough questions | C9: The Q&A is often more useful than the slides.
A10: Market data sites / terminal (e.g. Bloomberg, Iress, Sharenet, StockAnalysis) | B10: Prices, market cap, beta, consensus, historical multiples | C10: Check against company documents — these sites contain errors.
A11: SARB / national treasury | B11: Government bond yields (risk-free rate), repo rate, inflation
A12: Damodaran Online (NYU) | B12: Equity risk premiums by country, industry margins and multiples | C12: Free; widely used for ERP and country risk.
A13: Competitors' reports | B13: Industry trends, market share, peer margins | C13: Read at least one competitor's latest results.
A15: Common mistakes — check yours before submitting
A16: Mistake | B16: How to avoid it | C16: Done? (Y)
A17: Cents vs Rand | B17: JSE share prices and often EPS/DPS are in cents. Divide by 100. The market-cap check in Step 1 will catch this.
A18: Millions vs billions vs thousands | B18: Use ONE unit for all financial statement numbers; shares always in millions.
A19: Mixing up units in per-share value | B19: Equity value (millions) ÷ shares (millions) = value per share. Don't divide millions by billions.
A20: Stale share price | B20: Update the price on the day you submit. Upside changes daily.
A21: Comparing trailing with forward multiples | B21: Compare forward P/E with forward P/E. Write the basis in the peer notes.
A22: Different net debt in different places | B22: Use the Step 2 net debt everywhere. Decide if leases are included and be consistent.
A23: Wrong discounting of the terminal value | B23: Discount the terminal value at the year-5 factor — not year 4 or 4.5.
A24: Terminal growth too high | B24: Keep it at or below long-run nominal GDP growth (usually 2–5%).
A25: Arithmetic that doesn't tie | B25: Check that segments add up to the total and that your blended target equals the weighted sum shown.
A26: Using 'adjusted' numbers without saying so | B26: Label every figure as reported (IFRS/GAAP) or adjusted/headline.
A27: Copying data sites without checking | B27: Verify key numbers (revenue, profit, debt, shares) against the annual report.
A28: Target price horizon unclear | B28: State it: '12-month target'. Don't call a 3-month target '6-month'.
... A30: No sources | B30: Every number in your notes needs a source and page so your reviewer can check it.

Sheet 1. Company Info
A1: Step 1 — Company Info & Market Data
A2: Fill in the yellow cells. Grey cells calculate automatically. Hover over a cell's red corner (if any) for help.
A4: Item | B4: Your input | C4: What to enter / tip
A5: About the company
A6: Company name | C6: Full legal name, e.g. 'Shoprite Holdings Ltd'.
A7: Ticker | C7: e.g. SHP (JSE) or ADBE (NASDAQ).
A8: Exchange | C8: JSE, NYSE, NASDAQ, LSE…
A9: Sector / industry | C9: Use the exchange's classification (JSE uses ICB).
A10: Reporting currency | C10: ZAR, USD, GBP… All money figures in this workbook must be in this ONE currency.
A11: Units of the financial statements | C11: e.g. 'R millions'. Enter every Financials number in these units.
A12: Analyst (you)
A13: Reviewer (senior analyst) | C13: Who checks your work.
A14: Date started
A15: Share price & market data
A16: Current share price | C16: Per share, in the reporting currency. JSE quotes in CENTS (ZAc): divide by 100 to get Rand!
A17: Price date | C17: Refresh the price before submitting. Older than 7 days = flagged.
A18: 52-week high | C18: From any market data site.
A19: 52-week low
A20: Beta | C20: Measures how much the share moves vs the market (1.0 = same as market).
A21: Published market cap (in your units) | C21: Copy from a data site. Used to check you got price, shares and units right.
A22: Forecasts & consensus
A23: Next-12-month EPS estimate | C23: Your forecast, or consensus. Per share, same currency as price. State which you used in the notes.
A24: Consensus target price | C24: Average analyst target price (if available).
A25: Consensus rating | C25: e.g. Buy / Hold / Sell.
A26: Next results / key event date | C26: e.g. 'Interim results, 15 Mar 2027'.
A28: Calculated market statistics (do not type here)
A29: Market capitalisation | B29: =IF(OR('1. Company Info'!$B$16="",'2. Financials'!$E$15=""),"",'1. Company Info'!$B$16*'2. Financials'!$E$15) | C29: Price × diluted shares (in millions → same units as Financials).
A30: Check vs published market cap | B30: =IF(OR(B29="",'1. Company Info'!$B$21=""),"Enter published market cap",IF(ABS(B29/'1. Company Info'!$B$21-1)<=0.05,"OK","CHECK: price, shares or units wrong")) -> Enter published market cap | C30: Within 5% = OK. Off by ~100x usually means cents vs Rand.
A31: Enterprise value (EV) | B31: =IF(OR(B29="",'2. Financials'!$E$43=""),"",B29+'2. Financials'!$E$43) | C31: Market cap + net debt. What it would cost to buy the whole business.
A32: Trailing P/E | B32: =IFERROR(IF(OR('1. Company Info'!$B$16="",'2. Financials'!$E$13="",N('2. Financials'!$E$13)<=0),"",'1. Company Info'!$B$16/'2. Financials'!$E$13),"") | C32: Price ÷ latest EPS. How many years of current profit you pay for.
A33: Forward P/E | B33: =IFERROR(IF(OR('1. Company Info'!$B$16="",'1. Company Info'!$B$23="",N('1. Company Info'!$B$23)<=0),"",'1. Company Info'!$B$16/'1. Company Info'!$B$23),"") | C33: Price ÷ next-12-month EPS. Compare to peers on THIS basis (forward vs forward).
A34: EV / EBITDA | B34: =IFERROR(IF(OR(B31="",'2. Financials'!$E$36="",N('2. Financials'!$E$36)<=0),"",B31/'2. Financials'!$E$36),"") | C34: Valuation that ignores debt structure. Good for comparing companies with different debt.
A35: FCF yield | B35: =IFERROR(IF(OR(B29="",'2. Financials'!$E$38=""),"",'2. Financials'!$E$38/B29),"") | C35: FCF ÷ market cap. Compare with the government bond yield.
A36: Dividend yield | B36: =IFERROR(IF(OR('1. Company Info'!$B$16="",'2. Financials'!$E$14=""),"",'2. Financials'!$E$14/'1. Company Info'!$B$16),"") | C36: Dividend per share ÷ price.
A37: Price / book | B37: =IFERROR(IF(OR(B29="",'2. Financials'!$E$21="",N('2. Financials'!$E$21)<=0),"",B29/'2. Financials'!$E$21),"") | C37: Market cap ÷ equity. Key for banks and insurers.
A38: Position in 52-week range | B38: =IFERROR(IF(OR('1. Company Info'!$B$16="",'1. Company Info'!$B$18="",'1. Company Info'!$B$19=""),"",('1. Company Info'!$B$16-'1. Company Info'!$B$19)/('1. Company Info'!$B$18-'1. Company Info'!$B$19)),"") | C38: 0% = at 52-week low, 100% = at the high.
A39: Days since price date | B39: =IF('1. Company Info'!$B$17="","",TODAY()-'1. Company Info'!$B$17) | C39: More than 7 days old = refresh the price.

Sheet 2. Financials
A1: Step 2 — Financial Statements & Auto Ratios
A2: Enter 3 historical years + the latest year (or trailing 12 months) in the yellow cells, oldest on the left. All in the units from Step 1. Ratios below calculate themselves.
A4: Line item | B4: Year 1 (oldest) | C4: Year 2 | D4: Year 3 | E4: Latest year / TTM | F4: How to read it / where to find it
A5: Year label (e.g. FY2024) | F5: Type the year names. Use the same year-end every time.
A6: Income statement
A7: Revenue (turnover) | F7: Top line. Income statement.
A8: Gross profit | F8: Revenue − cost of sales. Banks/insurers: leave blank.
A9: Operating profit (EBIT) | F9: Profit before interest and tax. Use the reported figure.
A10: Depreciation & amortisation | F10: Cash flow statement or notes. Needed for EBITDA.
A11: Interest expense (enter as positive) | F11: Finance costs line on the income statement.
A12: Net income to shareholders | F12: Profit attributable to ordinary shareholders.
A13: Diluted EPS (per share) | F13: Per share, NOT in millions. JSE reports often in cents: convert to Rand.
A14: Dividend per share | F14: Per share, same currency as EPS.
A15: Diluted shares outstanding (millions) | F15: Weighted diluted shares, in MILLIONS. Notes to the EPS line.
A16: Balance sheet (end of each year)
A17: Cash & short-term investments | F17: Cash + short-term deposits/investments.
A18: Total current assets
A19: Total current liabilities
A20: Total debt (incl. lease liabilities) | F20: Short + long-term borrowings + leases. Be consistent every year.
A21: Total shareholders' equity | F21: Attributable to ordinary shareholders.
A22: Cash flow statement
A23: Cash from operating activities | F23: Cash flow statement, first subtotal.
A24: Capital expenditure (enter as positive) | F24: Purchases of PP&E + intangibles.
A25: Share-based compensation | F25: Cash flow statement add-back or notes. Important for tech companies.
A26: Share buybacks (enter as positive) | F26: Financing section.
A27: Dividends paid (enter as positive) | F27: Financing section.
A28: Effective tax rate (latest year) | F28: Tax expense ÷ profit before tax. Used for ROIC. SA company rate is 27% if unsure.
A30: Auto-calculated ratios (do not type here)
A31: Ratio | B31: Year 1 | C31: Year 2 | D31: Year 3 | E31: Latest | F31: What it tells you
A32: Revenue growth (y/y) | C32: =IFERROR(IF(OR(C7="",B7=""),"",C7/B7-1),"") | D32: =IFERROR(IF(OR(D7="",C7=""),"",D7/C7-1),"") | E32: =IFERROR(IF(OR(E7="",D7=""),"",E7/D7-1),"") | F32: How fast sales are growing. Compare with inflation (~4–5% in SA) and peers.
A33: Gross margin | B33: =IFERROR(IF(OR(B8="",B7=""),"",B8/B7),"") | C33: =IFERROR(IF(OR(C8="",C7=""),"",C8/C7),"") | D33: =IFERROR(IF(OR(D8="",D7=""),"",D8/D7),"") | E33: =IFERROR(IF(OR(E8="",E7=""),"",E8/E7),"") | F33: Share of each sale left after direct costs. High = pricing power. Varies hugely by industry.
A34: Operating margin | B34: =IFERROR(IF(OR(B9="",B7=""),"",B9/B7),"") | C34: =IFERROR(IF(OR(C9="",C7=""),"",C9/C7),"") | D34: =IFERROR(IF(OR(D9="",D7=""),"",D9/D7),"") | E34: =IFERROR(IF(OR(E9="",E7=""),"",E9/E7),"") | F34: Profit from operations per R1 of sales. Rising = getting more efficient.
A35: Net margin | B35: =IFERROR(IF(OR(B12="",B7=""),"",B12/B7),"") | C35: =IFERROR(IF(OR(C12="",C7=""),"",C12/C7),"") | D35: =IFERROR(IF(OR(D12="",D7=""),"",D12/D7),"") | E35: =IFERROR(IF(OR(E12="",E7=""),"",E12/E7),"") | F35: Bottom-line profit per R1 of sales.
A36: EBITDA | B36: =IFERROR(IF(OR(B9="",B10=""),"",B9+B10),"") | C36: =IFERROR(IF(OR(C9="",C10=""),"",C9+C10),"") | D36: =IFERROR(IF(OR(D9="",D10=""),"",D9+D10),"") | E36: =IFERROR(IF(OR(E9="",E10=""),"",E9+E10),"") | F36: Operating profit + depreciation & amortisation. Rough proxy for operating cash profit.
A37: EPS growth (y/y) | C37: =IFERROR(IF(OR(OR(C13="",B13=""),B13<=0),"",C13/B13-1),"") | D37: =IFERROR(IF(OR(OR(D13="",C13=""),C13<=0),"",D13/C13-1),"") | E37: =IFERROR(IF(OR(OR(E13="",D13=""),D13<=0),"",E13/D13-1),"") | F37: Growth in profit per share — what shareholders actually get.
A38: Free cash flow (FCF) | B38: =IFERROR(IF(OR(B23="",B24=""),"",B23-B24),"") | C38: =IFERROR(IF(OR(C23="",C24=""),"",C23-C24),"") | D38: =IFERROR(IF(OR(D23="",D24=""),"",D23-D24),"") | E38: =IFERROR(IF(OR(E23="",E24=""),"",E23-E24),"") | F38: Operating cash flow − capex. The cash left for dividends, buybacks, debt repayment.
A39: FCF margin | B39: =IFERROR(IF(OR(B38="",B7=""),"",B38/B7),"") | C39: =IFERROR(IF(OR(C38="",C7=""),"",C38/C7),"") | D39: =IFERROR(IF(OR(D38="",D7=""),"",D38/D7),"") | E39: =IFERROR(IF(OR(E38="",E7=""),"",E38/E7),"") | F39: FCF per R1 of sales.
A40: Cash conversion (FCF ÷ net income) | B40: =IFERROR(IF(OR(B38="",B12="",N(B12)<=0),"",B38/B12),"") | C40: =IFERROR(IF(OR(C38="",C12="",N(C12)<=0),"",C38/C12),"") | D40: =IFERROR(IF(OR(D38="",D12="",N(D12)<=0),"",D38/D12),"") | E40: =IFERROR(IF(OR(E38="",E12="",N(E12)<=0),"",E38/E12),"") | F40: Is profit turning into cash? Below 0.8x for years = question the earnings.
A41: Capex as % of revenue | B41: =IFERROR(IF(OR(B24="",B7=""),"",B24/B7),"") | C41: =IFERROR(IF(OR(C24="",C7=""),"",C24/C7),"") | D41: =IFERROR(IF(OR(D24="",D7=""),"",D24/D7),"") | E41: =IFERROR(IF(OR(E24="",E7=""),"",E24/E7),"") | F41: How much it must reinvest just to keep going. Miners/telcos high; software low.
A42: Share-based comp as % of revenue | B42: =IFERROR(IF(OR(B25="",B7=""),"",B25/B7),"") | C42: =IFERROR(IF(OR(C25="",C7=""),"",C25/C7),"") | D42: =IFERROR(IF(OR(D25="",D7=""),"",D25/D7),"") | E42: =IFERROR(IF(OR(E25="",E7=""),"",E25/E7),"") | F42: A real cost paid in shares. High SBC flatters 'adjusted' profit and FCF.
A43: Net debt (debt − cash) | B43: =IFERROR(IF(OR(B20="",B17=""),"",B20-B17),"") | C43: =IFERROR(IF(OR(C20="",C17=""),"",C20-C17),"") | D43: =IFERROR(IF(OR(D20="",D17=""),"",D20-D17),"") | E43: =IFERROR(IF(OR(E20="",E17=""),"",E20-E17),"") | F43: Negative = net cash (good). Positive = owes more than it holds.
A44: Net debt ÷ EBITDA | B44: =IFERROR(IF(OR(B43="",B36="",N(B36)<=0),"",B43/B36),"") | C44: =IFERROR(IF(OR(C43="",C36="",N(C36)<=0),"",C43/C36),"") | D44: =IFERROR(IF(OR(D43="",D36="",N(D36)<=0),"",D43/D36),"") | E44: =IFERROR(IF(OR(E43="",E36="",N(E36)<=0),"",E43/E36),"") | F44: Years of EBITDA to repay net debt. Below 1x comfortable; above 3x risky.
A45: Interest cover (EBIT ÷ interest) | B45: =IFERROR(IF(OR(OR(B9="",B11=""),N(B11)<=0),"",B9/B11),"") | C45: =IFERROR(IF(OR(OR(C9="",C11=""),N(C11)<=0),"",C9/C11),"") | D45: =IFERROR(IF(OR(OR(D9="",D11=""),N(D11)<=0),"",D9/D11),"") | E45: =IFERROR(IF(OR(OR(E9="",E11=""),N(E11)<=0),"",E9/E11),"") | F45: How many times profit covers interest. Below 3x is a warning.
A46: Current ratio | B46: =IFERROR(IF(OR(B18="",B19=""),"",B18/B19),"") | C46: =IFERROR(IF(OR(C18="",C19=""),"",C18/C19),"") | D46: =IFERROR(IF(OR(D18="",D19=""),"",D18/D19),"") | E46: =IFERROR(IF(OR(E18="",E19=""),"",E18/E19),"") | F46: Short-term assets ÷ short-term liabilities. Below 1x can be fine if it's due to prepaid/deferred revenue — check why.
A47: Return on equity (ROE) | B47: =IFERROR(IF(OR(OR(B12="",B21=""),N(B21)<=0),"",B12/B21),"") | C47: =IFERROR(IF(OR(OR(C12="",C21=""),N(C21)<=0),"",C12/C21),"") | D47: =IFERROR(IF(OR(OR(D12="",D21=""),N(D21)<=0),"",D12/D21),"") | E47: =IFERROR(IF(OR(OR(E12="",E21=""),N(E21)<=0),"",E12/E21),"") | F47: Profit ÷ shareholders' equity. High ROE from high debt or buybacks is less impressive.
A48: Return on invested capital (ROIC) | B48: =IFERROR(IF(OR(OR(B9="",B20="",B21="",B17="",$E$28=""),(B20+B21-B17)<=0),"",B9*(1-$E$28)/(B20+B21-B17)),"") | C48: =IFERROR(IF(OR(OR(C9="",C20="",C21="",C17="",$E$28=""),(C20+C21-C17)<=0),"",C9*(1-$E$28)/(C20+C21-C17)),"") | D48: =IFERROR(IF(OR(OR(D9="",D20="",D21="",D17="",$E$28=""),(D20+D21-D17)<=0),"",D9*(1-$E$28)/(D20+D21-D17)),"") | E48: =IFERROR(IF(OR(OR(E9="",E20="",E21="",E17="",$E$28=""),(E20+E21-E17)<=0),"",E9*(1-$E$28)/(E20+E21-E17)),"") | F48: After-tax operating profit ÷ (debt + equity − cash). Should beat the cost of capital (WACC).
A49: Change in share count (y/y) | C49: =IFERROR(IF(OR(C15="",B15=""),"",C15/B15-1),"") | D49: =IFERROR(IF(OR(D15="",C15=""),"",D15/C15-1),"") | E49: =IFERROR(IF(OR(E15="",D15=""),"",E15/D15-1),"") | F49: Negative = buybacks shrinking the count (good). Positive = dilution.
A50: Shareholder payout ÷ FCF | B50: =IFERROR(IF(OR(AND(B27="",B26=""),B38="",N(B38)<=0),"",(N(B27)+N(B26))/B38),"") | C50: =IFERROR(IF(OR(AND(C27="",C26=""),C38="",N(C38)<=0),"",(N(C27)+N(C26))/C38),"") | D50: =IFERROR(IF(OR(AND(D27="",D26=""),D38="",N(D38)<=0),"",(N(D27)+N(D26))/D38),"") | E50: =IFERROR(IF(OR(AND(E27="",E26=""),E38="",N(E38)<=0),"",(N(E27)+N(E26))/E38),"") | F50: (Dividends + buybacks) ÷ FCF. Above 100% means it's paying out more than it earns in cash.
A52: Multi-year trends
A53: Revenue growth per year over 3 years (CAGR) | E53: =IFERROR(IF(OR(OR(B7="",E7=""),B7<=0),"",(E7/B7)^(1/3)-1),"") | F53: Smooths out one good or bad year.
A54: EPS growth per year over 3 years (CAGR) | E54: =IFERROR(IF(OR(OR(B13="",E13=""),B13<=0),"",(E13/B13)^(1/3)-1),"")
A55: Change in operating margin, latest vs previous year | E55: =IFERROR(IF(OR(E34="",D34=""),"",E34-D34),"") | F55: In percentage points. +0.02 = margin up 2 points.
A56: Change in gross margin, latest vs 3 years ago | E56: =IFERROR(IF(OR(E33="",B33=""),"",E33-B33),"") | F56: Falling gross margin can mean losing pricing power.
A58: Data checks
A59: Gross profit ≤ revenue (latest) | E59: =IF(OR(E8="",E7=""),"-",IF(E8<=E7,"OK","CHECK")) -> -
A60: EPS × shares ≈ net income (within 10%) | E60: =IF(OR(E13="",E15="",E12=""),"-",IF(ABS(E13*E15/E12-1)<=0.1,"OK","CHECK units")) -> - | F60: If this says CHECK, EPS is probably in cents, or shares not in millions.
A61: Capex entered as a positive number | E61: =IF(COUNT(B24:E24)=0,"-",IF(MIN(B24:E24)>=0,"OK","Enter capex as positive")) -> -

Sheet 3. Checklist
A1: Step 3 — Analysis Checklist (score every item 1–5)
A2: Read the question, find the evidence, compare with the BUY / HOLD / SELL columns, then score. Grey 'Suggested' scores come from your numbers — accept or override them with your judgement. Use N/A if an item doesn't apply.
A4: ID | B4: Section | C4: Check item | D4: Question to answer | E4: Why it matters | F4: Where to find it | G4: Example of good evidence | H4: BUY looks like (4–5) | I4: HOLD looks like (3) | J4: SELL looks like (1–2) | K4: Critical? | L4: Metric (auto) | M4: Suggested score | N4: Your score (1–5 or N/A) | O4: Score used | P4: Status | Q4: Your evidence / notes | R4: Source (document, page) | S4: Auto BUY level | T4: Auto SELL level
A5: A. Understand the business
A6: A1 | B6: A | C6: Explain the business simply | D6: Can you explain in 2 sentences what it sells, to whom, and how it makes money? | E6: If you can't explain it, you can't value it. | F6: Annual report: business overview; investor presentation | G6: 'Sells subscription design & PDF software to creatives and companies; ~95% of revenue is subscriptions.' | H6: Clear, simple model you can explain | I6: Understand most of it | J6: Can't explain how it makes money | K6: N | L6: Judgement | O6: =IF(N6="N/A","",IF(N6<>"",VALUE(N6&""),IF(M6="","",M6))) | P6: =IF(N6="N/A","N/A",IF(O6="","To do",IF(O6>=4,"Supports BUY",IF(O6=3,"Neutral",IF(K6="Y","CRITICAL FLAG","Concern"))))) -> To do
A7: A2 | B7: A | C7: Recurring revenue | D7: What share of revenue repeats every year (subscriptions, contracts, consumables)? | E7: Recurring revenue is more predictable, so it's worth more. | F7: Segment note; revenue note in annual report | G7: 'Subscription = 97% of Q3 revenue.' | H7: Over 70% recurring | I7: 40–70% | J7: Under 40% / one-off sales | K7: N | L7: Judgement | O7: =IF(N7="N/A","",IF(N7<>"",VALUE(N7&""),IF(M7="","",M7))) | P7: =IF(N7="N/A","N/A",IF(O7="","To do",IF(O7>=4,"Supports BUY",IF(O7=3,"Neutral",IF(K7="Y","CRITICAL FLAG","Concern"))))) -> To do
A8: A3 | B8: A | C8: Customer & product concentration | D8: Does any one customer, product or country make up a big share of sales? | E8: Losing one big customer or market can hurt badly. | F8: Segment & geographic notes; risk factors | G8: 'No customer above 10%; biggest segment 69%.' | H8: No customer >10%; well spread | I8: Some dependence | J8: One customer/product dominates | K8: N | L8: Judgement | O8: =IF(N8="N/A","",IF(N8<>"",VALUE(N8&""),IF(M8="","",M8))) | P8: =IF(N8="N/A","N/A",IF(O8="","To do",IF(O8>=4,"Supports BUY",IF(O8=3,"Neutral",IF(K8="Y","CRITICAL FLAG","Concern"))))) -> To do
A9: A4 | B9: A | C9: Competitive advantage (moat) | D9: What stops competitors from taking its customers? (brand, network, switching costs, scale, licences, low cost) | E9: A moat protects profits for longer. | F9: Your own analysis; industry reports; competitor reports | G9: 'Customers' files and workflows are built in its software: costly to switch.' | H9: Clear, lasting advantage | I9: Some advantage, under pressure | J9: No real advantage | K9: N | L9: Judgement | O9: =IF(N9="N/A","",IF(N9<>"",VALUE(N9&""),IF(M9="","",M9))) | P9: =IF(N9="N/A","N/A",IF(O9="","To do",IF(O9>=4,"Supports BUY",IF(O9=3,"Neutral",IF(K9="Y","CRITICAL FLAG","Concern"))))) -> To do
A10: A5 | B10: A | C10: Pricing power | D10: Can it raise prices above inflation without losing customers? | E10: Pricing power protects margins when costs rise. | F10: Results commentary; price-increase history; margin trend | G10: 'Raised prices 2 years running; churn stable.' | H10: Regular price rises, volumes hold | I10: Prices keep pace with inflation | J10: Discounting / losing share on price | K10: N | L10: Judgement | O10: =IF(N10="N/A","",IF(N10<>"",VALUE(N10&""),IF(M10="","",M10))) | P10: =IF(N10="N/A","N/A",IF(O10="","To do",IF(O10>=4,"Supports BUY",IF(O10=3,"Neutral",IF(K10="Y","CRITICAL FLAG","Concern"))))) -> To do
A11: A6 | B11: A | C11: Read the source documents | D11: Have you read the latest annual report, results announcement and results presentation? | E11: Data sites contain errors. Primary documents are the truth. | F11: Company investor relations website; JSE SENS; SEC EDGAR | G11: 'Read FY25 integrated report, H1 results, CEO presentation.' | H11: All read, key notes taken | I11: Partly read | J11: Only used data websites | K11: N | L11: Judgement | O11: =IF(N11="N/A","",IF(N11<>"",VALUE(N11&""),IF(M11="","",M11))) | P11: =IF(N11="N/A","N/A",IF(O11="","To do",IF(O11>=4,"Supports BUY",IF(O11=3,"Neutral",IF(K11="Y","CRITICAL FLAG","Concern"))))) -> To do
A12: B. Industry & competition
A13: B1 | B13: B | C13: Industry growth | D13: Is the industry growing faster than the economy? | E13: It's easier to grow in a growing market. | F13: Industry reports; competitors' results; Stats SA / sector bodies | G13: 'Market growing ~10% a year as AI increases content demand.' | H13: Growing faster than GDP | I13: Growing with GDP | J13: Shrinking | K13: N | L13: Judgement | O13: =IF(N13="N/A","",IF(N13<>"",VALUE(N13&""),IF(M13="","",M13))) | P13: =IF(N13="N/A","N/A",IF(O13="","To do",IF(O13>=4,"Supports BUY",IF(O13=3,"Neutral",IF(K13="Y","CRITICAL FLAG","Concern"))))) -> To do
A14: B2 | B14: B | C14: Competition | D14: Who are the main competitors, and is the company winning or losing market share? | E14: Losing share is an early warning sign. | F14: Competitors' results; industry data; news | G14: 'Gaining share in enterprise; losing at the low end to Canva.' | H14: Gaining share; few strong rivals | I14: Stable share | J14: Losing share; price wars | K14: N | L14: Judgement | O14: =IF(N14="N/A","",IF(N14<>"",VALUE(N14&""),IF(M14="","",M14))) | P14: =IF(N14="N/A","N/A",IF(O14="","To do",IF(O14>=4,"Supports BUY",IF(O14=3,"Neutral",IF(K14="Y","CRITICAL FLAG","Concern"))))) -> To do
A15: B3 | B15: B | C15: Disruption threat | D15: Could new technology or a new business model make this product unnecessary? | E15: Disruption can destroy a business that looks fine today. | F15: News, industry research, management Q&A | G15: 'AI image tools could replace casual users; company's own AI products growing 150%.' | H15: Low; company leads the change | I15: Moderate; company adapting | J15: High; company falling behind | K15: Y | L15: Judgement | O15: =IF(N15="N/A","",IF(N15<>"",VALUE(N15&""),IF(M15="","",M15))) | P15: =IF(N15="N/A","N/A",IF(O15="","To do",IF(O15>=4,"Supports BUY",IF(O15=3,"Neutral",IF(K15="Y","CRITICAL FLAG","Concern"))))) -> To do
A16: B4 | B16: B | C16: Regulation & legal | D16: Are there laws, licences, court cases or government actions that could change profits? | E16: Regulation can cap prices or add costs overnight. | F16: Risk factors; legal note; news | G16: 'Consumer-protection case settled for $150m; now closed.' | H16: No material issues | I16: Manageable / settled | J16: Major open issue | K16: N | L16: Judgement | O16: =IF(N16="N/A","",IF(N16<>"",VALUE(N16&""),IF(M16="","",M16))) | P16: =IF(N16="N/A","N/A",IF(O16="","To do",IF(O16>=4,"Supports BUY",IF(O16=3,"Neutral",IF(K16="Y","CRITICAL FLAG","Concern"))))) -> To do
A17: B5 | B17: B | C17: Economic sensitivity | D17: How much do sales fall in a recession or when interest rates rise? | E17: Cyclical companies need a bigger safety margin. | F17: Performance in 2008/2020; management commentary | G17: 'Revenue grew through 2020 — subscriptions held up.' | H17: Defensive; little impact | I17: Some impact | J17: Highly cyclical, at risk now | K17: N | L17: Judgement | O17: =IF(N17="N/A","",IF(N17<>"",VALUE(N17&""),IF(M17="","",M17))) | P17: =IF(N17="N/A","N/A",IF(O17="","To do",IF(O17>=4,"Supports BUY",IF(O17=3,"Neutral",IF(K17="Y","CRITICAL FLAG","Concern"))))) -> To do
A18: C. Growth
A19: C1 | B19: C | C19: Revenue growth (latest year) | D19: How fast did revenue grow last year? | E19: Growth drives future profits. | F19: Financials sheet (auto) | G19: '+12% vs peer median +10%.' | H19: ≥10% (or above peers) | I19: 0–10% | J19: Falling revenue | K19: N | L19: =IF('2. Financials'!$E$32="","",'2. Financials'!$E$32) | M19: =IFERROR(IF(OR(L19="",S19="",T19=""),"",IF(((L19-T19)/(S19-T19))>=2,5,IF(((L19-T19)/(S19-T19))>=1,4,IF(((L19-T19)/(S19-T19))>0,3,IF(((L19-T19)/(S19-T19))>-1,2,1))))),"") | O19: =IF(N19="N/A","",IF(N19<>"",VALUE(N19&""),IF(M19="","",M19))) | P19: =IF(N19="N/A","N/A",IF(O19="","To do",IF(O19>=4,"Supports BUY",IF(O19=3,"Neutral",IF(K19="Y","CRITICAL FLAG","Concern"))))) -> To do | S19: 0.1 | T19: 0
A20: C2 | B20: C | C20: Revenue growth over 3 years | D20: What's the average yearly growth over 3 years? | E20: Shows if growth is steady, not a one-off. | F20: Financials sheet (auto) | G20: '3-yr CAGR 10.2%; every year between 10–12%.' | H20: ≥8% a year | I20: 0–8% | J20: Shrinking | K20: N | L20: =IF('2. Financials'!$E$53="","",'2. Financials'!$E$53) | M20: =IFERROR(IF(OR(L20="",S20="",T20=""),"",IF(((L20-T20)/(S20-T20))>=2,5,IF(((L20-T20)/(S20-T20))>=1,4,IF(((L20-T20)/(S20-T20))>0,3,IF(((L20-T20)/(S20-T20))>-1,2,1))))),"") | O20: =IF(N20="N/A","",IF(N20<>"",VALUE(N20&""),IF(M20="","",M20))) | P20: =IF(N20="N/A","N/A",IF(O20="","To do",IF(O20>=4,"Supports BUY",IF(O20=3,"Neutral",IF(K20="Y","CRITICAL FLAG","Concern"))))) -> To do | S20: 0.08 | T20: 0
A21: C3 | B21: C | C21: EPS growth | D21: Is earnings per share growing? | E21: EPS growth is what drives the share price over time. | F21: Financials sheet (auto) | G21: 'EPS +7% y/y; boosted by buybacks.' | H21: ≥10% | I21: 0–10% | J21: Falling EPS | K21: N | L21: =IF('2. Financials'!$E$37="","",'2. Financials'!$E$37) | M21: =IFERROR(IF(OR(L21="",S21="",T21=""),"",IF(((L21-T21)/(S21-T21))>=2,5,IF(((L21-T21)/(S21-T21))>=1,4,IF(((L21-T21)/(S21-T21))>0,3,IF(((L21-T21)/(S21-T21))>-1,2,1))))),"") | O21: =IF(N21="N/A","",IF(N21<>"",VALUE(N21&""),IF(M21="","",M21))) | P21: =IF(N21="N/A","N/A",IF(O21="","To do",IF(O21>=4,"Supports BUY",IF(O21=3,"Neutral",IF(K21="Y","CRITICAL FLAG","Concern"))))) -> To do | S21: 0.1 | T21: 0
A22: C4 | B22: C | C22: Guidance & outlook | D22: What does management expect for next year? Is it above or below what analysts expect? | E22: The market reacts to guidance vs expectations. | F22: Results announcement 'outlook' section; consensus | G22: 'FY guide raised twice; Q4 guide only in line.' | H22: Guidance raised / above consensus | I22: In line | J22: Cut / below consensus | K22: N | L22: Judgement | O22: =IF(N22="N/A","",IF(N22<>"",VALUE(N22&""),IF(M22="","",M22))) | P22: =IF(N22="N/A","N/A",IF(O22="","To do",IF(O22>=4,"Supports BUY",IF(O22=3,"Neutral",IF(K22="Y","CRITICAL FLAG","Concern"))))) -> To do
A23: C5 | B23: C | C23: Future growth drivers | D23: Which new products, markets or acquisitions will drive growth? Are they big enough to matter? | E23: Growth must come from somewhere specific. | F23: Investor presentation; strategy section | G23: 'AI products growing 150% but still only 3% of revenue.' | H23: Clear drivers, already material | I23: Promising but small | J23: No clear drivers | K23: N | L23: Judgement | O23: =IF(N23="N/A","",IF(N23<>"",VALUE(N23&""),IF(M23="","",M23))) | P23: =IF(N23="N/A","N/A",IF(O23="","To do",IF(O23>=4,"Supports BUY",IF(O23=3,"Neutral",IF(K23="Y","CRITICAL FLAG","Concern"))))) -> To do
A24: D. Profitability
A25: D1 | B25: D | C25: Gross margin | D25: What % of revenue is left after direct costs? | E25: High gross margin = pricing power. COMPARE WITH PEERS — levels differ by industry (retail ~20–25%, software ~80%+). | F25: Financials sheet (auto) | G25: '89% vs software peers ~75%.' | H25: ≥40% (or above peers) | I25: 20–40% | J25: <20% (or below peers) | K25: N | L25: =IF('2. Financials'!$E$33="","",'2. Financials'!$E$33) | M25: =IFERROR(IF(OR(L25="",S25="",T25=""),"",IF(((L25-T25)/(S25-T25))>=2,5,IF(((L25-T25)/(S25-T25))>=1,4,IF(((L25-T25)/(S25-T25))>0,3,IF(((L25-T25)/(S25-T25))>-1,2,1))))),"") | O25: =IF(N25="N/A","",IF(N25<>"",VALUE(N25&""),IF(M25="","",M25))) | P25: =IF(N25="N/A","N/A",IF(O25="","To do",IF(O25>=4,"Supports BUY",IF(O25=3,"Neutral",IF(K25="Y","CRITICAL FLAG","Concern"))))) -> To do | S25: 0.4 | T25: 0.2
A26: D2 | B26: D | C26: Operating margin | D26: What % of revenue is operating profit? | E26: Shows how efficiently the business is run. Compare with peers. | F26: Financials sheet (auto) | G26: '36% vs peer median 25%.' | H26: ≥15% (or above peers) | I26: 5–15% | J26: <5% / losses | K26: N | L26: =IF('2. Financials'!$E$34="","",'2. Financials'!$E$34) | M26: =IFERROR(IF(OR(L26="",S26="",T26=""),"",IF(((L26-T26)/(S26-T26))>=2,5,IF(((L26-T26)/(S26-T26))>=1,4,IF(((L26-T26)/(S26-T26))>0,3,IF(((L26-T26)/(S26-T26))>-1,2,1))))),"") | O26: =IF(N26="N/A","",IF(N26<>"",VALUE(N26&""),IF(M26="","",M26))) | P26: =IF(N26="N/A","N/A",IF(O26="","To do",IF(O26>=4,"Supports BUY",IF(O26=3,"Neutral",IF(K26="Y","CRITICAL FLAG","Concern"))))) -> To do | S26: 0.15 | T26: 0.05
A27: D3 | B27: D | C27: Margin trend | D27: Is the operating margin going up or down? | E27: Falling margins often come before falling profits. | F27: Financials sheet (auto) | G27: 'Down 0.9 points: higher AI costs.' | H27: Up ≥1 point | I27: Roughly flat | J27: Down ≥2 points | K27: N | L27: =IF('2. Financials'!$E$55="","",'2. Financials'!$E$55) | M27: =IFERROR(IF(OR(L27="",S27="",T27=""),"",IF(((L27-T27)/(S27-T27))>=2,5,IF(((L27-T27)/(S27-T27))>=1,4,IF(((L27-T27)/(S27-T27))>0,3,IF(((L27-T27)/(S27-T27))>-1,2,1))))),"") | O27: =IF(N27="N/A","",IF(N27<>"",VALUE(N27&""),IF(M27="","",M27))) | P27: =IF(N27="N/A","N/A",IF(O27="","To do",IF(O27>=4,"Supports BUY",IF(O27=3,"Neutral",IF(K27="Y","CRITICAL FLAG","Concern"))))) -> To do | S27: 0.01 | T27: -0.02
A28: D4 | B28: D | C28: Return on equity (ROE) | D28: How much profit does it earn on shareholders' money? | E28: High ROE = efficient use of capital. Check it's not just from high debt. | F28: Financials sheet (auto) | G28: '62% — flattered by buybacks reducing equity.' | H28: ≥15% | I28: 8–15% | J28: <8% | K28: N | L28: =IF('2. Financials'!$E$47="","",'2. Financials'!$E$47) | M28: =IFERROR(IF(OR(L28="",S28="",T28=""),"",IF(((L28-T28)/(S28-T28))>=2,5,IF(((L28-T28)/(S28-T28))>=1,4,IF(((L28-T28)/(S28-T28))>0,3,IF(((L28-T28)/(S28-T28))>-1,2,1))))),"") | O28: =IF(N28="N/A","",IF(N28<>"",VALUE(N28&""),IF(M28="","",M28))) | P28: =IF(N28="N/A","N/A",IF(O28="","To do",IF(O28>=4,"Supports BUY",IF(O28=3,"Neutral",IF(K28="Y","CRITICAL FLAG","Concern"))))) -> To do | S28: 0.15 | T28: 0.08
A29: D5 | B29: D | C29: Return on invested capital (ROIC) | D29: Does it earn more on its capital than its cost of capital (WACC)? | E29: ROIC above WACC = the company creates value as it grows. | F29: Financials sheet (auto); WACC on Valuation sheet | G29: 'ROIC 59% vs WACC 12.5%.' | H29: ≥12% (well above WACC) | I29: Around WACC | J29: Below WACC (<6%) | K29: N | L29: =IF('2. Financials'!$E$48="","",'2. Financials'!$E$48) | M29: =IFERROR(IF(OR(L29="",S29="",T29=""),"",IF(((L29-T29)/(S29-T29))>=2,5,IF(((L29-T29)/(S29-T29))>=1,4,IF(((L29-T29)/(S29-T29))>0,3,IF(((L29-T29)/(S29-T29))>-1,2,1))))),"") | O29: =IF(N29="N/A","",IF(N29<>"",VALUE(N29&""),IF(M29="","",M29))) | P29: =IF(N29="N/A","N/A",IF(O29="","To do",IF(O29>=4,"Supports BUY",IF(O29=3,"Neutral",IF(K29="Y","CRITICAL FLAG","Concern"))))) -> To do | S29: 0.12 | T29: 0.06
A30: D6 | B30: D | C30: Quality of earnings | D30: Are 'adjusted' / 'headline' earnings far above reported earnings? Any one-off gains? | E30: Big adjustments can hide real costs. | F30: Results: reconciliation of headline/adjusted earnings | G30: 'Adjusted profit 21% above reported — mainly share-based pay.' | H30: Small, clear adjustments | I30: Some adjustments | J30: Large, recurring 'one-offs' | K30: N | L30: Judgement | O30: =IF(N30="N/A","",IF(N30<>"",VALUE(N30&""),IF(M30="","",M30))) | P30: =IF(N30="N/A","N/A",IF(O30="","To do",IF(O30>=4,"Supports BUY",IF(O30=3,"Neutral",IF(K30="Y","CRITICAL FLAG","Concern"))))) -> To do
A31: E. Cash flow
A32: E1 | B32: E | C32: Free cash flow margin | D32: How much of revenue becomes free cash? | E32: Cash pays dividends and debt — profit alone doesn't. | F32: Financials sheet (auto) | G32: 'FCF margin 41%.' | H32: ≥10% | I32: 2–10% | J32: <2% / negative | K32: N | L32: =IF('2. Financials'!$E$39="","",'2. Financials'!$E$39) | M32: =IFERROR(IF(OR(L32="",S32="",T32=""),"",IF(((L32-T32)/(S32-T32))>=2,5,IF(((L32-T32)/(S32-T32))>=1,4,IF(((L32-T32)/(S32-T32))>0,3,IF(((L32-T32)/(S32-T32))>-1,2,1))))),"") | O32: =IF(N32="N/A","",IF(N32<>"",VALUE(N32&""),IF(M32="","",M32))) | P32: =IF(N32="N/A","N/A",IF(O32="","To do",IF(O32>=4,"Supports BUY",IF(O32=3,"Neutral",IF(K32="Y","CRITICAL FLAG","Concern"))))) -> To do | S32: 0.1 | T32: 0.02
A33: E2 | B33: E | C33: Cash conversion | D33: Is profit turning into cash? (FCF ÷ net income) | E33: Profit without cash is a red flag for accounting quality. | F33: Financials sheet (auto) | G33: '1.45x — strong.' | H33: ≥1.0x | I33: 0.7–1.0x | J33: <0.7x | K33: N | L33: =IF('2. Financials'!$E$40="","",'2. Financials'!$E$40) | M33: =IFERROR(IF(OR(L33="",S33="",T33=""),"",IF(((L33-T33)/(S33-T33))>=2,5,IF(((L33-T33)/(S33-T33))>=1,4,IF(((L33-T33)/(S33-T33))>0,3,IF(((L33-T33)/(S33-T33))>-1,2,1))))),"") | O33: =IF(N33="N/A","",IF(N33<>"",VALUE(N33&""),IF(M33="","",M33))) | P33: =IF(N33="N/A","N/A",IF(O33="","To do",IF(O33>=4,"Supports BUY",IF(O33=3,"Neutral",IF(K33="Y","CRITICAL FLAG","Concern"))))) -> To do | S33: 1 | T33: 0.7
A34: E3 | B34: E | C34: Capital intensity | D34: How much must it reinvest each year? (capex ÷ revenue) | E34: Lower capex = more cash for shareholders. | F34: Financials sheet (auto) | G34: 'Capex under 1% of revenue.' | H34: ≤5% | I34: 5–15% | J34: ≥15% | K34: N | L34: =IF('2. Financials'!$E$41="","",'2. Financials'!$E$41) | M34: =IFERROR(IF(OR(L34="",S34="",T34=""),"",IF(((L34-T34)/(S34-T34))>=2,5,IF(((L34-T34)/(S34-T34))>=1,4,IF(((L34-T34)/(S34-T34))>0,3,IF(((L34-T34)/(S34-T34))>-1,2,1))))),"") | O34: =IF(N34="N/A","",IF(N34<>"",VALUE(N34&""),IF(M34="","",M34))) | P34: =IF(N34="N/A","N/A",IF(O34="","To do",IF(O34>=4,"Supports BUY",IF(O34=3,"Neutral",IF(K34="Y","CRITICAL FLAG","Concern"))))) -> To do | S34: 0.05 | T34: 0.15
A35: E4 | B35: E | C35: Share-based pay | D35: How big is share-based compensation vs revenue? | E35: It's a real cost: it dilutes your ownership. | F35: Financials sheet (auto) | G35: 'SBC 7% of revenue — significant.' | H35: ≤2% | I35: 2–8% | J35: ≥8% | K35: N | L35: =IF('2. Financials'!$E$42="","",'2. Financials'!$E$42) | M35: =IFERROR(IF(OR(L35="",S35="",T35=""),"",IF(((L35-T35)/(S35-T35))>=2,5,IF(((L35-T35)/(S35-T35))>=1,4,IF(((L35-T35)/(S35-T35))>0,3,IF(((L35-T35)/(S35-T35))>-1,2,1))))),"") | O35: =IF(N35="N/A","",IF(N35<>"",VALUE(N35&""),IF(M35="","",M35))) | P35: =IF(N35="N/A","N/A",IF(O35="","To do",IF(O35>=4,"Supports BUY",IF(O35=3,"Neutral",IF(K35="Y","CRITICAL FLAG","Concern"))))) -> To do | S35: 0.02 | T35: 0.08
A36: F. Balance sheet & capital allocation
A37: F1 | B37: F | C37: Debt level | D37: Net debt ÷ EBITDA: how many years to repay debt? | E37: Too much debt can sink a company in a bad year. | F37: Financials sheet (auto) | G37: '0.1x — almost no net debt.' | H37: ≤1.0x or net cash | I37: 1–3x | J37: ≥3x | K37: Y | L37: =IF('2. Financials'!$E$44="","",'2. Financials'!$E$44) | M37: =IFERROR(IF(OR(L37="",S37="",T37=""),"",IF(((L37-T37)/(S37-T37))>=2,5,IF(((L37-T37)/(S37-T37))>=1,4,IF(((L37-T37)/(S37-T37))>0,3,IF(((L37-T37)/(S37-T37))>-1,2,1))))),"") | O37: =IF(N37="N/A","",IF(N37<>"",VALUE(N37&""),IF(M37="","",M37))) | P37: =IF(N37="N/A","N/A",IF(O37="","To do",IF(O37>=4,"Supports BUY",IF(O37=3,"Neutral",IF(K37="Y","CRITICAL FLAG","Concern"))))) -> To do | S37: 1 | T37: 3
A38: F2 | B38: F | C38: Interest cover | D38: How many times does operating profit cover interest? | E38: Below 3x, a profit dip can make interest hard to pay. | F38: Financials sheet (auto) | G38: 'Covers interest 35x.' | H38: ≥8x | I38: 3–8x | J38: ≤3x | K38: N | L38: =IF('2. Financials'!$E$45="","",'2. Financials'!$E$45) | M38: =IFERROR(IF(OR(L38="",S38="",T38=""),"",IF(((L38-T38)/(S38-T38))>=2,5,IF(((L38-T38)/(S38-T38))>=1,4,IF(((L38-T38)/(S38-T38))>0,3,IF(((L38-T38)/(S38-T38))>-1,2,1))))),"") | O38: =IF(N38="N/A","",IF(N38<>"",VALUE(N38&""),IF(M38="","",M38))) | P38: =IF(N38="N/A","N/A",IF(O38="","To do",IF(O38>=4,"Supports BUY",IF(O38=3,"Neutral",IF(K38="Y","CRITICAL FLAG","Concern"))))) -> To do | S38: 8 | T38: 3
A39: F3 | B39: F | C39: Liquidity | D39: Current ratio: can it pay its short-term bills? | E39: Running out of cash is how companies fail. (Below 1x can be fine if due to customer prepayments.) | F39: Financials sheet (auto) | G39: '0.77x — but due to deferred revenue, and R5.6bn cash.' | H39: ≥1.5x (or <1x explained) | I39: 1.0–1.5x | J39: <1.0x, unexplained | K39: N | L39: =IF('2. Financials'!$E$46="","",'2. Financials'!$E$46) | M39: =IFERROR(IF(OR(L39="",S39="",T39=""),"",IF(((L39-T39)/(S39-T39))>=2,5,IF(((L39-T39)/(S39-T39))>=1,4,IF(((L39-T39)/(S39-T39))>0,3,IF(((L39-T39)/(S39-T39))>-1,2,1))))),"") | O39: =IF(N39="N/A","",IF(N39<>"",VALUE(N39&""),IF(M39="","",M39))) | P39: =IF(N39="N/A","N/A",IF(O39="","To do",IF(O39>=4,"Supports BUY",IF(O39=3,"Neutral",IF(K39="Y","CRITICAL FLAG","Concern"))))) -> To do | S39: 1.5 | T39: 1
A40: F4 | B40: F | C40: Share count | D40: Is the number of shares going down (buybacks) or up (dilution)? | E40: Dilution means your slice of the company shrinks. | F40: Financials sheet (auto) | G40: 'Shares down 5.8% y/y.' | H40: Falling ≥1% a year | I40: Flat | J40: Rising ≥2% | K40: N | L40: =IF('2. Financials'!$E$49="","",'2. Financials'!$E$49) | M40: =IFERROR(IF(OR(L40="",S40="",T40=""),"",IF(((L40-T40)/(S40-T40))>=2,5,IF(((L40-T40)/(S40-T40))>=1,4,IF(((L40-T40)/(S40-T40))>0,3,IF(((L40-T40)/(S40-T40))>-1,2,1))))),"") | O40: =IF(N40="N/A","",IF(N40<>"",VALUE(N40&""),IF(M40="","",M40))) | P40: =IF(N40="N/A","N/A",IF(O40="","To do",IF(O40>=4,"Supports BUY",IF(O40=3,"Neutral",IF(K40="Y","CRITICAL FLAG","Concern"))))) -> To do | S40: -0.01 | T40: 0.02
A41: F5 | B41: F | C41: Affordable shareholder payouts | D41: Are dividends + buybacks paid out of free cash flow, not new debt? | E41: Borrowing to pay shareholders isn't sustainable. | F41: Financials sheet (auto) | G41: 'Payout 115% of FCF — part funded by debt.' | H41: ≤60% of FCF | I41: 60–100% | J41: ≥100% of FCF | K41: N | L41: =IF('2. Financials'!$E$50="","",'2. Financials'!$E$50) | M41: =IFERROR(IF(OR(L41="",S41="",T41=""),"",IF(((L41-T41)/(S41-T41))>=2,5,IF(((L41-T41)/(S41-T41))>=1,4,IF(((L41-T41)/(S41-T41))>0,3,IF(((L41-T41)/(S41-T41))>-1,2,1))))),"") | O41: =IF(N41="N/A","",IF(N41<>"",VALUE(N41&""),IF(M41="","",M41))) | P41: =IF(N41="N/A","N/A",IF(O41="","To do",IF(O41>=4,"Supports BUY",IF(O41=3,"Neutral",IF(K41="Y","CRITICAL FLAG","Concern"))))) -> To do | S41: 0.6 | T41: 1
A42: F6 | B42: F | C42: Acquisitions track record | D42: Have past acquisitions been sensible and well-priced? Any write-offs? | E42: Bad deals destroy shareholder value. | F42: Annual reports; impairment notes; news | G42: 'Small bolt-ons; no write-offs in 5 years.' | H42: Disciplined, value-adding | I42: Mixed record | J42: Overpaid / write-offs | K42: N | L42: Judgement | O42: =IF(N42="N/A","",IF(N42<>"",VALUE(N42&""),IF(M42="","",M42))) | P42: =IF(N42="N/A","N/A",IF(O42="","To do",IF(O42>=4,"Supports BUY",IF(O42=3,"Neutral",IF(K42="Y","CRITICAL FLAG","Concern"))))) -> To do
A43: G. Management & governance
A44: G1 | B44: G | C44: Management track record | D44: Has management done what it said it would in the past? | E44: Credible managers = more reliable forecasts. | F44: Compare old presentations/guidance with results | G44: 'Met or beat guidance 8 quarters in a row.' | H44: Consistently delivers | I44: Mixed | J44: Regularly misses / changes story | K44: N | L44: Judgement | O44: =IF(N44="N/A","",IF(N44<>"",VALUE(N44&""),IF(M44="","",M44))) | P44: =IF(N44="N/A","N/A",IF(O44="","To do",IF(O44>=4,"Supports BUY",IF(O44=3,"Neutral",IF(K44="Y","CRITICAL FLAG","Concern"))))) -> To do
A45: G2 | B45: G | C45: Leadership stability | D45: Any recent or upcoming CEO/CFO changes? | E45: New leaders often change strategy or 'kitchen-sink' results. | F45: SENS / 8-K announcements; news | G45: 'New CEO from 1 Dec; product head leaving.' | H45: Stable, proven team | I45: Planned, orderly change | J45: Sudden departures | K45: Y | L45: Judgement | O45: =IF(N45="N/A","",IF(N45<>"",VALUE(N45&""),IF(M45="","",M45))) | P45: =IF(N45="N/A","N/A",IF(O45="","To do",IF(O45>=4,"Supports BUY",IF(O45=3,"Neutral",IF(K45="Y","CRITICAL FLAG","Concern"))))) -> To do
A46: G3 | B46: G | C46: Insider ownership & trades | D46: Do directors own meaningful shares? Are they buying or selling? | E46: Owners act like owners. Heavy selling is a warning. | F46: Directors' dealings (SENS); Form 4 (US); remuneration report | G46: 'Directors own 0.3%; only routine sales.' | H46: Meaningful ownership; buying | I46: Small stake, routine trades | J46: Heavy selling | K46: N | L46: Judgement | O46: =IF(N46="N/A","",IF(N46<>"",VALUE(N46&""),IF(M46="","",M46))) | P46: =IF(N46="N/A","N/A",IF(O46="","To do",IF(O46>=4,"Supports BUY",IF(O46=3,"Neutral",IF(K46="Y","CRITICAL FLAG","Concern"))))) -> To do
A47: G4 | B47: G | C47: Accounting & audit | D47: Clean audit opinion? Any restatements, auditor changes or late results? | E47: Accounting problems can wipe out a share (think Steinhoff). | F47: Auditor's report; news; JSE/SEC notices | G47: 'Clean opinion, same auditor, no restatements.' | H47: Clean | I47: Minor concerns | J47: Restatement / qualified opinion | K47: Y | L47: Judgement | O47: =IF(N47="N/A","",IF(N47<>"",VALUE(N47&""),IF(M47="","",M47))) | P47: =IF(N47="N/A","N/A",IF(O47="","To do",IF(O47>=4,"Supports BUY",IF(O47=3,"Neutral",IF(K47="Y","CRITICAL FLAG","Concern"))))) -> To do
A48: G5 | B48: G | C48: Shareholder rights | D48: One share = one vote? Any controlling shareholder or BEE/lock-in structure? | E48: Minority shareholders may have little say. | F48: Annual report: shareholder analysis; MOI/proxy | G48: 'Single share class, no controlling shareholder.' | H48: Fair, single class | I48: Some special structures | J48: Controller can ignore minorities | K48: N | L48: Judgement | O48: =IF(N48="N/A","",IF(N48<>"",VALUE(N48&""),IF(M48="","",M48))) | P48: =IF(N48="N/A","N/A",IF(O48="","To do",IF(O48>=4,"Supports BUY",IF(O48=3,"Neutral",IF(K48="Y","CRITICAL FLAG","Concern"))))) -> To do
A49: G6 | B49: G | C49: ESG issues | D49: Any environmental, social or governance issues that could cost money or reputation? | E49: ESG problems can become fines, boycotts or lost licences. | F49: Sustainability report; news; controversies | G49: 'Creator backlash over AI training data; low carbon footprint.' | H49: Low / well managed | I49: Some issues, managed | J49: Serious and unmanaged | K49: N | L49: Judgement | O49: =IF(N49="N/A","",IF(N49<>"",VALUE(N49&""),IF(M49="","",M49))) | P49: =IF(N49="N/A","N/A",IF(O49="","To do",IF(O49>=4,"Supports BUY",IF(O49=3,"Neutral",IF(K49="Y","CRITICAL FLAG","Concern"))))) -> To do
A50: H. Valuation
A51: H1 | B51: H | C51: Upside to target price | D51: How much could the share rise to your blended target? | E51: This is the core of the rating. | F51: Valuation sheet (auto) | G51: '+20% to R315 target.' | H51: ≥15% upside | I51: −10% to +15% | J51: ≤ −10% | K51: N | L51: =IF('4. Valuation'!$C$64="","",'4. Valuation'!$C$64) | M51: =IFERROR(IF(OR(L51="",S51="",T51=""),"",IF(((L51-T51)/(S51-T51))>=2,5,IF(((L51-T51)/(S51-T51))>=1,4,IF(((L51-T51)/(S51-T51))>0,3,IF(((L51-T51)/(S51-T51))>-1,2,1))))),"") | O51: =IF(N51="N/A","",IF(N51<>"",VALUE(N51&""),IF(M51="","",M51))) | P51: =IF(N51="N/A","N/A",IF(O51="","To do",IF(O51>=4,"Supports BUY",IF(O51=3,"Neutral",IF(K51="Y","CRITICAL FLAG","Concern"))))) -> To do | S51: 0.15 | T51: -0.1
A52: H2 | B52: H | C52: Cheap vs peers? | D52: Forward P/E premium or discount to the peer median | E52: A discount is an opportunity only if fundamentals are as good. | F52: Valuation sheet (auto) | G52: '60% discount despite better margins.' | H52: ≥20% discount, not deserved | I52: Within ±20% | J52: ≥20% premium, not earned | K52: N | L52: =IF('4. Valuation'!$B$14="","",'4. Valuation'!$B$14) | M52: =IFERROR(IF(OR(L52="",S52="",T52=""),"",IF(((L52-T52)/(S52-T52))>=2,5,IF(((L52-T52)/(S52-T52))>=1,4,IF(((L52-T52)/(S52-T52))>0,3,IF(((L52-T52)/(S52-T52))>-1,2,1))))),"") | O52: =IF(N52="N/A","",IF(N52<>"",VALUE(N52&""),IF(M52="","",M52))) | P52: =IF(N52="N/A","N/A",IF(O52="","To do",IF(O52>=4,"Supports BUY",IF(O52=3,"Neutral",IF(K52="Y","CRITICAL FLAG","Concern"))))) -> To do | S52: -0.2 | T52: 0.2
A53: H3 | B53: H | C53: Cheap vs its own history? | D53: Is today's P/E low compared with the company's own last 5 years? | E53: Shares tend to revert toward normal valuations — unless the business changed. | F53: Data sites: historical P/E charts | G53: 'P/E 10x vs 5-yr average 30x.' | H53: Bottom of 5-yr range | I53: Middle | J53: Top of range | K53: N | L53: Judgement | O53: =IF(N53="N/A","",IF(N53<>"",VALUE(N53&""),IF(M53="","",M53))) | P53: =IF(N53="N/A","N/A",IF(O53="","To do",IF(O53>=4,"Supports BUY",IF(O53=3,"Neutral",IF(K53="Y","CRITICAL FLAG","Concern"))))) -> To do
A54: H4 | B54: H | C54: Free cash flow yield | D54: FCF ÷ market cap — the cash 'yield' you buy | E54: Compare to the government bond yield. | F54: Company Info sheet (auto) | G54: '10% FCF yield vs 4.3% bond yield.' | H54: ≥6% | I54: 3–6% | J54: ≤3% | K54: N | L54: =IF('1. Company Info'!$B$35="","",'1. Company Info'!$B$35) | M54: =IFERROR(IF(OR(L54="",S54="",T54=""),"",IF(((L54-T54)/(S54-T54))>=2,5,IF(((L54-T54)/(S54-T54))>=1,4,IF(((L54-T54)/(S54-T54))>0,3,IF(((L54-T54)/(S54-T54))>-1,2,1))))),"") | O54: =IF(N54="N/A","",IF(N54<>"",VALUE(N54&""),IF(M54="","",M54))) | P54: =IF(N54="N/A","N/A",IF(O54="","To do",IF(O54>=4,"Supports BUY",IF(O54=3,"Neutral",IF(K54="Y","CRITICAL FLAG","Concern"))))) -> To do | S54: 0.06 | T54: 0.03
A55: H5 | B55: H | C55: Robust to assumptions? | D55: In the sensitivity table, is the value still above today's price if WACC is 1 point higher? | E55: A good idea shouldn't need perfect assumptions. | F55: Valuation sheet: section G | G55: 'Upside in 20 of 25 cells.' | H55: Upside in most cells | I55: About half | J55: Downside in most cells | K55: N | L55: Judgement | O55: =IF(N55="N/A","",IF(N55<>"",VALUE(N55&""),IF(M55="","",M55))) | P55: =IF(N55="N/A","N/A",IF(O55="","To do",IF(O55>=4,"Supports BUY",IF(O55=3,"Neutral",IF(K55="Y","CRITICAL FLAG","Concern"))))) -> To do
A56: H6 | B56: H | C56: Risk / reward | D56: Bull upside ÷ bear downside | E56: You want to make more if right than you lose if wrong. | F56: Valuation sheet (auto) | G56: 'Bull +47% vs bear −27% = 1.7x.' | H56: ≥2x | I56: 1–2x | J56: ≤1x | K56: N | L56: =IF('4. Valuation'!$B$73="","",'4. Valuation'!$B$73) | M56: =IFERROR(IF(OR(L56="",S56="",T56=""),"",IF(((L56-T56)/(S56-T56))>=2,5,IF(((L56-T56)/(S56-T56))>=1,4,IF(((L56-T56)/(S56-T56))>0,3,IF(((L56-T56)/(S56-T56))>-1,2,1))))),"") | O56: =IF(N56="N/A","",IF(N56<>"",VALUE(N56&""),IF(M56="","",M56))) | P56: =IF(N56="N/A","N/A",IF(O56="","To do",IF(O56>=4,"Supports BUY",IF(O56=3,"Neutral",IF(K56="Y","CRITICAL FLAG","Concern"))))) -> To do | S56: 2 | T56: 1
A57: I. Catalysts & market view
A58: I1 | B58: I | C58: Catalyst | D58: Is there a dated event in the next 6–12 months that could move the share? (results, product launch, deal, rate cut) | E58: Without a catalyst, a cheap share can stay cheap. | F58: Results calendar; company announcements | G58: 'Full-year results in Dec — first under new CEO.' | H58: Clear, dated catalyst | I58: Possible catalyst | J58: None | K58: N | L58: Judgement | O58: =IF(N58="N/A","",IF(N58<>"",VALUE(N58&""),IF(M58="","",M58))) | P58: =IF(N58="N/A","N/A",IF(O58="","To do",IF(O58>=4,"Supports BUY",IF(O58=3,"Neutral",IF(K58="Y","CRITICAL FLAG","Concern"))))) -> To do
A59: I2 | B59: I | C59: Your different view | D59: What do YOU believe that the market doesn't — and what evidence will prove it? | E59: If you agree with everyone, there's no reason for the share to move. | F59: Your thesis | G59: 'Market thinks AI kills the product; data shows AI revenue growing 150%. Proof: next 2 quarters.' | H59: Clear, testable view | I59: Partly different | J59: Same as consensus | K59: N | L59: Judgement | O59: =IF(N59="N/A","",IF(N59<>"",VALUE(N59&""),IF(M59="","",M59))) | P59: =IF(N59="N/A","N/A",IF(O59="","To do",IF(O59>=4,"Supports BUY",IF(O59=3,"Neutral",IF(K59="Y","CRITICAL FLAG","Concern"))))) -> To do
A60: I3 | B60: I | C60: Analyst estimate changes | D60: Are other analysts raising or cutting their forecasts and targets? | E60: Rising estimates usually support the share price. | F60: Consensus data; broker notes; news | G60: '3 raised targets, 2 cut after results.' | H60: Mostly rising | I60: Mixed | J60: Mostly falling | K60: N | L60: Judgement | O60: =IF(N60="N/A","",IF(N60<>"",VALUE(N60&""),IF(M60="","",M60))) | P60: =IF(N60="N/A","N/A",IF(O60="","To do",IF(O60>=4,"Supports BUY",IF(O60=3,"Neutral",IF(K60="Y","CRITICAL FLAG","Concern"))))) -> To do
A61: I4 | B61: I | C61: Share price trend | D61: Is the share price trending up, sideways or down? | E61: Fighting a strong downtrend is risky; timing matters. | F61: Price chart (1-yr, 200-day average) | G61: 'Down 30% in a year; flat for 3 months.' | H61: Uptrend | I61: Sideways | J61: Downtrend | K61: N | L61: ='7. Technical Review'!$C$50 -> n/a | M61: =IF('7. Technical Review'!$C$50="UPTREND",4,IF('7. Technical Review'!$C$50="SIDEWAYS",3,IF('7. Technical Review'!$C$50="DOWNTREND",2,""))) | O61: =IF(N61="N/A","",IF(N61<>"",VALUE(N61&""),IF(M61="","",M61))) | P61: =IF(N61="N/A","N/A",IF(O61="","To do",IF(O61>=4,"Supports BUY",IF(O61=3,"Neutral",IF(K61="Y","CRITICAL FLAG","Concern"))))) -> To do
A62: I5 | B62: I | C62: Big investors' activity | D62: Are large funds buying or selling? | E62: Big funds have big research teams. | F62: Shareholder register; 13F filings (US); news | G62: 'Active funds mostly selling; some contrarian buying.' | H62: Net buying | I62: Mixed | J62: Net selling | K62: N | L62: Judgement | O62: =IF(N62="N/A","",IF(N62<>"",VALUE(N62&""),IF(M62="","",M62))) | P62: =IF(N62="N/A","N/A",IF(O62="","To do",IF(O62>=4,"Supports BUY",IF(O62=3,"Neutral",IF(K62="Y","CRITICAL FLAG","Concern"))))) -> To do
A63: J. Risks (5 = LOW risk)
A64: J1 | B64: J | C64: Biggest risk to your view | D64: What's the ONE thing most likely to make you wrong, and how bad would it be? | E64: Knowing your key risk tells you what to watch. | F64: Your analysis; risk factors section | G64: 'AI tools cut paid users faster than AI products grow.' | H64: Low impact / unlikely | I64: Moderate | J64: Severe and likely | K64: N | L64: Judgement | O64: =IF(N64="N/A","",IF(N64<>"",VALUE(N64&""),IF(M64="","",M64))) | P64: =IF(N64="N/A","N/A",IF(O64="","To do",IF(O64>=4,"Supports BUY",IF(O64=3,"Neutral",IF(K64="Y","CRITICAL FLAG","Concern"))))) -> To do
A65: J2 | B65: J | C65: Market risk (beta) | D65: How much more than the market does the share move? | E65: High-beta shares fall harder in sell-offs. | F65: Company Info (beta) | G65: 'Beta 1.42 — more volatile than the market.' | H65: Beta ≤1.0 | I65: 1.0–1.3 | J65: ≥1.3 | K65: N | L65: =IF('1. Company Info'!$B$20="","",'1. Company Info'!$B$20) | M65: =IFERROR(IF(OR(L65="",S65="",T65=""),"",IF(((L65-T65)/(S65-T65))>=2,5,IF(((L65-T65)/(S65-T65))>=1,4,IF(((L65-T65)/(S65-T65))>0,3,IF(((L65-T65)/(S65-T65))>-1,2,1))))),"") | O65: =IF(N65="N/A","",IF(N65<>"",VALUE(N65&""),IF(M65="","",M65))) | P65: =IF(N65="N/A","N/A",IF(O65="","To do",IF(O65>=4,"Supports BUY",IF(O65=3,"Neutral",IF(K65="Y","CRITICAL FLAG","Concern"))))) -> To do | S65: 1 | T65: 1.3
A66: J3 | B66: J | C66: Currency & country risk | D66: Is it exposed to exchange rates, one country, or political risk? | E66: A weak or volatile rand, or a single-country exposure, can swamp good operations. | F66: Geographic split; currency note | G66: '60% of revenue offshore — benefits from weak rand.' | H66: Low / natural hedge | I66: Moderate | J66: High, unhedged | K66: N | L66: Judgement | O66: =IF(N66="N/A","",IF(N66<>"",VALUE(N66&""),IF(M66="","",M66))) | P66: =IF(N66="N/A","N/A",IF(O66="","To do",IF(O66>=4,"Supports BUY",IF(O66=3,"Neutral",IF(K66="Y","CRITICAL FLAG","Concern"))))) -> To do
A67: J4 | B67: J | C67: Execution risk | D67: Does the plan depend on a big project, turnaround or acquisition going right? | E67: Big plans often run late and over budget. | F67: Strategy section; capex plans | G67: 'No big projects; organic growth.' | H67: Low | I67: Moderate | J67: High | K67: N | L67: Judgement | O67: =IF(N67="N/A","",IF(N67<>"",VALUE(N67&""),IF(M67="","",M67))) | P67: =IF(N67="N/A","N/A",IF(O67="","To do",IF(O67>=4,"Supports BUY",IF(O67=3,"Neutral",IF(K67="Y","CRITICAL FLAG","Concern"))))) -> To do
A68: J5 | B68: J | C68: Share liquidity | D68: Does the share trade enough to buy and sell easily? (daily value traded) | E68: Illiquid shares are hard to exit in a hurry — common for JSE small caps. | F68: Exchange data; data sites | G68: 'Trades >R50m a day.' | H68: Highly liquid | I68: Adequate | J68: Thinly traded | K68: N | L68: =IF('7. Technical Review'!$C$36="","Judgement",'7. Technical Review'!$C$36) -> Judgement | M68: =IF(NOT(ISNUMBER('7. Technical Review'!$C$36)),"",IF('7. Technical Review'!$C$36<=5,5,IF('7. Technical Review'!$C$36<=20,3,1))) | O68: =IF(N68="N/A","",IF(N68<>"",VALUE(N68&""),IF(M68="","",M68))) | P68: =IF(N68="N/A","N/A",IF(O68="","To do",IF(O68>=4,"Supports BUY",IF(O68=3,"Neutral",IF(K68="Y","CRITICAL FLAG","Concern"))))) -> To do

Sheet 4. Valuation
A1: Step 4 — Valuation: what is the share worth?
A2: Three methods → one blended target price. Yellow = your assumptions (explain each one in the notes column). Money in Financials units; per-share values in the share-price currency.
A4: A. Peer comparison — pick 4 to 6 listed companies that do similar things
A5: Peer company | B5: Forward P/E | C5: EV / EBITDA | D5: Revenue growth | E5: Operating margin | F5: Notes (basis, source, date)
A12: Peer median | B12: =IF(COUNT(B6:B11)=0,"",MEDIAN(B6:B11)) | C12: =IF(COUNT(C6:C11)=0,"",MEDIAN(C6:C11)) | D12: =IF(COUNT(D6:D11)=0,"",MEDIAN(D6:D11)) | E12: =IF(COUNT(E6:E11)=0,"",MEDIAN(E6:E11))
A13: Our company | B13: =IF('1. Company Info'!B33="","",'1. Company Info'!B33) | C13: =IF('1. Company Info'!B34="","",'1. Company Info'!B34) | D13: =IF('2. Financials'!$E$32="","",'2. Financials'!$E$32) | E13: =IF('2. Financials'!$E$34="","",'2. Financials'!$E$34)
A14: Premium / (discount) to peers | B14: =IFERROR(IF(OR(B13="",B12=""),"",B13/B12-1),"") | C14: =IFERROR(IF(OR(C13="",C12=""),"",C13/C12-1),"") | F14: A discount is only an opportunity if growth and margins are as good as peers'. Ask: WHY is it cheaper?
A16: B. Method 1 — Forward P/E (what peers pay for each R1 of profit)
A17: Next-12-month EPS | B17: =IF('1. Company Info'!$B$23="","",'1. Company Info'!$B$23) | F17: From Step 1.
A18: Target P/E multiple | C18: =IF(B12="","","Peer median: "&TEXT(B12,"0.0")&"x") | F18: Start from the peer median, then justify any discount or premium (growth, risk, quality).
A19: Method 1 value per share | B19: =IFERROR(IF(OR(B17="",B18=""),"",B17*B18),"")
A21: C. Method 2 — Discounted cash flow (DCF): value of all future free cash flow
A22: Discount rate (WACC) helper
A23: Risk-free rate | F23: 10-year government bond yield in the company's currency (SA 10-yr for ZAR stocks; US 10-yr Treasury for USD).
A24: Beta | B24: =IF('1. Company Info'!$B$20="","",'1. Company Info'!$B$20) | F24: From Step 1.
A25: Equity risk premium | F25: Extra return investors demand for shares over bonds. Damodaran publishes country estimates.
A26: Cost of equity (CAPM) | B26: =IF(OR(B23="",B24="",B25=""),"",B23+B24*B25) | F26: Risk-free + beta × equity risk premium.
A27: Pre-tax cost of debt | F27: Roughly: interest expense ÷ total debt, or the company's bond yield.
A28: Tax rate | B28: =IF('2. Financials'!$E$28="","",'2. Financials'!$E$28) | F28: From Step 2.
A29: Debt as % of (debt + market cap) | B29: =IFERROR(IF(OR('2. Financials'!$E$20="",'1. Company Info'!B29=""),0,'2. Financials'!$E$20/('2. Financials'!$E$20+'1. Company Info'!B29)),0) -> 0 | F29: Calculated from market values.
A30: WACC (calculated) | B30: =IF(B26="","",(1-B29)*B26+B29*N(B27)*(1-N(B28))) | F30: Weighted average of cost of equity and after-tax cost of debt.
A31: WACC override (optional) | F31: Leave blank to use the calculated WACC. If you override, explain why.
A32: WACC used | B32: =IF(B31<>"",B31,B30)
A33: Terminal growth rate | F33: Long-run growth forever. Keep at or below long-run inflation + real GDP (usually 2–5%). Must be below WACC.
A34: FCF margin assumed | C34: =IF('2. Financials'!$E$39="","","Latest actual: "&TEXT('2. Financials'!$E$39,"0.0%")) | F34: Compare with history (shown in column C). Don't assume a big improvement without a reason.
B36: Latest (actual) | C36: Year 1 | D36: Year 2 | E36: Year 3 | F36: Year 4 | G36: Year 5
A37: Revenue growth assumption
A38: Revenue | B38: =IF('2. Financials'!$E$7="","",'2. Financials'!$E$7) | C38: =IF(OR(B38="",C37=""),"",B38*(1+C37)) | D38: =IF(OR(C38="",D37=""),"",C38*(1+D37)) | E38: =IF(OR(D38="",E37=""),"",D38*(1+E37)) | F38: =IF(OR(E38="",F37=""),"",E38*(1+F37)) | G38: =IF(OR(F38="",G37=""),"",F38*(1+G37))
A39: Free cash flow (revenue × FCF margin) | C39: =IF(OR(C38="",$B$34=""),"",C38*$B$34) | D39: =IF(OR(D38="",$B$34=""),"",D38*$B$34) | E39: =IF(OR(E38="",$B$34=""),"",E38*$B$34) | F39: =IF(OR(F38="",$B$34=""),"",F38*$B$34) | G39: =IF(OR(G38="",$B$34=""),"",G38*$B$34)
A40: Years from today | C40: 1 | D40: 2 | E40: 3 | F40: 4 | G40: 5
A41: Discount factor = 1 ÷ (1+WACC)^years | C41: =IF($B$32="","",1/(1+$B$32)^C40) | D41: =IF($B$32="","",1/(1+$B$32)^D40) | E41: =IF($B$32="","",1/(1+$B$32)^E40) | F41: =IF($B$32="","",1/(1+$B$32)^F40) | G41: =IF($B$32="","",1/(1+$B$32)^G40)
A42: Present value of FCF | C42: =IFERROR(C39*C41,"") | D42: =IFERROR(D39*D41,"") | E42: =IFERROR(E39*E41,"") | F42: =IFERROR(F39*F41,"") | G42: =IFERROR(G39*G41,"")
A44: Sum of present values (years 1–5) | B44: =IF(COUNT(C42:G42)<5,"",SUM(C42:G42))
A45: Terminal value at year 5 | B45: =IFERROR(IF(OR(G39="",B33="",B32="",B32<=B33),"",G39*(1+B33)/(B32-B33)),"") | F45: Year-5 FCF × (1+g) ÷ (WACC − g). The value of everything after year 5.
A46: Present value of terminal value | B46: =IFERROR(B45*G41,"") | F46: Discounted at the YEAR-5 factor (a common error is using a smaller number of years).
A47: Enterprise value | B47: =IFERROR(B44+B46,"")
A48: Less: net debt | B48: =IF('2. Financials'!$E$43="","",'2. Financials'!$E$43) | F48: From Step 2. Use the SAME net debt figure everywhere.
A49: Equity value | B49: =IFERROR(B47-N(B48),"")
A50: Method 2 value per share | B50: =IFERROR(B49/'2. Financials'!$E$15,"") | F50: Equity value (millions) ÷ shares (millions) = value per share.
A51: Terminal value as % of EV | B51: =IFERROR(B46/B47,"") | F51: Above 75% means the answer depends mostly on your long-term guess. Be careful.
A53: D. Method 3 — EV / EBITDA multiple
A54: Next-year EBITDA (latest × (1 + year-1 growth)) | B54: =IFERROR(IF(OR('2. Financials'!$E$36="",C37=""),"",'2. Financials'!$E$36*(1+C37)),"")
A55: Target EV / EBITDA multiple | C55: =IF(C12="","","Peer median: "&TEXT(C12,"0.0")&"x") | F55: Start from peer median; justify adjustments.
A56: Implied enterprise value | B56: =IFERROR(IF(OR(B54="",B55=""),"",B54*B55),"")
A57: Method 3 value per share | B57: =IFERROR(IF(B56="","",(B56-N('2. Financials'!$E$43))/'2. Financials'!$E$15),"")
A59: E. Blended target price
A60: Method | B60: Value per share | C60: vs current price | D60: Weight | E60: Weight used | F60: Contribution
A61: 1. Forward P/E | B61: =B19 | C61: =IFERROR(IF(OR(B61="",'1. Company Info'!$B$16=""),"",B61/'1. Company Info'!$B$16-1),"") | D61: 0.4 | E61: =IF(ISNUMBER(B61),D61,0) -> 0 | F61: =IF(ISNUMBER(B61),B61*D61,0) -> 0
A62: 2. DCF | B62: =B50 | C62: =IFERROR(IF(OR(B62="",'1. Company Info'!$B$16=""),"",B62/'1. Company Info'!$B$16-1),"") | D62: 0.3 | E62: =IF(ISNUMBER(B62),D62,0) -> 0 | F62: =IF(ISNUMBER(B62),B62*D62,0) -> 0
A63: 3. EV / EBITDA | B63: =B57 | C63: =IFERROR(IF(OR(B63="",'1. Company Info'!$B$16=""),"",B63/'1. Company Info'!$B$16-1),"") | D63: 0.3 | E63: =IF(ISNUMBER(B63),D63,0) -> 0 | F63: =IF(ISNUMBER(B63),B63*D63,0) -> 0
A64: BLENDED TARGET PRICE | B64: =IF(SUM(E61:E63)=0,"",SUM(F61:F63)/SUM(E61:E63)) | C64: =IFERROR(IF(OR(B64="",'1. Company Info'!$B$16=""),"",B64/'1. Company Info'!$B$16-1),"") | D64: =SUM(D61:D63) -> 1 | F64: If a method is blank, its weight is shared among the others.
A65: Why these weights? (one sentence)
A67: F. Scenarios — what if you're wrong?
A68: Scenario | B68: Price | C68: vs current | D68: Probability | E68: What has to happen (write it)
A69: Bear (things go wrong) | C69: =IFERROR(IF(OR(B69="",'1. Company Info'!$B$16=""),"",B69/'1. Company Info'!$B$16-1),"") | D69: 0.25
A70: Base (blended target) | B70: =B64 | C70: =IFERROR(IF(OR(B70="",'1. Company Info'!$B$16=""),"",B70/'1. Company Info'!$B$16-1),"") | D70: 0.5
A71: Bull (things go right) | C71: =IFERROR(IF(OR(B71="",'1. Company Info'!$B$16=""),"",B71/'1. Company Info'!$B$16-1),"") | D71: 0.25
A72: Probability-weighted value | B72: =IFERROR(IF(COUNT(B69:B71)<3,"",SUMPRODUCT(B69:B71,D69:D71)),"") | C72: =IFERROR(B72/'1. Company Info'!$B$16-1,"") | D72: =SUM(D69:D71) -> 1
A73: Upside ÷ downside (bull gain ÷ bear loss) | B73: =IFERROR(IF(OR(C69="",C71="",C69>=0),"",C71/ABS(C69)),"") | E73: 2x or more = you can make twice what you could lose. Good risk/reward.
A75: G. DCF sensitivity — value per share if WACC (down) or terminal growth (across) is different
A76: WACC ↓ / growth → | B76: =IF($B$33="","",$B$33+-0.01) | C76: =IF($B$33="","",$B$33+-0.005) | D76: =IF($B$33="","",$B$33+0) | E76: =IF($B$33="","",$B$33+0.005) | F76: =IF($B$33="","",$B$33+0.01)
A77: =IF($B$32="","",$B$32+-0.02) | B77: =IFERROR(IF($A77<=B$76,"",(SUMPRODUCT($C$39:$G$39/(1+$A77)^$C$40:$G$40)+$G$39*(1+B$76)/($A77-B$76)/(1+$A77)^5-N('2. Financials'!$E$43))/'2. Financials'!$E$15),"") | C77: =IFERROR(IF($A77<=C$76,"",(SUMPRODUCT($C$39:$G$39/(1+$A77)^$C$40:$G$40)+$G$39*(1+C$76)/($A77-C$76)/(1+$A77)^5-N('2. Financials'!$E$43))/'2. Financials'!$E$15),"") | D77: =IFERROR(IF($A77<=D$76,"",(SUMPRODUCT($C$39:$G$39/(1+$A77)^$C$40:$G$40)+$G$39*(1+D$76)/($A77-D$76)/(1+$A77)^5-N('2. Financials'!$E$43))/'2. Financials'!$E$15),"") | E77: =IFERROR(IF($A77<=E$76,"",(SUMPRODUCT($C$39:$G$39/(1+$A77)^$C$40:$G$40)+$G$39*(1+E$76)/($A77-E$76)/(1+$A77)^5-N('2. Financials'!$E$43))/'2. Financials'!$E$15),"") | F77: =IFERROR(IF($A77<=F$76,"",(SUMPRODUCT($C$39:$G$39/(1+$A77)^$C$40:$G$40)+$G$39*(1+F$76)/($A77-F$76)/(1+$A77)^5-N('2. Financials'!$E$43))/'2. Financials'!$E$15),"")
A78: =IF($B$32="","",$B$32+-0.01) | B78: =IFERROR(IF($A78<=B$76,"",(SUMPRODUCT($C$39:$G$39/(1+$A78)^$C$40:$G$40)+$G$39*(1+B$76)/($A78-B$76)/(1+$A78)^5-N('2. Financials'!$E$43))/'2. Financials'!$E$15),"") | C78: =IFERROR(IF($A78<=C$76,"",(SUMPRODUCT($C$39:$G$39/(1+$A78)^$C$40:$G$40)+$G$39*(1+C$76)/($A78-C$76)/(1+$A78)^5-N('2. Financials'!$E$43))/'2. Financials'!$E$15),"") | D78: =IFERROR(IF($A78<=D$76,"",(SUMPRODUCT($C$39:$G$39/(1+$A78)^$C$40:$G$40)+$G$39*(1+D$76)/($A78-D$76)/(1+$A78)^5-N('2. Financials'!$E$43))/'2. Financials'!$E$15),"") | E78: =IFERROR(IF($A78<=E$76,"",(SUMPRODUCT($C$39:$G$39/(1+$A78)^$C$40:$G$40)+$G$39*(1+E$76)/($A78-E$76)/(1+$A78)^5-N('2. Financials'!$E$43))/'2. Financials'!$E$15),"") | F78: =IFERROR(IF($A78<=F$76,"",(SUMPRODUCT($C$39:$G$39/(1+$A78)^$C$40:$G$40)+$G$39*(1+F$76)/($A78-F$76)/(1+$A78)^5-N('2. Financials'!$E$43))/'2. Financials'!$E$15),"")
A79: =IF($B$32="","",$B$32+0) | B79: =IFERROR(IF($A79<=B$76,"",(SUMPRODUCT($C$39:$G$39/(1+$A79)^$C$40:$G$40)+$G$39*(1+B$76)/($A79-B$76)/(1+$A79)^5-N('2. Financials'!$E$43))/'2. Financials'!$E$15),"") | C79: =IFERROR(IF($A79<=C$76,"",(SUMPRODUCT($C$39:$G$39/(1+$A79)^$C$40:$G$40)+$G$39*(1+C$76)/($A79-C$76)/(1+$A79)^5-N('2. Financials'!$E$43))/'2. Financials'!$E$15),"") | D79: =IFERROR(IF($A79<=D$76,"",(SUMPRODUCT($C$39:$G$39/(1+$A79)^$C$40:$G$40)+$G$39*(1+D$76)/($A79-D$76)/(1+$A79)^5-N('2. Financials'!$E$43))/'2. Financials'!$E$15),"") | E79: =IFERROR(IF($A79<=E$76,"",(SUMPRODUCT($C$39:$G$39/(1+$A79)^$C$40:$G$40)+$G$39*(1+E$76)/($A79-E$76)/(1+$A79)^5-N('2. Financials'!$E$43))/'2. Financials'!$E$15),"") | F79: =IFERROR(IF($A79<=F$76,"",(SUMPRODUCT($C$39:$G$39/(1+$A79)^$C$40:$G$40)+$G$39*(1+F$76)/($A79-F$76)/(1+$A79)^5-N('2. Financials'!$E$43))/'2. Financials'!$E$15),"")
A80: =IF($B$32="","",$B$32+0.01) | B80: =IFERROR(IF($A80<=B$76,"",(SUMPRODUCT($C$39:$G$39/(1+$A80)^$C$40:$G$40)+$G$39*(1+B$76)/($A80-B$76)/(1+$A80)^5-N('2. Financials'!$E$43))/'2. Financials'!$E$15),"") | C80: =IFERROR(IF($A80<=C$76,"",(SUMPRODUCT($C$39:$G$39/(1+$A80)^$C$40:$G$40)+$G$39*(1+C$76)/($A80-C$76)/(1+$A80)^5-N('2. Financials'!$E$43))/'2. Financials'!$E$15),"") | D80: =IFERROR(IF($A80<=D$76,"",(SUMPRODUCT($C$39:$G$39/(1+$A80)^$C$40:$G$40)+$G$39*(1+D$76)/($A80-D$76)/(1+$A80)^5-N('2. Financials'!$E$43))/'2. Financials'!$E$15),"") | E80: =IFERROR(IF($A80<=E$76,"",(SUMPRODUCT($C$39:$G$39/(1+$A80)^$C$40:$G$40)+$G$39*(1+E$76)/($A80-E$76)/(1+$A80)^5-N('2. Financials'!$E$43))/'2. Financials'!$E$15),"") | F80: =IFERROR(IF($A80<=F$76,"",(SUMPRODUCT($C$39:$G$39/(1+$A80)^$C$40:$G$40)+$G$39*(1+F$76)/($A80-F$76)/(1+$A80)^5-N('2. Financials'!$E$43))/'2. Financials'!$E$15),"")
A81: =IF($B$32="","",$B$32+0.02) | B81: =IFERROR(IF($A81<=B$76,"",(SUMPRODUCT($C$39:$G$39/(1+$A81)^$C$40:$G$40)+$G$39*(1+B$76)/($A81-B$76)/(1+$A81)^5-N('2. Financials'!$E$43))/'2. Financials'!$E$15),"") | C81: =IFERROR(IF($A81<=C$76,"",(SUMPRODUCT($C$39:$G$39/(1+$A81)^$C$40:$G$40)+$G$39*(1+C$76)/($A81-C$76)/(1+$A81)^5-N('2. Financials'!$E$43))/'2. Financials'!$E$15),"") | D81: =IFERROR(IF($A81<=D$76,"",(SUMPRODUCT($C$39:$G$39/(1+$A81)^$C$40:$G$40)+$G$39*(1+D$76)/($A81-D$76)/(1+$A81)^5-N('2. Financials'!$E$43))/'2. Financials'!$E$15),"") | E81: =IFERROR(IF($A81<=E$76,"",(SUMPRODUCT($C$39:$G$39/(1+$A81)^$C$40:$G$40)+$G$39*(1+E$76)/($A81-E$76)/(1+$A81)^5-N('2. Financials'!$E$43))/'2. Financials'!$E$15),"") | F81: =IFERROR(IF($A81<=F$76,"",(SUMPRODUCT($C$39:$G$39/(1+$A81)^$C$40:$G$40)+$G$39*(1+F$76)/($A81-F$76)/(1+$A81)^5-N('2. Financials'!$E$43))/'2. Financials'!$E$15),"")
A82: Green = above today's price, red = below. If most cells are green, your upside doesn't depend on one lucky assumption.
A84: H. Valuation sanity checks — fix every FLAG before you submit
A85: Check | B85: Result | F85: Why it matters
A86: Method weights add up to 100% | B86: =IF(ABS(D64-1)<0.001,"OK","FLAG") -> OK | F86: Weights must total 100%.
A87: WACC is higher than terminal growth | B87: =IF(OR(B32="",B33=""),"-",IF(B32>B33,"OK","FLAG")) -> - | F87: Otherwise the DCF formula breaks (infinite value).
A88: Terminal value ≤ 75% of EV | B88: =IF(B51="","-",IF(B51<=0.75,"OK","FLAG")) -> - | F88: Otherwise value depends mostly on far-future guesses.
A89: Terminal growth ≤ 5% | B89: =IF(B33="","-",IF(B33<=0.05,"OK","FLAG")) -> - | F89: No company grows faster than the economy forever.
A90: FCF margin within 10 points of latest actual | B90: =IF(OR(B34="",'2. Financials'!$E$39=""),"-",IF(ABS(B34-'2. Financials'!$E$39)<=0.1,"OK","FLAG")) -> - | F90: Big jumps need a clear reason.
A91: Market cap matches published figure | B91: =IF(LEFT('1. Company Info'!B30,2)="OK","OK",IF(LEFT('1. Company Info'!B30,5)="Enter","-","FLAG")) -> - | F91: Catches cents-vs-Rand and millions-vs-billions mistakes.
A92: Price is less than 7 days old | B92: =IF('1. Company Info'!B39="","-",IF('1. Company Info'!B39<=7,"OK","FLAG")) -> - | F92: Upside is meaningless with a stale price.
A93: Target within ±50% of consensus target | B93: =IF(OR(B64="",'1. Company Info'!$B$24=""),"-",IF(ABS(B64/'1. Company Info'!$B$24-1)<=0.5,"OK","FLAG")) -> - | F93: Not wrong if outside — but you must explain why you differ so much.
A94: Peers compared on the same basis (all forward) | B94: ="CHECK" -> CHECK | F94: Don't mix trailing and forward multiples. Tick when done.

Sheet 5. Rating Summary
A1: Step 5 — Rating Summary: BUY / HOLD / SELL
A2: Calculated from your checklist scores and target price. Then write your thesis in your own words.
A4: Company | C4: =IF('1. Company Info'!$B$6="","(enter in Step 1)",'1. Company Info'!$B$6&" ("&'1. Company Info'!$B$7&")") -> (enter in Step 1)
A5: Analyst / reviewer | C5: ='1. Company Info'!$B$12&" / "&'1. Company Info'!$B$13 -> /
A7: Section scores
A8: Code | B8: Section | C8: Weight | D8: Items | E8: Scored | F8: N/A | G8: Average (1–5) | H8: Weighted
A9: A | B9: A. Understand the business | C9: 0.1 | D9: =COUNTIF('3. Checklist'!$B$5:$B$68,A9) -> 6 | E9: =COUNTIFS('3. Checklist'!$B$5:$B$68,A9,'3. Checklist'!$O$5:$O$68,">=1") -> 0 | F9: =COUNTIFS('3. Checklist'!$B$5:$B$68,A9,'3. Checklist'!$N$5:$N$68,"N/A") -> 0 | G9: =IF(E9=0,"",AVERAGEIF('3. Checklist'!$B$5:$B$68,A9,'3. Checklist'!$O$5:$O$68)) | H9: =IF(G9="","",C9*G9)
A10: B | B10: B. Industry & competition | C10: 0.1 | D10: =COUNTIF('3. Checklist'!$B$5:$B$68,A10) -> 5 | E10: =COUNTIFS('3. Checklist'!$B$5:$B$68,A10,'3. Checklist'!$O$5:$O$68,">=1") -> 0 | F10: =COUNTIFS('3. Checklist'!$B$5:$B$68,A10,'3. Checklist'!$N$5:$N$68,"N/A") -> 0 | G10: =IF(E10=0,"",AVERAGEIF('3. Checklist'!$B$5:$B$68,A10,'3. Checklist'!$O$5:$O$68)) | H10: =IF(G10="","",C10*G10)
A11: C | B11: C. Growth | C11: 0.12 | D11: =COUNTIF('3. Checklist'!$B$5:$B$68,A11) -> 5 | E11: =COUNTIFS('3. Checklist'!$B$5:$B$68,A11,'3. Checklist'!$O$5:$O$68,">=1") -> 0 | F11: =COUNTIFS('3. Checklist'!$B$5:$B$68,A11,'3. Checklist'!$N$5:$N$68,"N/A") -> 0 | G11: =IF(E11=0,"",AVERAGEIF('3. Checklist'!$B$5:$B$68,A11,'3. Checklist'!$O$5:$O$68)) | H11: =IF(G11="","",C11*G11)
A12: D | B12: D. Profitability | C12: 0.12 | D12: =COUNTIF('3. Checklist'!$B$5:$B$68,A12) -> 6 | E12: =COUNTIFS('3. Checklist'!$B$5:$B$68,A12,'3. Checklist'!$O$5:$O$68,">=1") -> 0 | F12: =COUNTIFS('3. Checklist'!$B$5:$B$68,A12,'3. Checklist'!$N$5:$N$68,"N/A") -> 0 | G12: =IF(E12=0,"",AVERAGEIF('3. Checklist'!$B$5:$B$68,A12,'3. Checklist'!$O$5:$O$68)) | H12: =IF(G12="","",C12*G12)
A13: E | B13: E. Cash flow | C13: 0.1 | D13: =COUNTIF('3. Checklist'!$B$5:$B$68,A13) -> 4 | E13: =COUNTIFS('3. Checklist'!$B$5:$B$68,A13,'3. Checklist'!$O$5:$O$68,">=1") -> 0 | F13: =COUNTIFS('3. Checklist'!$B$5:$B$68,A13,'3. Checklist'!$N$5:$N$68,"N/A") -> 0 | G13: =IF(E13=0,"",AVERAGEIF('3. Checklist'!$B$5:$B$68,A13,'3. Checklist'!$O$5:$O$68)) | H13: =IF(G13="","",C13*G13)
A14: F | B14: F. Balance sheet & capital allocation | C14: 0.1 | D14: =COUNTIF('3. Checklist'!$B$5:$B$68,A14) -> 6 | E14: =COUNTIFS('3. Checklist'!$B$5:$B$68,A14,'3. Checklist'!$O$5:$O$68,">=1") -> 0 | F14: =COUNTIFS('3. Checklist'!$B$5:$B$68,A14,'3. Checklist'!$N$5:$N$68,"N/A") -> 0 | G14: =IF(E14=0,"",AVERAGEIF('3. Checklist'!$B$5:$B$68,A14,'3. Checklist'!$O$5:$O$68)) | H14: =IF(G14="","",C14*G14)
A15: G | B15: G. Management & governance | C15: 0.08 | D15: =COUNTIF('3. Checklist'!$B$5:$B$68,A15) -> 6 | E15: =COUNTIFS('3. Checklist'!$B$5:$B$68,A15,'3. Checklist'!$O$5:$O$68,">=1") -> 0 | F15: =COUNTIFS('3. Checklist'!$B$5:$B$68,A15,'3. Checklist'!$N$5:$N$68,"N/A") -> 0 | G15: =IF(E15=0,"",AVERAGEIF('3. Checklist'!$B$5:$B$68,A15,'3. Checklist'!$O$5:$O$68)) | H15: =IF(G15="","",C15*G15)
A16: H | B16: H. Valuation | C16: 0.15 | D16: =COUNTIF('3. Checklist'!$B$5:$B$68,A16) -> 6 | E16: =COUNTIFS('3. Checklist'!$B$5:$B$68,A16,'3. Checklist'!$O$5:$O$68,">=1") -> 0 | F16: =COUNTIFS('3. Checklist'!$B$5:$B$68,A16,'3. Checklist'!$N$5:$N$68,"N/A") -> 0 | G16: =IF(E16=0,"",AVERAGEIF('3. Checklist'!$B$5:$B$68,A16,'3. Checklist'!$O$5:$O$68)) | H16: =IF(G16="","",C16*G16)
A17: I | B17: I. Catalysts & market view | C17: 0.05 | D17: =COUNTIF('3. Checklist'!$B$5:$B$68,A17) -> 5 | E17: =COUNTIFS('3. Checklist'!$B$5:$B$68,A17,'3. Checklist'!$O$5:$O$68,">=1") -> 0 | F17: =COUNTIFS('3. Checklist'!$B$5:$B$68,A17,'3. Checklist'!$N$5:$N$68,"N/A") -> 0 | G17: =IF(E17=0,"",AVERAGEIF('3. Checklist'!$B$5:$B$68,A17,'3. Checklist'!$O$5:$O$68)) | H17: =IF(G17="","",C17*G17)
A18: J | B18: J. Risks (5 = LOW risk) | C18: 0.08 | D18: =COUNTIF('3. Checklist'!$B$5:$B$68,A18) -> 5 | E18: =COUNTIFS('3. Checklist'!$B$5:$B$68,A18,'3. Checklist'!$O$5:$O$68,">=1") -> 0 | F18: =COUNTIFS('3. Checklist'!$B$5:$B$68,A18,'3. Checklist'!$N$5:$N$68,"N/A") -> 0 | G18: =IF(E18=0,"",AVERAGEIF('3. Checklist'!$B$5:$B$68,A18,'3. Checklist'!$O$5:$O$68)) | H18: =IF(G18="","",C18*G18)
B19: Total | C19: =SUM(C9:C18) -> 1 | D19: =SUM(D9:D18) -> 54 | E19: =SUM(E9:E18) -> 0 | F19: =SUM(F9:F18) -> 0
A21: Rating rules (set by the senior analyst — don't change without approval)
A22: BUY needs upside of at least | C22: 0.15
A23: …AND an overall score of at least | C23: 3.5
A24: SELL if downside is | C24: -0.1
A25: …OR the overall score is below | C25: 2.5
A26: A critical item (B3, F1, G2, G4) scored this or lower blocks a BUY | C26: 2
A27: Share of items you must score before a rating appears | C27: 0.8
A29: Result
A30: Current share price | C30: =IF('1. Company Info'!$B$16="","",'1. Company Info'!$B$16)
A31: Blended target price | C31: =IF('4. Valuation'!$B$64="","",'4. Valuation'!$B$64)
A32: Upside / (downside) | C32: =IFERROR(IF(OR(C31="",C30=""),"",C31/C30-1),"")
A33: Probability-weighted value | C33: =IF('4. Valuation'!$B$72="","",'4. Valuation'!$B$72)
A34: Overall score (1–5) | C34: =IFERROR(SUM(H9:H18)/SUMIF(E9:E18,">0",C9:C18),"")
A35: Critical items at or below the threshold | C35: =COUNTIFS('3. Checklist'!$K$5:$K$68,"Y",'3. Checklist'!$O$5:$O$68,"<="&C26) -> 0
A36: Checklist progress | C36: =IFERROR(E19/(D19-F19),0) -> 0
A37: RATING | C37: =IF(OR(C36<C27,C32="",C34=""),"INCOMPLETE",IF(OR(C32<=C24,C34<C25),"SELL",IF(AND(C32>=C22,C34>=C23,C35=0),"BUY","HOLD"))) -> INCOMPLETE
A38: Conviction | C38: =IF(C37="INCOMPLETE","-",IF(AND(C34>=4,ABS(C32)>=0.25),"High",IF(C34>=3.25,"Medium","Low"))) -> -
A39: Why this rating | C39: =IF(C37="INCOMPLETE",IF(C36<C27,"Score more items: "&TEXT(C36,"0%")&" done, need "&TEXT(C27,"0%"),"Finish the valuation (target price) and checklist"),IF(C37="BUY","Upside and quality both clear the bar, no critical flags",IF(C37="SELL",IF(C32<=C24,"Share looks overvalued","Quality score too low"),IF(C35>0,"Upside may be there, but "&C35&" critical item(s) flagged",IF(C32<C22,"Not enough upside for a BUY","Quality score below the BUY bar"))))) -> Score more items: 0% done, need 80%
A41: Write it up — in your own words
A42: My investment thesis (3 sentences)
A43: Top 3 reasons for the rating
A44: Top 3 risks
A45: What would make me change my mind?
A46: What I'm unsure about / need help with
A47: Override? (only with reviewer approval)
A49: Sign-off
B50: Name | C50: Date | D50: Comments
A51: Prepared by (analyst)
A52: Reviewed by (senior analyst)
A53: Approved (portfolio manager / IC)

Sheet 6. Fundamentals Scorecard
A1: Fundamentals Scorecard — one-page ratio check
A2: Every ratio fills in automatically from Steps 1, 2 and 4. GREAT / OK / WEAK flags compare each value with the limits in columns G–H (editable, blue). Use the Override column only to correct a distorted value — and say why.
A4: Company | B4: =IF('1. Company Info'!$B$6="","(enter in Step 1)",'1. Company Info'!$B$6&" ("&'1. Company Info'!$B$7&")") -> (enter in Step 1) | F4: GREAT | G4: =COUNTIF(I9:I38,"GREAT") -> 0 | H4: Health score | I4: =IFERROR((2*G4+G5)/(2*(G4+G5+G6)),"") | J4: Health score = (2 × GREAT + 1 × OK) ÷ (2 × ratios assessed). STRONG ≥ 70%, MIXED 45–70%, WEAK < 45%.
A5: Price / date | B5: =IF('1. Company Info'!$B$16="","",TEXT('1. Company Info'!$B$16,"#,##0.00")&" on "&TEXT('1. Company Info'!$B$17,"dd mmm yyyy")) | F5: OK | G5: =COUNTIF(I9:I38,"OK") -> 0 | H5: Verdict | I5: =IF(G4+G5+G6<10,"Not enough data",IF(I4>=0.7,"STRONG",IF(I4>=0.45,"MIXED","WEAK"))) -> Not enough data | J5: This is a screen, not a rating — the BUY / HOLD / SELL call is on Step 5.
A6: Currency / units | B6: ='1. Company Info'!$B$10&" / "&'1. Company Info'!$B$11 -> / | F6: WEAK | G6: =COUNTIF(I9:I38,"WEAK") -> 0 | H6: Ratios assessed | I6: =G4+G5+G6&" of 30" -> 0 of 30 | J6: ="Checklist rating: "&'5. Rating Summary'!C37 -> Checklist rating: INCOMPLETE
A8: Category | B8: Ratio | C8: How it's calculated | D8: Value | E8: Override | F8: Better if | G8: GREAT if | H8: WEAK if | I8: Flag | J8: What it tells you
A9: Valuation | B9: Forward P/E | C9: Price ÷ next-12-month EPS | D9: =IF(E9<>"",E9,IF('1. Company Info'!$B$33="","",'1. Company Info'!$B$33)) | F9: Lower | G9: 15 | H9: 25 | I9: =IF(NOT(ISNUMBER(D9)),"n/a",IF(D9<=G9,"GREAT",IF(D9>=H9,"WEAK","OK"))) -> n/a | J9: Years of next year's profit you pay. Lower = cheaper (compare with peers).
B10: Trailing P/E | C10: Price ÷ last 12 months' EPS | D10: =IF(E10<>"",E10,IF('1. Company Info'!$B$32="","",'1. Company Info'!$B$32)) | F10: Lower | G10: 15 | H10: 25 | I10: =IF(NOT(ISNUMBER(D10)),"n/a",IF(D10<=G10,"GREAT",IF(D10>=H10,"WEAK","OK"))) -> n/a | J10: Same, on actual (not forecast) earnings.
B11: PEG ratio | C11: Forward P/E ÷ 3-yr EPS growth (%) | D11: =IF(E11<>"",E11,IFERROR(IF(OR('1. Company Info'!$B$33="",'2. Financials'!$E$54="",N('2. Financials'!$E$54)<=0),"",'1. Company Info'!$B$33/('2. Financials'!$E$54*100)),"")) | F11: Lower | G11: 1 | H11: 2 | I11: =IF(NOT(ISNUMBER(D11)),"n/a",IF(D11<=G11,"GREAT",IF(D11>=H11,"WEAK","OK"))) -> n/a | J11: P/E adjusted for growth. Below 1 = paying little for the growth.
B12: EV / EBITDA | C12: Enterprise value ÷ EBITDA | D12: =IF(E12<>"",E12,IF('1. Company Info'!$B$34="","",'1. Company Info'!$B$34)) | F12: Lower | G12: 10 | H12: 15 | I12: =IF(NOT(ISNUMBER(D12)),"n/a",IF(D12<=G12,"GREAT",IF(D12>=H12,"WEAK","OK"))) -> n/a | J12: Valuation including debt. Good for comparing companies with different debt.
B13: Price / book | C13: Market cap ÷ shareholders' equity | D13: =IF(E13<>"",E13,IF('1. Company Info'!$B$37="","",'1. Company Info'!$B$37)) | F13: Lower | G13: 1.5 | H13: 5 | I13: =IF(NOT(ISNUMBER(D13)),"n/a",IF(D13<=G13,"GREAT",IF(D13>=H13,"WEAK","OK"))) -> n/a | J13: Key for banks/insurers. Less useful for software (buybacks shrink equity).
B14: FCF yield | C14: Free cash flow ÷ market cap | D14: =IF(E14<>"",E14,IF('1. Company Info'!$B$35="","",'1. Company Info'!$B$35)) | F14: Higher | G14: 0.06 | H14: 0.03 | I14: =IF(NOT(ISNUMBER(D14)),"n/a",IF(D14>=G14,"GREAT",IF(D14<=H14,"WEAK","OK"))) -> n/a | J14: The cash 'interest rate' the business earns on its price.
B15: Earnings yield − bond yield | C15: (1 ÷ forward P/E) − risk-free rate | D15: =IF(E15<>"",E15,IFERROR(IF(OR('1. Company Info'!$B$33="",'4. Valuation'!$B$23=""),"",1/'1. Company Info'!$B$33-'4. Valuation'!$B$23),"")) | F15: Higher | G15: 0.03 | H15: 0 | I15: =IF(NOT(ISNUMBER(D15)),"n/a",IF(D15>=G15,"GREAT",IF(D15<=H15,"WEAK","OK"))) -> n/a | J15: Extra return over a government bond. Negative = bonds pay more than the shares earn.
B16: Upside to target price | C16: Blended target ÷ price − 1 | D16: =IF(E16<>"",E16,'4. Valuation'!$C$64) | F16: Higher | G16: 0.15 | H16: -0.1 | I16: =IF(NOT(ISNUMBER(D16)),"n/a",IF(D16>=G16,"GREAT",IF(D16<=H16,"WEAK","OK"))) -> n/a | J16: From Step 4. Drives the rating.
A17: Growth | B17: Revenue growth (y/y) | C17: Latest revenue ÷ prior year − 1 | D17: =IF(E17<>"",E17,IF('2. Financials'!$E$32="","",'2. Financials'!$E$32)) | F17: Higher | G17: 0.1 | H17: 0 | I17: =IF(NOT(ISNUMBER(D17)),"n/a",IF(D17>=G17,"GREAT",IF(D17<=H17,"WEAK","OK"))) -> n/a | J17: How fast sales grow. Compare with inflation and peers.
B18: Revenue growth, 3-yr CAGR | C18: (Latest ÷ 3 years ago)^(1/3) − 1 | D18: =IF(E18<>"",E18,IF('2. Financials'!$E$53="","",'2. Financials'!$E$53)) | F18: Higher | G18: 0.08 | H18: 0 | I18: =IF(NOT(ISNUMBER(D18)),"n/a",IF(D18>=G18,"GREAT",IF(D18<=H18,"WEAK","OK"))) -> n/a | J18: Smooths out one-off years.
B19: EPS growth (y/y) | C19: Latest EPS ÷ prior year − 1 | D19: =IF(E19<>"",E19,IF('2. Financials'!$E$37="","",'2. Financials'!$E$37)) | F19: Higher | G19: 0.1 | H19: 0 | I19: =IF(NOT(ISNUMBER(D19)),"n/a",IF(D19>=G19,"GREAT",IF(D19<=H19,"WEAK","OK"))) -> n/a | J19: Growth in profit per share.
B20: EPS growth, 3-yr CAGR | C20: (Latest ÷ 3 years ago)^(1/3) − 1 | D20: =IF(E20<>"",E20,IF('2. Financials'!$E$54="","",'2. Financials'!$E$54)) | F20: Higher | G20: 0.1 | H20: 0 | I20: =IF(NOT(ISNUMBER(D20)),"n/a",IF(D20>=G20,"GREAT",IF(D20<=H20,"WEAK","OK"))) -> n/a
A21: Profitability | B21: Gross margin | C21: Gross profit ÷ revenue | D21: =IF(E21<>"",E21,IF('2. Financials'!$E$33="","",'2. Financials'!$E$33)) | F21: Higher | G21: 0.4 | H21: 0.2 | I21: =IF(NOT(ISNUMBER(D21)),"n/a",IF(D21>=G21,"GREAT",IF(D21<=H21,"WEAK","OK"))) -> n/a | J21: Pricing power. Industry-dependent: retail ~25% is normal.
B22: Operating margin | C22: Operating profit ÷ revenue | D22: =IF(E22<>"",E22,IF('2. Financials'!$E$34="","",'2. Financials'!$E$34)) | F22: Higher | G22: 0.15 | H22: 0.05 | I22: =IF(NOT(ISNUMBER(D22)),"n/a",IF(D22>=G22,"GREAT",IF(D22<=H22,"WEAK","OK"))) -> n/a | J22: Efficiency of the whole business.
B23: Net margin | C23: Net income ÷ revenue | D23: =IF(E23<>"",E23,IF('2. Financials'!$E$35="","",'2. Financials'!$E$35)) | F23: Higher | G23: 0.1 | H23: 0.03 | I23: =IF(NOT(ISNUMBER(D23)),"n/a",IF(D23>=G23,"GREAT",IF(D23<=H23,"WEAK","OK"))) -> n/a | J23: Bottom-line profit per R1 of sales.
B24: Return on equity (ROE) | C24: Net income ÷ equity | D24: =IF(E24<>"",E24,IF('2. Financials'!$E$47="","",'2. Financials'!$E$47)) | F24: Higher | G24: 0.15 | H24: 0.08 | I24: =IF(NOT(ISNUMBER(D24)),"n/a",IF(D24>=G24,"GREAT",IF(D24<=H24,"WEAK","OK"))) -> n/a | J24: Check it isn't driven by high debt.
B25: Return on invested capital (ROIC) | C25: EBIT × (1 − tax) ÷ (debt + equity − cash) | D25: =IF(E25<>"",E25,IF('2. Financials'!$E$48="","",'2. Financials'!$E$48)) | F25: Higher | G25: 0.12 | H25: 0.06 | I25: =IF(NOT(ISNUMBER(D25)),"n/a",IF(D25>=G25,"GREAT",IF(D25<=H25,"WEAK","OK"))) -> n/a | J25: The best single measure of business quality.
B26: ROIC − WACC spread | C26: ROIC minus cost of capital | D26: =IF(E26<>"",E26,IFERROR(IF(OR('2. Financials'!$E$48="",'4. Valuation'!$B$32=""),"",'2. Financials'!$E$48-'4. Valuation'!$B$32),"")) | F26: Higher | G26: 0.05 | H26: 0 | I26: =IF(NOT(ISNUMBER(D26)),"n/a",IF(D26>=G26,"GREAT",IF(D26<=H26,"WEAK","OK"))) -> n/a | J26: Positive = creates value as it grows. Negative = growth destroys value.
A27: Cash flow | B27: FCF margin | C27: Free cash flow ÷ revenue | D27: =IF(E27<>"",E27,IF('2. Financials'!$E$39="","",'2. Financials'!$E$39)) | F27: Higher | G27: 0.1 | H27: 0.02 | I27: =IF(NOT(ISNUMBER(D27)),"n/a",IF(D27>=G27,"GREAT",IF(D27<=H27,"WEAK","OK"))) -> n/a | J27: Share of sales that becomes free cash.
B28: Cash conversion | C28: Free cash flow ÷ net income | D28: =IF(E28<>"",E28,IF('2. Financials'!$E$40="","",'2. Financials'!$E$40)) | F28: Higher | G28: 1 | H28: 0.7 | I28: =IF(NOT(ISNUMBER(D28)),"n/a",IF(D28>=G28,"GREAT",IF(D28<=H28,"WEAK","OK"))) -> n/a | J28: Is profit real cash? Low for years = red flag.
B29: Capex intensity | C29: Capex ÷ revenue | D29: =IF(E29<>"",E29,IF('2. Financials'!$E$41="","",'2. Financials'!$E$41)) | F29: Lower | G29: 0.05 | H29: 0.15 | I29: =IF(NOT(ISNUMBER(D29)),"n/a",IF(D29<=G29,"GREAT",IF(D29>=H29,"WEAK","OK"))) -> n/a | J29: Reinvestment needed to stand still.
B30: Share-based pay | C30: Stock comp ÷ revenue | D30: =IF(E30<>"",E30,IF('2. Financials'!$E$42="","",'2. Financials'!$E$42)) | F30: Lower | G30: 0.02 | H30: 0.08 | I30: =IF(NOT(ISNUMBER(D30)),"n/a",IF(D30<=G30,"GREAT",IF(D30>=H30,"WEAK","OK"))) -> n/a | J30: A real cost paid in shares (dilution).
A31: Balance sheet | B31: Net debt ÷ EBITDA | C31: (Debt − cash) ÷ EBITDA | D31: =IF(E31<>"",E31,IF('2. Financials'!$E$44="","",'2. Financials'!$E$44)) | F31: Lower | G31: 1 | H31: 3 | I31: =IF(NOT(ISNUMBER(D31)),"n/a",IF(D31<=G31,"GREAT",IF(D31>=H31,"WEAK","OK"))) -> n/a | J31: Years of EBITDA to repay debt. Negative = net cash.
B32: Debt ÷ equity | C32: Total debt ÷ equity | D32: =IF(E32<>"",E32,IFERROR(IF(OR('2. Financials'!$E$20="",'2. Financials'!$E$21="",N('2. Financials'!$E$21)<=0),"",'2. Financials'!$E$20/'2. Financials'!$E$21),"")) | F32: Lower | G32: 0.5 | H32: 1.5 | I32: =IF(NOT(ISNUMBER(D32)),"n/a",IF(D32<=G32,"GREAT",IF(D32>=H32,"WEAK","OK"))) -> n/a | J32: Gearing. Buybacks can inflate it.
B33: Interest cover | C33: EBIT ÷ interest expense | D33: =IF(E33<>"",E33,IF('2. Financials'!$E$45="","",'2. Financials'!$E$45)) | F33: Higher | G33: 8 | H33: 3 | I33: =IF(NOT(ISNUMBER(D33)),"n/a",IF(D33>=G33,"GREAT",IF(D33<=H33,"WEAK","OK"))) -> n/a | J33: Safety margin on interest payments.
B34: Current ratio | C34: Current assets ÷ current liabilities | D34: =IF(E34<>"",E34,IF('2. Financials'!$E$46="","",'2. Financials'!$E$46)) | F34: Higher | G34: 1.5 | H34: 1 | I34: =IF(NOT(ISNUMBER(D34)),"n/a",IF(D34>=G34,"GREAT",IF(D34<=H34,"WEAK","OK"))) -> n/a | J34: Short-term liquidity. <1x can be fine if due to customer prepayments.
A35: Shareholders | B35: Change in share count | C35: Shares ÷ prior year − 1 | D35: =IF(E35<>"",E35,IF('2. Financials'!$E$49="","",'2. Financials'!$E$49)) | F35: Lower | G35: -0.01 | H35: 0.02 | I35: =IF(NOT(ISNUMBER(D35)),"n/a",IF(D35<=G35,"GREAT",IF(D35>=H35,"WEAK","OK"))) -> n/a | J35: Negative = buybacks; positive = dilution.
B36: Payout ÷ FCF | C36: (Dividends + buybacks) ÷ FCF | D36: =IF(E36<>"",E36,IF('2. Financials'!$E$50="","",'2. Financials'!$E$50)) | F36: Lower | G36: 0.6 | H36: 1 | I36: =IF(NOT(ISNUMBER(D36)),"n/a",IF(D36<=G36,"GREAT",IF(D36>=H36,"WEAK","OK"))) -> n/a | J36: Above 100% = paying out more cash than it makes.
B37: Dividend yield | C37: Dividend per share ÷ price | D37: =IF(E37<>"",E37,IF(OR('1. Company Info'!$B$36="",'1. Company Info'!$B$36=0),"",'1. Company Info'!$B$36)) | F37: Higher | G37: 0.03 | H37: 0.01 | I37: =IF(NOT(ISNUMBER(D37)),"n/a",IF(D37>=G37,"GREAT",IF(D37<=H37,"WEAK","OK"))) -> n/a | J37: Income return. No dividend shows n/a — fine for companies returning cash through buybacks.
A38: Risk | B38: Beta | C38: Share volatility vs the market | D38: =IF(E38<>"",E38,IF('1. Company Info'!$B$20="","",'1. Company Info'!$B$20)) | F38: Lower | G38: 1 | H38: 1.3 | I38: =IF(NOT(ISNUMBER(D38)),"n/a",IF(D38<=G38,"GREAT",IF(D38>=H38,"WEAK","OK"))) -> n/a | J38: Above 1 = moves more than the market.
A40: Notes
A41: • Limits are general rules of thumb for non-financial companies — the senior analyst should adjust them by sector (e.g. retail gross margins ~25% are normal; miners have high capex).
A42: • Banks & insurers: ignore gross margin, EBITDA, current ratio and net debt rows — use ROE, price/book, cost-to-income and capital ratios instead.
A43: • Always compare valuation ratios with peers (Step 4, section A): a P/E of 20x is cheap for a 25%-grower and expensive for a 3%-grower — that's what the PEG ratio is for.
A44: • Orange Override cell = a value typed over the automatic one. Write the reason in the notes on the Checklist.

Sheet 7. Technical Review
A1: ="Step 7 — Technical Review & Timing | "&IF('1. Company Info'!$B$6="","[Company]",'1. Company Info'!$B$6&" ("&'1. Company Info'!$B$7&")") -> Step 7 — Technical Review & Timing | [Company]
A2: Fundamentals decide WHAT to own. This page decides WHEN and HOW MUCH. It never changes the BUY / HOLD / SELL rating. Take inputs from any charting site (TradingView, Sharenet, Yahoo Finance) on the same date as the share price.
A4: A. Chart inputs (yellow) — same date as the share price
A5: # | B5: Input | C5: Value | E5: Where to find it / tip
A6: 1 | B6: Share price (from Step 1) | C6: =IF('1. Company Info'!$B$16="","",'1. Company Info'!$B$16) | E6: Linked. Must be the same date as the chart data.
A7: 2 | B7: 50-day moving average | E7: Average closing price of the last 50 trading days (~2½ months).
A8: 3 | B8: 200-day moving average | E8: Average of the last 200 trading days (~10 months). The main long-term trend line.
A9: 4 | B9: 200-day average, one month ago | E9: Tells you whether the long-term trend line is rising or falling.
A10: 5 | B10: RSI (14-day) | E10: 0–100. Above 70 = rose too far, too fast. Below 30 = fell too far, too fast.
A11: 6 | B11: Share price 6 months ago | E11: From the price history table.
A12: 7 | B12: Share price 12 months ago
A13: 8 | B13: Benchmark index | E13: JSE All Share (J203) for SA shares; S&P 500 for US shares.
A14: 9 | B14: Index return over 6 months | E14: e.g. 0.05 = +5%.
A15: 10 | B15: Index return over 12 months
A16: 11 | B16: Average daily value traded, 3 months (millions) | E16: Average daily volume × price, in the reporting currency, millions.
A17: 12 | B17: Planned position size (millions) | E17: Ask the PM. Same currency, millions.
A18: 13 | B18: Key support level | E18: A recent price floor where buyers stepped in (e.g. last major low).
A19: 14 | B19: Key resistance level | E19: A recent ceiling where the price kept failing.
A20: 15 | B20: Next results / major event date | E20: Results, trading statement, AGM or deal vote.
A21: 16 | B21: RULE: buffer below support for review level | C21: 0.03 | E21: Senior analyst sets this. Default 3%.
A22: 17 | B22: RULE: max share of daily volume we trade | C22: 0.2 | E22: Senior analyst sets this. Default 20%.
A24: B. Technical entry rules — look at the chart, then tick each rule yourself: ✔ = met ✘ = not met N/A = not relevant
A25: # | B25: Rule (for a BUY entry) | C25: Value | D25: Data says | E25: YOUR TICK | F25: Must pass | G25: Result | H25: How to check on the chart
A26: 1 | B26: Price is ABOVE the 200-day moving average | C26: =IFERROR(IF(OR($C$6="",$C$8=""),"",$C$6/$C$8-1),"") | D26: =IF(NOT(ISNUMBER(C26)),"no data",IF(C26>=0,"MET","NOT MET")) -> no data | E26: ☐ | G26: =IF(E26="✔","MET",IF(E26="✘","NOT MET",IF(E26="N/A","N/A","TO TICK")))&IF(OR(AND(E26="✔",D26="NOT MET"),AND(E26="✘",D26="MET"))," ⚠","") -> TO TICK | H26: Is the price line above the slow (200-day) line?
A27: 2 | B27: 200-day average is FLAT or RISING (not falling) | C27: =IFERROR(IF(OR($C$8="",$C$9=""),"",$C$8/$C$9-1),"") | D27: =IF(NOT(ISNUMBER(C27)),"no data",IF(C27>=-0.005,"MET","NOT MET")) -> no data | E27: ☐ | G27: =IF(E27="✔","MET",IF(E27="✘","NOT MET",IF(E27="N/A","N/A","TO TICK")))&IF(OR(AND(E27="✔",D27="NOT MET"),AND(E27="✘",D27="MET"))," ⚠","") -> TO TICK | H27: Compare the 200-day line today vs a month ago.
A28: 3 | B28: 50-day average is ABOVE the 200-day average | C28: =IFERROR(IF(OR($C$7="",$C$8=""),"",$C$7/$C$8-1),"") | D28: =IF(NOT(ISNUMBER(C28)),"no data",IF(C28>=0,"MET","NOT MET")) -> no data | E28: ☐ | G28: =IF(E28="✔","MET",IF(E28="✘","NOT MET",IF(E28="N/A","N/A","TO TICK")))&IF(OR(AND(E28="✔",D28="NOT MET"),AND(E28="✘",D28="MET"))," ⚠","") -> TO TICK | H28: Fast line above slow line = 'golden cross'.
A29: 4 | B29: Price is NOT stretched: within 15% of the 50-day average | C29: =IFERROR(IF(OR($C$6="",$C$7=""),"",$C$6/$C$7-1),"") | D29: =IF(NOT(ISNUMBER(C29)),"no data",IF(C29<0.15,"MET","NOT MET")) -> no data | E29: ☐ | G29: =IF(E29="✔","MET",IF(E29="✘","NOT MET",IF(E29="N/A","N/A","TO TICK")))&IF(OR(AND(E29="✔",D29="NOT MET"),AND(E29="✘",D29="MET"))," ⚠","") -> TO TICK | H29: Big gap above the 50-day line = chasing; wait.
A30: 5 | B30: RSI between 30 and 70 (not overbought / oversold) | C30: =IF($C$10="","",$C$10) | D30: =IF(NOT(ISNUMBER(C30)),"no data",IF(AND(C30>=30,C30<=70),"MET","NOT MET")) -> no data | E30: ☐ | G30: =IF(E30="✔","MET",IF(E30="✘","NOT MET",IF(E30="N/A","N/A","TO TICK")))&IF(OR(AND(E30="✔",D30="NOT MET"),AND(E30="✘",D30="MET"))," ⚠","") -> TO TICK | H30: RSI panel under the chart.
A31: 6 | B31: Share has BEATEN the index over 6 months | C31: =IFERROR(IF(OR($C$6="",$C$11="",$C$14=""),"",($C$6/$C$11-1)-$C$14),"") | D31: =IF(NOT(ISNUMBER(C31)),"no data",IF(C31>=0,"MET","NOT MET")) -> no data | E31: ☐ | G31: =IF(E31="✔","MET",IF(E31="✘","NOT MET",IF(E31="N/A","N/A","TO TICK")))&IF(OR(AND(E31="✔",D31="NOT MET"),AND(E31="✘",D31="MET"))," ⚠","") -> TO TICK | H31: Compare the share's 6-month % with the index.
A32: 7 | B32: Upper half of 52-week range, OR a clear base / higher low | C32: =IF('1. Company Info'!B38="","",'1. Company Info'!B38) | D32: =IF(NOT(ISNUMBER(C32)),"no data",IF(C32>=0.5,"MET","NOT MET")) -> no data | E32: ☐ | G32: =IF(E32="✔","MET",IF(E32="✘","NOT MET",IF(E32="N/A","N/A","TO TICK")))&IF(OR(AND(E32="✔",D32="NOT MET"),AND(E32="✘",D32="MET"))," ⚠","") -> TO TICK | H32: Data only checks the range — a visible higher low on the chart also counts as met.
A33: 8 | B33: Volume confirms: up-days on heavier volume than down-days (last month) | C33: ="" | D33: judgement | E33: ☐ | G33: =IF(E33="✔","MET",IF(E33="✘","NOT MET",IF(E33="N/A","N/A","TO TICK")))&IF(OR(AND(E33="✔",D33="NOT MET"),AND(E33="✘",D33="MET"))," ⚠","") -> TO TICK | H33: Look at the volume bars. Judgement only — no data check.
A34: 9 | B34: Price is ABOVE the review level (support − buffer) | C34: =IFERROR(IF(OR($C$6="",$C$18=""),"",$C$6/($C$18*(1-$C$21))-1),"") | D34: =IF(NOT(ISNUMBER(C34)),"no data",IF(C34>0,"MET","NOT MET")) -> no data | E34: ☐ | F34: Y | G34: =IF(E34="✔","MET",IF(E34="✘","NOT MET",IF(E34="N/A","N/A","TO TICK")))&IF(OR(AND(E34="✔",D34="NOT MET"),AND(E34="✘",D34="MET"))," ⚠","") -> TO TICK | H34: Below the review level = thesis under question. Never buy.
A35: 10 | B35: Reward ÷ risk to target is at least 3x | C35: =IFERROR(IF(OR($C$6="",$C$18="",'4. Valuation'!$B$64=""),"",IF($C$6<=($C$18*(1-$C$21)),0,('4. Valuation'!$B$64-$C$6)/($C$6-($C$18*(1-$C$21))))),"") | D35: =IF(NOT(ISNUMBER(C35)),"no data",IF(C35>=3,"MET","NOT MET")) -> no data | E35: ☐ | G35: =IF(E35="✔","MET",IF(E35="✘","NOT MET",IF(E35="N/A","N/A","TO TICK")))&IF(OR(AND(E35="✔",D35="NOT MET"),AND(E35="✘",D35="MET"))," ⚠","") -> TO TICK | H35: Gain to target ÷ loss to review level.
A36: 11 | B36: Position can be built in 5 days at ≤ max share of daily volume | C36: =IFERROR(IF(OR($C$17="",$C$16=""),"",$C$17/($C$16*$C$22)),"") | D36: =IF(NOT(ISNUMBER(C36)),"no data",IF(C36<=5,"MET","NOT MET")) -> no data | E36: ☐ | F36: Y | G36: =IF(E36="✔","MET",IF(E36="✘","NOT MET",IF(E36="N/A","N/A","TO TICK")))&IF(OR(AND(E36="✔",D36="NOT MET"),AND(E36="✘",D36="MET"))," ⚠","") -> TO TICK | H36: Days = position ÷ (daily value × max share).
A37: 12 | B37: No results / major event in the next 2 weeks | C37: =IFERROR(IF(OR($C$20="",'1. Company Info'!$B$17=""),"",$C$20-'1. Company Info'!$B$17),"") | D37: =IF(NOT(ISNUMBER(C37)),"no data",IF(OR(C37<0,C37>=14),"MET","NOT MET")) -> no data | E37: ☐ | G37: =IF(E37="✔","MET",IF(E37="✘","NOT MET",IF(E37="N/A","N/A","TO TICK")))&IF(OR(AND(E37="✔",D37="NOT MET"),AND(E37="✘",D37="MET"))," ⚠","") -> TO TICK | H37: Check the results calendar and SENS / news.
A38: ⚠ = your tick disagrees with the data — check the chart again and explain in the chart notes. Must pass = Y: a ✘ on this rule blocks clearance, whatever the score.
A40: C. Technical score & execution clearance (reacts to your ticks)
B41: RULE: score needed for clearance | C41: 0.7 | D41: Set by the senior analyst / PM.
B42: Rules met (✔) | C42: =COUNTIF($E$26:$E$37,"✔") -> 0 | D42: =IF($C$45=12,"Tick the 12 rules in section B to get a score.",IF($C$45>0,"Score so far: "&TEXT(IF($C$47="",0,$C$47),"0%")&" — "&$C$45&" rule(s) still to tick before clearance can be given.","All rules ticked. Score "&TEXT(IF($C$47="",0,$C$47),"0%")&" vs "&TEXT($C$41,"0%")&" needed"&IF($C$46>0," — but a must-pass rule failed.","."))) -> Tick the 12 rules in section B to get a score.
B43: Rules not met (✘) | C43: =COUNTIF($E$26:$E$37,"✘") -> 0
B44: Not relevant (N/A) | C44: =COUNTIF($E$26:$E$37,"N/A") -> 0
B45: Still to tick (☐) | C45: =12-C42-C43-C44 -> 12
B46: Must-pass rules failed | C46: =COUNTIFS($E$26:$E$37,"✘",$F$26:$F$37,"Y") -> 0
B47: TECHNICAL SCORE (met ÷ applicable) | C47: =IF(C42+C43=0,"",C42/(C42+C43))
A48: TECHNICAL CLEARANCE | C48: =IF($C$45>0,"INCOMPLETE — "&$C$45&" rule(s) still to tick",IF($C$42+$C$43=0,"INCOMPLETE — no applicable rules",IF($C$46>0,"NOT CLEARED — must-pass rule failed",IF($C$47>=1,"CLEARED — FULL POSITION",IF($C$47>=$C$41,"CLEARED — STAGED ENTRY","NOT CLEARED — score below "&TEXT($C$41,"0%")))))) -> INCOMPLETE — 12 rule(s) still to tick
A49: EXECUTION INSTRUCTION | C49: =IF(OR('5. Rating Summary'!$C$37="INCOMPLETE",'5. Rating Summary'!$C$37=""),"NO EXECUTION — fundamental analysis not finished",IF('5. Rating Summary'!$C$37="HOLD","NO EXECUTION — rating is HOLD (no new buying). Technical score for reference: "&IF($C$47="","n/a",TEXT($C$47,"0%")),IF(LEFT($C$48,10)="INCOMPLETE","WAITING — analyst must tick all rules before execution",IF('5. Rating Summary'!$C$37="SELL",IF($C$47>=$C$41,"EXECUTE SELL — chart is strong: exit over 1–2 weeks into strength","EXECUTE SELL — chart is weak: exit now"),IF(LEFT($C$48,14)="CLEARED — FULL","EXECUTE BUY — full position",IF(LEFT($C$48,16)="CLEARED — STAGED","EXECUTE BUY — first tranche 50%; rest when all rules are met or after next results","DO NOT EXECUTE — technical conditions not met; re-tick weekly")))))) -> NO EXECUTION — fundamental analysis not finished
B50: Trend (from data, for reference) | C50: =IF(NOT(ISNUMBER(C26)),"n/a",IF(AND(C26>=0,OR(NOT(ISNUMBER(C27)),C27>=-0.005),OR(NOT(ISNUMBER(C28)),C28>-0.02)),"UPTREND",IF(AND(C26<=-0.05,OR(NOT(ISNUMBER(C27)),C27<0.005)),"DOWNTREND","SIDEWAYS"))) -> n/a | D50: Review level: | E50: =IF($C$18="","",($C$18*(1-$C$21))) | F50: Entry zone: | G50: =IF(OR($C$18="",$C$7=""),"",TEXT(MIN($C$18,$C$7),"#,##0.00")&" – "&TEXT(MAX($C$18,$C$7),"#,##0.00"))
A52: D. Execution ticket — for the technical trader / executor
A53: Stock / action | C53: =IF('1. Company Info'!$B$7="","",'1. Company Info'!$B$7&" — ")&$C$49 -> NO EXECUTION — fundamental analysis not finished
A54: First order size (% of planned position) | C54: =IF(LEFT($C$49,20)="EXECUTE BUY — full p",1,IF(LEFT($C$49,20)="EXECUTE BUY — first ",0.5,IF(LEFT($C$49,12)="EXECUTE SELL",1,0))) -> 0
A55: First order value (millions) | C55: =IF($C$17="","enter planned position size in section A",IF(LEFT($C$49,20)="EXECUTE BUY — full p",1,IF(LEFT($C$49,20)="EXECUTE BUY — first ",0.5,IF(LEFT($C$49,12)="EXECUTE SELL",1,0)))*$C$17) -> enter planned position size in section A
A56: Entry zone (buy) / reference price | C56: =IF(G50="",TEXT($C$6,"#,##0.00"),G50)
A57: Review / stop level | C57: =IF(E50="","",E50)
A58: Max share of daily volume per day | C58: =$C$22 -> 0.2
A59: Clearance valid until | C59: =IF('1. Company Info'!$B$17="","",'1. Company Info'!$B$17+7)
A60: Analyst (cleared by) — name & date
A61: Trader (executed by) — name, date & avg price
A62: After the 'valid until' date, re-check the chart and re-tick before trading. A close below the review level forces a thesis review within 2 days (not an automatic sale).
A64: E. Price chart — paste a 12-month chart with the 50- and 200-day averages, support and review level marked
A65: Paste chart here (screenshot from TradingView / Sharenet / Yahoo: 1-year daily chart, 50- & 200-day moving averages, RSI, volume) Insert ▸ Pictures, or Ctrl+V, then resize to fit this box
A79: Chart date / source / notes

Sheet 8. Investor Summary
A1: ="Investor Summary — "&IF('1. Company Info'!$B$6="","[Company]",'1. Company Info'!$B$6&" ("&'1. Company Info'!$B$7&")") -> Investor Summary — [Company]
A2: ="A plain-English summary for everyday investors • Leago Rifumo Capital • Prices as of "&IF('1. Company Info'!$B$17="","[date]",TEXT('1. Company Info'!$B$17,"d mmmm yyyy")) -> A plain-English summary for everyday investors • Leago Rifumo Capital • Prices as of [date]
A4: OUR VIEW | C4: Share price today | D4: =IF('1. Company Info'!$B$16="","",TEXT('1. Company Info'!$B$16,"#,##0.00")&" "&'1. Company Info'!$B$10) | E4: In one sentence
A5: ='5. Rating Summary'!C37 -> INCOMPLETE | C5: What we think it's worth | D5: =IF('4. Valuation'!$B$64="","",TEXT('4. Valuation'!$B$64,"#,##0.00")&" "&'1. Company Info'!$B$10) | E5: [One plain sentence: what kind of company, is it good, is it cheap, what's the catch.]
C6: Possible gain / (loss) | D6: =IF('4. Valuation'!$C$64="","",TEXT('4. Valuation'!$C$64,"+0%;-0%"))
C7: Business health check | D7: ='6. Fundamentals Scorecard'!$I$5&" ("&TEXT('6. Fundamentals Scorecard'!$I$4,"0%")&")" -> Not enough data ()
A9: 1. What does the company do?
A10: [2–3 sentences anyone can follow: what it sells, who pays, how it earns money. Use an everyday comparison.]
A12: 2. Why we like it
A13: [Reason 1 — in plain words, with one number.]
A14: [Reason 2 — in plain words, with one number.]
A15: [Reason 3 — in plain words, with one number.]
A17: 3. What worries us
A18: [Risk 1 — what could go wrong and why it matters.]
A19: [Risk 2 — what could go wrong and why it matters.]
A20: [Risk 3 — what could go wrong and why it matters.]
A22: 4. Is the share cheap?
A23: =IF(OR('6. Fundamentals Scorecard'!$D$9="",'4. Valuation'!$B$12=""),"[Fills in automatically once Step 4 peers and Step 1 EPS are entered.]","Think of buying a business that earns 1 a year in profit. This company costs about "&TEXT('6. Fundamentals Scorecard'!$D$9,"0")&" (its price is "&TEXT('6. Fundamentals Scorecard'!$D$9,"0.0")&" times next year's expected profit per share). Similar companies cost about "&TEXT('4. Valuation'!$B$12,"0")&". "&IF('6. Fundamentals Scorecard'!$D$9<'4. Valuation'!$B$12,"So it is cheaper than its peers — the question is whether that discount is deserved.","So it is more expensive than its peers — it needs to grow faster to justify that.")) -> [Fills in automatically once Step 4 peers and Step 1 EPS are entered.]
A24: =IF('6. Fundamentals Scorecard'!$D$14="","","Another way to see it: for every 100 invested in the shares, the business produces about "&TEXT('6. Fundamentals Scorecard'!$D$14*100,"0")&" of spare cash a year (free cash flow), compared with about "&TEXT('4. Valuation'!$B$23*100,"0.0")&" a year from a safe government bond.")
A26: 5. What could happen to the share price?
A27: Scenario | B27: Price | C27: Gain / (loss) | D27: What would need to happen
A28: Bad case | B28: =IF('4. Valuation'!$B$69="","",TEXT('4. Valuation'!$B$69,"#,##0.00")&" "&'1. Company Info'!$B$10) | C28: =IF('4. Valuation'!$C$69="","",TEXT('4. Valuation'!$C$69,"+0%;-0%")) | D28: [In plain words]
A29: Our base case | B29: =IF('4. Valuation'!$B$70="","",TEXT('4. Valuation'!$B$70,"#,##0.00")&" "&'1. Company Info'!$B$10) | C29: =IF('4. Valuation'!$C$70="","",TEXT('4. Valuation'!$C$70,"+0%;-0%")) | D29: [In plain words]
A30: Good case | B30: =IF('4. Valuation'!$B$71="","",TEXT('4. Valuation'!$B$71,"#,##0.00")&" "&'1. Company Info'!$B$10) | C30: =IF('4. Valuation'!$C$71="","",TEXT('4. Valuation'!$C$71,"+0%;-0%")) | D30: [In plain words]
A32: 6. Why this rating?
A33: [Explain the rating in 3–4 plain sentences: the value gap, the main reason for any caution, and what it means for someone who owns / doesn't own the share.]
A35: 7. What to watch next
A36: [Event / sign 1, with a date if possible.]
A37: [Event / sign 2, with a date if possible.]
A38: [Event / sign 3, with a date if possible.]
A40: 8. Key facts in plain English
A41: Sales (last 12 months) | C41: =IF('2. Financials'!$E$7="","",TEXT('2. Financials'!$E$7/1000,"#,##0.0")&" bn "&'1. Company Info'!$B$10&", growing "&TEXT('6. Fundamentals Scorecard'!$D$17,"0%")&" a year")
A42: Spare cash kept per 100 of sales | C42: =IF('6. Fundamentals Scorecard'!$D$27="","","About "&TEXT('6. Fundamentals Scorecard'!$D$27*100,"0")&" (free cash flow margin)")
A43: Debt | C43: =IF('6. Fundamentals Scorecard'!$D$31="","",IF('2. Financials'!$E$43<=0,"More cash than debt","Low: "&TEXT('6. Fundamentals Scorecard'!$D$31,"0.0")&" years of profit would repay it"))
A44: How bumpy is the share? | C44: =IF('1. Company Info'!$B$20="","","Beta "&TEXT('1. Company Info'!$B$20,"0.00")&": "&IF('1. Company Info'!$B$20>1.2,"moves more than the market — expect big swings",IF('1. Company Info'!$B$20<0.8,"steadier than the market","moves roughly with the market")))
A45: Dividend | C45: =IF('1. Company Info'!$B$16="","",IF(N('2. Financials'!$E$14)=0,"None — returns cash by buying back its own shares instead","Yield of "&TEXT('2. Financials'!$E$14/'1. Company Info'!$B$16,"0.0%")&" a year"))
A46: Ratio health check | C46: ='6. Fundamentals Scorecard'!$G$4&" great, "&'6. Fundamentals Scorecard'!$G$5&" OK, "&'6. Fundamentals Scorecard'!$G$6&" weak (out of "&('6. Fundamentals Scorecard'!$G$4+'6. Fundamentals Scorecard'!$G$5+'6. Fundamentals Scorecard'!$G$6)&" ratios)" -> 0 great, 0 OK, 0 weak (out of 0 ratios)
A48: Words you might not know
A49: Share price: what one share costs today. Fair value / target: what we think one share is really worth. P/E ratio: share price ÷ profit per share — roughly how many years of today's profit you are paying for. Free cash flow: cash left over after paying all bills and investing in the business. Share buyback: the company buys its own shares, so each remaining share owns a bigger slice.
A50: BUY = we expect a gain of 15% or more and the business passes our quality checks. HOLD = worth owning, but the expected gain is smaller or there is a risk we want to see resolved first. SELL = we expect the price to fall 10% or more, or quality is poor.
A52: General information only — not personal financial advice. Think about your own goals and how much risk you can take, never put all your money into one share, and speak to a registered financial adviser if you are unsure.

Sheet 9. Analyst Summary
C1: ="Analyst Summary"&CHAR(10)&IF('1. Company Info'!$B$6="","[Company]",'1. Company Info'!$B$6&" ("&'1. Company Info'!$B$7&", "&'1. Company Info'!$B$8&")") -> Analyst Summary [Company] | G1: Company logo (Insert ▸ Pictures, place in this box)
A2: ="Prepared by: "&IF('1. Company Info'!$B$12="","[analyst]",'1. Company Info'!$B$12)&" | Reviewer: "&IF('1. Company Info'!$B$13="","[reviewer]",'1. Company Info'!$B$13)&" | Price date: "&IF('1. Company Info'!$B$17="","[date]",TEXT('1. Company Info'!$B$17,"d mmm yyyy"))&" | For: Investment Committee | Sector: "&'1. Company Info'!$B$9 -> Prepared by: [analyst] | Reviewer: [reviewer] | Price date: [date] | For: Investment Committee | Sector:
A4: Rating | B4: Target price | C4: Share price | D4: Upside | E4: Prob-weighted | F4: Conviction | G4: Checklist score | H4: Ratio health
A5: =IF('5. Rating Summary'!C37="","",'5. Rating Summary'!C37) -> INCOMPLETE | B5: =IF('4. Valuation'!B64="","",'4. Valuation'!B64) | C5: =IF('1. Company Info'!$B$16="","",'1. Company Info'!$B$16) | D5: =IF('4. Valuation'!C64="","",'4. Valuation'!C64) | E5: =IF('4. Valuation'!B72="","",'4. Valuation'!B72) | F5: =IF('5. Rating Summary'!C38="","",'5. Rating Summary'!C38) -> - | G5: =IF('5. Rating Summary'!C34="","",TEXT('5. Rating Summary'!C34,"0.00")&" / 5") | H5: =IF('6. Fundamentals Scorecard'!I5&" "&TEXT('6. Fundamentals Scorecard'!I4,"0%")="","",'6. Fundamentals Scorecard'!I5&" "&TEXT('6. Fundamentals Scorecard'!I4,"0%")) -> Not enough data
A6: Market cap (bn) | B6: EV (bn) | C6: Fwd P/E | D6: Peer fwd P/E | E6: EV / EBITDA | F6: FCF yield | G6: Consensus PT | H6: Consensus
A7: =IFERROR('1. Company Info'!B29/1000,"") | B7: =IFERROR('1. Company Info'!B31/1000,"") | C7: =IF('4. Valuation'!B13="","",'4. Valuation'!B13) | D7: =IF('4. Valuation'!B12="","",'4. Valuation'!B12) | E7: =IF('1. Company Info'!B34="","",'1. Company Info'!B34) | F7: =IF('1. Company Info'!B35="","",'1. Company Info'!B35) | G7: =IF('1. Company Info'!$B$24="","",'1. Company Info'!$B$24) | H7: =IF('1. Company Info'!$B$25="","",'1. Company Info'!$B$25)
A9: 1. Investment thesis
A10: [Thesis point 1: what is mispriced and why — lead with the number.]
A11: [Thesis point 2: what is mispriced and why — lead with the number.]
A12: [Thesis point 3: what is mispriced and why — lead with the number.]
A14: 2. Valuation
A15: Method | B15: Value / share | C15: vs price | D15: Weight | E15: Key assumptions
A16: Forward P/E | B16: ='4. Valuation'!B61 | C16: ='4. Valuation'!C61 | D16: ='4. Valuation'!D61 -> 0.4 | E16: =IF('4. Valuation'!B18="","",TEXT('4. Valuation'!B18,"0.0")&"x NTM EPS of "&TEXT('4. Valuation'!B17,"0.00")&" (peer median "&TEXT('4. Valuation'!B12,"0.0")&"x)")
A17: DCF | B17: ='4. Valuation'!B62 | C17: ='4. Valuation'!C62 | D17: ='4. Valuation'!D62 -> 0.3 | E17: =IF('4. Valuation'!B32="","","WACC "&TEXT('4. Valuation'!B32,"0.0%")&", terminal g "&TEXT('4. Valuation'!B33,"0.0%")&", FCF margin "&TEXT('4. Valuation'!B34,"0%")&", rev. growth "&TEXT('4. Valuation'!C37,"0%")&"→"&TEXT('4. Valuation'!G37,"0%")&"; TV "&TEXT('4. Valuation'!B51,"0%")&" of EV")
A18: EV / EBITDA | B18: ='4. Valuation'!B63 | C18: ='4. Valuation'!C63 | D18: ='4. Valuation'!D63 -> 0.3 | E18: =IF('4. Valuation'!B55="","",TEXT('4. Valuation'!B55,"0.0")&"x next-year EBITDA (peer median "&TEXT('4. Valuation'!C12,"0.0")&"x)")
A19: Blended target | B19: ='4. Valuation'!B64 | C19: ='4. Valuation'!C64 | D19: ='4. Valuation'!D64 -> 1 | E19: =IF(COUNT('4. Valuation'!B69:B71)<3,"","Bear "&TEXT('4. Valuation'!B69,"0")&" ("&TEXT('4. Valuation'!C69,"+0%;-0%")&") / Bull "&TEXT('4. Valuation'!B71,"0")&" ("&TEXT('4. Valuation'!C71,"+0%;-0%")&") • skew "&TEXT('4. Valuation'!B73,"0.0")&"x • DCF cells above price: "&COUNTIF('4. Valuation'!B77:F81,">"&'1. Company Info'!$B$16)&"/25")
A21: 3. Key financials | F21: 4. Checklist scores (1–5)
A22: ="("&'1. Company Info'!$B$11&")" -> () | B22: =IF('2. Financials'!B5="","",'2. Financials'!B5) | C22: =IF('2. Financials'!C5="","",'2. Financials'!C5) | D22: =IF('2. Financials'!D5="","",'2. Financials'!D5) | E22: =IF('2. Financials'!E5="","",'2. Financials'!E5) | F22: Section | H22: Score
A23: Revenue | B23: =IF('2. Financials'!B7="","",'2. Financials'!B7) | C23: =IF('2. Financials'!C7="","",'2. Financials'!C7) | D23: =IF('2. Financials'!D7="","",'2. Financials'!D7) | E23: =IF('2. Financials'!E7="","",'2. Financials'!E7) | F23: ='5. Rating Summary'!B9 -> A. Understand the business | H23: =IF('5. Rating Summary'!G9="","",'5. Rating Summary'!G9)
A24: Revenue growth | B24: =IF('2. Financials'!B32="","",'2. Financials'!B32) | C24: =IF('2. Financials'!C32="","",'2. Financials'!C32) | D24: =IF('2. Financials'!D32="","",'2. Financials'!D32) | E24: =IF('6. Fundamentals Scorecard'!D17="","",'6. Fundamentals Scorecard'!D17) | F24: ='5. Rating Summary'!B10 -> B. Industry & competition | H24: =IF('5. Rating Summary'!G10="","",'5. Rating Summary'!G10)
A25: Gross margin | B25: =IF('2. Financials'!B33="","",'2. Financials'!B33) | C25: =IF('2. Financials'!C33="","",'2. Financials'!C33) | D25: =IF('2. Financials'!D33="","",'2. Financials'!D33) | E25: =IF('2. Financials'!E33="","",'2. Financials'!E33) | F25: ='5. Rating Summary'!B11 -> C. Growth | H25: =IF('5. Rating Summary'!G11="","",'5. Rating Summary'!G11)
A26: Operating margin | B26: =IF('2. Financials'!B34="","",'2. Financials'!B34) | C26: =IF('2. Financials'!C34="","",'2. Financials'!C34) | D26: =IF('2. Financials'!D34="","",'2. Financials'!D34) | E26: =IF('2. Financials'!E34="","",'2. Financials'!E34) | F26: ='5. Rating Summary'!B12 -> D. Profitability | H26: =IF('5. Rating Summary'!G12="","",'5. Rating Summary'!G12)
A27: FCF margin | B27: =IF('2. Financials'!B39="","",'2. Financials'!B39) | C27: =IF('2. Financials'!C39="","",'2. Financials'!C39) | D27: =IF('2. Financials'!D39="","",'2. Financials'!D39) | E27: =IF('2. Financials'!E39="","",'2. Financials'!E39) | F27: ='5. Rating Summary'!B13 -> E. Cash flow | H27: =IF('5. Rating Summary'!G13="","",'5. Rating Summary'!G13)
A28: Diluted EPS | B28: =IF('2. Financials'!B13="","",'2. Financials'!B13) | C28: =IF('2. Financials'!C13="","",'2. Financials'!C13) | D28: =IF('2. Financials'!D13="","",'2. Financials'!D13) | E28: =IF('2. Financials'!E13="","",'2. Financials'!E13) | F28: ='5. Rating Summary'!B14 -> F. Balance sheet & capital allocation | H28: =IF('5. Rating Summary'!G14="","",'5. Rating Summary'!G14)
A29: Net debt / EBITDA | B29: =IF('2. Financials'!B44="","",'2. Financials'!B44) | C29: =IF('2. Financials'!C44="","",'2. Financials'!C44) | D29: =IF('2. Financials'!D44="","",'2. Financials'!D44) | E29: =IF('2. Financials'!E44="","",'2. Financials'!E44) | F29: ='5. Rating Summary'!B15 -> G. Management & governance | H29: =IF('5. Rating Summary'!G15="","",'5. Rating Summary'!G15)
A30: ROIC | B30: =IF('2. Financials'!B48="","",'2. Financials'!B48) | C30: =IF('2. Financials'!C48="","",'2. Financials'!C48) | D30: =IF('2. Financials'!D48="","",'2. Financials'!D48) | E30: =IF('2. Financials'!E48="","",'2. Financials'!E48) | F30: ='5. Rating Summary'!B16 -> H. Valuation | H30: =IF('5. Rating Summary'!G16="","",'5. Rating Summary'!G16)
A31: Shareholder payout / FCF | B31: =IF('2. Financials'!B50="","",'2. Financials'!B50) | C31: =IF('2. Financials'!C50="","",'2. Financials'!C50) | D31: =IF('2. Financials'!D50="","",'2. Financials'!D50) | E31: =IF('2. Financials'!E50="","",'2. Financials'!E50) | F31: ='5. Rating Summary'!B17 -> I. Catalysts & market view | H31: =IF('5. Rating Summary'!G17="","",'5. Rating Summary'!G17)
A32: Shares (m) | B32: =IF('2. Financials'!B15="","",'2. Financials'!B15) | C32: =IF('2. Financials'!C15="","",'2. Financials'!C15) | D32: =IF('2. Financials'!D15="","",'2. Financials'!D15) | E32: =IF('2. Financials'!E15="","",'2. Financials'!E15) | F32: ='5. Rating Summary'!B18 -> J. Risks (5 = LOW risk) | H32: =IF('5. Rating Summary'!G18="","",'5. Rating Summary'!G18)
A33: =IF('2. Financials'!E5="","","Latest column = "&'2. Financials'!E5&". Latest revenue growth uses the Scorecard value (incl. any override).")
A35: 5. Key risks | E35: 6. Catalysts & what to watch
A36: [Risk A — what, how likely, signal to watch] | E36: [Catalyst 1 — event + date]
A37: [Risk B — what, how likely, signal to watch] | E37: [Catalyst 2 — event + date]
A38: [Risk C — what, how likely, signal to watch] | E38: [Catalyst 3 — event + date]
A40: 7. What I checked & open questions for my reviewer
A41: [What I verified, which figures I corrected, data I couldn't get.]
A42: [Questions where I need my reviewer's judgement.]
A44: BOTTOM LINE
A45: =IF('5. Rating Summary'!C37="INCOMPLETE","Rating not yet available — finish the checklist and valuation.",'5. Rating Summary'!C37&" | Target "&TEXT('4. Valuation'!B64,"#,##0.00")&" "&'1. Company Info'!$B$10&" ("&TEXT('4. Valuation'!C64,"+0%;-0%")&") | Conviction: "&'5. Rating Summary'!C38&" | "&'5. Rating Summary'!C39) -> Rating not yet available — finish the checklist and valuation.
A46: ="Execution (Step 7): "&'7. Technical Review'!$C$49&" | Technical score: "&IF('7. Technical Review'!$C$47="","n/a",TEXT('7. Technical Review'!$C$47,"0%"))&" | "&'7. Technical Review'!$C$48&" | Review level: "&IF('7. Technical Review'!E50="","n/a",TEXT('7. Technical Review'!E50,"#,##0.00")) -> Execution (Step 7): NO EXECUTION — fundamental analysis not finished | Technical score: n/a | INCOMPLETE — 12 rule(s) still to tick | Review level: n/a
A47: [4–5 sentences: the call, the one reason that matters most, what would make you upgrade/downgrade, and the timing. Write it so the PM could read only this box.]
A49: Internal research — prepared by a junior analyst for review. Not investment advice. All figures in the reporting currency; sources and page references are on the Checklist tab.
